Workbook

Sheet Технологии
A1: ДЕРЕВО ТЕХНОЛОГИЙ — 15 ХОДОВ
A3: Вложения автоматически собираются с листов Ход 2026–2040. Незавершённые исследования накапливаются; prerequisites проверяются по накопленному прогрессу. Игровые эффекты технологий в состояние страны вносятся вручную.
A5: ВСЕГО ТЕХНОЛОГИЙ | E5: ОСНОВНЫХ ВЕТВЕЙ | I5: МЕЖВЕТВЕВЫХ | M5: СТАРТОВО ОТКРЫТО
A6: 40 | E6: 6 | I6: 4 | M6: 6
A10: ID | B10: Ветвь | C10: Уровень | D10: Технология | E10: Цена науки | F10: Требование 1 | G10: Требование 2 | H10: Требование 3 | I10: Суть | J10: Игровой эффект | K10: Вложено 2026 | L10: Вложено 2027 | M10: Вложено 2028 | N10: Вложено 2029 | O10: Вложено 2030 | P10: Вложено 2031 | Q10: Вложено 2032 | R10: Вложено 2033 | S10: Вложено 2034 | T10: Вложено 2035 | U10: Вложено 2036 | V10: Вложено 2037 | W10: Вложено 2038 | X10: Вложено 2039 | Y10: Вложено 2040 | Z10: Накоплено всего | AA10: Осталось | AB10: Текущий статус | AC10: Σ 2026 | AD10: Σ 2027 | AE10: Σ 2028 | AF10: Σ 2029 | AG10: Σ 2030 | AH10: Σ 2031 | AI10: Σ 2032 | AJ10: Σ 2033 | AK10: Σ 2034 | AL10: Σ 2035 | AM10: Σ 2036 | AN10: Σ 2037 | AO10: Σ 2038 | AP10: Σ 2039 | AQ10: Σ 2040 | AR10: Статус 2026 | AS10: Статус 2027 | AT10: Статус 2028 | AU10: Статус 2029 | AV10: Статус 2030 | AW10: Статус 2031 | AX10: Статус 2032 | AY10: Статус 2033 | AZ10: Статус 2034 | BA10: Статус 2035 | BB10: Статус 2036 | BC10: Статус 2037 | BD10: Статус 2038 | BE10: Статус 2039 | BF10: Статус 2040 | BG10: Год изучения | BH10: Эффект с года
A11: C1 | B11: Вычисления и аппаратная база | C11: I | D11: GPU-узлы с тензорными ядрами | E11: 20 | I11: Технология означает освоение серверных узлов на графических процессорах, выполняющих матричные операции при обучении и применении нейросетей. Государство получает доступ к относительно универсальной аппаратной базе, которую можно использовать для разных моделей без изготовления собственного процессора. Такой шаг повышает вычислительный потенциал и создаёт основу для специализированных ускорителей и крупных кластеров. На первом уровне инфраструктура достаточно ограничена, поэтому отдельный ресурсный штраф не вводится. | J11: + Вычислительные компоненты: +0,20 | K11: =SUMIF('Ход 2026'!$G$29:$G$38,$A11,'Ход 2026'!$I$29:$I$38)*(1+'Эффекты технологий'!J$7) -> 20 | L11: =SUMIF('Ход 2027'!$G$29:$G$38,$A11,'Ход 2027'!$I$29:$I$38)*(1+'Эффекты технологий'!K$7) -> 0 | M11: =SUMIF('Ход 2028'!$G$29:$G$38,$A11,'Ход 2028'!$I$29:$I$38)*(1+'Эффекты технологий'!L$7) -> 0 | N11: =SUMIF('Ход 2029'!$G$29:$G$38,$A11,'Ход 2029'!$I$29:$I$38)*(1+'Эффекты технологий'!M$7) -> 0 | O11: =SUMIF('Ход 2030'!$G$29:$G$38,$A11,'Ход 2030'!$I$29:$I$38)*(1+'Эффекты технологий'!N$7) -> 0 | P11: =SUMIF('Ход 2031'!$G$29:$G$38,$A11,'Ход 2031'!$I$29:$I$38)*(1+'Эффекты технологий'!O$7) -> 0 | Q11: =SUMIF('Ход 2032'!$G$29:$G$38,$A11,'Ход 2032'!$I$29:$I$38)*(1+'Эффекты технологий'!P$7) -> 0 | R11: =SUMIF('Ход 2033'!$G$29:$G$38,$A11,'Ход 2033'!$I$29:$I$38)*(1+'Эффекты технологий'!Q$7) -> 0 | S11: =SUMIF('Ход 2034'!$G$29:$G$38,$A11,'Ход 2034'!$I$29:$I$38)*(1+'Эффекты технологий'!R$7) -> 0 | T11: =SUMIF('Ход 2035'!$G$29:$G$38,$A11,'Ход 2035'!$I$29:$I$38)*(1+'Эффекты технологий'!S$7) -> 0 | U11: =SUMIF('Ход 2036'!$G$29:$G$38,$A11,'Ход 2036'!$I$29:$I$38)*(1+'Эффекты технологий'!T$7) -> 0 | V11: =SUMIF('Ход 2037'!$G$29:$G$38,$A11,'Ход 2037'!$I$29:$I$38)*(1+'Эффекты технологий'!U$7) -> 0 | W11: =SUMIF('Ход 2038'!$G$29:$G$38,$A11,'Ход 2038'!$I$29:$I$38)*(1+'Эффекты технологий'!V$7) -> 0 | X11: =SUMIF('Ход 2039'!$G$29:$G$38,$A11,'Ход 2039'!$I$29:$I$38)*(1+'Эффекты технологий'!W$7) -> 0 | Y11: =SUMIF('Ход 2040'!$G$29:$G$38,$A11,'Ход 2040'!$I$29:$I$38)*(1+'Эффекты технологий'!X$7) -> 0 | Z11: =SUM(K11:Y11) -> 20 | AA11: =MAX(0,E11-Z11) -> 0 | AB11: =BF11 -> ИЗУЧЕНО | AC11: =SUM($K11:K11) -> 20 | AD11: =SUM($K11:L11) -> 20 | AE11: =SUM($K11:M11) -> 20 | AF11: =SUM($K11:N11) -> 20 | AG11: =SUM($K11:O11) -> 20 | AH11: =SUM($K11:P11) -> 20 | AI11: =SUM($K11:Q11) -> 20 | AJ11: =SUM($K11:R11) -> 20 | ... AQ11: =SUM($K11:Y11) -> 20 | AR11: =IF(AND(AC11>=$E11,TRUE),"ИЗУЧЕНО",IF(TRUE,"ОТКРЫТО","ЗАКРЫТО")) -> ИЗУЧЕНО | AS11: =IF(AND(AD11>=$E11,TRUE),"ИЗУЧЕНО",IF(TRUE,"ОТКРЫТО","ЗАКРЫТО")) -> ИЗУЧЕНО | AT11: =IF(AND(AE11>=$E11,TRUE),"ИЗУЧЕНО",IF(TRUE,"ОТКРЫТО","ЗАКРЫТО")) -> ИЗУЧЕНО | AU11: =IF(AND(AF11>=$E11,TRUE),"ИЗУЧЕНО",IF(TRUE,"ОТКРЫТО","ЗАКРЫТО")) -> ИЗУЧЕНО | AV11: =IF(AND(AG11>=$E11,TRUE),"ИЗУЧЕНО",IF(TRUE,"ОТКРЫТО","ЗАКРЫТО")) -> ИЗУЧЕНО | AW11: =IF(AND(AH11>=$E11,TRUE),"ИЗУЧЕНО",IF(TRUE,"ОТКРЫТО","ЗАКРЫТО")) -> ИЗУЧЕНО | AX11: =IF(AND(AI11>=$E11,TRUE),"ИЗУЧЕНО",IF(TRUE,"ОТКРЫТО","ЗАКРЫТО")) -> ИЗУЧЕНО | AY11: =IF(AND(AJ11>=$E11,TRUE),"ИЗУЧЕНО",IF(TRUE,"ОТКРЫТО","ЗАКРЫТО")) -> ИЗУЧЕНО | ... BF11: =IF(AND(AQ11>=$E11,TRUE),"ИЗУЧЕНО",IF(TRUE,"ОТКРЫТО","ЗАКРЫТО")) -> ИЗУЧЕНО | BG11: =IFERROR(2025+MATCH("ИЗУЧЕНО",AR11:BF11,0),"") -> 2026 | BH11: =IF(BG11="","",BG11+1) -> 2027
A12: C2 | B12: Вычисления и аппаратная база | C12: II | D12: ASIC-ускорители с памятью HBM | E12: 40 | F12: C1 | I12: Специализированные интегральные схемы ASIC разрабатываются под определённые нейросетевые операции, а память HBM обеспечивает высокую пропускную способность доступа к данным. Вместе с аппаратурой развиваются драйверы, компиляторы и программные библиотеки. Выигрыш состоит в повышении производительности и лучшей согласованности программной и аппаратной частей. Производство таких ускорителей требует дополнительных металлов и редких материалов, поэтому технология уменьшает доступный сырьевой ресурс. | J12: + Вычислительные компоненты: +0,30; + Базовый программный стек вычислений: +0,20; − Минерально-сырьевые ресурсы: -0,15 | K12: =SUMIF('Ход 2026'!$G$29:$G$38,$A12,'Ход 2026'!$I$29:$I$38)*(1+'Эффекты технологий'!J$7) -> 0 | L12: =SUMIF('Ход 2027'!$G$29:$G$38,$A12,'Ход 2027'!$I$29:$I$38)*(1+'Эффекты технологий'!K$7) -> 0 | M12: =SUMIF('Ход 2028'!$G$29:$G$38,$A12,'Ход 2028'!$I$29:$I$38)*(1+'Эффекты технологий'!L$7) -> 0 | N12: =SUMIF('Ход 2029'!$G$29:$G$38,$A12,'Ход 2029'!$I$29:$I$38)*(1+'Эффекты технологий'!M$7) -> 0 | O12: =SUMIF('Ход 2030'!$G$29:$G$38,$A12,'Ход 2030'!$I$29:$I$38)*(1+'Эффекты технологий'!N$7) -> 0 | P12: =SUMIF('Ход 2031'!$G$29:$G$38,$A12,'Ход 2031'!$I$29:$I$38)*(1+'Эффекты технологий'!O$7) -> 0 | Q12: =SUMIF('Ход 2032'!$G$29:$G$38,$A12,'Ход 2032'!$I$29:$I$38)*(1+'Эффекты технологий'!P$7) -> 0 | R12: =SUMIF('Ход 2033'!$G$29:$G$38,$A12,'Ход 2033'!$I$29:$I$38)*(1+'Эффекты технологий'!Q$7) -> 0 | S12: =SUMIF('Ход 2034'!$G$29:$G$38,$A12,'Ход 2034'!$I$29:$I$38)*(1+'Эффекты технологий'!R$7) -> 0 | T12: =SUMIF('Ход 2035'!$G$29:$G$38,$A12,'Ход 2035'!$I$29:$I$38)*(1+'Эффекты технологий'!S$7) -> 0 | U12: =SUMIF('Ход 2036'!$G$29:$G$38,$A12,'Ход 2036'!$I$29:$I$38)*(1+'Эффекты технологий'!T$7) -> 0 | V12: =SUMIF('Ход 2037'!$G$29:$G$38,$A12,'Ход 2037'!$I$29:$I$38)*(1+'Эффекты технологий'!U$7) -> 0 | W12: =SUMIF('Ход 2038'!$G$29:$G$38,$A12,'Ход 2038'!$I$29:$I$38)*(1+'Эффекты технологий'!V$7) -> 0 | X12: =SUMIF('Ход 2039'!$G$29:$G$38,$A12,'Ход 2039'!$I$29:$I$38)*(1+'Эффекты технологий'!W$7) -> 0 | Y12: =SUMIF('Ход 2040'!$G$29:$G$38,$A12,'Ход 2040'!$I$29:$I$38)*(1+'Эффекты технологий'!X$7) -> 0 | Z12: =SUM(K12:Y12) -> 0 | AA12: =MAX(0,E12-Z12) -> 40 | AB12: =BF12 -> ОТКРЫТО | AC12: =SUM($K12:K12) -> 0 | AD12: =SUM($K12:L12) -> 0 | AE12: =SUM($K12:M12) -> 0 | AF12: =SUM($K12:N12) -> 0 | AG12: =SUM($K12:O12) -> 0 | AH12: =SUM($K12:P12) -> 0 | AI12: =SUM($K12:Q12) -> 0 | AJ12: =SUM($K12:R12) -> 0 | ... AQ12: =SUM($K12:Y12) -> 0 | AR12: =IF(AND(AC12>=$E12,TRUE),"ИЗУЧЕНО",IF(TRUE,"ОТКРЫТО","ЗАКРЫТО")) -> ОТКРЫТО | AS12: =IF(AND(AD12>=$E12,TRUE),"ИЗУЧЕНО",IF(TRUE,"ОТКРЫТО","ЗАКРЫТО")) -> ОТКРЫТО | AT12: =IF(AND(AE12>=$E12,TRUE),"ИЗУЧЕНО",IF(TRUE,"ОТКРЫТО","ЗАКРЫТО")) -> ОТКРЫТО | AU12: =IF(AND(AF12>=$E12,TRUE),"ИЗУЧЕНО",IF(TRUE,"ОТКРЫТО","ЗАКРЫТО")) -> ОТКРЫТО | AV12: =IF(AND(AG12>=$E12,TRUE),"ИЗУЧЕНО",IF(TRUE,"ОТКРЫТО","ЗАКРЫТО")) -> ОТКРЫТО | AW12: =IF(AND(AH12>=$E12,TRUE),"ИЗУЧЕНО",IF(TRUE,"ОТКРЫТО","ЗАКРЫТО")) -> ОТКРЫТО | AX12: =IF(AND(AI12>=$E12,TRUE),"ИЗУЧЕНО",IF(TRUE,"ОТКРЫТО","ЗАКРЫТО")) -> ОТКРЫТО | AY12: =IF(AND(AJ12>=$E12,TRUE),"ИЗУЧЕНО",IF(TRUE,"ОТКРЫТО","ЗАКРЫТО")) -> ОТКРЫТО | ... BF12: =IF(AND(AQ12>=$E12,TRUE),"ИЗУЧЕНО",IF(TRUE,"ОТКРЫТО","ЗАКРЫТО")) -> ОТКРЫТО | BG12: =IFERROR(2025+MATCH("ИЗУЧЕНО",AR12:BF12,0),"") | BH12: =IF(BG12="","",BG12+1)
A13: C3 | B13: Вычисления и аппаратная база | C13: II | D13: Чиплетная компоновка ИИ-процессоров 2.5D/3D | E13: 45 | F13: C1 | I13: Вместо одного большого кристалла процессор собирается из нескольких функциональных чиплетов, соединённых высокоплотной подложкой или многослойной компоновкой. Это позволяет комбинировать вычислительные блоки, память и ввод-вывод, а также развивать передовые производственные процессы. Технология даёт сразу три промышленных преимущества, но нуждается в более сложных производственных линиях и материальной базе. Сырьевой штраф здесь больше, чем у C2, отражая масштаб и сложность развёртывания. | J13: + Мощности производства полупроводников: +0,40; + Вычислительные компоненты: +0,20; + Химические и технологические материалы: +0,20; − Минерально-сырьевые ресурсы: -0,40 | K13: =SUMIF('Ход 2026'!$G$29:$G$38,$A13,'Ход 2026'!$I$29:$I$38)*(1+'Эффекты технологий'!J$7) -> 0 | L13: =SUMIF('Ход 2027'!$G$29:$G$38,$A13,'Ход 2027'!$I$29:$I$38)*(1+'Эффекты технологий'!K$7) -> 0 | M13: =SUMIF('Ход 2028'!$G$29:$G$38,$A13,'Ход 2028'!$I$29:$I$38)*(1+'Эффекты технологий'!L$7) -> 0 | N13: =SUMIF('Ход 2029'!$G$29:$G$38,$A13,'Ход 2029'!$I$29:$I$38)*(1+'Эффекты технологий'!M$7) -> 0 | O13: =SUMIF('Ход 2030'!$G$29:$G$38,$A13,'Ход 2030'!$I$29:$I$38)*(1+'Эффекты технологий'!N$7) -> 0 | P13: =SUMIF('Ход 2031'!$G$29:$G$38,$A13,'Ход 2031'!$I$29:$I$38)*(1+'Эффекты технологий'!O$7) -> 0 | Q13: =SUMIF('Ход 2032'!$G$29:$G$38,$A13,'Ход 2032'!$I$29:$I$38)*(1+'Эффекты технологий'!P$7) -> 0 | R13: =SUMIF('Ход 2033'!$G$29:$G$38,$A13,'Ход 2033'!$I$29:$I$38)*(1+'Эффекты технологий'!Q$7) -> 0 | S13: =SUMIF('Ход 2034'!$G$29:$G$38,$A13,'Ход 2034'!$I$29:$I$38)*(1+'Эффекты технологий'!R$7) -> 0 | T13: =SUMIF('Ход 2035'!$G$29:$G$38,$A13,'Ход 2035'!$I$29:$I$38)*(1+'Эффекты технологий'!S$7) -> 0 | U13: =SUMIF('Ход 2036'!$G$29:$G$38,$A13,'Ход 2036'!$I$29:$I$38)*(1+'Эффекты технологий'!T$7) -> 0 | V13: =SUMIF('Ход 2037'!$G$29:$G$38,$A13,'Ход 2037'!$I$29:$I$38)*(1+'Эффекты технологий'!U$7) -> 0 | W13: =SUMIF('Ход 2038'!$G$29:$G$38,$A13,'Ход 2038'!$I$29:$I$38)*(1+'Эффекты технологий'!V$7) -> 0 | X13: =SUMIF('Ход 2039'!$G$29:$G$38,$A13,'Ход 2039'!$I$29:$I$38)*(1+'Эффекты технологий'!W$7) -> 0 | Y13: =SUMIF('Ход 2040'!$G$29:$G$38,$A13,'Ход 2040'!$I$29:$I$38)*(1+'Эффекты технологий'!X$7) -> 0 | Z13: =SUM(K13:Y13) -> 0 | AA13: =MAX(0,E13-Z13) -> 45 | AB13: =BF13 -> ОТКРЫТО | AC13: =SUM($K13:K13) -> 0 | AD13: =SUM($K13:L13) -> 0 | AE13: =SUM($K13:M13) -> 0 | AF13: =SUM($K13:N13) -> 0 | AG13: =SUM($K13:O13) -> 0 | AH13: =SUM($K13:P13) -> 0 | AI13: =SUM($K13:Q13) -> 0 | AJ13: =SUM($K13:R13) -> 0 | ... AQ13: =SUM($K13:Y13) -> 0 | AR13: =IF(AND(AC13>=$E13,TRUE),"ИЗУЧЕНО",IF(TRUE,"ОТКРЫТО","ЗАКРЫТО")) -> ОТКРЫТО | AS13: =IF(AND(AD13>=$E13,TRUE),"ИЗУЧЕНО",IF(TRUE,"ОТКРЫТО","ЗАКРЫТО")) -> ОТКРЫТО | AT13: =IF(AND(AE13>=$E13,TRUE),"ИЗУЧЕНО",IF(TRUE,"ОТКРЫТО","ЗАКРЫТО")) -> ОТКРЫТО | AU13: =IF(AND(AF13>=$E13,TRUE),"ИЗУЧЕНО",IF(TRUE,"ОТКРЫТО","ЗАКРЫТО")) -> ОТКРЫТО | AV13: =IF(AND(AG13>=$E13,TRUE),"ИЗУЧЕНО",IF(TRUE,"ОТКРЫТО","ЗАКРЫТО")) -> ОТКРЫТО | AW13: =IF(AND(AH13>=$E13,TRUE),"ИЗУЧЕНО",IF(TRUE,"ОТКРЫТО","ЗАКРЫТО")) -> ОТКРЫТО | AX13: =IF(AND(AI13>=$E13,TRUE),"ИЗУЧЕНО",IF(TRUE,"ОТКРЫТО","ЗАКРЫТО")) -> ОТКРЫТО | AY13: =IF(AND(AJ13>=$E13,TRUE),"ИЗУЧЕНО",IF(TRUE,"ОТКРЫТО","ЗАКРЫТО")) -> ОТКРЫТО | ... BF13: =IF(AND(AQ13>=$E13,TRUE),"ИЗУЧЕНО",IF(TRUE,"ОТКРЫТО","ЗАКРЫТО")) -> ОТКРЫТО | BG13: =IFERROR(2025+MATCH("ИЗУЧЕНО",AR13:BF13,0),"") | BH13: =IF(BG13="","",BG13+1)
A14: C4 | B14: Вычисления и аппаратная база | C14: III | D14: Гетерогенные вычислительные кластеры | E14: 65 | F14: C2 | G14: C3 | I14: Кластер объединяет центральные процессоры, графические ускорители и специализированные ASIC в общую систему с распределённым управлением вычислениями. Основную роль играют планировщики задач, высокоскоростные соединения и согласованное использование памяти и ресурсов. Государство получает не просто отдельные чипы, а инфраструктуру промышленного масштаба. Такая концентрация оборудования увеличивает потребление электроэнергии и потребность в охлаждении, из-за чего появляются два постоянных ресурсных штрафа. | J14: + ЦОД и вычислительная инфраструктура: +0,40; + Стек эксплуатации ИИ: +0,20; + Сетевые ресурсы: +0,20; + Вычислительные компоненты: +0,20; − Энергетические ресурсы: -0,25; − Вода и ресурс отвода тепла: -0,20 | K14: =SUMIF('Ход 2026'!$G$29:$G$38,$A14,'Ход 2026'!$I$29:$I$38)*(1+'Эффекты технологий'!J$7) -> 0 | L14: =SUMIF('Ход 2027'!$G$29:$G$38,$A14,'Ход 2027'!$I$29:$I$38)*(1+'Эффекты технологий'!K$7) -> 0 | M14: =SUMIF('Ход 2028'!$G$29:$G$38,$A14,'Ход 2028'!$I$29:$I$38)*(1+'Эффекты технологий'!L$7) -> 0 | N14: =SUMIF('Ход 2029'!$G$29:$G$38,$A14,'Ход 2029'!$I$29:$I$38)*(1+'Эффекты технологий'!M$7) -> 0 | O14: =SUMIF('Ход 2030'!$G$29:$G$38,$A14,'Ход 2030'!$I$29:$I$38)*(1+'Эффекты технологий'!N$7) -> 0 | P14: =SUMIF('Ход 2031'!$G$29:$G$38,$A14,'Ход 2031'!$I$29:$I$38)*(1+'Эффекты технологий'!O$7) -> 0 | Q14: =SUMIF('Ход 2032'!$G$29:$G$38,$A14,'Ход 2032'!$I$29:$I$38)*(1+'Эффекты технологий'!P$7) -> 0 | R14: =SUMIF('Ход 2033'!$G$29:$G$38,$A14,'Ход 2033'!$I$29:$I$38)*(1+'Эффекты технологий'!Q$7) -> 0 | S14: =SUMIF('Ход 2034'!$G$29:$G$38,$A14,'Ход 2034'!$I$29:$I$38)*(1+'Эффекты технологий'!R$7) -> 0 | T14: =SUMIF('Ход 2035'!$G$29:$G$38,$A14,'Ход 2035'!$I$29:$I$38)*(1+'Эффекты технологий'!S$7) -> 0 | U14: =SUMIF('Ход 2036'!$G$29:$G$38,$A14,'Ход 2036'!$I$29:$I$38)*(1+'Эффекты технологий'!T$7) -> 0 | V14: =SUMIF('Ход 2037'!$G$29:$G$38,$A14,'Ход 2037'!$I$29:$I$38)*(1+'Эффекты технологий'!U$7) -> 0 | W14: =SUMIF('Ход 2038'!$G$29:$G$38,$A14,'Ход 2038'!$I$29:$I$38)*(1+'Эффекты технологий'!V$7) -> 0 | X14: =SUMIF('Ход 2039'!$G$29:$G$38,$A14,'Ход 2039'!$I$29:$I$38)*(1+'Эффекты технологий'!W$7) -> 0 | Y14: =SUMIF('Ход 2040'!$G$29:$G$38,$A14,'Ход 2040'!$I$29:$I$38)*(1+'Эффекты технологий'!X$7) -> 0 | Z14: =SUM(K14:Y14) -> 0 | AA14: =MAX(0,E14-Z14) -> 65 | AB14: =BF14 -> ОТКРЫТО | AC14: =SUM($K14:K14) -> 0 | AD14: =SUM($K14:L14) -> 0 | AE14: =SUM($K14:M14) -> 0 | AF14: =SUM($K14:N14) -> 0 | AG14: =SUM($K14:O14) -> 0 | AH14: =SUM($K14:P14) -> 0 | AI14: =SUM($K14:Q14) -> 0 | AJ14: =SUM($K14:R14) -> 0 | ... AQ14: =SUM($K14:Y14) -> 0 | AR14: =IF(AND(AC14>=$E14,TRUE),"ИЗУЧЕНО",IF(TRUE,"ОТКРЫТО","ЗАКРЫТО")) -> ОТКРЫТО | AS14: =IF(AND(AD14>=$E14,TRUE),"ИЗУЧЕНО",IF(TRUE,"ОТКРЫТО","ЗАКРЫТО")) -> ОТКРЫТО | AT14: =IF(AND(AE14>=$E14,TRUE),"ИЗУЧЕНО",IF(TRUE,"ОТКРЫТО","ЗАКРЫТО")) -> ОТКРЫТО | AU14: =IF(AND(AF14>=$E14,TRUE),"ИЗУЧЕНО",IF(TRUE,"ОТКРЫТО","ЗАКРЫТО")) -> ОТКРЫТО | AV14: =IF(AND(AG14>=$E14,TRUE),"ИЗУЧЕНО",IF(TRUE,"ОТКРЫТО","ЗАКРЫТО")) -> ОТКРЫТО | AW14: =IF(AND(AH14>=$E14,TRUE),"ИЗУЧЕНО",IF(TRUE,"ОТКРЫТО","ЗАКРЫТО")) -> ОТКРЫТО | AX14: =IF(AND(AI14>=$E14,TRUE),"ИЗУЧЕНО",IF(TRUE,"ОТКРЫТО","ЗАКРЫТО")) -> ОТКРЫТО | AY14: =IF(AND(AJ14>=$E14,TRUE),"ИЗУЧЕНО",IF(TRUE,"ОТКРЫТО","ЗАКРЫТО")) -> ОТКРЫТО | ... BF14: =IF(AND(AQ14>=$E14,TRUE),"ИЗУЧЕНО",IF(TRUE,"ОТКРЫТО","ЗАКРЫТО")) -> ОТКРЫТО | BG14: =IFERROR(2025+MATCH("ИЗУЧЕНО",AR14:BF14,0),"") | BH14: =IF(BG14="","",BG14+1)
A15: C5 | B15: Вычисления и аппаратная база | C15: IV | D15: Распределённые ЦОД с оптическими магистралями | E15: 100 | F15: C4 | I15: Географически разделённые вычислительные центры связываются оптическими каналами высокой пропускной способности и могут совместно предоставлять вычисления для обучения и эксплуатации моделей. Такая архитектура повышает устойчивость инфраструктуры и даёт преимущество в борьбе за цифровые потоки, что отражено бонусом к защите от войны Афины. Однако страна вынуждена размещать новые площадки, создавать энергоузлы и охлаждение, прокладывать сетевые магистрали. Поэтому увеличение цифровой устойчивости оплачивается тремя материальными ограничениями. | J15: + Сетевые ресурсы: +0,50; + ЦОД и вычислительная инфраструктура: +0,35; + Интеграционные ресурсы: +0,25; + Стек эксплуатации ИИ: +0,20; + Защита от войны Афины: +15%; − Энергетические ресурсы: -0,35; − Вода и ресурс отвода тепла: -0,25; − Пространственные и природно-географические ресурсы: -0,20 | K15: =SUMIF('Ход 2026'!$G$29:$G$38,$A15,'Ход 2026'!$I$29:$I$38)*(1+'Эффекты технологий'!J$7) -> 0 | L15: =SUMIF('Ход 2027'!$G$29:$G$38,$A15,'Ход 2027'!$I$29:$I$38)*(1+'Эффекты технологий'!K$7) -> 0 | M15: =SUMIF('Ход 2028'!$G$29:$G$38,$A15,'Ход 2028'!$I$29:$I$38)*(1+'Эффекты технологий'!L$7) -> 0 | N15: =SUMIF('Ход 2029'!$G$29:$G$38,$A15,'Ход 2029'!$I$29:$I$38)*(1+'Эффекты технологий'!M$7) -> 0 | O15: =SUMIF('Ход 2030'!$G$29:$G$38,$A15,'Ход 2030'!$I$29:$I$38)*(1+'Эффекты технологий'!N$7) -> 0 | P15: =SUMIF('Ход 2031'!$G$29:$G$38,$A15,'Ход 2031'!$I$29:$I$38)*(1+'Эффекты технологий'!O$7) -> 0 | Q15: =SUMIF('Ход 2032'!$G$29:$G$38,$A15,'Ход 2032'!$I$29:$I$38)*(1+'Эффекты технологий'!P$7) -> 0 | R15: =SUMIF('Ход 2033'!$G$29:$G$38,$A15,'Ход 2033'!$I$29:$I$38)*(1+'Эффекты технологий'!Q$7) -> 0 | S15: =SUMIF('Ход 2034'!$G$29:$G$38,$A15,'Ход 2034'!$I$29:$I$38)*(1+'Эффекты технологий'!R$7) -> 0 | T15: =SUMIF('Ход 2035'!$G$29:$G$38,$A15,'Ход 2035'!$I$29:$I$38)*(1+'Эффекты технологий'!S$7) -> 0 | U15: =SUMIF('Ход 2036'!$G$29:$G$38,$A15,'Ход 2036'!$I$29:$I$38)*(1+'Эффекты технологий'!T$7) -> 0 | V15: =SUMIF('Ход 2037'!$G$29:$G$38,$A15,'Ход 2037'!$I$29:$I$38)*(1+'Эффекты технологий'!U$7) -> 0 | W15: =SUMIF('Ход 2038'!$G$29:$G$38,$A15,'Ход 2038'!$I$29:$I$38)*(1+'Эффекты технологий'!V$7) -> 0 | X15: =SUMIF('Ход 2039'!$G$29:$G$38,$A15,'Ход 2039'!$I$29:$I$38)*(1+'Эффекты технологий'!W$7) -> 0 | Y15: =SUMIF('Ход 2040'!$G$29:$G$38,$A15,'Ход 2040'!$I$29:$I$38)*(1+'Эффекты технологий'!X$7) -> 0 | Z15: =SUM(K15:Y15) -> 0 | AA15: =MAX(0,E15-Z15) -> 100 | AB15: =BF15 -> ОТКРЫТО | AC15: =SUM($K15:K15) -> 0 | AD15: =SUM($K15:L15) -> 0 | AE15: =SUM($K15:M15) -> 0 | AF15: =SUM($K15:N15) -> 0 | AG15: =SUM($K15:O15) -> 0 | AH15: =SUM($K15:P15) -> 0 | AI15: =SUM($K15:Q15) -> 0 | AJ15: =SUM($K15:R15) -> 0 | ... AQ15: =SUM($K15:Y15) -> 0 | AR15: =IF(AND(AC15>=$E15,TRUE),"ИЗУЧЕНО",IF(TRUE,"ОТКРЫТО","ЗАКРЫТО")) -> ОТКРЫТО | AS15: =IF(AND(AD15>=$E15,TRUE),"ИЗУЧЕНО",IF(TRUE,"ОТКРЫТО","ЗАКРЫТО")) -> ОТКРЫТО | AT15: =IF(AND(AE15>=$E15,TRUE),"ИЗУЧЕНО",IF(TRUE,"ОТКРЫТО","ЗАКРЫТО")) -> ОТКРЫТО | AU15: =IF(AND(AF15>=$E15,TRUE),"ИЗУЧЕНО",IF(TRUE,"ОТКРЫТО","ЗАКРЫТО")) -> ОТКРЫТО | AV15: =IF(AND(AG15>=$E15,TRUE),"ИЗУЧЕНО",IF(TRUE,"ОТКРЫТО","ЗАКРЫТО")) -> ОТКРЫТО | AW15: =IF(AND(AH15>=$E15,TRUE),"ИЗУЧЕНО",IF(TRUE,"ОТКРЫТО","ЗАКРЫТО")) -> ОТКРЫТО | AX15: =IF(AND(AI15>=$E15,TRUE),"ИЗУЧЕНО",IF(TRUE,"ОТКРЫТО","ЗАКРЫТО")) -> ОТКРЫТО | AY15: =IF(AND(AJ15>=$E15,TRUE),"ИЗУЧЕНО",IF(TRUE,"ОТКРЫТО","ЗАКРЫТО")) -> ОТКРЫТО | ... BF15: =IF(AND(AQ15>=$E15,TRUE),"ИЗУЧЕНО",IF(TRUE,"ОТКРЫТО","ЗАКРЫТО")) -> ОТКРЫТО | BG15: =IFERROR(2025+MATCH("ИЗУЧЕНО",AR15:BF15,0),"") | BH15: =IF(BG15="","",BG15+1)
A16: C6 | B16: Вычисления и аппаратная база | C16: V | D16: Фотонно-нейроморфные вычислительные комплексы | E16: 150 | F16: C5 | I16: Высший уровень ветви объединяет исследования новых принципов аппаратной обработки информации: фотонных вычислительных элементов, нейроморфных структур и их интеграции с обычными процессорами. В игровом мире это дорогостоящие комплексы, которые расширяют как вычислительную базу, так и возможности создания моделей. Исследования ветви M становятся эффективнее. Несмотря на потенциальную экономичность отдельных операций, массовое изготовление и развёртывание инфраструктуры остаётся чрезвычайно материалоёмким и создаёт четыре вида ресурсной нагрузки. | J16: + Вычислительные компоненты: +0,50; + Математико-алгоритмические ресурсы: +0,35; + Мощности производства полупроводников: +0,35; + Модельные ресурсы: +0,25; + Прирост ЦОД и вычислительной инфраструктуры: +0,10/год; + Эффективность науки для ветви M: +10%; − Минерально-сырьевые ресурсы: -0,45; − Энергетические ресурсы: -0,50; − Вода и ресурс отвода тепла: -0,40; − Пространственные и природно-географические ресурсы: -0,30 | K16: =SUMIF('Ход 2026'!$G$29:$G$38,$A16,'Ход 2026'!$I$29:$I$38)*(1+'Эффекты технологий'!J$7) -> 0 | L16: =SUMIF('Ход 2027'!$G$29:$G$38,$A16,'Ход 2027'!$I$29:$I$38)*(1+'Эффекты технологий'!K$7) -> 0 | M16: =SUMIF('Ход 2028'!$G$29:$G$38,$A16,'Ход 2028'!$I$29:$I$38)*(1+'Эффекты технологий'!L$7) -> 0 | N16: =SUMIF('Ход 2029'!$G$29:$G$38,$A16,'Ход 2029'!$I$29:$I$38)*(1+'Эффекты технологий'!M$7) -> 0 | O16: =SUMIF('Ход 2030'!$G$29:$G$38,$A16,'Ход 2030'!$I$29:$I$38)*(1+'Эффекты технологий'!N$7) -> 0 | P16: =SUMIF('Ход 2031'!$G$29:$G$38,$A16,'Ход 2031'!$I$29:$I$38)*(1+'Эффекты технологий'!O$7) -> 0 | Q16: =SUMIF('Ход 2032'!$G$29:$G$38,$A16,'Ход 2032'!$I$29:$I$38)*(1+'Эффекты технологий'!P$7) -> 0 | R16: =SUMIF('Ход 2033'!$G$29:$G$38,$A16,'Ход 2033'!$I$29:$I$38)*(1+'Эффекты технологий'!Q$7) -> 0 | S16: =SUMIF('Ход 2034'!$G$29:$G$38,$A16,'Ход 2034'!$I$29:$I$38)*(1+'Эффекты технологий'!R$7) -> 0 | T16: =SUMIF('Ход 2035'!$G$29:$G$38,$A16,'Ход 2035'!$I$29:$I$38)*(1+'Эффекты технологий'!S$7) -> 0 | U16: =SUMIF('Ход 2036'!$G$29:$G$38,$A16,'Ход 2036'!$I$29:$I$38)*(1+'Эффекты технологий'!T$7) -> 0 | V16: =SUMIF('Ход 2037'!$G$29:$G$38,$A16,'Ход 2037'!$I$29:$I$38)*(1+'Эффекты технологий'!U$7) -> 0 | W16: =SUMIF('Ход 2038'!$G$29:$G$38,$A16,'Ход 2038'!$I$29:$I$38)*(1+'Эффекты технологий'!V$7) -> 0 | X16: =SUMIF('Ход 2039'!$G$29:$G$38,$A16,'Ход 2039'!$I$29:$I$38)*(1+'Эффекты технологий'!W$7) -> 0 | Y16: =SUMIF('Ход 2040'!$G$29:$G$38,$A16,'Ход 2040'!$I$29:$I$38)*(1+'Эффекты технологий'!X$7) -> 0 | Z16: =SUM(K16:Y16) -> 0 | AA16: =MAX(0,E16-Z16) -> 150 | AB16: =BF16 -> ОТКРЫТО | AC16: =SUM($K16:K16) -> 0 | AD16: =SUM($K16:L16) -> 0 | AE16: =SUM($K16:M16) -> 0 | AF16: =SUM($K16:N16) -> 0 | AG16: =SUM($K16:O16) -> 0 | AH16: =SUM($K16:P16) -> 0 | AI16: =SUM($K16:Q16) -> 0 | AJ16: =SUM($K16:R16) -> 0 | ... AQ16: =SUM($K16:Y16) -> 0 | AR16: =IF(AND(AC16>=$E16,TRUE),"ИЗУЧЕНО",IF(TRUE,"ОТКРЫТО","ЗАКРЫТО")) -> ОТКРЫТО | AS16: =IF(AND(AD16>=$E16,TRUE),"ИЗУЧЕНО",IF(TRUE,"ОТКРЫТО","ЗАКРЫТО")) -> ОТКРЫТО | AT16: =IF(AND(AE16>=$E16,TRUE),"ИЗУЧЕНО",IF(TRUE,"ОТКРЫТО","ЗАКРЫТО")) -> ОТКРЫТО | AU16: =IF(AND(AF16>=$E16,TRUE),"ИЗУЧЕНО",IF(TRUE,"ОТКРЫТО","ЗАКРЫТО")) -> ОТКРЫТО | AV16: =IF(AND(AG16>=$E16,TRUE),"ИЗУЧЕНО",IF(TRUE,"ОТКРЫТО","ЗАКРЫТО")) -> ОТКРЫТО | AW16: =IF(AND(AH16>=$E16,TRUE),"ИЗУЧЕНО",IF(TRUE,"ОТКРЫТО","ЗАКРЫТО")) -> ОТКРЫТО | AX16: =IF(AND(AI16>=$E16,TRUE),"ИЗУЧЕНО",IF(TRUE,"ОТКРЫТО","ЗАКРЫТО")) -> ОТКРЫТО | AY16: =IF(AND(AJ16>=$E16,TRUE),"ИЗУЧЕНО",IF(TRUE,"ОТКРЫТО","ЗАКРЫТО")) -> ОТКРЫТО | ... BF16: =IF(AND(AQ16>=$E16,TRUE),"ИЗУЧЕНО",IF(TRUE,"ОТКРЫТО","ЗАКРЫТО")) -> ОТКРЫТО | BG16: =IFERROR(2025+MATCH("ИЗУЧЕНО",AR16:BF16,0),"") | BH16: =IF(BG16="","",BG16+1)
A17: M1 | B17: Модели и алгоритмы | C17: I | D17: Обучение нейросетей со смешанной точностью и адаптивными оптимизаторами | E17: 20 | I17: Смешанная точность использует числовые представления разной разрядности для ускорения обучения без обязательного перехода к более мощному оборудованию. Адаптивные оптимизаторы изменяют величину шагов обучения для разных параметров нейросети. Вместе эти приёмы повышают технологическую культуру разработки моделей и позволяют эффективнее использовать имеющиеся ресурсы. Это базовое алгоритмическое усовершенствование: оно даёт один положительный эффект и ещё не требует дополнительного штрафа к ресурсам страны. | J17: + Методы построения и совершенствования моделей: +0,20 | K17: =SUMIF('Ход 2026'!$G$29:$G$38,$A17,'Ход 2026'!$I$29:$I$38)*(1+'Эффекты технологий'!J$7+'Эффекты технологий'!J$8+'Эффекты технологий'!J$9) -> 0 | L17: =SUMIF('Ход 2027'!$G$29:$G$38,$A17,'Ход 2027'!$I$29:$I$38)*(1+'Эффекты технологий'!K$7+'Эффекты технологий'!K$8+'Эффекты технологий'!K$9) -> 0 | M17: =SUMIF('Ход 2028'!$G$29:$G$38,$A17,'Ход 2028'!$I$29:$I$38)*(1+'Эффекты технологий'!L$7+'Эффекты технологий'!L$8+'Эффекты технологий'!L$9) -> 0 | N17: =SUMIF('Ход 2029'!$G$29:$G$38,$A17,'Ход 2029'!$I$29:$I$38)*(1+'Эффекты технологий'!M$7+'Эффекты технологий'!M$8+'Эффекты технологий'!M$9) -> 0 | O17: =SUMIF('Ход 2030'!$G$29:$G$38,$A17,'Ход 2030'!$I$29:$I$38)*(1+'Эффекты технологий'!N$7+'Эффекты технологий'!N$8+'Эффекты технологий'!N$9) -> 0 | P17: =SUMIF('Ход 2031'!$G$29:$G$38,$A17,'Ход 2031'!$I$29:$I$38)*(1+'Эффекты технологий'!O$7+'Эффекты технологий'!O$8+'Эффекты технологий'!O$9) -> 0 | Q17: =SUMIF('Ход 2032'!$G$29:$G$38,$A17,'Ход 2032'!$I$29:$I$38)*(1+'Эффекты технологий'!P$7+'Эффекты технологий'!P$8+'Эффекты технологий'!P$9) -> 0 | R17: =SUMIF('Ход 2033'!$G$29:$G$38,$A17,'Ход 2033'!$I$29:$I$38)*(1+'Эффекты технологий'!Q$7+'Эффекты технологий'!Q$8+'Эффекты технологий'!Q$9) -> 0 | S17: =SUMIF('Ход 2034'!$G$29:$G$38,$A17,'Ход 2034'!$I$29:$I$38)*(1+'Эффекты технологий'!R$7+'Эффекты технологий'!R$8+'Эффекты технологий'!R$9) -> 0 | T17: =SUMIF('Ход 2035'!$G$29:$G$38,$A17,'Ход 2035'!$I$29:$I$38)*(1+'Эффекты технологий'!S$7+'Эффекты технологий'!S$8+'Эффекты технологий'!S$9) -> 0 | U17: =SUMIF('Ход 2036'!$G$29:$G$38,$A17,'Ход 2036'!$I$29:$I$38)*(1+'Эффекты технологий'!T$7+'Эффекты технологий'!T$8+'Эффекты технологий'!T$9) -> 0 | V17: =SUMIF('Ход 2037'!$G$29:$G$38,$A17,'Ход 2037'!$I$29:$I$38)*(1+'Эффекты технологий'!U$7+'Эффекты технологий'!U$8+'Эффекты технологий'!U$9) -> 0 | W17: =SUMIF('Ход 2038'!$G$29:$G$38,$A17,'Ход 2038'!$I$29:$I$38)*(1+'Эффекты технологий'!V$7+'Эффекты технологий'!V$8+'Эффекты технологий'!V$9) -> 0 | X17: =SUMIF('Ход 2039'!$G$29:$G$38,$A17,'Ход 2039'!$I$29:$I$38)*(1+'Эффекты технологий'!W$7+'Эффекты технологий'!W$8+'Эффекты технологий'!W$9) -> 0 | Y17: =SUMIF('Ход 2040'!$G$29:$G$38,$A17,'Ход 2040'!$I$29:$I$38)*(1+'Эффекты технологий'!X$7+'Эффекты технологий'!X$8+'Эффекты технологий'!X$9) -> 0 | Z17: =SUM(K17:Y17) -> 0 | AA17: =MAX(0,E17-Z17) -> 20 | AB17: =BF17 -> ОТКРЫТО | AC17: =SUM($K17:K17) -> 0 | AD17: =SUM($K17:L17) -> 0 | AE17: =SUM($K17:M17) -> 0 | AF17: =SUM($K17:N17) -> 0 | AG17: =SUM($K17:O17) -> 0 | AH17: =SUM($K17:P17) -> 0 | AI17: =SUM($K17:Q17) -> 0 | AJ17: =SUM($K17:R17) -> 0 | ... AQ17: =SUM($K17:Y17) -> 0 | AR17: =IF(AND(AC17>=$E17,TRUE),"ИЗУЧЕНО",IF(TRUE,"ОТКРЫТО","ЗАКРЫТО")) -> ОТКРЫТО | AS17: =IF(AND(AD17>=$E17,TRUE),"ИЗУЧЕНО",IF(TRUE,"ОТКРЫТО","ЗАКРЫТО")) -> ОТКРЫТО | AT17: =IF(AND(AE17>=$E17,TRUE),"ИЗУЧЕНО",IF(TRUE,"ОТКРЫТО","ЗАКРЫТО")) -> ОТКРЫТО | AU17: =IF(AND(AF17>=$E17,TRUE),"ИЗУЧЕНО",IF(TRUE,"ОТКРЫТО","ЗАКРЫТО")) -> ОТКРЫТО | AV17: =IF(AND(AG17>=$E17,TRUE),"ИЗУЧЕНО",IF(TRUE,"ОТКРЫТО","ЗАКРЫТО")) -> ОТКРЫТО | AW17: =IF(AND(AH17>=$E17,TRUE),"ИЗУЧЕНО",IF(TRUE,"ОТКРЫТО","ЗАКРЫТО")) -> ОТКРЫТО | AX17: =IF(AND(AI17>=$E17,TRUE),"ИЗУЧЕНО",IF(TRUE,"ОТКРЫТО","ЗАКРЫТО")) -> ОТКРЫТО | AY17: =IF(AND(AJ17>=$E17,TRUE),"ИЗУЧЕНО",IF(TRUE,"ОТКРЫТО","ЗАКРЫТО")) -> ОТКРЫТО | ... BF17: =IF(AND(AQ17>=$E17,TRUE),"ИЗУЧЕНО",IF(TRUE,"ОТКРЫТО","ЗАКРЫТО")) -> ОТКРЫТО | BG17: =IFERROR(2025+MATCH("ИЗУЧЕНО",AR17:BF17,0),"") | BH17: =IF(BG17="","",BG17+1)
A18: M2 | B18: Модели и алгоритмы | C18: II | D18: Мультимодальные трансформеры с перекрёстным вниманием | E18: 40 | F18: M1 | I18: Мультимодальный трансформер объединяет текст, изображения, звук и другие виды информации в одной модели. Механизмы перекрёстного внимания позволяют связывать представления разных модальностей. Страна получает более богатые модельные ресурсы и средство воздействия на информационные смыслы, поэтому усиливается атака в войне Аполлона. Обучение и обслуживание таких систем требуют дополнительной вычислительной мощности и электроэнергии, что выражено небольшим энергетическим штрафом. | J18: + Модельные ресурсы: +0,30; + Атака в войне Аполлона: +10%; − Энергетические ресурсы: -0,15 | K18: =SUMIF('Ход 2026'!$G$29:$G$38,$A18,'Ход 2026'!$I$29:$I$38)*(1+'Эффекты технологий'!J$7+'Эффекты технологий'!J$8+'Эффекты технологий'!J$9) -> 0 | L18: =SUMIF('Ход 2027'!$G$29:$G$38,$A18,'Ход 2027'!$I$29:$I$38)*(1+'Эффекты технологий'!K$7+'Эффекты технологий'!K$8+'Эффекты технологий'!K$9) -> 0 | M18: =SUMIF('Ход 2028'!$G$29:$G$38,$A18,'Ход 2028'!$I$29:$I$38)*(1+'Эффекты технологий'!L$7+'Эффекты технологий'!L$8+'Эффекты технологий'!L$9) -> 0 | N18: =SUMIF('Ход 2029'!$G$29:$G$38,$A18,'Ход 2029'!$I$29:$I$38)*(1+'Эффекты технологий'!M$7+'Эффекты технологий'!M$8+'Эффекты технологий'!M$9) -> 0 | O18: =SUMIF('Ход 2030'!$G$29:$G$38,$A18,'Ход 2030'!$I$29:$I$38)*(1+'Эффекты технологий'!N$7+'Эффекты технологий'!N$8+'Эффекты технологий'!N$9) -> 0 | P18: =SUMIF('Ход 2031'!$G$29:$G$38,$A18,'Ход 2031'!$I$29:$I$38)*(1+'Эффекты технологий'!O$7+'Эффекты технологий'!O$8+'Эффекты технологий'!O$9) -> 0 | Q18: =SUMIF('Ход 2032'!$G$29:$G$38,$A18,'Ход 2032'!$I$29:$I$38)*(1+'Эффекты технологий'!P$7+'Эффекты технологий'!P$8+'Эффекты технологий'!P$9) -> 0 | R18: =SUMIF('Ход 2033'!$G$29:$G$38,$A18,'Ход 2033'!$I$29:$I$38)*(1+'Эффекты технологий'!Q$7+'Эффекты технологий'!Q$8+'Эффекты технологий'!Q$9) -> 0 | S18: =SUMIF('Ход 2034'!$G$29:$G$38,$A18,'Ход 2034'!$I$29:$I$38)*(1+'Эффекты технологий'!R$7+'Эффекты технологий'!R$8+'Эффекты технологий'!R$9) -> 0 | T18: =SUMIF('Ход 2035'!$G$29:$G$38,$A18,'Ход 2035'!$I$29:$I$38)*(1+'Эффекты технологий'!S$7+'Эффекты технологий'!S$8+'Эффекты технологий'!S$9) -> 0 | U18: =SUMIF('Ход 2036'!$G$29:$G$38,$A18,'Ход 2036'!$I$29:$I$38)*(1+'Эффекты технологий'!T$7+'Эффекты технологий'!T$8+'Эффекты технологий'!T$9) -> 0 | V18: =SUMIF('Ход 2037'!$G$29:$G$38,$A18,'Ход 2037'!$I$29:$I$38)*(1+'Эффекты технологий'!U$7+'Эффекты технологий'!U$8+'Эффекты технологий'!U$9) -> 0 | W18: =SUMIF('Ход 2038'!$G$29:$G$38,$A18,'Ход 2038'!$I$29:$I$38)*(1+'Эффекты технологий'!V$7+'Эффекты технологий'!V$8+'Эффекты технологий'!V$9) -> 0 | X18: =SUMIF('Ход 2039'!$G$29:$G$38,$A18,'Ход 2039'!$I$29:$I$38)*(1+'Эффекты технологий'!W$7+'Эффекты технологий'!W$8+'Эффекты технологий'!W$9) -> 0 | Y18: =SUMIF('Ход 2040'!$G$29:$G$38,$A18,'Ход 2040'!$I$29:$I$38)*(1+'Эффекты технологий'!X$7+'Эффекты технологий'!X$8+'Эффекты технологий'!X$9) -> 0 | Z18: =SUM(K18:Y18) -> 0 | AA18: =MAX(0,E18-Z18) -> 40 | AB18: =BF18 -> ОТКРЫТО | AC18: =SUM($K18:K18) -> 0 | AD18: =SUM($K18:L18) -> 0 | AE18: =SUM($K18:M18) -> 0 | AF18: =SUM($K18:N18) -> 0 | AG18: =SUM($K18:O18) -> 0 | AH18: =SUM($K18:P18) -> 0 | AI18: =SUM($K18:Q18) -> 0 | AJ18: =SUM($K18:R18) -> 0 | ... AQ18: =SUM($K18:Y18) -> 0 | AR18: =IF(AND(AC18>=$E18,TRUE),"ИЗУЧЕНО",IF(TRUE,"ОТКРЫТО","ЗАКРЫТО")) -> ОТКРЫТО | AS18: =IF(AND(AD18>=$E18,TRUE),"ИЗУЧЕНО",IF(TRUE,"ОТКРЫТО","ЗАКРЫТО")) -> ОТКРЫТО | AT18: =IF(AND(AE18>=$E18,TRUE),"ИЗУЧЕНО",IF(TRUE,"ОТКРЫТО","ЗАКРЫТО")) -> ОТКРЫТО | AU18: =IF(AND(AF18>=$E18,TRUE),"ИЗУЧЕНО",IF(TRUE,"ОТКРЫТО","ЗАКРЫТО")) -> ОТКРЫТО | AV18: =IF(AND(AG18>=$E18,TRUE),"ИЗУЧЕНО",IF(TRUE,"ОТКРЫТО","ЗАКРЫТО")) -> ОТКРЫТО | AW18: =IF(AND(AH18>=$E18,TRUE),"ИЗУЧЕНО",IF(TRUE,"ОТКРЫТО","ЗАКРЫТО")) -> ОТКРЫТО | AX18: =IF(AND(AI18>=$E18,TRUE),"ИЗУЧЕНО",IF(TRUE,"ОТКРЫТО","ЗАКРЫТО")) -> ОТКРЫТО | AY18: =IF(AND(AJ18>=$E18,TRUE),"ИЗУЧЕНО",IF(TRUE,"ОТКРЫТО","ЗАКРЫТО")) -> ОТКРЫТО | ... BF18: =IF(AND(AQ18>=$E18,TRUE),"ИЗУЧЕНО",IF(TRUE,"ОТКРЫТО","ЗАКРЫТО")) -> ОТКРЫТО | BG18: =IFERROR(2025+MATCH("ИЗУЧЕНО",AR18:BF18,0),"") | BH18: =IF(BG18="","",BG18+1)
A19: M3 | B19: Модели и алгоритмы | C19: II | D19: Нейросетевые модели рассуждения с поиском и проверкой решений | E19: 45 | F19: M1 | I19: Модель не ограничивается однократной генерацией ответа: она предлагает несколько вариантов решения, выполняет поиск по альтернативам и применяет процедуры проверки. Такой подход полезен в сложных задачах планирования и анализа, где результат можно оценивать по внешним критериям. Технология одновременно улучшает методическую базу, познание и оценку моделей. Плата за это - дополнительные вычисления при каждом сложном запросе, а значит, повышенная энергетическая нагрузка. | J19: + Методы построения и совершенствования моделей: +0,30; + Прирост сферы «Познание»: +0,08/год; + Ресурсы оценки: +0,20; − Энергетические ресурсы: -0,25 | K19: =SUMIF('Ход 2026'!$G$29:$G$38,$A19,'Ход 2026'!$I$29:$I$38)*(1+'Эффекты технологий'!J$7+'Эффекты технологий'!J$8+'Эффекты технологий'!J$9) -> 0 | L19: =SUMIF('Ход 2027'!$G$29:$G$38,$A19,'Ход 2027'!$I$29:$I$38)*(1+'Эффекты технологий'!K$7+'Эффекты технологий'!K$8+'Эффекты технологий'!K$9) -> 0 | M19: =SUMIF('Ход 2028'!$G$29:$G$38,$A19,'Ход 2028'!$I$29:$I$38)*(1+'Эффекты технологий'!L$7+'Эффекты технологий'!L$8+'Эффекты технологий'!L$9) -> 0 | N19: =SUMIF('Ход 2029'!$G$29:$G$38,$A19,'Ход 2029'!$I$29:$I$38)*(1+'Эффекты технологий'!M$7+'Эффекты технологий'!M$8+'Эффекты технологий'!M$9) -> 0 | O19: =SUMIF('Ход 2030'!$G$29:$G$38,$A19,'Ход 2030'!$I$29:$I$38)*(1+'Эффекты технологий'!N$7+'Эффекты технологий'!N$8+'Эффекты технологий'!N$9) -> 0 | P19: =SUMIF('Ход 2031'!$G$29:$G$38,$A19,'Ход 2031'!$I$29:$I$38)*(1+'Эффекты технологий'!O$7+'Эффекты технологий'!O$8+'Эффекты технологий'!O$9) -> 0 | Q19: =SUMIF('Ход 2032'!$G$29:$G$38,$A19,'Ход 2032'!$I$29:$I$38)*(1+'Эффекты технологий'!P$7+'Эффекты технологий'!P$8+'Эффекты технологий'!P$9) -> 0 | R19: =SUMIF('Ход 2033'!$G$29:$G$38,$A19,'Ход 2033'!$I$29:$I$38)*(1+'Эффекты технологий'!Q$7+'Эффекты технологий'!Q$8+'Эффекты технологий'!Q$9) -> 0 | S19: =SUMIF('Ход 2034'!$G$29:$G$38,$A19,'Ход 2034'!$I$29:$I$38)*(1+'Эффекты технологий'!R$7+'Эффекты технологий'!R$8+'Эффекты технологий'!R$9) -> 0 | T19: =SUMIF('Ход 2035'!$G$29:$G$38,$A19,'Ход 2035'!$I$29:$I$38)*(1+'Эффекты технологий'!S$7+'Эффекты технологий'!S$8+'Эффекты технологий'!S$9) -> 0 | U19: =SUMIF('Ход 2036'!$G$29:$G$38,$A19,'Ход 2036'!$I$29:$I$38)*(1+'Эффекты технологий'!T$7+'Эффекты технологий'!T$8+'Эффекты технологий'!T$9) -> 0 | V19: =SUMIF('Ход 2037'!$G$29:$G$38,$A19,'Ход 2037'!$I$29:$I$38)*(1+'Эффекты технологий'!U$7+'Эффекты технологий'!U$8+'Эффекты технологий'!U$9) -> 0 | W19: =SUMIF('Ход 2038'!$G$29:$G$38,$A19,'Ход 2038'!$I$29:$I$38)*(1+'Эффекты технологий'!V$7+'Эффекты технологий'!V$8+'Эффекты технологий'!V$9) -> 0 | X19: =SUMIF('Ход 2039'!$G$29:$G$38,$A19,'Ход 2039'!$I$29:$I$38)*(1+'Эффекты технологий'!W$7+'Эффекты технологий'!W$8+'Эффекты технологий'!W$9) -> 0 | Y19: =SUMIF('Ход 2040'!$G$29:$G$38,$A19,'Ход 2040'!$I$29:$I$38)*(1+'Эффекты технологий'!X$7+'Эффекты технологий'!X$8+'Эффекты технологий'!X$9) -> 0 | Z19: =SUM(K19:Y19) -> 0 | AA19: =MAX(0,E19-Z19) -> 45 | AB19: =BF19 -> ОТКРЫТО | AC19: =SUM($K19:K19) -> 0 | AD19: =SUM($K19:L19) -> 0 | AE19: =SUM($K19:M19) -> 0 | AF19: =SUM($K19:N19) -> 0 | AG19: =SUM($K19:O19) -> 0 | AH19: =SUM($K19:P19) -> 0 | AI19: =SUM($K19:Q19) -> 0 | AJ19: =SUM($K19:R19) -> 0 | ... AQ19: =SUM($K19:Y19) -> 0 | AR19: =IF(AND(AC19>=$E19,TRUE),"ИЗУЧЕНО",IF(TRUE,"ОТКРЫТО","ЗАКРЫТО")) -> ОТКРЫТО | AS19: =IF(AND(AD19>=$E19,TRUE),"ИЗУЧЕНО",IF(TRUE,"ОТКРЫТО","ЗАКРЫТО")) -> ОТКРЫТО | AT19: =IF(AND(AE19>=$E19,TRUE),"ИЗУЧЕНО",IF(TRUE,"ОТКРЫТО","ЗАКРЫТО")) -> ОТКРЫТО | AU19: =IF(AND(AF19>=$E19,TRUE),"ИЗУЧЕНО",IF(TRUE,"ОТКРЫТО","ЗАКРЫТО")) -> ОТКРЫТО | AV19: =IF(AND(AG19>=$E19,TRUE),"ИЗУЧЕНО",IF(TRUE,"ОТКРЫТО","ЗАКРЫТО")) -> ОТКРЫТО | AW19: =IF(AND(AH19>=$E19,TRUE),"ИЗУЧЕНО",IF(TRUE,"ОТКРЫТО","ЗАКРЫТО")) -> ОТКРЫТО | AX19: =IF(AND(AI19>=$E19,TRUE),"ИЗУЧЕНО",IF(TRUE,"ОТКРЫТО","ЗАКРЫТО")) -> ОТКРЫТО | AY19: =IF(AND(AJ19>=$E19,TRUE),"ИЗУЧЕНО",IF(TRUE,"ОТКРЫТО","ЗАКРЫТО")) -> ОТКРЫТО | ... BF19: =IF(AND(AQ19>=$E19,TRUE),"ИЗУЧЕНО",IF(TRUE,"ОТКРЫТО","ЗАКРЫТО")) -> ОТКРЫТО | BG19: =IFERROR(2025+MATCH("ИЗУЧЕНО",AR19:BF19,0),"") | BH19: =IF(BG19="","",BG19+1)
A20: M4 | B20: Модели и алгоритмы | C20: III | D20: Непрерывное обучение нейросетей с адаптерами и буферами воспроизведения | E20: 65 | F20: M2 | G20: M3 | I20: Адаптеры позволяют обновлять отдельные части модели, а буферы воспроизведения - повторно использовать прошлые данные, уменьшая риск забывания ранее освоенных задач. Такие модели быстрее приспосабливаются к изменяющейся среде и полезны для управленческих процессов. Постоянные обновления требуют непрерывной оценки качества, дополнительных вычислений и контроля безопасности. Поэтому технология увеличивает четыре показателя, но одновременно нагружает энергосистему и усложняет защиту модельного контура. | J20: + Модельные ресурсы: +0,40; прирост +0,08/год; + Методы построения и совершенствования моделей: +0,20; + Прирост сферы «Управление»: +0,05/год; + Ресурсы оценки: +0,20; − Энергетические ресурсы: -0,25; − Кибербезопасностные ресурсы: -0,15 | K20: =SUMIF('Ход 2026'!$G$29:$G$38,$A20,'Ход 2026'!$I$29:$I$38)*(1+'Эффекты технологий'!J$7+'Эффекты технологий'!J$8+'Эффекты технологий'!J$9) -> 0 | L20: =SUMIF('Ход 2027'!$G$29:$G$38,$A20,'Ход 2027'!$I$29:$I$38)*(1+'Эффекты технологий'!K$7+'Эффекты технологий'!K$8+'Эффекты технологий'!K$9) -> 0 | M20: =SUMIF('Ход 2028'!$G$29:$G$38,$A20,'Ход 2028'!$I$29:$I$38)*(1+'Эффекты технологий'!L$7+'Эффекты технологий'!L$8+'Эффекты технологий'!L$9) -> 0 | N20: =SUMIF('Ход 2029'!$G$29:$G$38,$A20,'Ход 2029'!$I$29:$I$38)*(1+'Эффекты технологий'!M$7+'Эффекты технологий'!M$8+'Эффекты технологий'!M$9) -> 0 | O20: =SUMIF('Ход 2030'!$G$29:$G$38,$A20,'Ход 2030'!$I$29:$I$38)*(1+'Эффекты технологий'!N$7+'Эффекты технологий'!N$8+'Эффекты технологий'!N$9) -> 0 | P20: =SUMIF('Ход 2031'!$G$29:$G$38,$A20,'Ход 2031'!$I$29:$I$38)*(1+'Эффекты технологий'!O$7+'Эффекты технологий'!O$8+'Эффекты технологий'!O$9) -> 0 | Q20: =SUMIF('Ход 2032'!$G$29:$G$38,$A20,'Ход 2032'!$I$29:$I$38)*(1+'Эффекты технологий'!P$7+'Эффекты технологий'!P$8+'Эффекты технологий'!P$9) -> 0 | R20: =SUMIF('Ход 2033'!$G$29:$G$38,$A20,'Ход 2033'!$I$29:$I$38)*(1+'Эффекты технологий'!Q$7+'Эффекты технологий'!Q$8+'Эффекты технологий'!Q$9) -> 0 | S20: =SUMIF('Ход 2034'!$G$29:$G$38,$A20,'Ход 2034'!$I$29:$I$38)*(1+'Эффекты технологий'!R$7+'Эффекты технологий'!R$8+'Эффекты технологий'!R$9) -> 0 | T20: =SUMIF('Ход 2035'!$G$29:$G$38,$A20,'Ход 2035'!$I$29:$I$38)*(1+'Эффекты технологий'!S$7+'Эффекты технологий'!S$8+'Эффекты технологий'!S$9) -> 0 | U20: =SUMIF('Ход 2036'!$G$29:$G$38,$A20,'Ход 2036'!$I$29:$I$38)*(1+'Эффекты технологий'!T$7+'Эффекты технологий'!T$8+'Эффекты технологий'!T$9) -> 0 | V20: =SUMIF('Ход 2037'!$G$29:$G$38,$A20,'Ход 2037'!$I$29:$I$38)*(1+'Эффекты технологий'!U$7+'Эффекты технологий'!U$8+'Эффекты технологий'!U$9) -> 0 | W20: =SUMIF('Ход 2038'!$G$29:$G$38,$A20,'Ход 2038'!$I$29:$I$38)*(1+'Эффекты технологий'!V$7+'Эффекты технологий'!V$8+'Эффекты технологий'!V$9) -> 0 | X20: =SUMIF('Ход 2039'!$G$29:$G$38,$A20,'Ход 2039'!$I$29:$I$38)*(1+'Эффекты технологий'!W$7+'Эффекты технологий'!W$8+'Эффекты технологий'!W$9) -> 0 | Y20: =SUMIF('Ход 2040'!$G$29:$G$38,$A20,'Ход 2040'!$I$29:$I$38)*(1+'Эффекты технологий'!X$7+'Эффекты технологий'!X$8+'Эффекты технологий'!X$9) -> 0 | Z20: =SUM(K20:Y20) -> 0 | AA20: =MAX(0,E20-Z20) -> 65 | AB20: =BF20 -> ОТКРЫТО | AC20: =SUM($K20:K20) -> 0 | AD20: =SUM($K20:L20) -> 0 | AE20: =SUM($K20:M20) -> 0 | AF20: =SUM($K20:N20) -> 0 | AG20: =SUM($K20:O20) -> 0 | AH20: =SUM($K20:P20) -> 0 | AI20: =SUM($K20:Q20) -> 0 | AJ20: =SUM($K20:R20) -> 0 | ... AQ20: =SUM($K20:Y20) -> 0 | AR20: =IF(AND(AC20>=$E20,TRUE),"ИЗУЧЕНО",IF(TRUE,"ОТКРЫТО","ЗАКРЫТО")) -> ОТКРЫТО | AS20: =IF(AND(AD20>=$E20,TRUE),"ИЗУЧЕНО",IF(TRUE,"ОТКРЫТО","ЗАКРЫТО")) -> ОТКРЫТО | AT20: =IF(AND(AE20>=$E20,TRUE),"ИЗУЧЕНО",IF(TRUE,"ОТКРЫТО","ЗАКРЫТО")) -> ОТКРЫТО | AU20: =IF(AND(AF20>=$E20,TRUE),"ИЗУЧЕНО",IF(TRUE,"ОТКРЫТО","ЗАКРЫТО")) -> ОТКРЫТО | AV20: =IF(AND(AG20>=$E20,TRUE),"ИЗУЧЕНО",IF(TRUE,"ОТКРЫТО","ЗАКРЫТО")) -> ОТКРЫТО | AW20: =IF(AND(AH20>=$E20,TRUE),"ИЗУЧЕНО",IF(TRUE,"ОТКРЫТО","ЗАКРЫТО")) -> ОТКРЫТО | AX20: =IF(AND(AI20>=$E20,TRUE),"ИЗУЧЕНО",IF(TRUE,"ОТКРЫТО","ЗАКРЫТО")) -> ОТКРЫТО | AY20: =IF(AND(AJ20>=$E20,TRUE),"ИЗУЧЕНО",IF(TRUE,"ОТКРЫТО","ЗАКРЫТО")) -> ОТКРЫТО | ... BF20: =IF(AND(AQ20>=$E20,TRUE),"ИЗУЧЕНО",IF(TRUE,"ОТКРЫТО","ЗАКРЫТО")) -> ОТКРЫТО | BG20: =IFERROR(2025+MATCH("ИЗУЧЕНО",AR20:BF20,0),"") | BH20: =IF(BG20="","",BG20+1)
A21: M5 | B21: Модели и алгоритмы | C21: IV | D21: Латентные модели мира с причинным и контрфактическим прогнозированием | E21: 100 | F21: M4 | I21: Модель мира строит внутреннее представление изменений среды и позволяет проверять альтернативные сценарии: что произошло бы при другом решении. Это расширяет возможности прогноза, управления и разработки стратегий в условиях неопределённости. Бонус к войне Афины отражает преимущество в борьбе за информационные потоки и принятие решений. При этом сложность модели повышает ресурсопотребление, а чрезмерная опора на непрозрачные прогнозы может снижать общественное доверие. | J21: + Сфера «Познание»: +0,30; прирост +0,10/год; + Модельные ресурсы: +0,25; + Прирост сферы «Государственное управление»: +0,08/год; + Математико-алгоритмические ресурсы: +0,20; + Атака в войне Афины: +10%; − Энергетические ресурсы: -0,30; − Вода и ресурс отвода тепла: -0,20; − Социальное доверие: -0,15 | K21: =SUMIF('Ход 2026'!$G$29:$G$38,$A21,'Ход 2026'!$I$29:$I$38)*(1+'Эффекты технологий'!J$7+'Эффекты технологий'!J$8+'Эффекты технологий'!J$9) -> 0 | L21: =SUMIF('Ход 2027'!$G$29:$G$38,$A21,'Ход 2027'!$I$29:$I$38)*(1+'Эффекты технологий'!K$7+'Эффекты технологий'!K$8+'Эффекты технологий'!K$9) -> 0 | M21: =SUMIF('Ход 2028'!$G$29:$G$38,$A21,'Ход 2028'!$I$29:$I$38)*(1+'Эффекты технологий'!L$7+'Эффекты технологий'!L$8+'Эффекты технологий'!L$9) -> 0 | N21: =SUMIF('Ход 2029'!$G$29:$G$38,$A21,'Ход 2029'!$I$29:$I$38)*(1+'Эффекты технологий'!M$7+'Эффекты технологий'!M$8+'Эффекты технологий'!M$9) -> 0 | O21: =SUMIF('Ход 2030'!$G$29:$G$38,$A21,'Ход 2030'!$I$29:$I$38)*(1+'Эффекты технологий'!N$7+'Эффекты технологий'!N$8+'Эффекты технологий'!N$9) -> 0 | P21: =SUMIF('Ход 2031'!$G$29:$G$38,$A21,'Ход 2031'!$I$29:$I$38)*(1+'Эффекты технологий'!O$7+'Эффекты технологий'!O$8+'Эффекты технологий'!O$9) -> 0 | Q21: =SUMIF('Ход 2032'!$G$29:$G$38,$A21,'Ход 2032'!$I$29:$I$38)*(1+'Эффекты технологий'!P$7+'Эффекты технологий'!P$8+'Эффекты технологий'!P$9) -> 0 | R21: =SUMIF('Ход 2033'!$G$29:$G$38,$A21,'Ход 2033'!$I$29:$I$38)*(1+'Эффекты технологий'!Q$7+'Эффекты технологий'!Q$8+'Эффекты технологий'!Q$9) -> 0 | S21: =SUMIF('Ход 2034'!$G$29:$G$38,$A21,'Ход 2034'!$I$29:$I$38)*(1+'Эффекты технологий'!R$7+'Эффекты технологий'!R$8+'Эффекты технологий'!R$9) -> 0 | T21: =SUMIF('Ход 2035'!$G$29:$G$38,$A21,'Ход 2035'!$I$29:$I$38)*(1+'Эффекты технологий'!S$7+'Эффекты технологий'!S$8+'Эффекты технологий'!S$9) -> 0 | U21: =SUMIF('Ход 2036'!$G$29:$G$38,$A21,'Ход 2036'!$I$29:$I$38)*(1+'Эффекты технологий'!T$7+'Эффекты технологий'!T$8+'Эффекты технологий'!T$9) -> 0 | V21: =SUMIF('Ход 2037'!$G$29:$G$38,$A21,'Ход 2037'!$I$29:$I$38)*(1+'Эффекты технологий'!U$7+'Эффекты технологий'!U$8+'Эффекты технологий'!U$9) -> 0 | W21: =SUMIF('Ход 2038'!$G$29:$G$38,$A21,'Ход 2038'!$I$29:$I$38)*(1+'Эффекты технологий'!V$7+'Эффекты технологий'!V$8+'Эффекты технологий'!V$9) -> 0 | X21: =SUMIF('Ход 2039'!$G$29:$G$38,$A21,'Ход 2039'!$I$29:$I$38)*(1+'Эффекты технологий'!W$7+'Эффекты технологий'!W$8+'Эффекты технологий'!W$9) -> 0 | Y21: =SUMIF('Ход 2040'!$G$29:$G$38,$A21,'Ход 2040'!$I$29:$I$38)*(1+'Эффекты технологий'!X$7+'Эффекты технологий'!X$8+'Эффекты технологий'!X$9) -> 0 | Z21: =SUM(K21:Y21) -> 0 | AA21: =MAX(0,E21-Z21) -> 100 | AB21: =BF21 -> ОТКРЫТО | AC21: =SUM($K21:K21) -> 0 | AD21: =SUM($K21:L21) -> 0 | AE21: =SUM($K21:M21) -> 0 | AF21: =SUM($K21:N21) -> 0 | AG21: =SUM($K21:O21) -> 0 | AH21: =SUM($K21:P21) -> 0 | AI21: =SUM($K21:Q21) -> 0 | AJ21: =SUM($K21:R21) -> 0 | ... AQ21: =SUM($K21:Y21) -> 0 | AR21: =IF(AND(AC21>=$E21,TRUE),"ИЗУЧЕНО",IF(TRUE,"ОТКРЫТО","ЗАКРЫТО")) -> ОТКРЫТО | AS21: =IF(AND(AD21>=$E21,TRUE),"ИЗУЧЕНО",IF(TRUE,"ОТКРЫТО","ЗАКРЫТО")) -> ОТКРЫТО | AT21: =IF(AND(AE21>=$E21,TRUE),"ИЗУЧЕНО",IF(TRUE,"ОТКРЫТО","ЗАКРЫТО")) -> ОТКРЫТО | AU21: =IF(AND(AF21>=$E21,TRUE),"ИЗУЧЕНО",IF(TRUE,"ОТКРЫТО","ЗАКРЫТО")) -> ОТКРЫТО | AV21: =IF(AND(AG21>=$E21,TRUE),"ИЗУЧЕНО",IF(TRUE,"ОТКРЫТО","ЗАКРЫТО")) -> ОТКРЫТО | AW21: =IF(AND(AH21>=$E21,TRUE),"ИЗУЧЕНО",IF(TRUE,"ОТКРЫТО","ЗАКРЫТО")) -> ОТКРЫТО | AX21: =IF(AND(AI21>=$E21,TRUE),"ИЗУЧЕНО",IF(TRUE,"ОТКРЫТО","ЗАКРЫТО")) -> ОТКРЫТО | AY21: =IF(AND(AJ21>=$E21,TRUE),"ИЗУЧЕНО",IF(TRUE,"ОТКРЫТО","ЗАКРЫТО")) -> ОТКРЫТО | ... BF21: =IF(AND(AQ21>=$E21,TRUE),"ИЗУЧЕНО",IF(TRUE,"ОТКРЫТО","ЗАКРЫТО")) -> ОТКРЫТО | BG21: =IFERROR(2025+MATCH("ИЗУЧЕНО",AR21:BF21,0),"") | BH21: =IF(BG21="","",BG21+1)
A22: M6 | B22: Модели и алгоритмы | C22: V | D22: Автоматизированный поиск архитектур и самообновление нейросетей | E22: 155 | F22: M5 | I22: Исследовательский контур самостоятельно предлагает новые архитектуры нейросетей, обучает кандидатов, сравнивает результаты и обновляет наиболее успешные модели. Человек определяет цели и границы экспериментов, но большая часть технического перебора автоматизирована. Это ускоряет развитие моделей и смежных агентных исследований. Вместе с тем поиск требует больших вычислительных серий, охлаждения и финансирования; повышение автономности экспериментов также усиливает проблему общественного контроля. | J22: + Прирост методов построения и совершенствования моделей: +0,15/год; + Прирост модельных ресурсов: +0,10/год; + Математико-алгоритмические ресурсы: +0,25; + Ресурсы оценки: +0,20; + Прирост сферы «Познание»: +0,08/год; + Эффективность науки для ветвей M, A, X: +15%; − Энергетические ресурсы: -0,40; − Вода и ресурс отвода тепла: -0,25; − Финансовые ресурсы: -0,20; − Социальное доверие: -0,20 | K22: =SUMIF('Ход 2026'!$G$29:$G$38,$A22,'Ход 2026'!$I$29:$I$38)*(1+'Эффекты технологий'!J$7+'Эффекты технологий'!J$8+'Эффекты технологий'!J$9) -> 0 | L22: =SUMIF('Ход 2027'!$G$29:$G$38,$A22,'Ход 2027'!$I$29:$I$38)*(1+'Эффекты технологий'!K$7+'Эффекты технологий'!K$8+'Эффекты технологий'!K$9) -> 0 | M22: =SUMIF('Ход 2028'!$G$29:$G$38,$A22,'Ход 2028'!$I$29:$I$38)*(1+'Эффекты технологий'!L$7+'Эффекты технологий'!L$8+'Эффекты технологий'!L$9) -> 0 | N22: =SUMIF('Ход 2029'!$G$29:$G$38,$A22,'Ход 2029'!$I$29:$I$38)*(1+'Эффекты технологий'!M$7+'Эффекты технологий'!M$8+'Эффекты технологий'!M$9) -> 0 | O22: =SUMIF('Ход 2030'!$G$29:$G$38,$A22,'Ход 2030'!$I$29:$I$38)*(1+'Эффекты технологий'!N$7+'Эффекты технологий'!N$8+'Эффекты технологий'!N$9) -> 0 | P22: =SUMIF('Ход 2031'!$G$29:$G$38,$A22,'Ход 2031'!$I$29:$I$38)*(1+'Эффекты технологий'!O$7+'Эффекты технологий'!O$8+'Эффекты технологий'!O$9) -> 0 | Q22: =SUMIF('Ход 2032'!$G$29:$G$38,$A22,'Ход 2032'!$I$29:$I$38)*(1+'Эффекты технологий'!P$7+'Эффекты технологий'!P$8+'Эффекты технологий'!P$9) -> 0 | R22: =SUMIF('Ход 2033'!$G$29:$G$38,$A22,'Ход 2033'!$I$29:$I$38)*(1+'Эффекты технологий'!Q$7+'Эффекты технологий'!Q$8+'Эффекты технологий'!Q$9) -> 0 | S22: =SUMIF('Ход 2034'!$G$29:$G$38,$A22,'Ход 2034'!$I$29:$I$38)*(1+'Эффекты технологий'!R$7+'Эффекты технологий'!R$8+'Эффекты технологий'!R$9) -> 0 | T22: =SUMIF('Ход 2035'!$G$29:$G$38,$A22,'Ход 2035'!$I$29:$I$38)*(1+'Эффекты технологий'!S$7+'Эффекты технологий'!S$8+'Эффекты технологий'!S$9) -> 0 | U22: =SUMIF('Ход 2036'!$G$29:$G$38,$A22,'Ход 2036'!$I$29:$I$38)*(1+'Эффекты технологий'!T$7+'Эффекты технологий'!T$8+'Эффекты технологий'!T$9) -> 0 | V22: =SUMIF('Ход 2037'!$G$29:$G$38,$A22,'Ход 2037'!$I$29:$I$38)*(1+'Эффекты технологий'!U$7+'Эффекты технологий'!U$8+'Эффекты технологий'!U$9) -> 0 | W22: =SUMIF('Ход 2038'!$G$29:$G$38,$A22,'Ход 2038'!$I$29:$I$38)*(1+'Эффекты технологий'!V$7+'Эффекты технологий'!V$8+'Эффекты технологий'!V$9) -> 0 | X22: =SUMIF('Ход 2039'!$G$29:$G$38,$A22,'Ход 2039'!$I$29:$I$38)*(1+'Эффекты технологий'!W$7+'Эффекты технологий'!W$8+'Эффекты технологий'!W$9) -> 0 | Y22: =SUMIF('Ход 2040'!$G$29:$G$38,$A22,'Ход 2040'!$I$29:$I$38)*(1+'Эффекты технологий'!X$7+'Эффекты технологий'!X$8+'Эффекты технологий'!X$9) -> 0 | Z22: =SUM(K22:Y22) -> 0 | AA22: =MAX(0,E22-Z22) -> 155 | AB22: =BF22 -> ОТКРЫТО | AC22: =SUM($K22:K22) -> 0 | AD22: =SUM($K22:L22) -> 0 | AE22: =SUM($K22:M22) -> 0 | AF22: =SUM($K22:N22) -> 0 | AG22: =SUM($K22:O22) -> 0 | AH22: =SUM($K22:P22) -> 0 | AI22: =SUM($K22:Q22) -> 0 | AJ22: =SUM($K22:R22) -> 0 | ... AQ22: =SUM($K22:Y22) -> 0 | AR22: =IF(AND(AC22>=$E22,TRUE),"ИЗУЧЕНО",IF(TRUE,"ОТКРЫТО","ЗАКРЫТО")) -> ОТКРЫТО | AS22: =IF(AND(AD22>=$E22,TRUE),"ИЗУЧЕНО",IF(TRUE,"ОТКРЫТО","ЗАКРЫТО")) -> ОТКРЫТО | AT22: =IF(AND(AE22>=$E22,TRUE),"ИЗУЧЕНО",IF(TRUE,"ОТКРЫТО","ЗАКРЫТО")) -> ОТКРЫТО | AU22: =IF(AND(AF22>=$E22,TRUE),"ИЗУЧЕНО",IF(TRUE,"ОТКРЫТО","ЗАКРЫТО")) -> ОТКРЫТО | AV22: =IF(AND(AG22>=$E22,TRUE),"ИЗУЧЕНО",IF(TRUE,"ОТКРЫТО","ЗАКРЫТО")) -> ОТКРЫТО | AW22: =IF(AND(AH22>=$E22,TRUE),"ИЗУЧЕНО",IF(TRUE,"ОТКРЫТО","ЗАКРЫТО")) -> ОТКРЫТО | AX22: =IF(AND(AI22>=$E22,TRUE),"ИЗУЧЕНО",IF(TRUE,"ОТКРЫТО","ЗАКРЫТО")) -> ОТКРЫТО | AY22: =IF(AND(AJ22>=$E22,TRUE),"ИЗУЧЕНО",IF(TRUE,"ОТКРЫТО","ЗАКРЫТО")) -> ОТКРЫТО | ... BF22: =IF(AND(AQ22>=$E22,TRUE),"ИЗУЧЕНО",IF(TRUE,"ОТКРЫТО","ЗАКРЫТО")) -> ОТКРЫТО | BG22: =IFERROR(2025+MATCH("ИЗУЧЕНО",AR22:BF22,0),"") | BH22: =IF(BG22="","",BG22+1)
A23: D1 | B23: Данные и знания | C23: I | D23: Унифицированные API и схемы обмена данными | E23: 20 | I23: Разные информационные системы начинают описывать данные в согласованных форматах и обмениваться ими через документированные программные интерфейсы. Это снижает стоимость подключения новых источников и облегчает передачу информации между ведомствами и организациями. Выигрыш направлен прежде всего на интеграционные ресурсы: объём данных сам по себе ещё не возрастает, но существующие массивы становятся совместимее. Первый шаг не предполагает заметного дополнительного постоянного расхода ресурсов. | J23: + Интеграционные ресурсы: +0,20 | K23: =SUMIF('Ход 2026'!$G$29:$G$38,$A23,'Ход 2026'!$I$29:$I$38)*(1+'Эффекты технологий'!J$7) -> 0 | L23: =SUMIF('Ход 2027'!$G$29:$G$38,$A23,'Ход 2027'!$I$29:$I$38)*(1+'Эффекты технологий'!K$7) -> 0 | M23: =SUMIF('Ход 2028'!$G$29:$G$38,$A23,'Ход 2028'!$I$29:$I$38)*(1+'Эффекты технологий'!L$7) -> 0 | N23: =SUMIF('Ход 2029'!$G$29:$G$38,$A23,'Ход 2029'!$I$29:$I$38)*(1+'Эффекты технологий'!M$7) -> 0 | O23: =SUMIF('Ход 2030'!$G$29:$G$38,$A23,'Ход 2030'!$I$29:$I$38)*(1+'Эффекты технологий'!N$7) -> 0 | P23: =SUMIF('Ход 2031'!$G$29:$G$38,$A23,'Ход 2031'!$I$29:$I$38)*(1+'Эффекты технологий'!O$7) -> 0 | Q23: =SUMIF('Ход 2032'!$G$29:$G$38,$A23,'Ход 2032'!$I$29:$I$38)*(1+'Эффекты технологий'!P$7) -> 0 | R23: =SUMIF('Ход 2033'!$G$29:$G$38,$A23,'Ход 2033'!$I$29:$I$38)*(1+'Эффекты технологий'!Q$7) -> 0 | S23: =SUMIF('Ход 2034'!$G$29:$G$38,$A23,'Ход 2034'!$I$29:$I$38)*(1+'Эффекты технологий'!R$7) -> 0 | T23: =SUMIF('Ход 2035'!$G$29:$G$38,$A23,'Ход 2035'!$I$29:$I$38)*(1+'Эффекты технологий'!S$7) -> 0 | U23: =SUMIF('Ход 2036'!$G$29:$G$38,$A23,'Ход 2036'!$I$29:$I$38)*(1+'Эффекты технологий'!T$7) -> 0 | V23: =SUMIF('Ход 2037'!$G$29:$G$38,$A23,'Ход 2037'!$I$29:$I$38)*(1+'Эффекты технологий'!U$7) -> 0 | W23: =SUMIF('Ход 2038'!$G$29:$G$38,$A23,'Ход 2038'!$I$29:$I$38)*(1+'Эффекты технологий'!V$7) -> 0 | X23: =SUMIF('Ход 2039'!$G$29:$G$38,$A23,'Ход 2039'!$I$29:$I$38)*(1+'Эффекты технологий'!W$7) -> 0 | Y23: =SUMIF('Ход 2040'!$G$29:$G$38,$A23,'Ход 2040'!$I$29:$I$38)*(1+'Эффекты технологий'!X$7) -> 0 | Z23: =SUM(K23:Y23) -> 0 | AA23: =MAX(0,E23-Z23) -> 20 | AB23: =BF23 -> ОТКРЫТО | AC23: =SUM($K23:K23) -> 0 | AD23: =SUM($K23:L23) -> 0 | AE23: =SUM($K23:M23) -> 0 | AF23: =SUM($K23:N23) -> 0 | AG23: =SUM($K23:O23) -> 0 | AH23: =SUM($K23:P23) -> 0 | AI23: =SUM($K23:Q23) -> 0 | AJ23: =SUM($K23:R23) -> 0 | ... AQ23: =SUM($K23:Y23) -> 0 | AR23: =IF(AND(AC23>=$E23,TRUE),"ИЗУЧЕНО",IF(TRUE,"ОТКРЫТО","ЗАКРЫТО")) -> ОТКРЫТО | AS23: =IF(AND(AD23>=$E23,TRUE),"ИЗУЧЕНО",IF(TRUE,"ОТКРЫТО","ЗАКРЫТО")) -> ОТКРЫТО | AT23: =IF(AND(AE23>=$E23,TRUE),"ИЗУЧЕНО",IF(TRUE,"ОТКРЫТО","ЗАКРЫТО")) -> ОТКРЫТО | AU23: =IF(AND(AF23>=$E23,TRUE),"ИЗУЧЕНО",IF(TRUE,"ОТКРЫТО","ЗАКРЫТО")) -> ОТКРЫТО | AV23: =IF(AND(AG23>=$E23,TRUE),"ИЗУЧЕНО",IF(TRUE,"ОТКРЫТО","ЗАКРЫТО")) -> ОТКРЫТО | AW23: =IF(AND(AH23>=$E23,TRUE),"ИЗУЧЕНО",IF(TRUE,"ОТКРЫТО","ЗАКРЫТО")) -> ОТКРЫТО | AX23: =IF(AND(AI23>=$E23,TRUE),"ИЗУЧЕНО",IF(TRUE,"ОТКРЫТО","ЗАКРЫТО")) -> ОТКРЫТО | AY23: =IF(AND(AJ23>=$E23,TRUE),"ИЗУЧЕНО",IF(TRUE,"ОТКРЫТО","ЗАКРЫТО")) -> ОТКРЫТО | ... BF23: =IF(AND(AQ23>=$E23,TRUE),"ИЗУЧЕНО",IF(TRUE,"ОТКРЫТО","ЗАКРЫТО")) -> ОТКРЫТО | BG23: =IFERROR(2025+MATCH("ИЗУЧЕНО",AR23:BF23,0),"") | BH23: =IF(BG23="","",BG23+1)
A24: D2 | B24: Данные и знания | C24: II | D24: Генерация синтетических данных диффузионными и генеративно-состязательными моделями | E24: 35 | F24: D1 | I24: Генеративные методы создают новые искусственные наблюдения, изображения и сценарии на основе структуры исходных данных. Они помогают расширять редкие обучающие выборки и проверять модели на нестандартных ситуациях. Вместе с ростом производных данных развиваются методы оценки их качества. Однако широкое появление синтетических материалов затрудняет проверку происхождения информации и может уменьшать доверие к цифровому контенту. | J24: + Производные данные: +0,30; прирост +0,10/год; + Ресурсы оценки: +0,20; − Социальное доверие: -0,10 | K24: =SUMIF('Ход 2026'!$G$29:$G$38,$A24,'Ход 2026'!$I$29:$I$38)*(1+'Эффекты технологий'!J$7) -> 0 | L24: =SUMIF('Ход 2027'!$G$29:$G$38,$A24,'Ход 2027'!$I$29:$I$38)*(1+'Эффекты технологий'!K$7) -> 0 | M24: =SUMIF('Ход 2028'!$G$29:$G$38,$A24,'Ход 2028'!$I$29:$I$38)*(1+'Эффекты технологий'!L$7) -> 0 | N24: =SUMIF('Ход 2029'!$G$29:$G$38,$A24,'Ход 2029'!$I$29:$I$38)*(1+'Эффекты технологий'!M$7) -> 0 | O24: =SUMIF('Ход 2030'!$G$29:$G$38,$A24,'Ход 2030'!$I$29:$I$38)*(1+'Эффекты технологий'!N$7) -> 0 | P24: =SUMIF('Ход 2031'!$G$29:$G$38,$A24,'Ход 2031'!$I$29:$I$38)*(1+'Эффекты технологий'!O$7) -> 0 | Q24: =SUMIF('Ход 2032'!$G$29:$G$38,$A24,'Ход 2032'!$I$29:$I$38)*(1+'Эффекты технологий'!P$7) -> 0 | R24: =SUMIF('Ход 2033'!$G$29:$G$38,$A24,'Ход 2033'!$I$29:$I$38)*(1+'Эффекты технологий'!Q$7) -> 0 | S24: =SUMIF('Ход 2034'!$G$29:$G$38,$A24,'Ход 2034'!$I$29:$I$38)*(1+'Эффекты технологий'!R$7) -> 0 | T24: =SUMIF('Ход 2035'!$G$29:$G$38,$A24,'Ход 2035'!$I$29:$I$38)*(1+'Эффекты технологий'!S$7) -> 0 | U24: =SUMIF('Ход 2036'!$G$29:$G$38,$A24,'Ход 2036'!$I$29:$I$38)*(1+'Эффекты технологий'!T$7) -> 0 | V24: =SUMIF('Ход 2037'!$G$29:$G$38,$A24,'Ход 2037'!$I$29:$I$38)*(1+'Эффекты технологий'!U$7) -> 0 | W24: =SUMIF('Ход 2038'!$G$29:$G$38,$A24,'Ход 2038'!$I$29:$I$38)*(1+'Эффекты технологий'!V$7) -> 0 | X24: =SUMIF('Ход 2039'!$G$29:$G$38,$A24,'Ход 2039'!$I$29:$I$38)*(1+'Эффекты технологий'!W$7) -> 0 | Y24: =SUMIF('Ход 2040'!$G$29:$G$38,$A24,'Ход 2040'!$I$29:$I$38)*(1+'Эффекты технологий'!X$7) -> 0 | Z24: =SUM(K24:Y24) -> 0 | AA24: =MAX(0,E24-Z24) -> 35 | AB24: =BF24 -> ОТКРЫТО | AC24: =SUM($K24:K24) -> 0 | AD24: =SUM($K24:L24) -> 0 | AE24: =SUM($K24:M24) -> 0 | AF24: =SUM($K24:N24) -> 0 | AG24: =SUM($K24:O24) -> 0 | AH24: =SUM($K24:P24) -> 0 | AI24: =SUM($K24:Q24) -> 0 | AJ24: =SUM($K24:R24) -> 0 | ... AQ24: =SUM($K24:Y24) -> 0 | AR24: =IF(AND(AC24>=$E24,TRUE),"ИЗУЧЕНО",IF(TRUE,"ОТКРЫТО","ЗАКРЫТО")) -> ОТКРЫТО | AS24: =IF(AND(AD24>=$E24,TRUE),"ИЗУЧЕНО",IF(TRUE,"ОТКРЫТО","ЗАКРЫТО")) -> ОТКРЫТО | AT24: =IF(AND(AE24>=$E24,TRUE),"ИЗУЧЕНО",IF(TRUE,"ОТКРЫТО","ЗАКРЫТО")) -> ОТКРЫТО | AU24: =IF(AND(AF24>=$E24,TRUE),"ИЗУЧЕНО",IF(TRUE,"ОТКРЫТО","ЗАКРЫТО")) -> ОТКРЫТО | AV24: =IF(AND(AG24>=$E24,TRUE),"ИЗУЧЕНО",IF(TRUE,"ОТКРЫТО","ЗАКРЫТО")) -> ОТКРЫТО | AW24: =IF(AND(AH24>=$E24,TRUE),"ИЗУЧЕНО",IF(TRUE,"ОТКРЫТО","ЗАКРЫТО")) -> ОТКРЫТО | AX24: =IF(AND(AI24>=$E24,TRUE),"ИЗУЧЕНО",IF(TRUE,"ОТКРЫТО","ЗАКРЫТО")) -> ОТКРЫТО | AY24: =IF(AND(AJ24>=$E24,TRUE),"ИЗУЧЕНО",IF(TRUE,"ОТКРЫТО","ЗАКРЫТО")) -> ОТКРЫТО | ... BF24: =IF(AND(AQ24>=$E24,TRUE),"ИЗУЧЕНО",IF(TRUE,"ОТКРЫТО","ЗАКРЫТО")) -> ОТКРЫТО | BG24: =IFERROR(2025+MATCH("ИЗУЧЕНО",AR24:BF24,0),"") | BH24: =IF(BG24="","",BG24+1)
A25: D3 | B25: Данные и знания | C25: II | D25: Графовые базы знаний на RDF/OWL с семантическими запросами | E25: 40 | F25: D1 | I25: Факты описываются как связи между сущностями, а онтологии задают смысл классов и отношений. Машина получает возможность искать не только совпадающие слова, но и содержательные зависимости между объектами. Это улучшает контекстные ресурсы и ускоряет познание. Создание графа требует разметки, согласования терминов и постоянного сопровождения, поэтому технология создаёт дополнительные финансовые обязательства. | J25: + Контекстные информационные ресурсы: +0,30; + Прирост сферы «Познание»: +0,05/год; + Документационные ресурсы: +0,20; − Финансовые ресурсы: -0,15 | K25: =SUMIF('Ход 2026'!$G$29:$G$38,$A25,'Ход 2026'!$I$29:$I$38)*(1+'Эффекты технологий'!J$7) -> 0 | L25: =SUMIF('Ход 2027'!$G$29:$G$38,$A25,'Ход 2027'!$I$29:$I$38)*(1+'Эффекты технологий'!K$7) -> 0 | M25: =SUMIF('Ход 2028'!$G$29:$G$38,$A25,'Ход 2028'!$I$29:$I$38)*(1+'Эффекты технологий'!L$7) -> 0 | N25: =SUMIF('Ход 2029'!$G$29:$G$38,$A25,'Ход 2029'!$I$29:$I$38)*(1+'Эффекты технологий'!M$7) -> 0 | O25: =SUMIF('Ход 2030'!$G$29:$G$38,$A25,'Ход 2030'!$I$29:$I$38)*(1+'Эффекты технологий'!N$7) -> 0 | P25: =SUMIF('Ход 2031'!$G$29:$G$38,$A25,'Ход 2031'!$I$29:$I$38)*(1+'Эффекты технологий'!O$7) -> 0 | Q25: =SUMIF('Ход 2032'!$G$29:$G$38,$A25,'Ход 2032'!$I$29:$I$38)*(1+'Эффекты технологий'!P$7) -> 0 | R25: =SUMIF('Ход 2033'!$G$29:$G$38,$A25,'Ход 2033'!$I$29:$I$38)*(1+'Эффекты технологий'!Q$7) -> 0 | S25: =SUMIF('Ход 2034'!$G$29:$G$38,$A25,'Ход 2034'!$I$29:$I$38)*(1+'Эффекты технологий'!R$7) -> 0 | T25: =SUMIF('Ход 2035'!$G$29:$G$38,$A25,'Ход 2035'!$I$29:$I$38)*(1+'Эффекты технологий'!S$7) -> 0 | U25: =SUMIF('Ход 2036'!$G$29:$G$38,$A25,'Ход 2036'!$I$29:$I$38)*(1+'Эффекты технологий'!T$7) -> 0 | V25: =SUMIF('Ход 2037'!$G$29:$G$38,$A25,'Ход 2037'!$I$29:$I$38)*(1+'Эффекты технологий'!U$7) -> 0 | W25: =SUMIF('Ход 2038'!$G$29:$G$38,$A25,'Ход 2038'!$I$29:$I$38)*(1+'Эффекты технологий'!V$7) -> 0 | X25: =SUMIF('Ход 2039'!$G$29:$G$38,$A25,'Ход 2039'!$I$29:$I$38)*(1+'Эффекты технологий'!W$7) -> 0 | Y25: =SUMIF('Ход 2040'!$G$29:$G$38,$A25,'Ход 2040'!$I$29:$I$38)*(1+'Эффекты технологий'!X$7) -> 0 | Z25: =SUM(K25:Y25) -> 0 | AA25: =MAX(0,E25-Z25) -> 40 | AB25: =BF25 -> ОТКРЫТО | AC25: =SUM($K25:K25) -> 0 | AD25: =SUM($K25:L25) -> 0 | AE25: =SUM($K25:M25) -> 0 | AF25: =SUM($K25:N25) -> 0 | AG25: =SUM($K25:O25) -> 0 | AH25: =SUM($K25:P25) -> 0 | AI25: =SUM($K25:Q25) -> 0 | AJ25: =SUM($K25:R25) -> 0 | ... AQ25: =SUM($K25:Y25) -> 0 | AR25: =IF(AND(AC25>=$E25,TRUE),"ИЗУЧЕНО",IF(TRUE,"ОТКРЫТО","ЗАКРЫТО")) -> ОТКРЫТО | AS25: =IF(AND(AD25>=$E25,TRUE),"ИЗУЧЕНО",IF(TRUE,"ОТКРЫТО","ЗАКРЫТО")) -> ОТКРЫТО | AT25: =IF(AND(AE25>=$E25,TRUE),"ИЗУЧЕНО",IF(TRUE,"ОТКРЫТО","ЗАКРЫТО")) -> ОТКРЫТО | AU25: =IF(AND(AF25>=$E25,TRUE),"ИЗУЧЕНО",IF(TRUE,"ОТКРЫТО","ЗАКРЫТО")) -> ОТКРЫТО | AV25: =IF(AND(AG25>=$E25,TRUE),"ИЗУЧЕНО",IF(TRUE,"ОТКРЫТО","ЗАКРЫТО")) -> ОТКРЫТО | AW25: =IF(AND(AH25>=$E25,TRUE),"ИЗУЧЕНО",IF(TRUE,"ОТКРЫТО","ЗАКРЫТО")) -> ОТКРЫТО | AX25: =IF(AND(AI25>=$E25,TRUE),"ИЗУЧЕНО",IF(TRUE,"ОТКРЫТО","ЗАКРЫТО")) -> ОТКРЫТО | AY25: =IF(AND(AJ25>=$E25,TRUE),"ИЗУЧЕНО",IF(TRUE,"ОТКРЫТО","ЗАКРЫТО")) -> ОТКРЫТО | ... BF25: =IF(AND(AQ25>=$E25,TRUE),"ИЗУЧЕНО",IF(TRUE,"ОТКРЫТО","ЗАКРЫТО")) -> ОТКРЫТО | BG25: =IFERROR(2025+MATCH("ИЗУЧЕНО",AR25:BF25,0),"") | BH25: =IF(BG25="","",BG25+1)
A26: D4 | B26: Данные и знания | C26: III | D26: Системы RAG с проверкой происхождения и цитированием источников | E26: 60 | F26: D2 | G26: D3 | I26: Система извлекает относящиеся к запросу фрагменты из контролируемых источников и передаёт их языковой модели вместе с указанием происхождения. Дополнительная проверка помогает снизить долю неподтверждённых ответов и обеспечивает прослеживаемость используемых документов. Такие инструменты особенно полезны для государственных справочных и аналитических задач. Новые индексы, подключения и поисковые сервисы увеличивают вычислительную нагрузку и поверхность возможных атак. | J26: + Документационные ресурсы: +0,30; + Права доступа к информационным ресурсам: +0,20; + Прирост сферы «Государственное управление»: +0,05/год; + Ресурсы оценки: +0,20; − Энергетические ресурсы: -0,20; − Кибербезопасностные ресурсы: -0,15 | K26: =SUMIF('Ход 2026'!$G$29:$G$38,$A26,'Ход 2026'!$I$29:$I$38)*(1+'Эффекты технологий'!J$7) -> 0 | L26: =SUMIF('Ход 2027'!$G$29:$G$38,$A26,'Ход 2027'!$I$29:$I$38)*(1+'Эффекты технологий'!K$7) -> 0 | M26: =SUMIF('Ход 2028'!$G$29:$G$38,$A26,'Ход 2028'!$I$29:$I$38)*(1+'Эффекты технологий'!L$7) -> 0 | N26: =SUMIF('Ход 2029'!$G$29:$G$38,$A26,'Ход 2029'!$I$29:$I$38)*(1+'Эффекты технологий'!M$7) -> 0 | O26: =SUMIF('Ход 2030'!$G$29:$G$38,$A26,'Ход 2030'!$I$29:$I$38)*(1+'Эффекты технологий'!N$7) -> 0 | P26: =SUMIF('Ход 2031'!$G$29:$G$38,$A26,'Ход 2031'!$I$29:$I$38)*(1+'Эффекты технологий'!O$7) -> 0 | Q26: =SUMIF('Ход 2032'!$G$29:$G$38,$A26,'Ход 2032'!$I$29:$I$38)*(1+'Эффекты технологий'!P$7) -> 0 | R26: =SUMIF('Ход 2033'!$G$29:$G$38,$A26,'Ход 2033'!$I$29:$I$38)*(1+'Эффекты технологий'!Q$7) -> 0 | S26: =SUMIF('Ход 2034'!$G$29:$G$38,$A26,'Ход 2034'!$I$29:$I$38)*(1+'Эффекты технологий'!R$7) -> 0 | T26: =SUMIF('Ход 2035'!$G$29:$G$38,$A26,'Ход 2035'!$I$29:$I$38)*(1+'Эффекты технологий'!S$7) -> 0 | U26: =SUMIF('Ход 2036'!$G$29:$G$38,$A26,'Ход 2036'!$I$29:$I$38)*(1+'Эффекты технологий'!T$7) -> 0 | V26: =SUMIF('Ход 2037'!$G$29:$G$38,$A26,'Ход 2037'!$I$29:$I$38)*(1+'Эффекты технологий'!U$7) -> 0 | W26: =SUMIF('Ход 2038'!$G$29:$G$38,$A26,'Ход 2038'!$I$29:$I$38)*(1+'Эффекты технологий'!V$7) -> 0 | X26: =SUMIF('Ход 2039'!$G$29:$G$38,$A26,'Ход 2039'!$I$29:$I$38)*(1+'Эффекты технологий'!W$7) -> 0 | Y26: =SUMIF('Ход 2040'!$G$29:$G$38,$A26,'Ход 2040'!$I$29:$I$38)*(1+'Эффекты технологий'!X$7) -> 0 | Z26: =SUM(K26:Y26) -> 0 | AA26: =MAX(0,E26-Z26) -> 60 | AB26: =BF26 -> ОТКРЫТО | AC26: =SUM($K26:K26) -> 0 | AD26: =SUM($K26:L26) -> 0 | AE26: =SUM($K26:M26) -> 0 | AF26: =SUM($K26:N26) -> 0 | AG26: =SUM($K26:O26) -> 0 | AH26: =SUM($K26:P26) -> 0 | AI26: =SUM($K26:Q26) -> 0 | AJ26: =SUM($K26:R26) -> 0 | ... AQ26: =SUM($K26:Y26) -> 0 | AR26: =IF(AND(AC26>=$E26,TRUE),"ИЗУЧЕНО",IF(TRUE,"ОТКРЫТО","ЗАКРЫТО")) -> ОТКРЫТО | AS26: =IF(AND(AD26>=$E26,TRUE),"ИЗУЧЕНО",IF(TRUE,"ОТКРЫТО","ЗАКРЫТО")) -> ОТКРЫТО | AT26: =IF(AND(AE26>=$E26,TRUE),"ИЗУЧЕНО",IF(TRUE,"ОТКРЫТО","ЗАКРЫТО")) -> ОТКРЫТО | AU26: =IF(AND(AF26>=$E26,TRUE),"ИЗУЧЕНО",IF(TRUE,"ОТКРЫТО","ЗАКРЫТО")) -> ОТКРЫТО | AV26: =IF(AND(AG26>=$E26,TRUE),"ИЗУЧЕНО",IF(TRUE,"ОТКРЫТО","ЗАКРЫТО")) -> ОТКРЫТО | AW26: =IF(AND(AH26>=$E26,TRUE),"ИЗУЧЕНО",IF(TRUE,"ОТКРЫТО","ЗАКРЫТО")) -> ОТКРЫТО | AX26: =IF(AND(AI26>=$E26,TRUE),"ИЗУЧЕНО",IF(TRUE,"ОТКРЫТО","ЗАКРЫТО")) -> ОТКРЫТО | AY26: =IF(AND(AJ26>=$E26,TRUE),"ИЗУЧЕНО",IF(TRUE,"ОТКРЫТО","ЗАКРЫТО")) -> ОТКРЫТО | ... BF26: =IF(AND(AQ26>=$E26,TRUE),"ИЗУЧЕНО",IF(TRUE,"ОТКРЫТО","ЗАКРЫТО")) -> ОТКРЫТО | BG26: =IFERROR(2025+MATCH("ИЗУЧЕНО",AR26:BF26,0),"") | BH26: =IF(BG26="","",BG26+1)
A27: D5 | B27: Данные и знания | C27: IV | D27: Федеративные каталоги данных и машиночитаемые онтологии | E27: 95 | F27: D4 | I27: Независимые организации сохраняют собственные хранилища, но подключают их к общей системе описания, поиска и интерпретации данных. Каталоги и онтологии позволяют находить совместимые источники без обязательного объединения всех массивов в одной точке. Государство лучше контролирует информационные смыслы и контекст, поэтому получает защиту от войны Аполлона. Федерация требует устойчивого финансирования, энергоснабжения и сложной политики безопасности. | J27: + Контекстные информационные ресурсы: +0,50; прирост +0,10/год; + Интеграционные ресурсы: +0,30; + Документационные ресурсы: +0,20; + Прирост сферы «Государственное управление»: +0,08/год; + Защита от войны Аполлона: +15%; − Финансовые ресурсы: -0,25; − Кибербезопасностные ресурсы: -0,20; − Энергетические ресурсы: -0,20 | K27: =SUMIF('Ход 2026'!$G$29:$G$38,$A27,'Ход 2026'!$I$29:$I$38)*(1+'Эффекты технологий'!J$7) -> 0 | L27: =SUMIF('Ход 2027'!$G$29:$G$38,$A27,'Ход 2027'!$I$29:$I$38)*(1+'Эффекты технологий'!K$7) -> 0 | M27: =SUMIF('Ход 2028'!$G$29:$G$38,$A27,'Ход 2028'!$I$29:$I$38)*(1+'Эффекты технологий'!L$7) -> 0 | N27: =SUMIF('Ход 2029'!$G$29:$G$38,$A27,'Ход 2029'!$I$29:$I$38)*(1+'Эффекты технологий'!M$7) -> 0 | O27: =SUMIF('Ход 2030'!$G$29:$G$38,$A27,'Ход 2030'!$I$29:$I$38)*(1+'Эффекты технологий'!N$7) -> 0 | P27: =SUMIF('Ход 2031'!$G$29:$G$38,$A27,'Ход 2031'!$I$29:$I$38)*(1+'Эффекты технологий'!O$7) -> 0 | Q27: =SUMIF('Ход 2032'!$G$29:$G$38,$A27,'Ход 2032'!$I$29:$I$38)*(1+'Эффекты технологий'!P$7) -> 0 | R27: =SUMIF('Ход 2033'!$G$29:$G$38,$A27,'Ход 2033'!$I$29:$I$38)*(1+'Эффекты технологий'!Q$7) -> 0 | S27: =SUMIF('Ход 2034'!$G$29:$G$38,$A27,'Ход 2034'!$I$29:$I$38)*(1+'Эффекты технологий'!R$7) -> 0 | T27: =SUMIF('Ход 2035'!$G$29:$G$38,$A27,'Ход 2035'!$I$29:$I$38)*(1+'Эффекты технологий'!S$7) -> 0 | U27: =SUMIF('Ход 2036'!$G$29:$G$38,$A27,'Ход 2036'!$I$29:$I$38)*(1+'Эффекты технологий'!T$7) -> 0 | V27: =SUMIF('Ход 2037'!$G$29:$G$38,$A27,'Ход 2037'!$I$29:$I$38)*(1+'Эффекты технологий'!U$7) -> 0 | W27: =SUMIF('Ход 2038'!$G$29:$G$38,$A27,'Ход 2038'!$I$29:$I$38)*(1+'Эффекты технологий'!V$7) -> 0 | X27: =SUMIF('Ход 2039'!$G$29:$G$38,$A27,'Ход 2039'!$I$29:$I$38)*(1+'Эффекты технологий'!W$7) -> 0 | Y27: =SUMIF('Ход 2040'!$G$29:$G$38,$A27,'Ход 2040'!$I$29:$I$38)*(1+'Эффекты технологий'!X$7) -> 0 | Z27: =SUM(K27:Y27) -> 0 | AA27: =MAX(0,E27-Z27) -> 95 | AB27: =BF27 -> ОТКРЫТО | AC27: =SUM($K27:K27) -> 0 | AD27: =SUM($K27:L27) -> 0 | AE27: =SUM($K27:M27) -> 0 | AF27: =SUM($K27:N27) -> 0 | AG27: =SUM($K27:O27) -> 0 | AH27: =SUM($K27:P27) -> 0 | AI27: =SUM($K27:Q27) -> 0 | AJ27: =SUM($K27:R27) -> 0 | ... AQ27: =SUM($K27:Y27) -> 0 | AR27: =IF(AND(AC27>=$E27,TRUE),"ИЗУЧЕНО",IF(TRUE,"ОТКРЫТО","ЗАКРЫТО")) -> ОТКРЫТО | AS27: =IF(AND(AD27>=$E27,TRUE),"ИЗУЧЕНО",IF(TRUE,"ОТКРЫТО","ЗАКРЫТО")) -> ОТКРЫТО | AT27: =IF(AND(AE27>=$E27,TRUE),"ИЗУЧЕНО",IF(TRUE,"ОТКРЫТО","ЗАКРЫТО")) -> ОТКРЫТО | AU27: =IF(AND(AF27>=$E27,TRUE),"ИЗУЧЕНО",IF(TRUE,"ОТКРЫТО","ЗАКРЫТО")) -> ОТКРЫТО | AV27: =IF(AND(AG27>=$E27,TRUE),"ИЗУЧЕНО",IF(TRUE,"ОТКРЫТО","ЗАКРЫТО")) -> ОТКРЫТО | AW27: =IF(AND(AH27>=$E27,TRUE),"ИЗУЧЕНО",IF(TRUE,"ОТКРЫТО","ЗАКРЫТО")) -> ОТКРЫТО | AX27: =IF(AND(AI27>=$E27,TRUE),"ИЗУЧЕНО",IF(TRUE,"ОТКРЫТО","ЗАКРЫТО")) -> ОТКРЫТО | AY27: =IF(AND(AJ27>=$E27,TRUE),"ИЗУЧЕНО",IF(TRUE,"ОТКРЫТО","ЗАКРЫТО")) -> ОТКРЫТО | ... BF27: =IF(AND(AQ27>=$E27,TRUE),"ИЗУЧЕНО",IF(TRUE,"ОТКРЫТО","ЗАКРЫТО")) -> ОТКРЫТО | BG27: =IFERROR(2025+MATCH("ИЗУЧЕНО",AR27:BF27,0),"") | BH27: =IF(BG27="","",BG27+1)
A28: D6 | B28: Данные и знания | C28: V | D28: Автоматизированные конвейеры очистки, разметки и контроля происхождения данных | E28: 140 | F28: D5 | I28: Конвейер автоматически обнаруживает дефекты данных, выполняет разметку, проверяет согласованность и записывает происхождение каждой версии набора. Он связывает сбор, подготовку и контроль качества в воспроизводимый жизненный цикл. Это увеличивает ежегодный приток пригодных данных и облегчает их использование в ИИ. Высокая степень автоматизации создаёт постоянные инфраструктурные издержки, а ошибочные операции над крупными массивами могут подрывать доверие к результатам. | J28: + Прирост исходных данных: +0,10/год; + Прирост производных данных: +0,15/год; + Прирост ресурсов оценки: +0,10/год; + Документационные ресурсы: +0,20; + Контекстные информационные ресурсы: +0,30; + Прирост сферы «Принятие ИИ»: +0,05/год; − Финансовые ресурсы: -0,20; − Энергетические ресурсы: -0,25; − Вода и ресурс отвода тепла: -0,15; − Социальное доверие: -0,15 | K28: =SUMIF('Ход 2026'!$G$29:$G$38,$A28,'Ход 2026'!$I$29:$I$38)*(1+'Эффекты технологий'!J$7) -> 0 | L28: =SUMIF('Ход 2027'!$G$29:$G$38,$A28,'Ход 2027'!$I$29:$I$38)*(1+'Эффекты технологий'!K$7) -> 0 | M28: =SUMIF('Ход 2028'!$G$29:$G$38,$A28,'Ход 2028'!$I$29:$I$38)*(1+'Эффекты технологий'!L$7) -> 0 | N28: =SUMIF('Ход 2029'!$G$29:$G$38,$A28,'Ход 2029'!$I$29:$I$38)*(1+'Эффекты технологий'!M$7) -> 0 | O28: =SUMIF('Ход 2030'!$G$29:$G$38,$A28,'Ход 2030'!$I$29:$I$38)*(1+'Эффекты технологий'!N$7) -> 0 | P28: =SUMIF('Ход 2031'!$G$29:$G$38,$A28,'Ход 2031'!$I$29:$I$38)*(1+'Эффекты технологий'!O$7) -> 0 | Q28: =SUMIF('Ход 2032'!$G$29:$G$38,$A28,'Ход 2032'!$I$29:$I$38)*(1+'Эффекты технологий'!P$7) -> 0 | R28: =SUMIF('Ход 2033'!$G$29:$G$38,$A28,'Ход 2033'!$I$29:$I$38)*(1+'Эффекты технологий'!Q$7) -> 0 | S28: =SUMIF('Ход 2034'!$G$29:$G$38,$A28,'Ход 2034'!$I$29:$I$38)*(1+'Эффекты технологий'!R$7) -> 0 | T28: =SUMIF('Ход 2035'!$G$29:$G$38,$A28,'Ход 2035'!$I$29:$I$38)*(1+'Эффекты технологий'!S$7) -> 0 | U28: =SUMIF('Ход 2036'!$G$29:$G$38,$A28,'Ход 2036'!$I$29:$I$38)*(1+'Эффекты технологий'!T$7) -> 0 | V28: =SUMIF('Ход 2037'!$G$29:$G$38,$A28,'Ход 2037'!$I$29:$I$38)*(1+'Эффекты технологий'!U$7) -> 0 | W28: =SUMIF('Ход 2038'!$G$29:$G$38,$A28,'Ход 2038'!$I$29:$I$38)*(1+'Эффекты технологий'!V$7) -> 0 | X28: =SUMIF('Ход 2039'!$G$29:$G$38,$A28,'Ход 2039'!$I$29:$I$38)*(1+'Эффекты технологий'!W$7) -> 0 | Y28: =SUMIF('Ход 2040'!$G$29:$G$38,$A28,'Ход 2040'!$I$29:$I$38)*(1+'Эффекты технологий'!X$7) -> 0 | Z28: =SUM(K28:Y28) -> 0 | AA28: =MAX(0,E28-Z28) -> 140 | AB28: =BF28 -> ОТКРЫТО | AC28: =SUM($K28:K28) -> 0 | AD28: =SUM($K28:L28) -> 0 | AE28: =SUM($K28:M28) -> 0 | AF28: =SUM($K28:N28) -> 0 | AG28: =SUM($K28:O28) -> 0 | AH28: =SUM($K28:P28) -> 0 | AI28: =SUM($K28:Q28) -> 0 | AJ28: =SUM($K28:R28) -> 0 | ... AQ28: =SUM($K28:Y28) -> 0 | AR28: =IF(AND(AC28>=$E28,TRUE),"ИЗУЧЕНО",IF(TRUE,"ОТКРЫТО","ЗАКРЫТО")) -> ОТКРЫТО | AS28: =IF(AND(AD28>=$E28,TRUE),"ИЗУЧЕНО",IF(TRUE,"ОТКРЫТО","ЗАКРЫТО")) -> ОТКРЫТО | AT28: =IF(AND(AE28>=$E28,TRUE),"ИЗУЧЕНО",IF(TRUE,"ОТКРЫТО","ЗАКРЫТО")) -> ОТКРЫТО | AU28: =IF(AND(AF28>=$E28,TRUE),"ИЗУЧЕНО",IF(TRUE,"ОТКРЫТО","ЗАКРЫТО")) -> ОТКРЫТО | AV28: =IF(AND(AG28>=$E28,TRUE),"ИЗУЧЕНО",IF(TRUE,"ОТКРЫТО","ЗАКРЫТО")) -> ОТКРЫТО | AW28: =IF(AND(AH28>=$E28,TRUE),"ИЗУЧЕНО",IF(TRUE,"ОТКРЫТО","ЗАКРЫТО")) -> ОТКРЫТО | AX28: =IF(AND(AI28>=$E28,TRUE),"ИЗУЧЕНО",IF(TRUE,"ОТКРЫТО","ЗАКРЫТО")) -> ОТКРЫТО | AY28: =IF(AND(AJ28>=$E28,TRUE),"ИЗУЧЕНО",IF(TRUE,"ОТКРЫТО","ЗАКРЫТО")) -> ОТКРЫТО | ... BF28: =IF(AND(AQ28>=$E28,TRUE),"ИЗУЧЕНО",IF(TRUE,"ОТКРЫТО","ЗАКРЫТО")) -> ОТКРЫТО | BG28: =IFERROR(2025+MATCH("ИЗУЧЕНО",AR28:BF28,0),"") | BH28: =IF(BG28="","",BG28+1)
A29: A1 | B29: Агенты и автономные системы | C29: I | D29: Программные ИИ-агенты с вызовом внешних инструментов через API | E29: 20 | I29: Агент получает возможность не только отвечать на запросы, но и вызывать разрешённые программные инструменты: поиск, расчёты, запросы к базам данных и другие функции. Человек сохраняет контроль над задачей и границами действий. Даже такая ограниченная инструментальная автономия повышает производительность управленческой работы, поэтому технология добавляет ежегодный прирост соответствующей сферы. На этом уровне риск ограничен и отдельный постоянный штраф не вводится. | J29: + Прирост сферы «Управление»: +0,05/год | K29: =SUMIF('Ход 2026'!$G$29:$G$38,$A29,'Ход 2026'!$I$29:$I$38)*(1+'Эффекты технологий'!J$7+'Эффекты технологий'!J$9) -> 20 | L29: =SUMIF('Ход 2027'!$G$29:$G$38,$A29,'Ход 2027'!$I$29:$I$38)*(1+'Эффекты технологий'!K$7+'Эффекты технологий'!K$9) -> 0 | M29: =SUMIF('Ход 2028'!$G$29:$G$38,$A29,'Ход 2028'!$I$29:$I$38)*(1+'Эффекты технологий'!L$7+'Эффекты технологий'!L$9) -> 0 | N29: =SUMIF('Ход 2029'!$G$29:$G$38,$A29,'Ход 2029'!$I$29:$I$38)*(1+'Эффекты технологий'!M$7+'Эффекты технологий'!M$9) -> 0 | O29: =SUMIF('Ход 2030'!$G$29:$G$38,$A29,'Ход 2030'!$I$29:$I$38)*(1+'Эффекты технологий'!N$7+'Эффекты технологий'!N$9) -> 0 | P29: =SUMIF('Ход 2031'!$G$29:$G$38,$A29,'Ход 2031'!$I$29:$I$38)*(1+'Эффекты технологий'!O$7+'Эффекты технологий'!O$9) -> 0 | Q29: =SUMIF('Ход 2032'!$G$29:$G$38,$A29,'Ход 2032'!$I$29:$I$38)*(1+'Эффекты технологий'!P$7+'Эффекты технологий'!P$9) -> 0 | R29: =SUMIF('Ход 2033'!$G$29:$G$38,$A29,'Ход 2033'!$I$29:$I$38)*(1+'Эффекты технологий'!Q$7+'Эффекты технологий'!Q$9) -> 0 | S29: =SUMIF('Ход 2034'!$G$29:$G$38,$A29,'Ход 2034'!$I$29:$I$38)*(1+'Эффекты технологий'!R$7+'Эффекты технологий'!R$9) -> 0 | T29: =SUMIF('Ход 2035'!$G$29:$G$38,$A29,'Ход 2035'!$I$29:$I$38)*(1+'Эффекты технологий'!S$7+'Эффекты технологий'!S$9) -> 0 | U29: =SUMIF('Ход 2036'!$G$29:$G$38,$A29,'Ход 2036'!$I$29:$I$38)*(1+'Эффекты технологий'!T$7+'Эффекты технологий'!T$9) -> 0 | V29: =SUMIF('Ход 2037'!$G$29:$G$38,$A29,'Ход 2037'!$I$29:$I$38)*(1+'Эффекты технологий'!U$7+'Эффекты технологий'!U$9) -> 0 | W29: =SUMIF('Ход 2038'!$G$29:$G$38,$A29,'Ход 2038'!$I$29:$I$38)*(1+'Эффекты технологий'!V$7+'Эффекты технологий'!V$9) -> 0 | X29: =SUMIF('Ход 2039'!$G$29:$G$38,$A29,'Ход 2039'!$I$29:$I$38)*(1+'Эффекты технологий'!W$7+'Эффекты технологий'!W$9) -> 0 | Y29: =SUMIF('Ход 2040'!$G$29:$G$38,$A29,'Ход 2040'!$I$29:$I$38)*(1+'Эффекты технологий'!X$7+'Эффекты технологий'!X$9) -> 0 | Z29: =SUM(K29:Y29) -> 20 | AA29: =MAX(0,E29-Z29) -> 0 | AB29: =BF29 -> ИЗУЧЕНО | AC29: =SUM($K29:K29) -> 20 | AD29: =SUM($K29:L29) -> 20 | AE29: =SUM($K29:M29) -> 20 | AF29: =SUM($K29:N29) -> 20 | AG29: =SUM($K29:O29) -> 20 | AH29: =SUM($K29:P29) -> 20 | AI29: =SUM($K29:Q29) -> 20 | AJ29: =SUM($K29:R29) -> 20 | ... AQ29: =SUM($K29:Y29) -> 20 | AR29: =IF(AND(AC29>=$E29,TRUE),"ИЗУЧЕНО",IF(TRUE,"ОТКРЫТО","ЗАКРЫТО")) -> ИЗУЧЕНО | AS29: =IF(AND(AD29>=$E29,TRUE),"ИЗУЧЕНО",IF(TRUE,"ОТКРЫТО","ЗАКРЫТО")) -> ИЗУЧЕНО | AT29: =IF(AND(AE29>=$E29,TRUE),"ИЗУЧЕНО",IF(TRUE,"ОТКРЫТО","ЗАКРЫТО")) -> ИЗУЧЕНО | AU29: =IF(AND(AF29>=$E29,TRUE),"ИЗУЧЕНО",IF(TRUE,"ОТКРЫТО","ЗАКРЫТО")) -> ИЗУЧЕНО | AV29: =IF(AND(AG29>=$E29,TRUE),"ИЗУЧЕНО",IF(TRUE,"ОТКРЫТО","ЗАКРЫТО")) -> ИЗУЧЕНО | AW29: =IF(AND(AH29>=$E29,TRUE),"ИЗУЧЕНО",IF(TRUE,"ОТКРЫТО","ЗАКРЫТО")) -> ИЗУЧЕНО | AX29: =IF(AND(AI29>=$E29,TRUE),"ИЗУЧЕНО",IF(TRUE,"ОТКРЫТО","ЗАКРЫТО")) -> ИЗУЧЕНО | AY29: =IF(AND(AJ29>=$E29,TRUE),"ИЗУЧЕНО",IF(TRUE,"ОТКРЫТО","ЗАКРЫТО")) -> ИЗУЧЕНО | ... BF29: =IF(AND(AQ29>=$E29,TRUE),"ИЗУЧЕНО",IF(TRUE,"ОТКРЫТО","ЗАКРЫТО")) -> ИЗУЧЕНО | BG29: =IFERROR(2025+MATCH("ИЗУЧЕНО",AR29:BF29,0),"") -> 2026 | BH29: =IF(BG29="","",BG29+1) -> 2027
A30: A2 | B30: Агенты и автономные системы | C30: II | D30: Агенты бизнес-процессов с управлением состояниями и BPMN-маршрутами | E30: 35 | F30: A1 | I30: В отличие от отдельного помощника, агент встраивается в описанный бизнес-процесс и проходит его шаги с сохранением состояния, ролей и условий перехода. BPMN-маршруты задают наблюдаемую структуру исполнения. Такая интеграция улучшает организационную архитектуру и цифровизацию, но расширяет число систем, к которым ИИ должен обращаться. Поэтому появляется небольшой штраф к кибербезопасностному ресурсу. | J30: + Организационная архитектура внедрения: +0,30; прирост +0,08/год; + Оцифрованность деятельности: +0,20; − Кибербезопасностные ресурсы: -0,15 | K30: =SUMIF('Ход 2026'!$G$29:$G$38,$A30,'Ход 2026'!$I$29:$I$38)*(1+'Эффекты технологий'!J$7+'Эффекты технологий'!J$9) -> 0 | L30: =SUMIF('Ход 2027'!$G$29:$G$38,$A30,'Ход 2027'!$I$29:$I$38)*(1+'Эффекты технологий'!K$7+'Эффекты технологий'!K$9) -> 0 | M30: =SUMIF('Ход 2028'!$G$29:$G$38,$A30,'Ход 2028'!$I$29:$I$38)*(1+'Эффекты технологий'!L$7+'Эффекты технологий'!L$9) -> 0 | N30: =SUMIF('Ход 2029'!$G$29:$G$38,$A30,'Ход 2029'!$I$29:$I$38)*(1+'Эффекты технологий'!M$7+'Эффекты технологий'!M$9) -> 0 | O30: =SUMIF('Ход 2030'!$G$29:$G$38,$A30,'Ход 2030'!$I$29:$I$38)*(1+'Эффекты технологий'!N$7+'Эффекты технологий'!N$9) -> 0 | P30: =SUMIF('Ход 2031'!$G$29:$G$38,$A30,'Ход 2031'!$I$29:$I$38)*(1+'Эффекты технологий'!O$7+'Эффекты технологий'!O$9) -> 0 | Q30: =SUMIF('Ход 2032'!$G$29:$G$38,$A30,'Ход 2032'!$I$29:$I$38)*(1+'Эффекты технологий'!P$7+'Эффекты технологий'!P$9) -> 0 | R30: =SUMIF('Ход 2033'!$G$29:$G$38,$A30,'Ход 2033'!$I$29:$I$38)*(1+'Эффекты технологий'!Q$7+'Эффекты технологий'!Q$9) -> 0 | S30: =SUMIF('Ход 2034'!$G$29:$G$38,$A30,'Ход 2034'!$I$29:$I$38)*(1+'Эффекты технологий'!R$7+'Эффекты технологий'!R$9) -> 0 | T30: =SUMIF('Ход 2035'!$G$29:$G$38,$A30,'Ход 2035'!$I$29:$I$38)*(1+'Эффекты технологий'!S$7+'Эффекты технологий'!S$9) -> 0 | U30: =SUMIF('Ход 2036'!$G$29:$G$38,$A30,'Ход 2036'!$I$29:$I$38)*(1+'Эффекты технологий'!T$7+'Эффекты технологий'!T$9) -> 0 | V30: =SUMIF('Ход 2037'!$G$29:$G$38,$A30,'Ход 2037'!$I$29:$I$38)*(1+'Эффекты технологий'!U$7+'Эффекты технологий'!U$9) -> 0 | W30: =SUMIF('Ход 2038'!$G$29:$G$38,$A30,'Ход 2038'!$I$29:$I$38)*(1+'Эффекты технологий'!V$7+'Эффекты технологий'!V$9) -> 0 | X30: =SUMIF('Ход 2039'!$G$29:$G$38,$A30,'Ход 2039'!$I$29:$I$38)*(1+'Эффекты технологий'!W$7+'Эффекты технологий'!W$9) -> 0 | Y30: =SUMIF('Ход 2040'!$G$29:$G$38,$A30,'Ход 2040'!$I$29:$I$38)*(1+'Эффекты технологий'!X$7+'Эффекты технологий'!X$9) -> 0 | Z30: =SUM(K30:Y30) -> 0 | AA30: =MAX(0,E30-Z30) -> 35 | AB30: =BF30 -> ОТКРЫТО | AC30: =SUM($K30:K30) -> 0 | AD30: =SUM($K30:L30) -> 0 | AE30: =SUM($K30:M30) -> 0 | AF30: =SUM($K30:N30) -> 0 | AG30: =SUM($K30:O30) -> 0 | AH30: =SUM($K30:P30) -> 0 | AI30: =SUM($K30:Q30) -> 0 | AJ30: =SUM($K30:R30) -> 0 | ... AQ30: =SUM($K30:Y30) -> 0 | AR30: =IF(AND(AC30>=$E30,TRUE),"ИЗУЧЕНО",IF(TRUE,"ОТКРЫТО","ЗАКРЫТО")) -> ОТКРЫТО | AS30: =IF(AND(AD30>=$E30,TRUE),"ИЗУЧЕНО",IF(TRUE,"ОТКРЫТО","ЗАКРЫТО")) -> ОТКРЫТО | AT30: =IF(AND(AE30>=$E30,TRUE),"ИЗУЧЕНО",IF(TRUE,"ОТКРЫТО","ЗАКРЫТО")) -> ОТКРЫТО | AU30: =IF(AND(AF30>=$E30,TRUE),"ИЗУЧЕНО",IF(TRUE,"ОТКРЫТО","ЗАКРЫТО")) -> ОТКРЫТО | AV30: =IF(AND(AG30>=$E30,TRUE),"ИЗУЧЕНО",IF(TRUE,"ОТКРЫТО","ЗАКРЫТО")) -> ОТКРЫТО | AW30: =IF(AND(AH30>=$E30,TRUE),"ИЗУЧЕНО",IF(TRUE,"ОТКРЫТО","ЗАКРЫТО")) -> ОТКРЫТО | AX30: =IF(AND(AI30>=$E30,TRUE),"ИЗУЧЕНО",IF(TRUE,"ОТКРЫТО","ЗАКРЫТО")) -> ОТКРЫТО | AY30: =IF(AND(AJ30>=$E30,TRUE),"ИЗУЧЕНО",IF(TRUE,"ОТКРЫТО","ЗАКРЫТО")) -> ОТКРЫТО | ... BF30: =IF(AND(AQ30>=$E30,TRUE),"ИЗУЧЕНО",IF(TRUE,"ОТКРЫТО","ЗАКРЫТО")) -> ОТКРЫТО | BG30: =IFERROR(2025+MATCH("ИЗУЧЕНО",AR30:BF30,0),"") | BH30: =IF(BG30="","",BG30+1)
A31: A3 | B31: Агенты и автономные системы | C31: III | D31: Многоагентная маршрутизация задач с распределением ролей | E31: 55 | F31: A2 | I31: Система распределяет общую задачу между несколькими агентами: планировщиком, исполнителями, проверяющим и координатором. Передача промежуточных результатов позволяет решать более сложные задачи и быстрее направлять потоки данных и поручений. Бонус к войне Афины отражает преимущество в управлении информационными взаимодействиями. Вместе с тем усложняется разграничение полномочий, и страна несёт штраф к ресурсам контроля доступа. | J31: + Прирост сферы «Управление»: +0,08/год; + Организационная архитектура внедрения: +0,20; + Атака в войне Афины: +10%; − Права доступа к информационным ресурсам: -0,20 | K31: =SUMIF('Ход 2026'!$G$29:$G$38,$A31,'Ход 2026'!$I$29:$I$38)*(1+'Эффекты технологий'!J$7+'Эффекты технологий'!J$9) -> 0 | L31: =SUMIF('Ход 2027'!$G$29:$G$38,$A31,'Ход 2027'!$I$29:$I$38)*(1+'Эффекты технологий'!K$7+'Эффекты технологий'!K$9) -> 0 | M31: =SUMIF('Ход 2028'!$G$29:$G$38,$A31,'Ход 2028'!$I$29:$I$38)*(1+'Эффекты технологий'!L$7+'Эффекты технологий'!L$9) -> 0 | N31: =SUMIF('Ход 2029'!$G$29:$G$38,$A31,'Ход 2029'!$I$29:$I$38)*(1+'Эффекты технологий'!M$7+'Эффекты технологий'!M$9) -> 0 | O31: =SUMIF('Ход 2030'!$G$29:$G$38,$A31,'Ход 2030'!$I$29:$I$38)*(1+'Эффекты технологий'!N$7+'Эффекты технологий'!N$9) -> 0 | P31: =SUMIF('Ход 2031'!$G$29:$G$38,$A31,'Ход 2031'!$I$29:$I$38)*(1+'Эффекты технологий'!O$7+'Эффекты технологий'!O$9) -> 0 | Q31: =SUMIF('Ход 2032'!$G$29:$G$38,$A31,'Ход 2032'!$I$29:$I$38)*(1+'Эффекты технологий'!P$7+'Эффекты технологий'!P$9) -> 0 | R31: =SUMIF('Ход 2033'!$G$29:$G$38,$A31,'Ход 2033'!$I$29:$I$38)*(1+'Эффекты технологий'!Q$7+'Эффекты технологий'!Q$9) -> 0 | S31: =SUMIF('Ход 2034'!$G$29:$G$38,$A31,'Ход 2034'!$I$29:$I$38)*(1+'Эффекты технологий'!R$7+'Эффекты технологий'!R$9) -> 0 | T31: =SUMIF('Ход 2035'!$G$29:$G$38,$A31,'Ход 2035'!$I$29:$I$38)*(1+'Эффекты технологий'!S$7+'Эффекты технологий'!S$9) -> 0 | U31: =SUMIF('Ход 2036'!$G$29:$G$38,$A31,'Ход 2036'!$I$29:$I$38)*(1+'Эффекты технологий'!T$7+'Эффекты технологий'!T$9) -> 0 | V31: =SUMIF('Ход 2037'!$G$29:$G$38,$A31,'Ход 2037'!$I$29:$I$38)*(1+'Эффекты технологий'!U$7+'Эффекты технологий'!U$9) -> 0 | W31: =SUMIF('Ход 2038'!$G$29:$G$38,$A31,'Ход 2038'!$I$29:$I$38)*(1+'Эффекты технологий'!V$7+'Эффекты технологий'!V$9) -> 0 | X31: =SUMIF('Ход 2039'!$G$29:$G$38,$A31,'Ход 2039'!$I$29:$I$38)*(1+'Эффекты технологий'!W$7+'Эффекты технологий'!W$9) -> 0 | Y31: =SUMIF('Ход 2040'!$G$29:$G$38,$A31,'Ход 2040'!$I$29:$I$38)*(1+'Эффекты технологий'!X$7+'Эффекты технологий'!X$9) -> 0 | Z31: =SUM(K31:Y31) -> 0 | AA31: =MAX(0,E31-Z31) -> 55 | AB31: =BF31 -> ОТКРЫТО | AC31: =SUM($K31:K31) -> 0 | AD31: =SUM($K31:L31) -> 0 | AE31: =SUM($K31:M31) -> 0 | AF31: =SUM($K31:N31) -> 0 | AG31: =SUM($K31:O31) -> 0 | AH31: =SUM($K31:P31) -> 0 | AI31: =SUM($K31:Q31) -> 0 | AJ31: =SUM($K31:R31) -> 0 | ... AQ31: =SUM($K31:Y31) -> 0 | AR31: =IF(AND(AC31>=$E31,TRUE),"ИЗУЧЕНО",IF(TRUE,"ОТКРЫТО","ЗАКРЫТО")) -> ОТКРЫТО | AS31: =IF(AND(AD31>=$E31,TRUE),"ИЗУЧЕНО",IF(TRUE,"ОТКРЫТО","ЗАКРЫТО")) -> ОТКРЫТО | AT31: =IF(AND(AE31>=$E31,TRUE),"ИЗУЧЕНО",IF(TRUE,"ОТКРЫТО","ЗАКРЫТО")) -> ОТКРЫТО | AU31: =IF(AND(AF31>=$E31,TRUE),"ИЗУЧЕНО",IF(TRUE,"ОТКРЫТО","ЗАКРЫТО")) -> ОТКРЫТО | AV31: =IF(AND(AG31>=$E31,TRUE),"ИЗУЧЕНО",IF(TRUE,"ОТКРЫТО","ЗАКРЫТО")) -> ОТКРЫТО | AW31: =IF(AND(AH31>=$E31,TRUE),"ИЗУЧЕНО",IF(TRUE,"ОТКРЫТО","ЗАКРЫТО")) -> ОТКРЫТО | AX31: =IF(AND(AI31>=$E31,TRUE),"ИЗУЧЕНО",IF(TRUE,"ОТКРЫТО","ЗАКРЫТО")) -> ОТКРЫТО | AY31: =IF(AND(AJ31>=$E31,TRUE),"ИЗУЧЕНО",IF(TRUE,"ОТКРЫТО","ЗАКРЫТО")) -> ОТКРЫТО | ... BF31: =IF(AND(AQ31>=$E31,TRUE),"ИЗУЧЕНО",IF(TRUE,"ОТКРЫТО","ЗАКРЫТО")) -> ОТКРЫТО | BG31: =IFERROR(2025+MATCH("ИЗУЧЕНО",AR31:BF31,0),"") | BH31: =IF(BG31="","",BG31+1)
A32: A4 | B32: Агенты и автономные системы | C32: III | D32: Автономное исполнение регламентов с анализом бизнес-процессов | E32: 70 | F32: A3 | I32: Агенты анализируют журналы исполнения процессов, находят повторяющиеся операции и выполняют заранее определённые регламенты с минимальным участием человека. Возрастает скорость организационных изменений и экономическая отдача от цифровизации. Вместе с тем автоматизация привычных функций может вызывать недоверие и сопротивление работников, особенно если способы пересмотра решений недостаточно понятны. Эти социальные издержки представлены двумя отрицательными эффектами. | J32: + Организационная способность к изменению: +0,40; + Прирост сферы «Экономика»: +0,08/год; + Оцифрованность деятельности: +0,20; + Прирост сферы «Принятие ИИ»: +0,05/год; − Социальное доверие: -0,15; − Готовность работников к использованию ИИ: -0,15 | K32: =SUMIF('Ход 2026'!$G$29:$G$38,$A32,'Ход 2026'!$I$29:$I$38)*(1+'Эффекты технологий'!J$7+'Эффекты технологий'!J$9) -> 0 | L32: =SUMIF('Ход 2027'!$G$29:$G$38,$A32,'Ход 2027'!$I$29:$I$38)*(1+'Эффекты технологий'!K$7+'Эффекты технологий'!K$9) -> 0 | M32: =SUMIF('Ход 2028'!$G$29:$G$38,$A32,'Ход 2028'!$I$29:$I$38)*(1+'Эффекты технологий'!L$7+'Эффекты технологий'!L$9) -> 0 | N32: =SUMIF('Ход 2029'!$G$29:$G$38,$A32,'Ход 2029'!$I$29:$I$38)*(1+'Эффекты технологий'!M$7+'Эффекты технологий'!M$9) -> 0 | O32: =SUMIF('Ход 2030'!$G$29:$G$38,$A32,'Ход 2030'!$I$29:$I$38)*(1+'Эффекты технологий'!N$7+'Эффекты технологий'!N$9) -> 0 | P32: =SUMIF('Ход 2031'!$G$29:$G$38,$A32,'Ход 2031'!$I$29:$I$38)*(1+'Эффекты технологий'!O$7+'Эффекты технологий'!O$9) -> 0 | Q32: =SUMIF('Ход 2032'!$G$29:$G$38,$A32,'Ход 2032'!$I$29:$I$38)*(1+'Эффекты технологий'!P$7+'Эффекты технологий'!P$9) -> 0 | R32: =SUMIF('Ход 2033'!$G$29:$G$38,$A32,'Ход 2033'!$I$29:$I$38)*(1+'Эффекты технологий'!Q$7+'Эффекты технологий'!Q$9) -> 0 | S32: =SUMIF('Ход 2034'!$G$29:$G$38,$A32,'Ход 2034'!$I$29:$I$38)*(1+'Эффекты технологий'!R$7+'Эффекты технологий'!R$9) -> 0 | T32: =SUMIF('Ход 2035'!$G$29:$G$38,$A32,'Ход 2035'!$I$29:$I$38)*(1+'Эффекты технологий'!S$7+'Эффекты технологий'!S$9) -> 0 | U32: =SUMIF('Ход 2036'!$G$29:$G$38,$A32,'Ход 2036'!$I$29:$I$38)*(1+'Эффекты технологий'!T$7+'Эффекты технологий'!T$9) -> 0 | V32: =SUMIF('Ход 2037'!$G$29:$G$38,$A32,'Ход 2037'!$I$29:$I$38)*(1+'Эффекты технологий'!U$7+'Эффекты технологий'!U$9) -> 0 | W32: =SUMIF('Ход 2038'!$G$29:$G$38,$A32,'Ход 2038'!$I$29:$I$38)*(1+'Эффекты технологий'!V$7+'Эффекты технологий'!V$9) -> 0 | X32: =SUMIF('Ход 2039'!$G$29:$G$38,$A32,'Ход 2039'!$I$29:$I$38)*(1+'Эффекты технологий'!W$7+'Эффекты технологий'!W$9) -> 0 | Y32: =SUMIF('Ход 2040'!$G$29:$G$38,$A32,'Ход 2040'!$I$29:$I$38)*(1+'Эффекты технологий'!X$7+'Эффекты технологий'!X$9) -> 0 | Z32: =SUM(K32:Y32) -> 0 | AA32: =MAX(0,E32-Z32) -> 70 | AB32: =BF32 -> ОТКРЫТО | AC32: =SUM($K32:K32) -> 0 | AD32: =SUM($K32:L32) -> 0 | AE32: =SUM($K32:M32) -> 0 | AF32: =SUM($K32:N32) -> 0 | AG32: =SUM($K32:O32) -> 0 | AH32: =SUM($K32:P32) -> 0 | AI32: =SUM($K32:Q32) -> 0 | AJ32: =SUM($K32:R32) -> 0 | ... AQ32: =SUM($K32:Y32) -> 0 | AR32: =IF(AND(AC32>=$E32,TRUE),"ИЗУЧЕНО",IF(TRUE,"ОТКРЫТО","ЗАКРЫТО")) -> ОТКРЫТО | AS32: =IF(AND(AD32>=$E32,TRUE),"ИЗУЧЕНО",IF(TRUE,"ОТКРЫТО","ЗАКРЫТО")) -> ОТКРЫТО | AT32: =IF(AND(AE32>=$E32,TRUE),"ИЗУЧЕНО",IF(TRUE,"ОТКРЫТО","ЗАКРЫТО")) -> ОТКРЫТО | AU32: =IF(AND(AF32>=$E32,TRUE),"ИЗУЧЕНО",IF(TRUE,"ОТКРЫТО","ЗАКРЫТО")) -> ОТКРЫТО | AV32: =IF(AND(AG32>=$E32,TRUE),"ИЗУЧЕНО",IF(TRUE,"ОТКРЫТО","ЗАКРЫТО")) -> ОТКРЫТО | AW32: =IF(AND(AH32>=$E32,TRUE),"ИЗУЧЕНО",IF(TRUE,"ОТКРЫТО","ЗАКРЫТО")) -> ОТКРЫТО | AX32: =IF(AND(AI32>=$E32,TRUE),"ИЗУЧЕНО",IF(TRUE,"ОТКРЫТО","ЗАКРЫТО")) -> ОТКРЫТО | AY32: =IF(AND(AJ32>=$E32,TRUE),"ИЗУЧЕНО",IF(TRUE,"ОТКРЫТО","ЗАКРЫТО")) -> ОТКРЫТО | ... BF32: =IF(AND(AQ32>=$E32,TRUE),"ИЗУЧЕНО",IF(TRUE,"ОТКРЫТО","ЗАКРЫТО")) -> ОТКРЫТО | BG32: =IFERROR(2025+MATCH("ИЗУЧЕНО",AR32:BF32,0),"") | BH32: =IF(BG32="","",BG32+1)
A33: A5 | B33: Агенты и автономные системы | C33: IV | D33: Государственные ИИ-агенты с транзакционным доступом к реестрам | E33: 105 | F33: A4 | I33: Агенты подключаются к государственным информационным системам и могут выполнять разрешённые операции с реестрами, заявлениями и документами. Это ускоряет предоставление услуг, координацию ведомств и подготовку управленческих решений. Международное взаимодействие также становится эффективнее. Высокие полномочия агентов создают значительные риски несанкционированных операций, нарушения разграничения доступа и снижения доверия граждан, поэтому технология требует существенных институциональных издержек. | J33: + Прирост сферы «Государственное управление»: +0,12/год; + Прирост сферы «Управление»: +0,08/год; + Система управления ИИ: +0,30; + Документационные ресурсы: +0,20; + Эффективность улучшения дипломатических отношений: +10%; − Кибербезопасностные ресурсы: -0,25; − Права доступа к информационным ресурсам: -0,20; − Социальное доверие: -0,15 | K33: =SUMIF('Ход 2026'!$G$29:$G$38,$A33,'Ход 2026'!$I$29:$I$38)*(1+'Эффекты технологий'!J$7+'Эффекты технологий'!J$9) -> 0 | L33: =SUMIF('Ход 2027'!$G$29:$G$38,$A33,'Ход 2027'!$I$29:$I$38)*(1+'Эффекты технологий'!K$7+'Эффекты технологий'!K$9) -> 0 | M33: =SUMIF('Ход 2028'!$G$29:$G$38,$A33,'Ход 2028'!$I$29:$I$38)*(1+'Эффекты технологий'!L$7+'Эффекты технологий'!L$9) -> 0 | N33: =SUMIF('Ход 2029'!$G$29:$G$38,$A33,'Ход 2029'!$I$29:$I$38)*(1+'Эффекты технологий'!M$7+'Эффекты технологий'!M$9) -> 0 | O33: =SUMIF('Ход 2030'!$G$29:$G$38,$A33,'Ход 2030'!$I$29:$I$38)*(1+'Эффекты технологий'!N$7+'Эффекты технологий'!N$9) -> 0 | P33: =SUMIF('Ход 2031'!$G$29:$G$38,$A33,'Ход 2031'!$I$29:$I$38)*(1+'Эффекты технологий'!O$7+'Эффекты технологий'!O$9) -> 0 | Q33: =SUMIF('Ход 2032'!$G$29:$G$38,$A33,'Ход 2032'!$I$29:$I$38)*(1+'Эффекты технологий'!P$7+'Эффекты технологий'!P$9) -> 0 | R33: =SUMIF('Ход 2033'!$G$29:$G$38,$A33,'Ход 2033'!$I$29:$I$38)*(1+'Эффекты технологий'!Q$7+'Эффекты технологий'!Q$9) -> 0 | S33: =SUMIF('Ход 2034'!$G$29:$G$38,$A33,'Ход 2034'!$I$29:$I$38)*(1+'Эффекты технологий'!R$7+'Эффекты технологий'!R$9) -> 0 | T33: =SUMIF('Ход 2035'!$G$29:$G$38,$A33,'Ход 2035'!$I$29:$I$38)*(1+'Эффекты технологий'!S$7+'Эффекты технологий'!S$9) -> 0 | U33: =SUMIF('Ход 2036'!$G$29:$G$38,$A33,'Ход 2036'!$I$29:$I$38)*(1+'Эффекты технологий'!T$7+'Эффекты технологий'!T$9) -> 0 | V33: =SUMIF('Ход 2037'!$G$29:$G$38,$A33,'Ход 2037'!$I$29:$I$38)*(1+'Эффекты технологий'!U$7+'Эффекты технологий'!U$9) -> 0 | W33: =SUMIF('Ход 2038'!$G$29:$G$38,$A33,'Ход 2038'!$I$29:$I$38)*(1+'Эффекты технологий'!V$7+'Эффекты технологий'!V$9) -> 0 | X33: =SUMIF('Ход 2039'!$G$29:$G$38,$A33,'Ход 2039'!$I$29:$I$38)*(1+'Эффекты технологий'!W$7+'Эффекты технологий'!W$9) -> 0 | Y33: =SUMIF('Ход 2040'!$G$29:$G$38,$A33,'Ход 2040'!$I$29:$I$38)*(1+'Эффекты технологий'!X$7+'Эффекты технологий'!X$9) -> 0 | Z33: =SUM(K33:Y33) -> 0 | AA33: =MAX(0,E33-Z33) -> 105 | AB33: =BF33 -> ОТКРЫТО | AC33: =SUM($K33:K33) -> 0 | AD33: =SUM($K33:L33) -> 0 | AE33: =SUM($K33:M33) -> 0 | AF33: =SUM($K33:N33) -> 0 | AG33: =SUM($K33:O33) -> 0 | AH33: =SUM($K33:P33) -> 0 | AI33: =SUM($K33:Q33) -> 0 | AJ33: =SUM($K33:R33) -> 0 | ... AQ33: =SUM($K33:Y33) -> 0 | AR33: =IF(AND(AC33>=$E33,TRUE),"ИЗУЧЕНО",IF(TRUE,"ОТКРЫТО","ЗАКРЫТО")) -> ОТКРЫТО | AS33: =IF(AND(AD33>=$E33,TRUE),"ИЗУЧЕНО",IF(TRUE,"ОТКРЫТО","ЗАКРЫТО")) -> ОТКРЫТО | AT33: =IF(AND(AE33>=$E33,TRUE),"ИЗУЧЕНО",IF(TRUE,"ОТКРЫТО","ЗАКРЫТО")) -> ОТКРЫТО | AU33: =IF(AND(AF33>=$E33,TRUE),"ИЗУЧЕНО",IF(TRUE,"ОТКРЫТО","ЗАКРЫТО")) -> ОТКРЫТО | AV33: =IF(AND(AG33>=$E33,TRUE),"ИЗУЧЕНО",IF(TRUE,"ОТКРЫТО","ЗАКРЫТО")) -> ОТКРЫТО | AW33: =IF(AND(AH33>=$E33,TRUE),"ИЗУЧЕНО",IF(TRUE,"ОТКРЫТО","ЗАКРЫТО")) -> ОТКРЫТО | AX33: =IF(AND(AI33>=$E33,TRUE),"ИЗУЧЕНО",IF(TRUE,"ОТКРЫТО","ЗАКРЫТО")) -> ОТКРЫТО | AY33: =IF(AND(AJ33>=$E33,TRUE),"ИЗУЧЕНО",IF(TRUE,"ОТКРЫТО","ЗАКРЫТО")) -> ОТКРЫТО | ... BF33: =IF(AND(AQ33>=$E33,TRUE),"ИЗУЧЕНО",IF(TRUE,"ОТКРЫТО","ЗАКРЫТО")) -> ОТКРЫТО | BG33: =IFERROR(2025+MATCH("ИЗУЧЕНО",AR33:BF33,0),"") | BH33: =IF(BG33="","",BG33+1)
A34: A6 | B34: Агенты и автономные системы | C34: V | D34: Агентные контуры стратегического планирования с цифровыми двойниками | E34: 155 | F34: A5 | I34: Цифровые двойники государственных и экономических процессов позволяют агентам моделировать последствия альтернативных решений, распределять задачи и координировать исполнение. Страна получает стратегическое преимущество в управлении потоками и смыслами, отражённое бонусами к двум видам войны. Однако глубокая автоматизация делает государство зависимым от сложной системы полномочий и алгоритмов. Возникают риски кибератак, непрозрачности и технологической инерции при изменении управленческой архитектуры. | J34: + Сфера «Управление»: +0,40; + Сфера «Государственное управление»: +0,30; + Сфера «Познание»: +0,25; + Прирост сферы «Экономика»: +0,10/год; + Атака в войне Афины: +15%; + Атака в войне Аполлона: +15%; − Кибербезопасностные ресурсы: -0,30; − Права доступа к информационным ресурсам: -0,25; − Социальное доверие: -0,20; − Организационная способность к изменению: -0,15 | K34: =SUMIF('Ход 2026'!$G$29:$G$38,$A34,'Ход 2026'!$I$29:$I$38)*(1+'Эффекты технологий'!J$7+'Эффекты технологий'!J$9) -> 0 | L34: =SUMIF('Ход 2027'!$G$29:$G$38,$A34,'Ход 2027'!$I$29:$I$38)*(1+'Эффекты технологий'!K$7+'Эффекты технологий'!K$9) -> 0 | M34: =SUMIF('Ход 2028'!$G$29:$G$38,$A34,'Ход 2028'!$I$29:$I$38)*(1+'Эффекты технологий'!L$7+'Эффекты технологий'!L$9) -> 0 | N34: =SUMIF('Ход 2029'!$G$29:$G$38,$A34,'Ход 2029'!$I$29:$I$38)*(1+'Эффекты технологий'!M$7+'Эффекты технологий'!M$9) -> 0 | O34: =SUMIF('Ход 2030'!$G$29:$G$38,$A34,'Ход 2030'!$I$29:$I$38)*(1+'Эффекты технологий'!N$7+'Эффекты технологий'!N$9) -> 0 | P34: =SUMIF('Ход 2031'!$G$29:$G$38,$A34,'Ход 2031'!$I$29:$I$38)*(1+'Эффекты технологий'!O$7+'Эффекты технологий'!O$9) -> 0 | Q34: =SUMIF('Ход 2032'!$G$29:$G$38,$A34,'Ход 2032'!$I$29:$I$38)*(1+'Эффекты технологий'!P$7+'Эффекты технологий'!P$9) -> 0 | R34: =SUMIF('Ход 2033'!$G$29:$G$38,$A34,'Ход 2033'!$I$29:$I$38)*(1+'Эффекты технологий'!Q$7+'Эффекты технологий'!Q$9) -> 0 | S34: =SUMIF('Ход 2034'!$G$29:$G$38,$A34,'Ход 2034'!$I$29:$I$38)*(1+'Эффекты технологий'!R$7+'Эффекты технологий'!R$9) -> 0 | T34: =SUMIF('Ход 2035'!$G$29:$G$38,$A34,'Ход 2035'!$I$29:$I$38)*(1+'Эффекты технологий'!S$7+'Эффекты технологий'!S$9) -> 0 | U34: =SUMIF('Ход 2036'!$G$29:$G$38,$A34,'Ход 2036'!$I$29:$I$38)*(1+'Эффекты технологий'!T$7+'Эффекты технологий'!T$9) -> 0 | V34: =SUMIF('Ход 2037'!$G$29:$G$38,$A34,'Ход 2037'!$I$29:$I$38)*(1+'Эффекты технологий'!U$7+'Эффекты технологий'!U$9) -> 0 | W34: =SUMIF('Ход 2038'!$G$29:$G$38,$A34,'Ход 2038'!$I$29:$I$38)*(1+'Эффекты технологий'!V$7+'Эффекты технологий'!V$9) -> 0 | X34: =SUMIF('Ход 2039'!$G$29:$G$38,$A34,'Ход 2039'!$I$29:$I$38)*(1+'Эффекты технологий'!W$7+'Эффекты технологий'!W$9) -> 0 | Y34: =SUMIF('Ход 2040'!$G$29:$G$38,$A34,'Ход 2040'!$I$29:$I$38)*(1+'Эффекты технологий'!X$7+'Эффекты технологий'!X$9) -> 0 | Z34: =SUM(K34:Y34) -> 0 | AA34: =MAX(0,E34-Z34) -> 155 | AB34: =BF34 -> ОТКРЫТО | AC34: =SUM($K34:K34) -> 0 | AD34: =SUM($K34:L34) -> 0 | AE34: =SUM($K34:M34) -> 0 | AF34: =SUM($K34:N34) -> 0 | AG34: =SUM($K34:O34) -> 0 | AH34: =SUM($K34:P34) -> 0 | AI34: =SUM($K34:Q34) -> 0 | AJ34: =SUM($K34:R34) -> 0 | ... AQ34: =SUM($K34:Y34) -> 0 | AR34: =IF(AND(AC34>=$E34,TRUE),"ИЗУЧЕНО",IF(TRUE,"ОТКРЫТО","ЗАКРЫТО")) -> ОТКРЫТО | AS34: =IF(AND(AD34>=$E34,TRUE),"ИЗУЧЕНО",IF(TRUE,"ОТКРЫТО","ЗАКРЫТО")) -> ОТКРЫТО | AT34: =IF(AND(AE34>=$E34,TRUE),"ИЗУЧЕНО",IF(TRUE,"ОТКРЫТО","ЗАКРЫТО")) -> ОТКРЫТО | AU34: =IF(AND(AF34>=$E34,TRUE),"ИЗУЧЕНО",IF(TRUE,"ОТКРЫТО","ЗАКРЫТО")) -> ОТКРЫТО | AV34: =IF(AND(AG34>=$E34,TRUE),"ИЗУЧЕНО",IF(TRUE,"ОТКРЫТО","ЗАКРЫТО")) -> ОТКРЫТО | AW34: =IF(AND(AH34>=$E34,TRUE),"ИЗУЧЕНО",IF(TRUE,"ОТКРЫТО","ЗАКРЫТО")) -> ОТКРЫТО | AX34: =IF(AND(AI34>=$E34,TRUE),"ИЗУЧЕНО",IF(TRUE,"ОТКРЫТО","ЗАКРЫТО")) -> ОТКРЫТО | AY34: =IF(AND(AJ34>=$E34,TRUE),"ИЗУЧЕНО",IF(TRUE,"ОТКРЫТО","ЗАКРЫТО")) -> ОТКРЫТО | ... BF34: =IF(AND(AQ34>=$E34,TRUE),"ИЗУЧЕНО",IF(TRUE,"ОТКРЫТО","ЗАКРЫТО")) -> ОТКРЫТО | BG34: =IFERROR(2025+MATCH("ИЗУЧЕНО",AR34:BF34,0),"") | BH34: =IF(BG34="","",BG34+1)
A35: R1 | B35: Физический ИИ и робототехника | C35: I | D35: Машинное зрение для промышленного контроля качества | E35: 20 | I35: Камеры и алгоритмы компьютерного зрения автоматически выявляют дефекты изделий, измеряют параметры и фиксируют состояние производственных процессов. Возникают цифровые данные о ранее слабо наблюдаемых операциях. Это первый шаг к физическому ИИ: он ещё не передаёт машинам самостоятельное управление материальными объектами, но создаёт информационную основу для роботизации. Поэтому технология даёт один эффект на цифровизацию без дополнительных ресурсных штрафов. | J35: + Оцифрованность деятельности: +0,20 | K35: =SUMIF('Ход 2026'!$G$29:$G$38,$A35,'Ход 2026'!$I$29:$I$38)*(1+'Эффекты технологий'!J$7) -> 20 | L35: =SUMIF('Ход 2027'!$G$29:$G$38,$A35,'Ход 2027'!$I$29:$I$38)*(1+'Эффекты технологий'!K$7) -> 0 | M35: =SUMIF('Ход 2028'!$G$29:$G$38,$A35,'Ход 2028'!$I$29:$I$38)*(1+'Эффекты технологий'!L$7) -> 0 | N35: =SUMIF('Ход 2029'!$G$29:$G$38,$A35,'Ход 2029'!$I$29:$I$38)*(1+'Эффекты технологий'!M$7) -> 0 | O35: =SUMIF('Ход 2030'!$G$29:$G$38,$A35,'Ход 2030'!$I$29:$I$38)*(1+'Эффекты технологий'!N$7) -> 0 | P35: =SUMIF('Ход 2031'!$G$29:$G$38,$A35,'Ход 2031'!$I$29:$I$38)*(1+'Эффекты технологий'!O$7) -> 0 | Q35: =SUMIF('Ход 2032'!$G$29:$G$38,$A35,'Ход 2032'!$I$29:$I$38)*(1+'Эффекты технологий'!P$7) -> 0 | R35: =SUMIF('Ход 2033'!$G$29:$G$38,$A35,'Ход 2033'!$I$29:$I$38)*(1+'Эффекты технологий'!Q$7) -> 0 | S35: =SUMIF('Ход 2034'!$G$29:$G$38,$A35,'Ход 2034'!$I$29:$I$38)*(1+'Эффекты технологий'!R$7) -> 0 | T35: =SUMIF('Ход 2035'!$G$29:$G$38,$A35,'Ход 2035'!$I$29:$I$38)*(1+'Эффекты технологий'!S$7) -> 0 | U35: =SUMIF('Ход 2036'!$G$29:$G$38,$A35,'Ход 2036'!$I$29:$I$38)*(1+'Эффекты технологий'!T$7) -> 0 | V35: =SUMIF('Ход 2037'!$G$29:$G$38,$A35,'Ход 2037'!$I$29:$I$38)*(1+'Эффекты технологий'!U$7) -> 0 | W35: =SUMIF('Ход 2038'!$G$29:$G$38,$A35,'Ход 2038'!$I$29:$I$38)*(1+'Эффекты технологий'!V$7) -> 0 | X35: =SUMIF('Ход 2039'!$G$29:$G$38,$A35,'Ход 2039'!$I$29:$I$38)*(1+'Эффекты технологий'!W$7) -> 0 | Y35: =SUMIF('Ход 2040'!$G$29:$G$38,$A35,'Ход 2040'!$I$29:$I$38)*(1+'Эффекты технологий'!X$7) -> 0 | Z35: =SUM(K35:Y35) -> 20 | AA35: =MAX(0,E35-Z35) -> 0 | AB35: =BF35 -> ИЗУЧЕНО | AC35: =SUM($K35:K35) -> 20 | AD35: =SUM($K35:L35) -> 20 | AE35: =SUM($K35:M35) -> 20 | AF35: =SUM($K35:N35) -> 20 | AG35: =SUM($K35:O35) -> 20 | AH35: =SUM($K35:P35) -> 20 | AI35: =SUM($K35:Q35) -> 20 | AJ35: =SUM($K35:R35) -> 20 | ... AQ35: =SUM($K35:Y35) -> 20 | AR35: =IF(AND(AC35>=$E35,TRUE),"ИЗУЧЕНО",IF(TRUE,"ОТКРЫТО","ЗАКРЫТО")) -> ИЗУЧЕНО | AS35: =IF(AND(AD35>=$E35,TRUE),"ИЗУЧЕНО",IF(TRUE,"ОТКРЫТО","ЗАКРЫТО")) -> ИЗУЧЕНО | AT35: =IF(AND(AE35>=$E35,TRUE),"ИЗУЧЕНО",IF(TRUE,"ОТКРЫТО","ЗАКРЫТО")) -> ИЗУЧЕНО | AU35: =IF(AND(AF35>=$E35,TRUE),"ИЗУЧЕНО",IF(TRUE,"ОТКРЫТО","ЗАКРЫТО")) -> ИЗУЧЕНО | AV35: =IF(AND(AG35>=$E35,TRUE),"ИЗУЧЕНО",IF(TRUE,"ОТКРЫТО","ЗАКРЫТО")) -> ИЗУЧЕНО | AW35: =IF(AND(AH35>=$E35,TRUE),"ИЗУЧЕНО",IF(TRUE,"ОТКРЫТО","ЗАКРЫТО")) -> ИЗУЧЕНО | AX35: =IF(AND(AI35>=$E35,TRUE),"ИЗУЧЕНО",IF(TRUE,"ОТКРЫТО","ЗАКРЫТО")) -> ИЗУЧЕНО | AY35: =IF(AND(AJ35>=$E35,TRUE),"ИЗУЧЕНО",IF(TRUE,"ОТКРЫТО","ЗАКРЫТО")) -> ИЗУЧЕНО | ... BF35: =IF(AND(AQ35>=$E35,TRUE),"ИЗУЧЕНО",IF(TRUE,"ОТКРЫТО","ЗАКРЫТО")) -> ИЗУЧЕНО | BG35: =IFERROR(2025+MATCH("ИЗУЧЕНО",AR35:BF35,0),"") -> 2026 | BH35: =IF(BG35="","",BG35+1) -> 2027
A36: R2 | B36: Физический ИИ и робототехника | C36: II | D36: Роботы-манипуляторы с силомоментным управлением | E36: 40 | F36: R1 | I36: Манипуляторы используют датчики усилия, положения и обратную связь для захвата предметов, сборки деталей и выполнения точных операций. Они могут работать с изменяющимися объектами и взаимодействовать с людьми на производстве. Технология непосредственно повышает производство и создаёт опыт использования интеллектуальных машин работниками. Постоянная эксплуатация приводов, сенсоров и контроллеров требует дополнительных энергетических ресурсов. | J36: + Сфера «Производство»: +0,30; прирост +0,08/год; + Готовность работников к использованию ИИ: +0,20; − Энергетические ресурсы: -0,15 | K36: =SUMIF('Ход 2026'!$G$29:$G$38,$A36,'Ход 2026'!$I$29:$I$38)*(1+'Эффекты технологий'!J$7) -> 0 | L36: =SUMIF('Ход 2027'!$G$29:$G$38,$A36,'Ход 2027'!$I$29:$I$38)*(1+'Эффекты технологий'!K$7) -> 0 | M36: =SUMIF('Ход 2028'!$G$29:$G$38,$A36,'Ход 2028'!$I$29:$I$38)*(1+'Эффекты технологий'!L$7) -> 0 | N36: =SUMIF('Ход 2029'!$G$29:$G$38,$A36,'Ход 2029'!$I$29:$I$38)*(1+'Эффекты технологий'!M$7) -> 0 | O36: =SUMIF('Ход 2030'!$G$29:$G$38,$A36,'Ход 2030'!$I$29:$I$38)*(1+'Эффекты технологий'!N$7) -> 0 | P36: =SUMIF('Ход 2031'!$G$29:$G$38,$A36,'Ход 2031'!$I$29:$I$38)*(1+'Эффекты технологий'!O$7) -> 0 | Q36: =SUMIF('Ход 2032'!$G$29:$G$38,$A36,'Ход 2032'!$I$29:$I$38)*(1+'Эффекты технологий'!P$7) -> 0 | R36: =SUMIF('Ход 2033'!$G$29:$G$38,$A36,'Ход 2033'!$I$29:$I$38)*(1+'Эффекты технологий'!Q$7) -> 0 | S36: =SUMIF('Ход 2034'!$G$29:$G$38,$A36,'Ход 2034'!$I$29:$I$38)*(1+'Эффекты технологий'!R$7) -> 0 | T36: =SUMIF('Ход 2035'!$G$29:$G$38,$A36,'Ход 2035'!$I$29:$I$38)*(1+'Эффекты технологий'!S$7) -> 0 | U36: =SUMIF('Ход 2036'!$G$29:$G$38,$A36,'Ход 2036'!$I$29:$I$38)*(1+'Эффекты технологий'!T$7) -> 0 | V36: =SUMIF('Ход 2037'!$G$29:$G$38,$A36,'Ход 2037'!$I$29:$I$38)*(1+'Эффекты технологий'!U$7) -> 0 | W36: =SUMIF('Ход 2038'!$G$29:$G$38,$A36,'Ход 2038'!$I$29:$I$38)*(1+'Эффекты технологий'!V$7) -> 0 | X36: =SUMIF('Ход 2039'!$G$29:$G$38,$A36,'Ход 2039'!$I$29:$I$38)*(1+'Эффекты технологий'!W$7) -> 0 | Y36: =SUMIF('Ход 2040'!$G$29:$G$38,$A36,'Ход 2040'!$I$29:$I$38)*(1+'Эффекты технологий'!X$7) -> 0 | Z36: =SUM(K36:Y36) -> 0 | AA36: =MAX(0,E36-Z36) -> 40 | AB36: =BF36 -> ОТКРЫТО | AC36: =SUM($K36:K36) -> 0 | AD36: =SUM($K36:L36) -> 0 | AE36: =SUM($K36:M36) -> 0 | AF36: =SUM($K36:N36) -> 0 | AG36: =SUM($K36:O36) -> 0 | AH36: =SUM($K36:P36) -> 0 | AI36: =SUM($K36:Q36) -> 0 | AJ36: =SUM($K36:R36) -> 0 | ... AQ36: =SUM($K36:Y36) -> 0 | AR36: =IF(AND(AC36>=$E36,TRUE),"ИЗУЧЕНО",IF(TRUE,"ОТКРЫТО","ЗАКРЫТО")) -> ОТКРЫТО | AS36: =IF(AND(AD36>=$E36,TRUE),"ИЗУЧЕНО",IF(TRUE,"ОТКРЫТО","ЗАКРЫТО")) -> ОТКРЫТО | AT36: =IF(AND(AE36>=$E36,TRUE),"ИЗУЧЕНО",IF(TRUE,"ОТКРЫТО","ЗАКРЫТО")) -> ОТКРЫТО | AU36: =IF(AND(AF36>=$E36,TRUE),"ИЗУЧЕНО",IF(TRUE,"ОТКРЫТО","ЗАКРЫТО")) -> ОТКРЫТО | AV36: =IF(AND(AG36>=$E36,TRUE),"ИЗУЧЕНО",IF(TRUE,"ОТКРЫТО","ЗАКРЫТО")) -> ОТКРЫТО | AW36: =IF(AND(AH36>=$E36,TRUE),"ИЗУЧЕНО",IF(TRUE,"ОТКРЫТО","ЗАКРЫТО")) -> ОТКРЫТО | AX36: =IF(AND(AI36>=$E36,TRUE),"ИЗУЧЕНО",IF(TRUE,"ОТКРЫТО","ЗАКРЫТО")) -> ОТКРЫТО | AY36: =IF(AND(AJ36>=$E36,TRUE),"ИЗУЧЕНО",IF(TRUE,"ОТКРЫТО","ЗАКРЫТО")) -> ОТКРЫТО | ... BF36: =IF(AND(AQ36>=$E36,TRUE),"ИЗУЧЕНО",IF(TRUE,"ОТКРЫТО","ЗАКРЫТО")) -> ОТКРЫТО | BG36: =IFERROR(2025+MATCH("ИЗУЧЕНО",AR36:BF36,0),"") | BH36: =IF(BG36="","",BG36+1)
A37: R3 | B37: Физический ИИ и робототехника | C37: II | D37: Автономная логистика с SLAM и многороботной маршрутизацией | E37: 45 | F37: R1 | I37: Мобильные роботы строят карту окружающей среды, оценивают своё положение и совместно планируют маршруты. Такие системы могут управлять складской, производственной и частью транспортной логистики. Выигрыш проявляется в экономике и управлении потоками, что дополнительно усиливает защиту в войне Афины. Для массового развёртывания требуется перестройка площадок, терминалов и транспортных коридоров, поэтому уменьшается доступный пространственный ресурс. | J37: + Прирост сферы «Экономика»: +0,08/год; + Сетевые ресурсы: +0,20; + Защита от войны Афины: +10%; − Пространственные и природно-географические ресурсы: -0,20 | K37: =SUMIF('Ход 2026'!$G$29:$G$38,$A37,'Ход 2026'!$I$29:$I$38)*(1+'Эффекты технологий'!J$7) -> 0 | L37: =SUMIF('Ход 2027'!$G$29:$G$38,$A37,'Ход 2027'!$I$29:$I$38)*(1+'Эффекты технологий'!K$7) -> 0 | M37: =SUMIF('Ход 2028'!$G$29:$G$38,$A37,'Ход 2028'!$I$29:$I$38)*(1+'Эффекты технологий'!L$7) -> 0 | N37: =SUMIF('Ход 2029'!$G$29:$G$38,$A37,'Ход 2029'!$I$29:$I$38)*(1+'Эффекты технологий'!M$7) -> 0 | O37: =SUMIF('Ход 2030'!$G$29:$G$38,$A37,'Ход 2030'!$I$29:$I$38)*(1+'Эффекты технологий'!N$7) -> 0 | P37: =SUMIF('Ход 2031'!$G$29:$G$38,$A37,'Ход 2031'!$I$29:$I$38)*(1+'Эффекты технологий'!O$7) -> 0 | Q37: =SUMIF('Ход 2032'!$G$29:$G$38,$A37,'Ход 2032'!$I$29:$I$38)*(1+'Эффекты технологий'!P$7) -> 0 | R37: =SUMIF('Ход 2033'!$G$29:$G$38,$A37,'Ход 2033'!$I$29:$I$38)*(1+'Эффекты технологий'!Q$7) -> 0 | S37: =SUMIF('Ход 2034'!$G$29:$G$38,$A37,'Ход 2034'!$I$29:$I$38)*(1+'Эффекты технологий'!R$7) -> 0 | T37: =SUMIF('Ход 2035'!$G$29:$G$38,$A37,'Ход 2035'!$I$29:$I$38)*(1+'Эффекты технологий'!S$7) -> 0 | U37: =SUMIF('Ход 2036'!$G$29:$G$38,$A37,'Ход 2036'!$I$29:$I$38)*(1+'Эффекты технологий'!T$7) -> 0 | V37: =SUMIF('Ход 2037'!$G$29:$G$38,$A37,'Ход 2037'!$I$29:$I$38)*(1+'Эффекты технологий'!U$7) -> 0 | W37: =SUMIF('Ход 2038'!$G$29:$G$38,$A37,'Ход 2038'!$I$29:$I$38)*(1+'Эффекты технологий'!V$7) -> 0 | X37: =SUMIF('Ход 2039'!$G$29:$G$38,$A37,'Ход 2039'!$I$29:$I$38)*(1+'Эффекты технологий'!W$7) -> 0 | Y37: =SUMIF('Ход 2040'!$G$29:$G$38,$A37,'Ход 2040'!$I$29:$I$38)*(1+'Эффекты технологий'!X$7) -> 0 | Z37: =SUM(K37:Y37) -> 0 | AA37: =MAX(0,E37-Z37) -> 45 | AB37: =BF37 -> ОТКРЫТО | AC37: =SUM($K37:K37) -> 0 | AD37: =SUM($K37:L37) -> 0 | AE37: =SUM($K37:M37) -> 0 | AF37: =SUM($K37:N37) -> 0 | AG37: =SUM($K37:O37) -> 0 | AH37: =SUM($K37:P37) -> 0 | AI37: =SUM($K37:Q37) -> 0 | AJ37: =SUM($K37:R37) -> 0 | ... AQ37: =SUM($K37:Y37) -> 0 | AR37: =IF(AND(AC37>=$E37,TRUE),"ИЗУЧЕНО",IF(TRUE,"ОТКРЫТО","ЗАКРЫТО")) -> ОТКРЫТО | AS37: =IF(AND(AD37>=$E37,TRUE),"ИЗУЧЕНО",IF(TRUE,"ОТКРЫТО","ЗАКРЫТО")) -> ОТКРЫТО | AT37: =IF(AND(AE37>=$E37,TRUE),"ИЗУЧЕНО",IF(TRUE,"ОТКРЫТО","ЗАКРЫТО")) -> ОТКРЫТО | AU37: =IF(AND(AF37>=$E37,TRUE),"ИЗУЧЕНО",IF(TRUE,"ОТКРЫТО","ЗАКРЫТО")) -> ОТКРЫТО | AV37: =IF(AND(AG37>=$E37,TRUE),"ИЗУЧЕНО",IF(TRUE,"ОТКРЫТО","ЗАКРЫТО")) -> ОТКРЫТО | AW37: =IF(AND(AH37>=$E37,TRUE),"ИЗУЧЕНО",IF(TRUE,"ОТКРЫТО","ЗАКРЫТО")) -> ОТКРЫТО | AX37: =IF(AND(AI37>=$E37,TRUE),"ИЗУЧЕНО",IF(TRUE,"ОТКРЫТО","ЗАКРЫТО")) -> ОТКРЫТО | AY37: =IF(AND(AJ37>=$E37,TRUE),"ИЗУЧЕНО",IF(TRUE,"ОТКРЫТО","ЗАКРЫТО")) -> ОТКРЫТО | ... BF37: =IF(AND(AQ37>=$E37,TRUE),"ИЗУЧЕНО",IF(TRUE,"ОТКРЫТО","ЗАКРЫТО")) -> ОТКРЫТО | BG37: =IFERROR(2025+MATCH("ИЗУЧЕНО",AR37:BF37,0),"") | BH37: =IF(BG37="","",BG37+1)
A38: R4 | B38: Физический ИИ и робототехника | C38: III | D38: Автономные мобильные роботизированные комплексы с коллективным управлением | E38: 70 | F38: R2 | G38: R3 | I38: Несколько мобильных платформ координируют движение и действия через общие каналы связи и алгоритмы коллективного управления. Такие машины применимы в промышленной среде, мониторинге территории и материально-пространственных операциях. Именно поэтому технология повышает атаку в войне Ареса. Производство мобильных платформ требует металлов, электроники и аккумуляторов, а эксплуатация - постоянного энергоснабжения, что приводит к двум материальным штрафам. | J38: + Прирост сферы «Война»: +0,08/год; + Сфера «Производство»: +0,20; + Сетевые ресурсы: +0,20; + Атака в войне Ареса: +15%; − Минерально-сырьевые ресурсы: -0,20; − Энергетические ресурсы: -0,30 | K38: =SUMIF('Ход 2026'!$G$29:$G$38,$A38,'Ход 2026'!$I$29:$I$38)*(1+'Эффекты технологий'!J$7) -> 0 | L38: =SUMIF('Ход 2027'!$G$29:$G$38,$A38,'Ход 2027'!$I$29:$I$38)*(1+'Эффекты технологий'!K$7) -> 0 | M38: =SUMIF('Ход 2028'!$G$29:$G$38,$A38,'Ход 2028'!$I$29:$I$38)*(1+'Эффекты технологий'!L$7) -> 0 | N38: =SUMIF('Ход 2029'!$G$29:$G$38,$A38,'Ход 2029'!$I$29:$I$38)*(1+'Эффекты технологий'!M$7) -> 0 | O38: =SUMIF('Ход 2030'!$G$29:$G$38,$A38,'Ход 2030'!$I$29:$I$38)*(1+'Эффекты технологий'!N$7) -> 0 | P38: =SUMIF('Ход 2031'!$G$29:$G$38,$A38,'Ход 2031'!$I$29:$I$38)*(1+'Эффекты технологий'!O$7) -> 0 | Q38: =SUMIF('Ход 2032'!$G$29:$G$38,$A38,'Ход 2032'!$I$29:$I$38)*(1+'Эффекты технологий'!P$7) -> 0 | R38: =SUMIF('Ход 2033'!$G$29:$G$38,$A38,'Ход 2033'!$I$29:$I$38)*(1+'Эффекты технологий'!Q$7) -> 0 | S38: =SUMIF('Ход 2034'!$G$29:$G$38,$A38,'Ход 2034'!$I$29:$I$38)*(1+'Эффекты технологий'!R$7) -> 0 | T38: =SUMIF('Ход 2035'!$G$29:$G$38,$A38,'Ход 2035'!$I$29:$I$38)*(1+'Эффекты технологий'!S$7) -> 0 | U38: =SUMIF('Ход 2036'!$G$29:$G$38,$A38,'Ход 2036'!$I$29:$I$38)*(1+'Эффекты технологий'!T$7) -> 0 | V38: =SUMIF('Ход 2037'!$G$29:$G$38,$A38,'Ход 2037'!$I$29:$I$38)*(1+'Эффекты технологий'!U$7) -> 0 | W38: =SUMIF('Ход 2038'!$G$29:$G$38,$A38,'Ход 2038'!$I$29:$I$38)*(1+'Эффекты технологий'!V$7) -> 0 | X38: =SUMIF('Ход 2039'!$G$29:$G$38,$A38,'Ход 2039'!$I$29:$I$38)*(1+'Эффекты технологий'!W$7) -> 0 | Y38: =SUMIF('Ход 2040'!$G$29:$G$38,$A38,'Ход 2040'!$I$29:$I$38)*(1+'Эффекты технологий'!X$7) -> 0 | Z38: =SUM(K38:Y38) -> 0 | AA38: =MAX(0,E38-Z38) -> 70 | AB38: =BF38 -> ОТКРЫТО | AC38: =SUM($K38:K38) -> 0 | AD38: =SUM($K38:L38) -> 0 | AE38: =SUM($K38:M38) -> 0 | AF38: =SUM($K38:N38) -> 0 | AG38: =SUM($K38:O38) -> 0 | AH38: =SUM($K38:P38) -> 0 | AI38: =SUM($K38:Q38) -> 0 | AJ38: =SUM($K38:R38) -> 0 | ... AQ38: =SUM($K38:Y38) -> 0 | AR38: =IF(AND(AC38>=$E38,TRUE),"ИЗУЧЕНО",IF(TRUE,"ОТКРЫТО","ЗАКРЫТО")) -> ОТКРЫТО | AS38: =IF(AND(AD38>=$E38,TRUE),"ИЗУЧЕНО",IF(TRUE,"ОТКРЫТО","ЗАКРЫТО")) -> ОТКРЫТО | AT38: =IF(AND(AE38>=$E38,TRUE),"ИЗУЧЕНО",IF(TRUE,"ОТКРЫТО","ЗАКРЫТО")) -> ОТКРЫТО | AU38: =IF(AND(AF38>=$E38,TRUE),"ИЗУЧЕНО",IF(TRUE,"ОТКРЫТО","ЗАКРЫТО")) -> ОТКРЫТО | AV38: =IF(AND(AG38>=$E38,TRUE),"ИЗУЧЕНО",IF(TRUE,"ОТКРЫТО","ЗАКРЫТО")) -> ОТКРЫТО | AW38: =IF(AND(AH38>=$E38,TRUE),"ИЗУЧЕНО",IF(TRUE,"ОТКРЫТО","ЗАКРЫТО")) -> ОТКРЫТО | AX38: =IF(AND(AI38>=$E38,TRUE),"ИЗУЧЕНО",IF(TRUE,"ОТКРЫТО","ЗАКРЫТО")) -> ОТКРЫТО | AY38: =IF(AND(AJ38>=$E38,TRUE),"ИЗУЧЕНО",IF(TRUE,"ОТКРЫТО","ЗАКРЫТО")) -> ОТКРЫТО | ... BF38: =IF(AND(AQ38>=$E38,TRUE),"ИЗУЧЕНО",IF(TRUE,"ОТКРЫТО","ЗАКРЫТО")) -> ОТКРЫТО | BG38: =IFERROR(2025+MATCH("ИЗУЧЕНО",AR38:BF38,0),"") | BH38: =IF(BG38="","",BG38+1)
A39: R5 | B39: Физический ИИ и робототехника | C39: IV | D39: Универсальные роботы с моделями «изображение - язык - действие» (VLA) | E39: 105 | F39: R4 | I39: Модель VLA связывает зрительное восприятие и языковую инструкцию с последовательностью физических действий робота. Один комплекс способен переобучаться на разные операции вместо выполнения единственной жёстко запрограммированной задачи. Это ускоряет производство, цифровизацию и распространение ИИ. Но массовое внедрение требует новых машин, энергии и специалистов по их настройке; на переходном этапе спрос на квалификацию может опережать предложение. | J39: + Прирост сферы «Производство»: +0,12/год; + Готовность работников к использованию ИИ: +0,20; + Прирост сферы «Принятие ИИ»: +0,05/год; + Оцифрованность деятельности: +0,25; + Прирост сферы «Экономика»: +0,05/год; − Минерально-сырьевые ресурсы: -0,30; − Энергетические ресурсы: -0,25; − Квалифицированный человеческий ресурс: -0,15 | K39: =SUMIF('Ход 2026'!$G$29:$G$38,$A39,'Ход 2026'!$I$29:$I$38)*(1+'Эффекты технологий'!J$7) -> 0 | L39: =SUMIF('Ход 2027'!$G$29:$G$38,$A39,'Ход 2027'!$I$29:$I$38)*(1+'Эффекты технологий'!K$7) -> 0 | M39: =SUMIF('Ход 2028'!$G$29:$G$38,$A39,'Ход 2028'!$I$29:$I$38)*(1+'Эффекты технологий'!L$7) -> 0 | N39: =SUMIF('Ход 2029'!$G$29:$G$38,$A39,'Ход 2029'!$I$29:$I$38)*(1+'Эффекты технологий'!M$7) -> 0 | O39: =SUMIF('Ход 2030'!$G$29:$G$38,$A39,'Ход 2030'!$I$29:$I$38)*(1+'Эффекты технологий'!N$7) -> 0 | P39: =SUMIF('Ход 2031'!$G$29:$G$38,$A39,'Ход 2031'!$I$29:$I$38)*(1+'Эффекты технологий'!O$7) -> 0 | Q39: =SUMIF('Ход 2032'!$G$29:$G$38,$A39,'Ход 2032'!$I$29:$I$38)*(1+'Эффекты технологий'!P$7) -> 0 | R39: =SUMIF('Ход 2033'!$G$29:$G$38,$A39,'Ход 2033'!$I$29:$I$38)*(1+'Эффекты технологий'!Q$7) -> 0 | S39: =SUMIF('Ход 2034'!$G$29:$G$38,$A39,'Ход 2034'!$I$29:$I$38)*(1+'Эффекты технологий'!R$7) -> 0 | T39: =SUMIF('Ход 2035'!$G$29:$G$38,$A39,'Ход 2035'!$I$29:$I$38)*(1+'Эффекты технологий'!S$7) -> 0 | U39: =SUMIF('Ход 2036'!$G$29:$G$38,$A39,'Ход 2036'!$I$29:$I$38)*(1+'Эффекты технологий'!T$7) -> 0 | V39: =SUMIF('Ход 2037'!$G$29:$G$38,$A39,'Ход 2037'!$I$29:$I$38)*(1+'Эффекты технологий'!U$7) -> 0 | W39: =SUMIF('Ход 2038'!$G$29:$G$38,$A39,'Ход 2038'!$I$29:$I$38)*(1+'Эффекты технологий'!V$7) -> 0 | X39: =SUMIF('Ход 2039'!$G$29:$G$38,$A39,'Ход 2039'!$I$29:$I$38)*(1+'Эффекты технологий'!W$7) -> 0 | Y39: =SUMIF('Ход 2040'!$G$29:$G$38,$A39,'Ход 2040'!$I$29:$I$38)*(1+'Эффекты технологий'!X$7) -> 0 | Z39: =SUM(K39:Y39) -> 0 | AA39: =MAX(0,E39-Z39) -> 105 | AB39: =BF39 -> ОТКРЫТО | AC39: =SUM($K39:K39) -> 0 | AD39: =SUM($K39:L39) -> 0 | AE39: =SUM($K39:M39) -> 0 | AF39: =SUM($K39:N39) -> 0 | AG39: =SUM($K39:O39) -> 0 | AH39: =SUM($K39:P39) -> 0 | AI39: =SUM($K39:Q39) -> 0 | AJ39: =SUM($K39:R39) -> 0 | ... AQ39: =SUM($K39:Y39) -> 0 | AR39: =IF(AND(AC39>=$E39,TRUE),"ИЗУЧЕНО",IF(TRUE,"ОТКРЫТО","ЗАКРЫТО")) -> ОТКРЫТО | AS39: =IF(AND(AD39>=$E39,TRUE),"ИЗУЧЕНО",IF(TRUE,"ОТКРЫТО","ЗАКРЫТО")) -> ОТКРЫТО | AT39: =IF(AND(AE39>=$E39,TRUE),"ИЗУЧЕНО",IF(TRUE,"ОТКРЫТО","ЗАКРЫТО")) -> ОТКРЫТО | AU39: =IF(AND(AF39>=$E39,TRUE),"ИЗУЧЕНО",IF(TRUE,"ОТКРЫТО","ЗАКРЫТО")) -> ОТКРЫТО | AV39: =IF(AND(AG39>=$E39,TRUE),"ИЗУЧЕНО",IF(TRUE,"ОТКРЫТО","ЗАКРЫТО")) -> ОТКРЫТО | AW39: =IF(AND(AH39>=$E39,TRUE),"ИЗУЧЕНО",IF(TRUE,"ОТКРЫТО","ЗАКРЫТО")) -> ОТКРЫТО | AX39: =IF(AND(AI39>=$E39,TRUE),"ИЗУЧЕНО",IF(TRUE,"ОТКРЫТО","ЗАКРЫТО")) -> ОТКРЫТО | AY39: =IF(AND(AJ39>=$E39,TRUE),"ИЗУЧЕНО",IF(TRUE,"ОТКРЫТО","ЗАКРЫТО")) -> ОТКРЫТО | ... BF39: =IF(AND(AQ39>=$E39,TRUE),"ИЗУЧЕНО",IF(TRUE,"ОТКРЫТО","ЗАКРЫТО")) -> ОТКРЫТО | BG39: =IFERROR(2025+MATCH("ИЗУЧЕНО",AR39:BF39,0),"") | BH39: =IF(BG39="","",BG39+1)
A40: R6 | B40: Физический ИИ и робототехника | C40: V | D40: Автономные производственные линии с цифровыми двойниками | E40: 150 | F40: R5 | I40: Производственная линия объединяет роботизированные участки, датчики, планирование и цифровой двойник для контроля полного технологического цикла. Система самостоятельно обнаруживает отклонения, перестраивает операции и формирует цифровое описание процесса. Страна получает крупный прирост промышленного потенциала и более результативные вложения в материальную базу. Однако построение автоматизированных комплексов требует оборудования, энергии, воды, площадок и сырья; поэтому на высшем уровне возникают четыре ресурсных штрафа. | J40: + Сфера «Производство»: +0,50; прирост +0,15/год; + Организационная архитектура внедрения: +0,30; + Оцифрованность деятельности: +0,30; + Квалифицированный человеческий ресурс: +0,20; + Прирост сферы «Экономика»: +0,10/год; + Эффективность трансформации в ресурсах группы I: +15%; − Минерально-сырьевые ресурсы: -0,45; − Энергетические ресурсы: -0,40; − Вода и ресурс отвода тепла: -0,30; − Пространственные и природно-географические ресурсы: -0,25 | K40: =SUMIF('Ход 2026'!$G$29:$G$38,$A40,'Ход 2026'!$I$29:$I$38)*(1+'Эффекты технологий'!J$7) -> 0 | L40: =SUMIF('Ход 2027'!$G$29:$G$38,$A40,'Ход 2027'!$I$29:$I$38)*(1+'Эффекты технологий'!K$7) -> 0 | M40: =SUMIF('Ход 2028'!$G$29:$G$38,$A40,'Ход 2028'!$I$29:$I$38)*(1+'Эффекты технологий'!L$7) -> 0 | N40: =SUMIF('Ход 2029'!$G$29:$G$38,$A40,'Ход 2029'!$I$29:$I$38)*(1+'Эффекты технологий'!M$7) -> 0 | O40: =SUMIF('Ход 2030'!$G$29:$G$38,$A40,'Ход 2030'!$I$29:$I$38)*(1+'Эффекты технологий'!N$7) -> 0 | P40: =SUMIF('Ход 2031'!$G$29:$G$38,$A40,'Ход 2031'!$I$29:$I$38)*(1+'Эффекты технологий'!O$7) -> 0 | Q40: =SUMIF('Ход 2032'!$G$29:$G$38,$A40,'Ход 2032'!$I$29:$I$38)*(1+'Эффекты технологий'!P$7) -> 0 | R40: =SUMIF('Ход 2033'!$G$29:$G$38,$A40,'Ход 2033'!$I$29:$I$38)*(1+'Эффекты технологий'!Q$7) -> 0 | S40: =SUMIF('Ход 2034'!$G$29:$G$38,$A40,'Ход 2034'!$I$29:$I$38)*(1+'Эффекты технологий'!R$7) -> 0 | T40: =SUMIF('Ход 2035'!$G$29:$G$38,$A40,'Ход 2035'!$I$29:$I$38)*(1+'Эффекты технологий'!S$7) -> 0 | U40: =SUMIF('Ход 2036'!$G$29:$G$38,$A40,'Ход 2036'!$I$29:$I$38)*(1+'Эффекты технологий'!T$7) -> 0 | V40: =SUMIF('Ход 2037'!$G$29:$G$38,$A40,'Ход 2037'!$I$29:$I$38)*(1+'Эффекты технологий'!U$7) -> 0 | W40: =SUMIF('Ход 2038'!$G$29:$G$38,$A40,'Ход 2038'!$I$29:$I$38)*(1+'Эффекты технологий'!V$7) -> 0 | X40: =SUMIF('Ход 2039'!$G$29:$G$38,$A40,'Ход 2039'!$I$29:$I$38)*(1+'Эффекты технологий'!W$7) -> 0 | Y40: =SUMIF('Ход 2040'!$G$29:$G$38,$A40,'Ход 2040'!$I$29:$I$38)*(1+'Эффекты технологий'!X$7) -> 0 | Z40: =SUM(K40:Y40) -> 0 | AA40: =MAX(0,E40-Z40) -> 150 | AB40: =BF40 -> ОТКРЫТО | AC40: =SUM($K40:K40) -> 0 | AD40: =SUM($K40:L40) -> 0 | AE40: =SUM($K40:M40) -> 0 | AF40: =SUM($K40:N40) -> 0 | AG40: =SUM($K40:O40) -> 0 | AH40: =SUM($K40:P40) -> 0 | AI40: =SUM($K40:Q40) -> 0 | AJ40: =SUM($K40:R40) -> 0 | ... AQ40: =SUM($K40:Y40) -> 0 | AR40: =IF(AND(AC40>=$E40,TRUE),"ИЗУЧЕНО",IF(TRUE,"ОТКРЫТО","ЗАКРЫТО")) -> ОТКРЫТО | AS40: =IF(AND(AD40>=$E40,TRUE),"ИЗУЧЕНО",IF(TRUE,"ОТКРЫТО","ЗАКРЫТО")) -> ОТКРЫТО | AT40: =IF(AND(AE40>=$E40,TRUE),"ИЗУЧЕНО",IF(TRUE,"ОТКРЫТО","ЗАКРЫТО")) -> ОТКРЫТО | AU40: =IF(AND(AF40>=$E40,TRUE),"ИЗУЧЕНО",IF(TRUE,"ОТКРЫТО","ЗАКРЫТО")) -> ОТКРЫТО | AV40: =IF(AND(AG40>=$E40,TRUE),"ИЗУЧЕНО",IF(TRUE,"ОТКРЫТО","ЗАКРЫТО")) -> ОТКРЫТО | AW40: =IF(AND(AH40>=$E40,TRUE),"ИЗУЧЕНО",IF(TRUE,"ОТКРЫТО","ЗАКРЫТО")) -> ОТКРЫТО | AX40: =IF(AND(AI40>=$E40,TRUE),"ИЗУЧЕНО",IF(TRUE,"ОТКРЫТО","ЗАКРЫТО")) -> ОТКРЫТО | AY40: =IF(AND(AJ40>=$E40,TRUE),"ИЗУЧЕНО",IF(TRUE,"ОТКРЫТО","ЗАКРЫТО")) -> ОТКРЫТО | ... BF40: =IF(AND(AQ40>=$E40,TRUE),"ИЗУЧЕНО",IF(TRUE,"ОТКРЫТО","ЗАКРЫТО")) -> ОТКРЫТО | BG40: =IFERROR(2025+MATCH("ИЗУЧЕНО",AR40:BF40,0),"") | BH40: =IF(BG40="","",BG40+1)
A41: S1 | B41: Надёжность, безопасность и контроль | C41: I | D41: Автоматизированные наборы тестов и бенчмарков качества ИИ | E41: 20 | I41: Создаются наборы эталонных задач, автоматические проверки и процедуры повторяемого сравнения ИИ-моделей. Разработчик может измерять качество после обучения и перед внедрением, не полагаясь только на отдельные удачные примеры. Страна получает более развитые ресурсы оценки и основу для дальнейшей безопасности. Базовое тестирование не меняет другие показатели и не даёт самостоятельного ресурсного штрафа. | J41: + Ресурсы оценки: +0,30 | K41: =SUMIF('Ход 2026'!$G$29:$G$38,$A41,'Ход 2026'!$I$29:$I$38)*(1+'Эффекты технологий'!J$7) -> 13.9 | L41: =SUMIF('Ход 2027'!$G$29:$G$38,$A41,'Ход 2027'!$I$29:$I$38)*(1+'Эффекты технологий'!K$7) -> 0 | M41: =SUMIF('Ход 2028'!$G$29:$G$38,$A41,'Ход 2028'!$I$29:$I$38)*(1+'Эффекты технологий'!L$7) -> 0 | N41: =SUMIF('Ход 2029'!$G$29:$G$38,$A41,'Ход 2029'!$I$29:$I$38)*(1+'Эффекты технологий'!M$7) -> 0 | O41: =SUMIF('Ход 2030'!$G$29:$G$38,$A41,'Ход 2030'!$I$29:$I$38)*(1+'Эффекты технологий'!N$7) -> 0 | P41: =SUMIF('Ход 2031'!$G$29:$G$38,$A41,'Ход 2031'!$I$29:$I$38)*(1+'Эффекты технологий'!O$7) -> 0 | Q41: =SUMIF('Ход 2032'!$G$29:$G$38,$A41,'Ход 2032'!$I$29:$I$38)*(1+'Эффекты технологий'!P$7) -> 0 | R41: =SUMIF('Ход 2033'!$G$29:$G$38,$A41,'Ход 2033'!$I$29:$I$38)*(1+'Эффекты технологий'!Q$7) -> 0 | S41: =SUMIF('Ход 2034'!$G$29:$G$38,$A41,'Ход 2034'!$I$29:$I$38)*(1+'Эффекты технологий'!R$7) -> 0 | T41: =SUMIF('Ход 2035'!$G$29:$G$38,$A41,'Ход 2035'!$I$29:$I$38)*(1+'Эффекты технологий'!S$7) -> 0 | U41: =SUMIF('Ход 2036'!$G$29:$G$38,$A41,'Ход 2036'!$I$29:$I$38)*(1+'Эффекты технологий'!T$7) -> 0 | V41: =SUMIF('Ход 2037'!$G$29:$G$38,$A41,'Ход 2037'!$I$29:$I$38)*(1+'Эффекты технологий'!U$7) -> 0 | W41: =SUMIF('Ход 2038'!$G$29:$G$38,$A41,'Ход 2038'!$I$29:$I$38)*(1+'Эффекты технологий'!V$7) -> 0 | X41: =SUMIF('Ход 2039'!$G$29:$G$38,$A41,'Ход 2039'!$I$29:$I$38)*(1+'Эффекты технологий'!W$7) -> 0 | Y41: =SUMIF('Ход 2040'!$G$29:$G$38,$A41,'Ход 2040'!$I$29:$I$38)*(1+'Эффекты технологий'!X$7) -> 0 | Z41: =SUM(K41:Y41) -> 13.9 | AA41: =MAX(0,E41-Z41) -> 6.1 | AB41: =BF41 -> ОТКРЫТО | AC41: =SUM($K41:K41) -> 13.9 | AD41: =SUM($K41:L41) -> 13.9 | AE41: =SUM($K41:M41) -> 13.9 | AF41: =SUM($K41:N41) -> 13.9 | AG41: =SUM($K41:O41) -> 13.9 | AH41: =SUM($K41:P41) -> 13.9 | AI41: =SUM($K41:Q41) -> 13.9 | AJ41: =SUM($K41:R41) -> 13.9 | ... AQ41: =SUM($K41:Y41) -> 13.9 | AR41: =IF(AND(AC41>=$E41,TRUE),"ИЗУЧЕНО",IF(TRUE,"ОТКРЫТО","ЗАКРЫТО")) -> ОТКРЫТО | AS41: =IF(AND(AD41>=$E41,TRUE),"ИЗУЧЕНО",IF(TRUE,"ОТКРЫТО","ЗАКРЫТО")) -> ОТКРЫТО | AT41: =IF(AND(AE41>=$E41,TRUE),"ИЗУЧЕНО",IF(TRUE,"ОТКРЫТО","ЗАКРЫТО")) -> ОТКРЫТО | AU41: =IF(AND(AF41>=$E41,TRUE),"ИЗУЧЕНО",IF(TRUE,"ОТКРЫТО","ЗАКРЫТО")) -> ОТКРЫТО | AV41: =IF(AND(AG41>=$E41,TRUE),"ИЗУЧЕНО",IF(TRUE,"ОТКРЫТО","ЗАКРЫТО")) -> ОТКРЫТО | AW41: =IF(AND(AH41>=$E41,TRUE),"ИЗУЧЕНО",IF(TRUE,"ОТКРЫТО","ЗАКРЫТО")) -> ОТКРЫТО | AX41: =IF(AND(AI41>=$E41,TRUE),"ИЗУЧЕНО",IF(TRUE,"ОТКРЫТО","ЗАКРЫТО")) -> ОТКРЫТО | AY41: =IF(AND(AJ41>=$E41,TRUE),"ИЗУЧЕНО",IF(TRUE,"ОТКРЫТО","ЗАКРЫТО")) -> ОТКРЫТО | ... BF41: =IF(AND(AQ41>=$E41,TRUE),"ИЗУЧЕНО",IF(TRUE,"ОТКРЫТО","ЗАКРЫТО")) -> ОТКРЫТО | BG41: =IFERROR(2025+MATCH("ИЗУЧЕНО",AR41:BF41,0),"") | BH41: =IF(BG41="","",BG41+1)
A42: S2 | B42: Надёжность, безопасность и контроль | C42: II | D42: Интерпретация решений нейросетей на основе SHAP и концептуальных признаков | E42: 35 | F42: S1 | I42: Методы объяснения выявляют влияние входных признаков на результат модели, а концептуальные представления связывают вычислительные факторы с понятными человеку категориями. Это помогает документировать решения и повышает доверие к внедрению. В игровой модели дополнительное требование интерпретируемости слегка ограничивает выбор сложных и непрозрачных моделей, что представлено небольшим отрицательным эффектом на модельные ресурсы. | J42: + Документационные ресурсы: +0,20; + Социальное доверие: +0,20; − Модельные ресурсы: -0,10 | K42: =SUMIF('Ход 2026'!$G$29:$G$38,$A42,'Ход 2026'!$I$29:$I$38)*(1+'Эффекты технологий'!J$7) -> 0 | L42: =SUMIF('Ход 2027'!$G$29:$G$38,$A42,'Ход 2027'!$I$29:$I$38)*(1+'Эффекты технологий'!K$7) -> 0 | M42: =SUMIF('Ход 2028'!$G$29:$G$38,$A42,'Ход 2028'!$I$29:$I$38)*(1+'Эффекты технологий'!L$7) -> 0 | N42: =SUMIF('Ход 2029'!$G$29:$G$38,$A42,'Ход 2029'!$I$29:$I$38)*(1+'Эффекты технологий'!M$7) -> 0 | O42: =SUMIF('Ход 2030'!$G$29:$G$38,$A42,'Ход 2030'!$I$29:$I$38)*(1+'Эффекты технологий'!N$7) -> 0 | P42: =SUMIF('Ход 2031'!$G$29:$G$38,$A42,'Ход 2031'!$I$29:$I$38)*(1+'Эффекты технологий'!O$7) -> 0 | Q42: =SUMIF('Ход 2032'!$G$29:$G$38,$A42,'Ход 2032'!$I$29:$I$38)*(1+'Эффекты технологий'!P$7) -> 0 | R42: =SUMIF('Ход 2033'!$G$29:$G$38,$A42,'Ход 2033'!$I$29:$I$38)*(1+'Эффекты технологий'!Q$7) -> 0 | S42: =SUMIF('Ход 2034'!$G$29:$G$38,$A42,'Ход 2034'!$I$29:$I$38)*(1+'Эффекты технологий'!R$7) -> 0 | T42: =SUMIF('Ход 2035'!$G$29:$G$38,$A42,'Ход 2035'!$I$29:$I$38)*(1+'Эффекты технологий'!S$7) -> 0 | U42: =SUMIF('Ход 2036'!$G$29:$G$38,$A42,'Ход 2036'!$I$29:$I$38)*(1+'Эффекты технологий'!T$7) -> 0 | V42: =SUMIF('Ход 2037'!$G$29:$G$38,$A42,'Ход 2037'!$I$29:$I$38)*(1+'Эффекты технологий'!U$7) -> 0 | W42: =SUMIF('Ход 2038'!$G$29:$G$38,$A42,'Ход 2038'!$I$29:$I$38)*(1+'Эффекты технологий'!V$7) -> 0 | X42: =SUMIF('Ход 2039'!$G$29:$G$38,$A42,'Ход 2039'!$I$29:$I$38)*(1+'Эффекты технологий'!W$7) -> 0 | Y42: =SUMIF('Ход 2040'!$G$29:$G$38,$A42,'Ход 2040'!$I$29:$I$38)*(1+'Эффекты технологий'!X$7) -> 0 | Z42: =SUM(K42:Y42) -> 0 | AA42: =MAX(0,E42-Z42) -> 35 | AB42: =BF42 -> ОТКРЫТО | AC42: =SUM($K42:K42) -> 0 | AD42: =SUM($K42:L42) -> 0 | AE42: =SUM($K42:M42) -> 0 | AF42: =SUM($K42:N42) -> 0 | AG42: =SUM($K42:O42) -> 0 | AH42: =SUM($K42:P42) -> 0 | AI42: =SUM($K42:Q42) -> 0 | AJ42: =SUM($K42:R42) -> 0 | ... AQ42: =SUM($K42:Y42) -> 0 | AR42: =IF(AND(AC42>=$E42,TRUE),"ИЗУЧЕНО",IF(TRUE,"ОТКРЫТО","ЗАКРЫТО")) -> ОТКРЫТО | AS42: =IF(AND(AD42>=$E42,TRUE),"ИЗУЧЕНО",IF(TRUE,"ОТКРЫТО","ЗАКРЫТО")) -> ОТКРЫТО | AT42: =IF(AND(AE42>=$E42,TRUE),"ИЗУЧЕНО",IF(TRUE,"ОТКРЫТО","ЗАКРЫТО")) -> ОТКРЫТО | AU42: =IF(AND(AF42>=$E42,TRUE),"ИЗУЧЕНО",IF(TRUE,"ОТКРЫТО","ЗАКРЫТО")) -> ОТКРЫТО | AV42: =IF(AND(AG42>=$E42,TRUE),"ИЗУЧЕНО",IF(TRUE,"ОТКРЫТО","ЗАКРЫТО")) -> ОТКРЫТО | AW42: =IF(AND(AH42>=$E42,TRUE),"ИЗУЧЕНО",IF(TRUE,"ОТКРЫТО","ЗАКРЫТО")) -> ОТКРЫТО | AX42: =IF(AND(AI42>=$E42,TRUE),"ИЗУЧЕНО",IF(TRUE,"ОТКРЫТО","ЗАКРЫТО")) -> ОТКРЫТО | AY42: =IF(AND(AJ42>=$E42,TRUE),"ИЗУЧЕНО",IF(TRUE,"ОТКРЫТО","ЗАКРЫТО")) -> ОТКРЫТО | ... BF42: =IF(AND(AQ42>=$E42,TRUE),"ИЗУЧЕНО",IF(TRUE,"ОТКРЫТО","ЗАКРЫТО")) -> ОТКРЫТО | BG42: =IFERROR(2025+MATCH("ИЗУЧЕНО",AR42:BF42,0),"") | BH42: =IF(BG42="","",BG42+1)
A43: S3 | B43: Надёжность, безопасность и контроль | C43: II | D43: Защищённый MLOps с подписанными моделями и контролем цепочки поставок | E43: 40 | F43: S1 | I43: Модели, контейнеры и другие компоненты инфраструктуры получают проверяемое происхождение, цифровые подписи и контролируемые процедуры выпуска. Развёртывание становится воспроизводимым и менее уязвимым к подмене артефактов. Государство укрепляет кибербезопасность и цифровую защиту, включая войну Афины. Постоянное сопровождение защищённых конвейеров требует дополнительного финансирования, что отражено небольшим финансовым штрафом. | J43: + Кибербезопасностные ресурсы: +0,30; + Стек эксплуатации ИИ: +0,20; + Защита от войны Афины: +10%; − Финансовые ресурсы: -0,15 | K43: =SUMIF('Ход 2026'!$G$29:$G$38,$A43,'Ход 2026'!$I$29:$I$38)*(1+'Эффекты технологий'!J$7) -> 0 | L43: =SUMIF('Ход 2027'!$G$29:$G$38,$A43,'Ход 2027'!$I$29:$I$38)*(1+'Эффекты технологий'!K$7) -> 0 | M43: =SUMIF('Ход 2028'!$G$29:$G$38,$A43,'Ход 2028'!$I$29:$I$38)*(1+'Эффекты технологий'!L$7) -> 0 | N43: =SUMIF('Ход 2029'!$G$29:$G$38,$A43,'Ход 2029'!$I$29:$I$38)*(1+'Эффекты технологий'!M$7) -> 0 | O43: =SUMIF('Ход 2030'!$G$29:$G$38,$A43,'Ход 2030'!$I$29:$I$38)*(1+'Эффекты технологий'!N$7) -> 0 | P43: =SUMIF('Ход 2031'!$G$29:$G$38,$A43,'Ход 2031'!$I$29:$I$38)*(1+'Эффекты технологий'!O$7) -> 0 | Q43: =SUMIF('Ход 2032'!$G$29:$G$38,$A43,'Ход 2032'!$I$29:$I$38)*(1+'Эффекты технологий'!P$7) -> 0 | R43: =SUMIF('Ход 2033'!$G$29:$G$38,$A43,'Ход 2033'!$I$29:$I$38)*(1+'Эффекты технологий'!Q$7) -> 0 | S43: =SUMIF('Ход 2034'!$G$29:$G$38,$A43,'Ход 2034'!$I$29:$I$38)*(1+'Эффекты технологий'!R$7) -> 0 | T43: =SUMIF('Ход 2035'!$G$29:$G$38,$A43,'Ход 2035'!$I$29:$I$38)*(1+'Эффекты технологий'!S$7) -> 0 | U43: =SUMIF('Ход 2036'!$G$29:$G$38,$A43,'Ход 2036'!$I$29:$I$38)*(1+'Эффекты технологий'!T$7) -> 0 | V43: =SUMIF('Ход 2037'!$G$29:$G$38,$A43,'Ход 2037'!$I$29:$I$38)*(1+'Эффекты технологий'!U$7) -> 0 | W43: =SUMIF('Ход 2038'!$G$29:$G$38,$A43,'Ход 2038'!$I$29:$I$38)*(1+'Эффекты технологий'!V$7) -> 0 | X43: =SUMIF('Ход 2039'!$G$29:$G$38,$A43,'Ход 2039'!$I$29:$I$38)*(1+'Эффекты технологий'!W$7) -> 0 | Y43: =SUMIF('Ход 2040'!$G$29:$G$38,$A43,'Ход 2040'!$I$29:$I$38)*(1+'Эффекты технологий'!X$7) -> 0 | Z43: =SUM(K43:Y43) -> 0 | AA43: =MAX(0,E43-Z43) -> 40 | AB43: =BF43 -> ОТКРЫТО | AC43: =SUM($K43:K43) -> 0 | AD43: =SUM($K43:L43) -> 0 | AE43: =SUM($K43:M43) -> 0 | AF43: =SUM($K43:N43) -> 0 | AG43: =SUM($K43:O43) -> 0 | AH43: =SUM($K43:P43) -> 0 | AI43: =SUM($K43:Q43) -> 0 | AJ43: =SUM($K43:R43) -> 0 | ... AQ43: =SUM($K43:Y43) -> 0 | AR43: =IF(AND(AC43>=$E43,TRUE),"ИЗУЧЕНО",IF(TRUE,"ОТКРЫТО","ЗАКРЫТО")) -> ОТКРЫТО | AS43: =IF(AND(AD43>=$E43,TRUE),"ИЗУЧЕНО",IF(TRUE,"ОТКРЫТО","ЗАКРЫТО")) -> ОТКРЫТО | AT43: =IF(AND(AE43>=$E43,TRUE),"ИЗУЧЕНО",IF(TRUE,"ОТКРЫТО","ЗАКРЫТО")) -> ОТКРЫТО | AU43: =IF(AND(AF43>=$E43,TRUE),"ИЗУЧЕНО",IF(TRUE,"ОТКРЫТО","ЗАКРЫТО")) -> ОТКРЫТО | AV43: =IF(AND(AG43>=$E43,TRUE),"ИЗУЧЕНО",IF(TRUE,"ОТКРЫТО","ЗАКРЫТО")) -> ОТКРЫТО | AW43: =IF(AND(AH43>=$E43,TRUE),"ИЗУЧЕНО",IF(TRUE,"ОТКРЫТО","ЗАКРЫТО")) -> ОТКРЫТО | AX43: =IF(AND(AI43>=$E43,TRUE),"ИЗУЧЕНО",IF(TRUE,"ОТКРЫТО","ЗАКРЫТО")) -> ОТКРЫТО | AY43: =IF(AND(AJ43>=$E43,TRUE),"ИЗУЧЕНО",IF(TRUE,"ОТКРЫТО","ЗАКРЫТО")) -> ОТКРЫТО | ... BF43: =IF(AND(AQ43>=$E43,TRUE),"ИЗУЧЕНО",IF(TRUE,"ОТКРЫТО","ЗАКРЫТО")) -> ОТКРЫТО | BG43: =IFERROR(2025+MATCH("ИЗУЧЕНО",AR43:BF43,0),"") | BH43: =IF(BG43="","",BG43+1)
A44: S4 | B44: Надёжность, безопасность и контроль | C44: III | D44: Автоматизированное adversarial-тестирование и red teaming моделей | E44: 65 | F44: S2 | G44: S3 | I44: Система автоматически создаёт сложные, нестандартные и потенциально враждебные сценарии взаимодействия с моделью, выявляя ошибки, небезопасные ответы и обходы ограничений. Выводы превращаются в отчёты и требования к доработке. Это улучшает оценку и защищает от смысловых атак, что соответствует бонусу в войне Аполлона. Многочисленные стресс-тесты создают заметную вычислительную и энергетическую нагрузку. | J44: + Ресурсы оценки: +0,40; + Прирост кибербезопасностных ресурсов: +0,08/год; + Документационные ресурсы: +0,20; + Защита от войны Аполлона: +10%; − Энергетические ресурсы: -0,15; − Вычислительные компоненты: -0,10 | K44: =SUMIF('Ход 2026'!$G$29:$G$38,$A44,'Ход 2026'!$I$29:$I$38)*(1+'Эффекты технологий'!J$7) -> 0 | L44: =SUMIF('Ход 2027'!$G$29:$G$38,$A44,'Ход 2027'!$I$29:$I$38)*(1+'Эффекты технологий'!K$7) -> 0 | M44: =SUMIF('Ход 2028'!$G$29:$G$38,$A44,'Ход 2028'!$I$29:$I$38)*(1+'Эффекты технологий'!L$7) -> 0 | N44: =SUMIF('Ход 2029'!$G$29:$G$38,$A44,'Ход 2029'!$I$29:$I$38)*(1+'Эффекты технологий'!M$7) -> 0 | O44: =SUMIF('Ход 2030'!$G$29:$G$38,$A44,'Ход 2030'!$I$29:$I$38)*(1+'Эффекты технологий'!N$7) -> 0 | P44: =SUMIF('Ход 2031'!$G$29:$G$38,$A44,'Ход 2031'!$I$29:$I$38)*(1+'Эффекты технологий'!O$7) -> 0 | Q44: =SUMIF('Ход 2032'!$G$29:$G$38,$A44,'Ход 2032'!$I$29:$I$38)*(1+'Эффекты технологий'!P$7) -> 0 | R44: =SUMIF('Ход 2033'!$G$29:$G$38,$A44,'Ход 2033'!$I$29:$I$38)*(1+'Эффекты технологий'!Q$7) -> 0 | S44: =SUMIF('Ход 2034'!$G$29:$G$38,$A44,'Ход 2034'!$I$29:$I$38)*(1+'Эффекты технологий'!R$7) -> 0 | T44: =SUMIF('Ход 2035'!$G$29:$G$38,$A44,'Ход 2035'!$I$29:$I$38)*(1+'Эффекты технологий'!S$7) -> 0 | U44: =SUMIF('Ход 2036'!$G$29:$G$38,$A44,'Ход 2036'!$I$29:$I$38)*(1+'Эффекты технологий'!T$7) -> 0 | V44: =SUMIF('Ход 2037'!$G$29:$G$38,$A44,'Ход 2037'!$I$29:$I$38)*(1+'Эффекты технологий'!U$7) -> 0 | W44: =SUMIF('Ход 2038'!$G$29:$G$38,$A44,'Ход 2038'!$I$29:$I$38)*(1+'Эффекты технологий'!V$7) -> 0 | X44: =SUMIF('Ход 2039'!$G$29:$G$38,$A44,'Ход 2039'!$I$29:$I$38)*(1+'Эффекты технологий'!W$7) -> 0 | Y44: =SUMIF('Ход 2040'!$G$29:$G$38,$A44,'Ход 2040'!$I$29:$I$38)*(1+'Эффекты технологий'!X$7) -> 0 | Z44: =SUM(K44:Y44) -> 0 | AA44: =MAX(0,E44-Z44) -> 65 | AB44: =BF44 -> ОТКРЫТО | AC44: =SUM($K44:K44) -> 0 | AD44: =SUM($K44:L44) -> 0 | AE44: =SUM($K44:M44) -> 0 | AF44: =SUM($K44:N44) -> 0 | AG44: =SUM($K44:O44) -> 0 | AH44: =SUM($K44:P44) -> 0 | AI44: =SUM($K44:Q44) -> 0 | AJ44: =SUM($K44:R44) -> 0 | ... AQ44: =SUM($K44:Y44) -> 0 | AR44: =IF(AND(AC44>=$E44,TRUE),"ИЗУЧЕНО",IF(TRUE,"ОТКРЫТО","ЗАКРЫТО")) -> ОТКРЫТО | AS44: =IF(AND(AD44>=$E44,TRUE),"ИЗУЧЕНО",IF(TRUE,"ОТКРЫТО","ЗАКРЫТО")) -> ОТКРЫТО | AT44: =IF(AND(AE44>=$E44,TRUE),"ИЗУЧЕНО",IF(TRUE,"ОТКРЫТО","ЗАКРЫТО")) -> ОТКРЫТО | AU44: =IF(AND(AF44>=$E44,TRUE),"ИЗУЧЕНО",IF(TRUE,"ОТКРЫТО","ЗАКРЫТО")) -> ОТКРЫТО | AV44: =IF(AND(AG44>=$E44,TRUE),"ИЗУЧЕНО",IF(TRUE,"ОТКРЫТО","ЗАКРЫТО")) -> ОТКРЫТО | AW44: =IF(AND(AH44>=$E44,TRUE),"ИЗУЧЕНО",IF(TRUE,"ОТКРЫТО","ЗАКРЫТО")) -> ОТКРЫТО | AX44: =IF(AND(AI44>=$E44,TRUE),"ИЗУЧЕНО",IF(TRUE,"ОТКРЫТО","ЗАКРЫТО")) -> ОТКРЫТО | AY44: =IF(AND(AJ44>=$E44,TRUE),"ИЗУЧЕНО",IF(TRUE,"ОТКРЫТО","ЗАКРЫТО")) -> ОТКРЫТО | ... BF44: =IF(AND(AQ44>=$E44,TRUE),"ИЗУЧЕНО",IF(TRUE,"ОТКРЫТО","ЗАКРЫТО")) -> ОТКРЫТО | BG44: =IFERROR(2025+MATCH("ИЗУЧЕНО",AR44:BF44,0),"") | BH44: =IF(BG44="","",BG44+1)
A45: S5 | B45: Надёжность, безопасность и контроль | C45: IV | D45: Мониторинг и ограничение действий автономных ИИ-агентов | E45: 100 | F45: S4 | I45: Во время работы агента специальные механизмы проверяют запросы к инструментам, ограничения полномочий и допустимость принимаемых решений. При опасном действии система может потребовать подтверждение, заменить операцию или остановить исполнение. Это повышает безопасность и готовность общества к агентному ИИ, усиливая две формы внешнеполитической защиты. Плата состоит в сопровождении контрольной инфраструктуры, дополнительных вычислениях и снижении организационной гибкости. | J45: + Система управления ИИ: +0,40; + Прирост сферы «Принятие ИИ»: +0,08/год; + Ресурсы оценки: +0,20; + Защита от войны Афины: +10%; + Защита от войны Аполлона: +10%; − Финансовые ресурсы: -0,25; − Организационная способность к изменению: -0,15; − Энергетические ресурсы: -0,10 | K45: =SUMIF('Ход 2026'!$G$29:$G$38,$A45,'Ход 2026'!$I$29:$I$38)*(1+'Эффекты технологий'!J$7) -> 0 | L45: =SUMIF('Ход 2027'!$G$29:$G$38,$A45,'Ход 2027'!$I$29:$I$38)*(1+'Эффекты технологий'!K$7) -> 0 | M45: =SUMIF('Ход 2028'!$G$29:$G$38,$A45,'Ход 2028'!$I$29:$I$38)*(1+'Эффекты технологий'!L$7) -> 0 | N45: =SUMIF('Ход 2029'!$G$29:$G$38,$A45,'Ход 2029'!$I$29:$I$38)*(1+'Эффекты технологий'!M$7) -> 0 | O45: =SUMIF('Ход 2030'!$G$29:$G$38,$A45,'Ход 2030'!$I$29:$I$38)*(1+'Эффекты технологий'!N$7) -> 0 | P45: =SUMIF('Ход 2031'!$G$29:$G$38,$A45,'Ход 2031'!$I$29:$I$38)*(1+'Эффекты технологий'!O$7) -> 0 | Q45: =SUMIF('Ход 2032'!$G$29:$G$38,$A45,'Ход 2032'!$I$29:$I$38)*(1+'Эффекты технологий'!P$7) -> 0 | R45: =SUMIF('Ход 2033'!$G$29:$G$38,$A45,'Ход 2033'!$I$29:$I$38)*(1+'Эффекты технологий'!Q$7) -> 0 | S45: =SUMIF('Ход 2034'!$G$29:$G$38,$A45,'Ход 2034'!$I$29:$I$38)*(1+'Эффекты технологий'!R$7) -> 0 | T45: =SUMIF('Ход 2035'!$G$29:$G$38,$A45,'Ход 2035'!$I$29:$I$38)*(1+'Эффекты технологий'!S$7) -> 0 | U45: =SUMIF('Ход 2036'!$G$29:$G$38,$A45,'Ход 2036'!$I$29:$I$38)*(1+'Эффекты технологий'!T$7) -> 0 | V45: =SUMIF('Ход 2037'!$G$29:$G$38,$A45,'Ход 2037'!$I$29:$I$38)*(1+'Эффекты технологий'!U$7) -> 0 | W45: =SUMIF('Ход 2038'!$G$29:$G$38,$A45,'Ход 2038'!$I$29:$I$38)*(1+'Эффекты технологий'!V$7) -> 0 | X45: =SUMIF('Ход 2039'!$G$29:$G$38,$A45,'Ход 2039'!$I$29:$I$38)*(1+'Эффекты технологий'!W$7) -> 0 | Y45: =SUMIF('Ход 2040'!$G$29:$G$38,$A45,'Ход 2040'!$I$29:$I$38)*(1+'Эффекты технологий'!X$7) -> 0 | Z45: =SUM(K45:Y45) -> 0 | AA45: =MAX(0,E45-Z45) -> 100 | AB45: =BF45 -> ОТКРЫТО | AC45: =SUM($K45:K45) -> 0 | AD45: =SUM($K45:L45) -> 0 | AE45: =SUM($K45:M45) -> 0 | AF45: =SUM($K45:N45) -> 0 | AG45: =SUM($K45:O45) -> 0 | AH45: =SUM($K45:P45) -> 0 | AI45: =SUM($K45:Q45) -> 0 | AJ45: =SUM($K45:R45) -> 0 | ... AQ45: =SUM($K45:Y45) -> 0 | AR45: =IF(AND(AC45>=$E45,TRUE),"ИЗУЧЕНО",IF(TRUE,"ОТКРЫТО","ЗАКРЫТО")) -> ОТКРЫТО | AS45: =IF(AND(AD45>=$E45,TRUE),"ИЗУЧЕНО",IF(TRUE,"ОТКРЫТО","ЗАКРЫТО")) -> ОТКРЫТО | AT45: =IF(AND(AE45>=$E45,TRUE),"ИЗУЧЕНО",IF(TRUE,"ОТКРЫТО","ЗАКРЫТО")) -> ОТКРЫТО | AU45: =IF(AND(AF45>=$E45,TRUE),"ИЗУЧЕНО",IF(TRUE,"ОТКРЫТО","ЗАКРЫТО")) -> ОТКРЫТО | AV45: =IF(AND(AG45>=$E45,TRUE),"ИЗУЧЕНО",IF(TRUE,"ОТКРЫТО","ЗАКРЫТО")) -> ОТКРЫТО | AW45: =IF(AND(AH45>=$E45,TRUE),"ИЗУЧЕНО",IF(TRUE,"ОТКРЫТО","ЗАКРЫТО")) -> ОТКРЫТО | AX45: =IF(AND(AI45>=$E45,TRUE),"ИЗУЧЕНО",IF(TRUE,"ОТКРЫТО","ЗАКРЫТО")) -> ОТКРЫТО | AY45: =IF(AND(AJ45>=$E45,TRUE),"ИЗУЧЕНО",IF(TRUE,"ОТКРЫТО","ЗАКРЫТО")) -> ОТКРЫТО | ... BF45: =IF(AND(AQ45>=$E45,TRUE),"ИЗУЧЕНО",IF(TRUE,"ОТКРЫТО","ЗАКРЫТО")) -> ОТКРЫТО | BG45: =IFERROR(2025+MATCH("ИЗУЧЕНО",AR45:BF45,0),"") | BH45: =IF(BG45="","",BG45+1)
A46: S6 | B46: Надёжность, безопасность и контроль | C46: V | D46: Формальная верификация политик и протоколов автономных ИИ-систем | E46: 150 | F46: S5 | I46: Формальные методы задают правила доступа, допустимые последовательности действий и условия безопасности в виде проверяемых спецификаций. Верифицируются прежде всего политики и протоколы агентной системы, а не все возможные свойства нейросети. Государство получает сильный контур контроля и дополнительные гарантии во всех трёх видах войны. Однако создание доказательств, проверка обновлений и обязательная сертификация дороги и могут замедлять организационные изменения. | J46: + Система управления ИИ: +0,50; + Регуляторная и стандартная среда: +0,30; + Прирост социального доверия: +0,10/год; + Защита от войны Ареса: +10%; + Защита от войны Афины: +10%; + Защита от войны Аполлона: +10%; − Финансовые ресурсы: -0,35; − Энергетические ресурсы: -0,20; − Вычислительные компоненты: -0,20; − Организационная способность к изменению: -0,15 | K46: =SUMIF('Ход 2026'!$G$29:$G$38,$A46,'Ход 2026'!$I$29:$I$38)*(1+'Эффекты технологий'!J$7) -> 0 | L46: =SUMIF('Ход 2027'!$G$29:$G$38,$A46,'Ход 2027'!$I$29:$I$38)*(1+'Эффекты технологий'!K$7) -> 0 | M46: =SUMIF('Ход 2028'!$G$29:$G$38,$A46,'Ход 2028'!$I$29:$I$38)*(1+'Эффекты технологий'!L$7) -> 0 | N46: =SUMIF('Ход 2029'!$G$29:$G$38,$A46,'Ход 2029'!$I$29:$I$38)*(1+'Эффекты технологий'!M$7) -> 0 | O46: =SUMIF('Ход 2030'!$G$29:$G$38,$A46,'Ход 2030'!$I$29:$I$38)*(1+'Эффекты технологий'!N$7) -> 0 | P46: =SUMIF('Ход 2031'!$G$29:$G$38,$A46,'Ход 2031'!$I$29:$I$38)*(1+'Эффекты технологий'!O$7) -> 0 | Q46: =SUMIF('Ход 2032'!$G$29:$G$38,$A46,'Ход 2032'!$I$29:$I$38)*(1+'Эффекты технологий'!P$7) -> 0 | R46: =SUMIF('Ход 2033'!$G$29:$G$38,$A46,'Ход 2033'!$I$29:$I$38)*(1+'Эффекты технологий'!Q$7) -> 0 | S46: =SUMIF('Ход 2034'!$G$29:$G$38,$A46,'Ход 2034'!$I$29:$I$38)*(1+'Эффекты технологий'!R$7) -> 0 | T46: =SUMIF('Ход 2035'!$G$29:$G$38,$A46,'Ход 2035'!$I$29:$I$38)*(1+'Эффекты технологий'!S$7) -> 0 | U46: =SUMIF('Ход 2036'!$G$29:$G$38,$A46,'Ход 2036'!$I$29:$I$38)*(1+'Эффекты технологий'!T$7) -> 0 | V46: =SUMIF('Ход 2037'!$G$29:$G$38,$A46,'Ход 2037'!$I$29:$I$38)*(1+'Эффекты технологий'!U$7) -> 0 | W46: =SUMIF('Ход 2038'!$G$29:$G$38,$A46,'Ход 2038'!$I$29:$I$38)*(1+'Эффекты технологий'!V$7) -> 0 | X46: =SUMIF('Ход 2039'!$G$29:$G$38,$A46,'Ход 2039'!$I$29:$I$38)*(1+'Эффекты технологий'!W$7) -> 0 | Y46: =SUMIF('Ход 2040'!$G$29:$G$38,$A46,'Ход 2040'!$I$29:$I$38)*(1+'Эффекты технологий'!X$7) -> 0 | Z46: =SUM(K46:Y46) -> 0 | AA46: =MAX(0,E46-Z46) -> 150 | AB46: =BF46 -> ОТКРЫТО | AC46: =SUM($K46:K46) -> 0 | AD46: =SUM($K46:L46) -> 0 | AE46: =SUM($K46:M46) -> 0 | AF46: =SUM($K46:N46) -> 0 | AG46: =SUM($K46:O46) -> 0 | AH46: =SUM($K46:P46) -> 0 | AI46: =SUM($K46:Q46) -> 0 | AJ46: =SUM($K46:R46) -> 0 | ... AQ46: =SUM($K46:Y46) -> 0 | AR46: =IF(AND(AC46>=$E46,TRUE),"ИЗУЧЕНО",IF(TRUE,"ОТКРЫТО","ЗАКРЫТО")) -> ОТКРЫТО | AS46: =IF(AND(AD46>=$E46,TRUE),"ИЗУЧЕНО",IF(TRUE,"ОТКРЫТО","ЗАКРЫТО")) -> ОТКРЫТО | AT46: =IF(AND(AE46>=$E46,TRUE),"ИЗУЧЕНО",IF(TRUE,"ОТКРЫТО","ЗАКРЫТО")) -> ОТКРЫТО | AU46: =IF(AND(AF46>=$E46,TRUE),"ИЗУЧЕНО",IF(TRUE,"ОТКРЫТО","ЗАКРЫТО")) -> ОТКРЫТО | AV46: =IF(AND(AG46>=$E46,TRUE),"ИЗУЧЕНО",IF(TRUE,"ОТКРЫТО","ЗАКРЫТО")) -> ОТКРЫТО | AW46: =IF(AND(AH46>=$E46,TRUE),"ИЗУЧЕНО",IF(TRUE,"ОТКРЫТО","ЗАКРЫТО")) -> ОТКРЫТО | AX46: =IF(AND(AI46>=$E46,TRUE),"ИЗУЧЕНО",IF(TRUE,"ОТКРЫТО","ЗАКРЫТО")) -> ОТКРЫТО | AY46: =IF(AND(AJ46>=$E46,TRUE),"ИЗУЧЕНО",IF(TRUE,"ОТКРЫТО","ЗАКРЫТО")) -> ОТКРЫТО | ... BF46: =IF(AND(AQ46>=$E46,TRUE),"ИЗУЧЕНО",IF(TRUE,"ОТКРЫТО","ЗАКРЫТО")) -> ОТКРЫТО | BG46: =IFERROR(2025+MATCH("ИЗУЧЕНО",AR46:BF46,0),"") | BH46: =IF(BG46="","",BG46+1)
A47: X1 | B47: Межветвевые | C47: IV | D47: Мультиагентные конвейеры генерации и проверки научных гипотез | E47: 100 | F47: M4 | G47: D4 | H47: A3 | I47: Научные агенты предлагают гипотезы, подбирают литературу и данные, проектируют проверки и оценивают результаты. Исследователь сохраняет ответственность за корректность методов, а ИИ ускоряет рутинные и поисковые этапы работы. Для создания конвейера одновременно нужны достаточно развитые модели, проверяемый доступ к знаниям и многоагентная координация. Технология даёт один, но широкий стратегический эффект - увеличение результативности вложенных очков науки. | J47: + Эффективность науки во всех направлениях: +15% | K47: =SUMIF('Ход 2026'!$G$29:$G$38,$A47,'Ход 2026'!$I$29:$I$38)*(1+'Эффекты технологий'!J$7+'Эффекты технологий'!J$9) -> 0 | L47: =SUMIF('Ход 2027'!$G$29:$G$38,$A47,'Ход 2027'!$I$29:$I$38)*(1+'Эффекты технологий'!K$7+'Эффекты технологий'!K$9) -> 0 | M47: =SUMIF('Ход 2028'!$G$29:$G$38,$A47,'Ход 2028'!$I$29:$I$38)*(1+'Эффекты технологий'!L$7+'Эффекты технологий'!L$9) -> 0 | N47: =SUMIF('Ход 2029'!$G$29:$G$38,$A47,'Ход 2029'!$I$29:$I$38)*(1+'Эффекты технологий'!M$7+'Эффекты технологий'!M$9) -> 0 | O47: =SUMIF('Ход 2030'!$G$29:$G$38,$A47,'Ход 2030'!$I$29:$I$38)*(1+'Эффекты технологий'!N$7+'Эффекты технологий'!N$9) -> 0 | P47: =SUMIF('Ход 2031'!$G$29:$G$38,$A47,'Ход 2031'!$I$29:$I$38)*(1+'Эффекты технологий'!O$7+'Эффекты технологий'!O$9) -> 0 | Q47: =SUMIF('Ход 2032'!$G$29:$G$38,$A47,'Ход 2032'!$I$29:$I$38)*(1+'Эффекты технологий'!P$7+'Эффекты технологий'!P$9) -> 0 | R47: =SUMIF('Ход 2033'!$G$29:$G$38,$A47,'Ход 2033'!$I$29:$I$38)*(1+'Эффекты технологий'!Q$7+'Эффекты технологий'!Q$9) -> 0 | S47: =SUMIF('Ход 2034'!$G$29:$G$38,$A47,'Ход 2034'!$I$29:$I$38)*(1+'Эффекты технологий'!R$7+'Эффекты технологий'!R$9) -> 0 | T47: =SUMIF('Ход 2035'!$G$29:$G$38,$A47,'Ход 2035'!$I$29:$I$38)*(1+'Эффекты технологий'!S$7+'Эффекты технологий'!S$9) -> 0 | U47: =SUMIF('Ход 2036'!$G$29:$G$38,$A47,'Ход 2036'!$I$29:$I$38)*(1+'Эффекты технологий'!T$7+'Эффекты технологий'!T$9) -> 0 | V47: =SUMIF('Ход 2037'!$G$29:$G$38,$A47,'Ход 2037'!$I$29:$I$38)*(1+'Эффекты технологий'!U$7+'Эффекты технологий'!U$9) -> 0 | W47: =SUMIF('Ход 2038'!$G$29:$G$38,$A47,'Ход 2038'!$I$29:$I$38)*(1+'Эффекты технологий'!V$7+'Эффекты технологий'!V$9) -> 0 | X47: =SUMIF('Ход 2039'!$G$29:$G$38,$A47,'Ход 2039'!$I$29:$I$38)*(1+'Эффекты технологий'!W$7+'Эффекты технологий'!W$9) -> 0 | Y47: =SUMIF('Ход 2040'!$G$29:$G$38,$A47,'Ход 2040'!$I$29:$I$38)*(1+'Эффекты технологий'!X$7+'Эффекты технологий'!X$9) -> 0 | Z47: =SUM(K47:Y47) -> 0 | AA47: =MAX(0,E47-Z47) -> 100 | AB47: =BF47 -> ОТКРЫТО | AC47: =SUM($K47:K47) -> 0 | AD47: =SUM($K47:L47) -> 0 | AE47: =SUM($K47:M47) -> 0 | AF47: =SUM($K47:N47) -> 0 | AG47: =SUM($K47:O47) -> 0 | AH47: =SUM($K47:P47) -> 0 | AI47: =SUM($K47:Q47) -> 0 | AJ47: =SUM($K47:R47) -> 0 | ... AQ47: =SUM($K47:Y47) -> 0 | AR47: =IF(AND(AC47>=$E47,TRUE),"ИЗУЧЕНО",IF(TRUE,"ОТКРЫТО","ЗАКРЫТО")) -> ОТКРЫТО | AS47: =IF(AND(AD47>=$E47,TRUE),"ИЗУЧЕНО",IF(TRUE,"ОТКРЫТО","ЗАКРЫТО")) -> ОТКРЫТО | AT47: =IF(AND(AE47>=$E47,TRUE),"ИЗУЧЕНО",IF(TRUE,"ОТКРЫТО","ЗАКРЫТО")) -> ОТКРЫТО | AU47: =IF(AND(AF47>=$E47,TRUE),"ИЗУЧЕНО",IF(TRUE,"ОТКРЫТО","ЗАКРЫТО")) -> ОТКРЫТО | AV47: =IF(AND(AG47>=$E47,TRUE),"ИЗУЧЕНО",IF(TRUE,"ОТКРЫТО","ЗАКРЫТО")) -> ОТКРЫТО | AW47: =IF(AND(AH47>=$E47,TRUE),"ИЗУЧЕНО",IF(TRUE,"ОТКРЫТО","ЗАКРЫТО")) -> ОТКРЫТО | AX47: =IF(AND(AI47>=$E47,TRUE),"ИЗУЧЕНО",IF(TRUE,"ОТКРЫТО","ЗАКРЫТО")) -> ОТКРЫТО | AY47: =IF(AND(AJ47>=$E47,TRUE),"ИЗУЧЕНО",IF(TRUE,"ОТКРЫТО","ЗАКРЫТО")) -> ОТКРЫТО | ... BF47: =IF(AND(AQ47>=$E47,TRUE),"ИЗУЧЕНО",IF(TRUE,"ОТКРЫТО","ЗАКРЫТО")) -> ОТКРЫТО | BG47: =IFERROR(2025+MATCH("ИЗУЧЕНО",AR47:BF47,0),"") | BH47: =IF(BG47="","",BG47+1)
A48: X2 | B48: Межветвевые | C48: IV | D48: Национальная платформа инференса ИИ с маршрутизацией моделей через API | E48: 110 | F48: C4 | G48: D4 | H48: S3 | I48: Платформа объединяет вычислительные мощности, маршрутизацию запросов к разным моделям, учёт доступа и типовые программные интерфейсы для организаций. Это снижает порог подключения ИИ к экономике и государственным услугам. Необходимы развитые кластеры, инфраструктура данных и защищённая эксплуатация. Чем больше пользователей и задач обслуживается, тем выше совокупная потребность в электроэнергии. | J48: + Прирост сферы «Принятие ИИ»: +0,10/год; + Эффективность вложения очков ИИ в сферы: +10%; − Энергетические ресурсы: -0,20 | K48: =SUMIF('Ход 2026'!$G$29:$G$38,$A48,'Ход 2026'!$I$29:$I$38)*(1+'Эффекты технологий'!J$7+'Эффекты технологий'!J$9) -> 0 | L48: =SUMIF('Ход 2027'!$G$29:$G$38,$A48,'Ход 2027'!$I$29:$I$38)*(1+'Эффекты технологий'!K$7+'Эффекты технологий'!K$9) -> 0 | M48: =SUMIF('Ход 2028'!$G$29:$G$38,$A48,'Ход 2028'!$I$29:$I$38)*(1+'Эффекты технологий'!L$7+'Эффекты технологий'!L$9) -> 0 | N48: =SUMIF('Ход 2029'!$G$29:$G$38,$A48,'Ход 2029'!$I$29:$I$38)*(1+'Эффекты технологий'!M$7+'Эффекты технологий'!M$9) -> 0 | O48: =SUMIF('Ход 2030'!$G$29:$G$38,$A48,'Ход 2030'!$I$29:$I$38)*(1+'Эффекты технологий'!N$7+'Эффекты технологий'!N$9) -> 0 | P48: =SUMIF('Ход 2031'!$G$29:$G$38,$A48,'Ход 2031'!$I$29:$I$38)*(1+'Эффекты технологий'!O$7+'Эффекты технологий'!O$9) -> 0 | Q48: =SUMIF('Ход 2032'!$G$29:$G$38,$A48,'Ход 2032'!$I$29:$I$38)*(1+'Эффекты технологий'!P$7+'Эффекты технологий'!P$9) -> 0 | R48: =SUMIF('Ход 2033'!$G$29:$G$38,$A48,'Ход 2033'!$I$29:$I$38)*(1+'Эффекты технологий'!Q$7+'Эффекты технологий'!Q$9) -> 0 | S48: =SUMIF('Ход 2034'!$G$29:$G$38,$A48,'Ход 2034'!$I$29:$I$38)*(1+'Эффекты технологий'!R$7+'Эффекты технологий'!R$9) -> 0 | T48: =SUMIF('Ход 2035'!$G$29:$G$38,$A48,'Ход 2035'!$I$29:$I$38)*(1+'Эффекты технологий'!S$7+'Эффекты технологий'!S$9) -> 0 | U48: =SUMIF('Ход 2036'!$G$29:$G$38,$A48,'Ход 2036'!$I$29:$I$38)*(1+'Эффекты технологий'!T$7+'Эффекты технологий'!T$9) -> 0 | V48: =SUMIF('Ход 2037'!$G$29:$G$38,$A48,'Ход 2037'!$I$29:$I$38)*(1+'Эффекты технологий'!U$7+'Эффекты технологий'!U$9) -> 0 | W48: =SUMIF('Ход 2038'!$G$29:$G$38,$A48,'Ход 2038'!$I$29:$I$38)*(1+'Эффекты технологий'!V$7+'Эффекты технологий'!V$9) -> 0 | X48: =SUMIF('Ход 2039'!$G$29:$G$38,$A48,'Ход 2039'!$I$29:$I$38)*(1+'Эффекты технологий'!W$7+'Эффекты технологий'!W$9) -> 0 | Y48: =SUMIF('Ход 2040'!$G$29:$G$38,$A48,'Ход 2040'!$I$29:$I$38)*(1+'Эффекты технологий'!X$7+'Эффекты технологий'!X$9) -> 0 | Z48: =SUM(K48:Y48) -> 0 | AA48: =MAX(0,E48-Z48) -> 110 | AB48: =BF48 -> ОТКРЫТО | AC48: =SUM($K48:K48) -> 0 | AD48: =SUM($K48:L48) -> 0 | AE48: =SUM($K48:M48) -> 0 | AF48: =SUM($K48:N48) -> 0 | AG48: =SUM($K48:O48) -> 0 | AH48: =SUM($K48:P48) -> 0 | AI48: =SUM($K48:Q48) -> 0 | AJ48: =SUM($K48:R48) -> 0 | ... AQ48: =SUM($K48:Y48) -> 0 | AR48: =IF(AND(AC48>=$E48,TRUE),"ИЗУЧЕНО",IF(TRUE,"ОТКРЫТО","ЗАКРЫТО")) -> ОТКРЫТО | AS48: =IF(AND(AD48>=$E48,TRUE),"ИЗУЧЕНО",IF(TRUE,"ОТКРЫТО","ЗАКРЫТО")) -> ОТКРЫТО | AT48: =IF(AND(AE48>=$E48,TRUE),"ИЗУЧЕНО",IF(TRUE,"ОТКРЫТО","ЗАКРЫТО")) -> ОТКРЫТО | AU48: =IF(AND(AF48>=$E48,TRUE),"ИЗУЧЕНО",IF(TRUE,"ОТКРЫТО","ЗАКРЫТО")) -> ОТКРЫТО | AV48: =IF(AND(AG48>=$E48,TRUE),"ИЗУЧЕНО",IF(TRUE,"ОТКРЫТО","ЗАКРЫТО")) -> ОТКРЫТО | AW48: =IF(AND(AH48>=$E48,TRUE),"ИЗУЧЕНО",IF(TRUE,"ОТКРЫТО","ЗАКРЫТО")) -> ОТКРЫТО | AX48: =IF(AND(AI48>=$E48,TRUE),"ИЗУЧЕНО",IF(TRUE,"ОТКРЫТО","ЗАКРЫТО")) -> ОТКРЫТО | AY48: =IF(AND(AJ48>=$E48,TRUE),"ИЗУЧЕНО",IF(TRUE,"ОТКРЫТО","ЗАКРЫТО")) -> ОТКРЫТО | ... BF48: =IF(AND(AQ48>=$E48,TRUE),"ИЗУЧЕНО",IF(TRUE,"ОТКРЫТО","ЗАКРЫТО")) -> ОТКРЫТО | BG48: =IFERROR(2025+MATCH("ИЗУЧЕНО",AR48:BF48,0),"") | BH48: =IF(BG48="","",BG48+1)
A49: X3 | B49: Межветвевые | C49: V | D49: Межведомственный контур транзакционных ИИ-агентов | E49: 140 | F49: A5 | G49: D5 | H49: S5 | I49: Государственные ИИ-агенты могут координировать разрешённые операции между разными ведомствами, пользуясь согласованными каталогами данных и механизмами контроля действий. Это создаёт единый цифровой контур обработки сложных задач и усиливает международную координацию. Одновременно растут последствия ошибок разграничения полномочий и несанкционированного доступа к сведениям. Поэтому стратегическая выгода сопровождается штрафами к правам доступа и общественному доверию. | J49: + Сфера «Государственное управление»: +0,50; прирост +0,12/год; + Эффективность улучшения дипломатических отношений: +15%; + Защита от войны Аполлона: +10%; − Права доступа к информационным ресурсам: -0,30; − Социальное доверие: -0,25 | K49: =SUMIF('Ход 2026'!$G$29:$G$38,$A49,'Ход 2026'!$I$29:$I$38)*(1+'Эффекты технологий'!J$7+'Эффекты технологий'!J$9) -> 0 | L49: =SUMIF('Ход 2027'!$G$29:$G$38,$A49,'Ход 2027'!$I$29:$I$38)*(1+'Эффекты технологий'!K$7+'Эффекты технологий'!K$9) -> 0 | M49: =SUMIF('Ход 2028'!$G$29:$G$38,$A49,'Ход 2028'!$I$29:$I$38)*(1+'Эффекты технологий'!L$7+'Эффекты технологий'!L$9) -> 0 | N49: =SUMIF('Ход 2029'!$G$29:$G$38,$A49,'Ход 2029'!$I$29:$I$38)*(1+'Эффекты технологий'!M$7+'Эффекты технологий'!M$9) -> 0 | O49: =SUMIF('Ход 2030'!$G$29:$G$38,$A49,'Ход 2030'!$I$29:$I$38)*(1+'Эффекты технологий'!N$7+'Эффекты технологий'!N$9) -> 0 | P49: =SUMIF('Ход 2031'!$G$29:$G$38,$A49,'Ход 2031'!$I$29:$I$38)*(1+'Эффекты технологий'!O$7+'Эффекты технологий'!O$9) -> 0 | Q49: =SUMIF('Ход 2032'!$G$29:$G$38,$A49,'Ход 2032'!$I$29:$I$38)*(1+'Эффекты технологий'!P$7+'Эффекты технологий'!P$9) -> 0 | R49: =SUMIF('Ход 2033'!$G$29:$G$38,$A49,'Ход 2033'!$I$29:$I$38)*(1+'Эффекты технологий'!Q$7+'Эффекты технологий'!Q$9) -> 0 | S49: =SUMIF('Ход 2034'!$G$29:$G$38,$A49,'Ход 2034'!$I$29:$I$38)*(1+'Эффекты технологий'!R$7+'Эффекты технологий'!R$9) -> 0 | T49: =SUMIF('Ход 2035'!$G$29:$G$38,$A49,'Ход 2035'!$I$29:$I$38)*(1+'Эффекты технологий'!S$7+'Эффекты технологий'!S$9) -> 0 | U49: =SUMIF('Ход 2036'!$G$29:$G$38,$A49,'Ход 2036'!$I$29:$I$38)*(1+'Эффекты технологий'!T$7+'Эффекты технологий'!T$9) -> 0 | V49: =SUMIF('Ход 2037'!$G$29:$G$38,$A49,'Ход 2037'!$I$29:$I$38)*(1+'Эффекты технологий'!U$7+'Эффекты технологий'!U$9) -> 0 | W49: =SUMIF('Ход 2038'!$G$29:$G$38,$A49,'Ход 2038'!$I$29:$I$38)*(1+'Эффекты технологий'!V$7+'Эффекты технологий'!V$9) -> 0 | X49: =SUMIF('Ход 2039'!$G$29:$G$38,$A49,'Ход 2039'!$I$29:$I$38)*(1+'Эффекты технологий'!W$7+'Эффекты технологий'!W$9) -> 0 | Y49: =SUMIF('Ход 2040'!$G$29:$G$38,$A49,'Ход 2040'!$I$29:$I$38)*(1+'Эффекты технологий'!X$7+'Эффекты технологий'!X$9) -> 0 | Z49: =SUM(K49:Y49) -> 0 | AA49: =MAX(0,E49-Z49) -> 140 | AB49: =BF49 -> ОТКРЫТО | AC49: =SUM($K49:K49) -> 0 | AD49: =SUM($K49:L49) -> 0 | AE49: =SUM($K49:M49) -> 0 | AF49: =SUM($K49:N49) -> 0 | AG49: =SUM($K49:O49) -> 0 | AH49: =SUM($K49:P49) -> 0 | AI49: =SUM($K49:Q49) -> 0 | AJ49: =SUM($K49:R49) -> 0 | ... AQ49: =SUM($K49:Y49) -> 0 | AR49: =IF(AND(AC49>=$E49,TRUE),"ИЗУЧЕНО",IF(TRUE,"ОТКРЫТО","ЗАКРЫТО")) -> ОТКРЫТО | AS49: =IF(AND(AD49>=$E49,TRUE),"ИЗУЧЕНО",IF(TRUE,"ОТКРЫТО","ЗАКРЫТО")) -> ОТКРЫТО | AT49: =IF(AND(AE49>=$E49,TRUE),"ИЗУЧЕНО",IF(TRUE,"ОТКРЫТО","ЗАКРЫТО")) -> ОТКРЫТО | AU49: =IF(AND(AF49>=$E49,TRUE),"ИЗУЧЕНО",IF(TRUE,"ОТКРЫТО","ЗАКРЫТО")) -> ОТКРЫТО | AV49: =IF(AND(AG49>=$E49,TRUE),"ИЗУЧЕНО",IF(TRUE,"ОТКРЫТО","ЗАКРЫТО")) -> ОТКРЫТО | AW49: =IF(AND(AH49>=$E49,TRUE),"ИЗУЧЕНО",IF(TRUE,"ОТКРЫТО","ЗАКРЫТО")) -> ОТКРЫТО | AX49: =IF(AND(AI49>=$E49,TRUE),"ИЗУЧЕНО",IF(TRUE,"ОТКРЫТО","ЗАКРЫТО")) -> ОТКРЫТО | AY49: =IF(AND(AJ49>=$E49,TRUE),"ИЗУЧЕНО",IF(TRUE,"ОТКРЫТО","ЗАКРЫТО")) -> ОТКРЫТО | ... BF49: =IF(AND(AQ49>=$E49,TRUE),"ИЗУЧЕНО",IF(TRUE,"ОТКРЫТО","ЗАКРЫТО")) -> ОТКРЫТО | BG49: =IFERROR(2025+MATCH("ИЗУЧЕНО",AR49:BF49,0),"") | BH49: =IF(BG49="","",BG49+1)
A50: X4 | B50: Межветвевые | C50: V+ | D50: Замкнутый контур автоматизированного исследования и развёртывания моделей ИИ | E50: 190 | F50: M6 | G50: A6 | H50: S6 | I50: Система объединяет постановку исследовательской задачи, автоматический поиск архитектуры, обучение, оценку безопасности и контролируемое развёртывание модели. Результаты очередного цикла используются для выбора следующего направления развития, формируя самоускоряющийся исследовательский контур. Это самая дорогая межветвевая технология, доступная только после ведущих достижений в моделях, агентах и контроле. Она открывает специальные игровые карты, но создаёт высокую энергетическую нагрузку и новые системные риски. | J50: + Эффективность науки во всех направлениях: +25%; + Прирост методов построения и совершенствования моделей: +0,10/год; + Прирост модельных ресурсов: +0,10/год; + Доступ к картам технологических прорывов и рисков; − Энергетические ресурсы: -0,40; − Кибербезопасностные ресурсы: -0,30; − Социальное доверие: -0,25 | K50: =SUMIF('Ход 2026'!$G$29:$G$38,$A50,'Ход 2026'!$I$29:$I$38)*(1+'Эффекты технологий'!J$7+'Эффекты технологий'!J$9) -> 0 | L50: =SUMIF('Ход 2027'!$G$29:$G$38,$A50,'Ход 2027'!$I$29:$I$38)*(1+'Эффекты технологий'!K$7+'Эффекты технологий'!K$9) -> 0 | M50: =SUMIF('Ход 2028'!$G$29:$G$38,$A50,'Ход 2028'!$I$29:$I$38)*(1+'Эффекты технологий'!L$7+'Эффекты технологий'!L$9) -> 0 | N50: =SUMIF('Ход 2029'!$G$29:$G$38,$A50,'Ход 2029'!$I$29:$I$38)*(1+'Эффекты технологий'!M$7+'Эффекты технологий'!M$9) -> 0 | O50: =SUMIF('Ход 2030'!$G$29:$G$38,$A50,'Ход 2030'!$I$29:$I$38)*(1+'Эффекты технологий'!N$7+'Эффекты технологий'!N$9) -> 0 | P50: =SUMIF('Ход 2031'!$G$29:$G$38,$A50,'Ход 2031'!$I$29:$I$38)*(1+'Эффекты технологий'!O$7+'Эффекты технологий'!O$9) -> 0 | Q50: =SUMIF('Ход 2032'!$G$29:$G$38,$A50,'Ход 2032'!$I$29:$I$38)*(1+'Эффекты технологий'!P$7+'Эффекты технологий'!P$9) -> 0 | R50: =SUMIF('Ход 2033'!$G$29:$G$38,$A50,'Ход 2033'!$I$29:$I$38)*(1+'Эффекты технологий'!Q$7+'Эффекты технологий'!Q$9) -> 0 | S50: =SUMIF('Ход 2034'!$G$29:$G$38,$A50,'Ход 2034'!$I$29:$I$38)*(1+'Эффекты технологий'!R$7+'Эффекты технологий'!R$9) -> 0 | T50: =SUMIF('Ход 2035'!$G$29:$G$38,$A50,'Ход 2035'!$I$29:$I$38)*(1+'Эффекты технологий'!S$7+'Эффекты технологий'!S$9) -> 0 | U50: =SUMIF('Ход 2036'!$G$29:$G$38,$A50,'Ход 2036'!$I$29:$I$38)*(1+'Эффекты технологий'!T$7+'Эффекты технологий'!T$9) -> 0 | V50: =SUMIF('Ход 2037'!$G$29:$G$38,$A50,'Ход 2037'!$I$29:$I$38)*(1+'Эффекты технологий'!U$7+'Эффекты технологий'!U$9) -> 0 | W50: =SUMIF('Ход 2038'!$G$29:$G$38,$A50,'Ход 2038'!$I$29:$I$38)*(1+'Эффекты технологий'!V$7+'Эффекты технологий'!V$9) -> 0 | X50: =SUMIF('Ход 2039'!$G$29:$G$38,$A50,'Ход 2039'!$I$29:$I$38)*(1+'Эффекты технологий'!W$7+'Эффекты технологий'!W$9) -> 0 | Y50: =SUMIF('Ход 2040'!$G$29:$G$38,$A50,'Ход 2040'!$I$29:$I$38)*(1+'Эффекты технологий'!X$7+'Эффекты технологий'!X$9) -> 0 | Z50: =SUM(K50:Y50) -> 0 | AA50: =MAX(0,E50-Z50) -> 190 | AB50: =BF50 -> ОТКРЫТО | AC50: =SUM($K50:K50) -> 0 | AD50: =SUM($K50:L50) -> 0 | AE50: =SUM($K50:M50) -> 0 | AF50: =SUM($K50:N50) -> 0 | AG50: =SUM($K50:O50) -> 0 | AH50: =SUM($K50:P50) -> 0 | AI50: =SUM($K50:Q50) -> 0 | AJ50: =SUM($K50:R50) -> 0 | ... AQ50: =SUM($K50:Y50) -> 0 | AR50: =IF(AND(AC50>=$E50,TRUE),"ИЗУЧЕНО",IF(TRUE,"ОТКРЫТО","ЗАКРЫТО")) -> ОТКРЫТО | AS50: =IF(AND(AD50>=$E50,TRUE),"ИЗУЧЕНО",IF(TRUE,"ОТКРЫТО","ЗАКРЫТО")) -> ОТКРЫТО | AT50: =IF(AND(AE50>=$E50,TRUE),"ИЗУЧЕНО",IF(TRUE,"ОТКРЫТО","ЗАКРЫТО")) -> ОТКРЫТО | AU50: =IF(AND(AF50>=$E50,TRUE),"ИЗУЧЕНО",IF(TRUE,"ОТКРЫТО","ЗАКРЫТО")) -> ОТКРЫТО | AV50: =IF(AND(AG50>=$E50,TRUE),"ИЗУЧЕНО",IF(TRUE,"ОТКРЫТО","ЗАКРЫТО")) -> ОТКРЫТО | AW50: =IF(AND(AH50>=$E50,TRUE),"ИЗУЧЕНО",IF(TRUE,"ОТКРЫТО","ЗАКРЫТО")) -> ОТКРЫТО | AX50: =IF(AND(AI50>=$E50,TRUE),"ИЗУЧЕНО",IF(TRUE,"ОТКРЫТО","ЗАКРЫТО")) -> ОТКРЫТО | AY50: =IF(AND(AJ50>=$E50,TRUE),"ИЗУЧЕНО",IF(TRUE,"ОТКРЫТО","ЗАКРЫТО")) -> ОТКРЫТО | ... BF50: =IF(AND(AQ50>=$E50,TRUE),"ИЗУЧЕНО",IF(TRUE,"ОТКРЫТО","ЗАКРЫТО")) -> ОТКРЫТО | BG50: =IFERROR(2025+MATCH("ИЗУЧЕНО",AR50:BF50,0),"") | BH50: =IF(BG50="","",BG50+1)

Sheet Россия 2026
A1: РОССИЯ — СОСТОЯНИЕ НА НАЧАЛО 2026 ГОДА
A3: Жёлтые поля заполняются вручную. Четыре колонки эффектов всегда создаются с нулём и не содержат формул.
A5: 1. РЕСУРСНАЯ БАЗА ИИ | K5: ОЧКИ ИИ | N5: ОЧКИ НАУКИ | Q5: ВНЕШНЕПОЛИТИЧЕСКИЕ ОЧКИ | U5: ОЧКИ ТРАНСФОРМАЦИИ
A6: Ресурс | B6: Начальное значение | C6: Базовый годовой прирост | D6: Постоянный эффект на значение | E6: Временный эффект на значение | F6: Постоянный эффект на прирост | G6: Временный эффект на прирост | H6: От торговли | I6: Реальное значение | J6: От науки | K6: =MIN(100,(100*POWER((POWER(POWER((POWER(I8/10,-1)+POWER(I9/10,-1)+POWER(I10/10,-1)+POWER(I11/10,-1)+POWER(I12/10,-1)+POWER(I13/10,-1)+POWER(I14/10,-1)+POWER(I15/10,-1)+POWER(I16/10,-1)+POWER(I17/10,-1))/10,1/-1),0.3)*POWER(POWER((POWER(I19/10,-0.5)+POWER(I20/10,-0.5)+POWER(I21/10,-0.5)+POWER(I22/10,-0.5)+POWER(I23/10,-0.5))/5,1/-0.5),0.2)*POWER(POWER((POWER(I25/10,-0.5)+POWER(I26/10,-0.5)+POWER(I27/10,-0.5)+POWER(I28/10,-0.5)+POWER(I29/10,-0.5)+POWER(I30/10,-0.5)+POWER(I31/10,-0.5)+POWER(I32/10,-0.5))/8,1/-0.5),0.2)*POWER(POWER((POWER(I34/10,-0.25)+POWER(I35/10,-0.25)+POWER(I36/10,-0.25)+POWER(I37/10,-0.25)+POWER(I38/10,-0.25)+POWER(I39/10,-0.25)+POWER(I40/10,-0.25)+POWER(I41/10,-0.25)+POWER(I42/10,-0.25))/9,1/-0.25),0.15)*POWER(POWER((POWER(I44/10,0.25)+POWER(I45/10,0.25)+POWER(I46/10,0.25)+POWER(I47/10,0.25)+POWER(I48/10,0.25)+POWER(I49/10,0.25)+POWER(I50/10,0.25)+POWER(I51/10,0.25))/8,1/0.25),0.1)*POWER(POWER((I53/10)*(I54/10)*(I55/10),1/3),0.05)),3)/(POWER(0.55,3)+POWER((POWER(POWER((POWER(I8/10,-1)+POWER(I9/10,-1)+POWER(I10/10,-1)+POWER(I11/10,-1)+POWER(I12/10,-1)+POWER(I13/10,-1)+POWER(I14/10,-1)+POWER(I15/10,-1)+POWER(I16/10,-1)+POWER(I17/10,-1))/10,1/-1),0.3)*POWER(POWER((POWER(I19/10,-0.5)+POWER(I20/10,-0.5)+POWER(I21/10,-0.5)+POWER(I22/10,-0.5)+POWER(I23/10,-0.5))/5,1/-0.5),0.2)*POWER(POWER((POWER(I25/10,-0.5)+POWER(I26/10,-0.5)+POWER(I27/10,-0.5)+POWER(I28/10,-0.5)+POWER(I29/10,-0.5)+POWER(I30/10,-0.5)+POWER(I31/10,-0.5)+POWER(I32/10,-0.5))/8,1/-0.5),0.2)*POWER(POWER((POWER(I34/10,-0.25)+POWER(I35/10,-0.25)+POWER(I36/10,-0.25)+POWER(I37/10,-0.25)+POWER(I38/10,-0.25)+POWER(I39/10,-0.25)+POWER(I40/10,-0.25)+POWER(I41/10,-0.25)+POWER(I42/10,-0.25))/9,1/-0.25),0.15)*POWER(POWER((POWER(I44/10,0.25)+POWER(I45/10,0.25)+POWER(I46/10,0.25)+POWER(I47/10,0.25)+POWER(I48/10,0.25)+POWER(I49/10,0.25)+POWER(I50/10,0.25)+POWER(I51/10,0.25))/8,1/0.25),0.1)*POWER(POWER((I53/10)*(I54/10)*(I55/10),1/3),0.05)),3)))*(1+POWER(0.55,3))) -> 72.313822 | N6: =MIN(100,(100*POWER((POWER((POWER(S13/10,0.45)*POWER(S14/10,0.25)*POWER(S12/10,0.1)*POWER(S17/10,0.1)*POWER(S16/10,0.05)*POWER(S18/10,0.05)),0.8)*POWER((POWER(I34/10,0.2)*POWER(I22/10,0.15)*POWER(I25/10,0.1)*POWER(I27/10,0.1)*POWER(I15/10,0.15)*POWER(I28/10,0.1)*POWER(I40/10,0.1)*POWER(I31/10,0.1)),0.2)),2)/(POWER(0.55,2)+POWER((POWER((POWER(S13/10,0.45)*POWER(S14/10,0.25)*POWER(S12/10,0.1)*POWER(S17/10,0.1)*POWER(S16/10,0.05)*POWER(S18/10,0.05)),0.8)*POWER((POWER(I34/10,0.2)*POWER(I22/10,0.15)*POWER(I25/10,0.1)*POWER(I27/10,0.1)*POWER(I15/10,0.15)*POWER(I28/10,0.1)*POWER(I40/10,0.1)*POWER(I31/10,0.1)),0.2)),2)))*(1+POWER(0.55,2))) -> 73.933944 | Q6: =100*POWER(((AVERAGE(V11:V25)+5)/10),0.3)*POWER((POWER(I16/10,0.15)*POWER(I32/10,0.15)*POWER(I40/10,0.2)*POWER(I41/10,0.15)*POWER(I46/10,0.15)*POWER(I47/10,0.2)),0.3)*POWER((POWER(S12/10,0.2)*POWER(S15/10,0.2)*POWER(S16/10,0.3)*POWER(S17/10,0.3)),0.4) -> 58.945692 | U6: =100*LN(1+20*(POWER((POWER(S11/10,0.2)*POWER(S12/10,0.15)*POWER(S13/10,0.1)*POWER(S14/10,0.1)*POWER(S15/10,0.05)*POWER(S16/10,0.15)*POWER(S17/10,0.15)*POWER(S18/10,0.1)),0.65)*POWER((POWER(I8/10,0.06)*POWER(I9/10,0.1)*POWER(I10/10,0.12)*POWER(I11/10,0.05)*POWER(I12/10,0.04)*POWER(I13/10,0.17)*POWER(I14/10,0.15)*POWER(I15/10,0.15)*POWER(I16/10,0.1)*POWER(I17/10,0.06)),0.35)))/LN(21) -> 83.126867
A7: I. Материально-физическая и вычислительная база
A8: Минерально-сырьевые ресурсы | B8: 9 | C8: 0.05 | D8: 0 | E8: 0 | F8: 0 | G8: 0 | H8: 0 | I8: =MAX(1,MIN(10,B8+D8+E8+H8+J8)) -> 9 | J8: =SUMIFS('Эффекты технологий'!$J$25:$J$240,'Эффекты технологий'!$C$25:$C$240,$A8,'Эффекты технологий'!$D$25:$D$240,"Значение") -> 0
A9: Химические и технологические материалы | B9: 5 | C9: 0.2 | D9: 0 | E9: 0 | F9: 0 | G9: 0 | H9: 0 | I9: =MAX(1,MIN(10,B9+D9+E9+H9+J9)) -> 5 | J9: =SUMIFS('Эффекты технологий'!$J$25:$J$240,'Эффекты технологий'!$C$25:$C$240,$A9,'Эффекты технологий'!$D$25:$D$240,"Значение") -> 0 | K9: 2. СФЕРЫ ВНЕДРЕНИЯ ИИ | U9: 3. МЕЖДУНАРОДНЫЕ ОТНОШЕНИЯ
A10: Энергетические ресурсы | B10: 9 | C10: 0.1 | D10: 0 | E10: 0 | F10: 0 | G10: 0 | H10: 0 | I10: =MAX(1,MIN(10,B10+D10+E10+H10+J10)) -> 9 | J10: =SUMIFS('Эффекты технологий'!$J$25:$J$240,'Эффекты технологий'!$C$25:$C$240,$A10,'Эффекты технологий'!$D$25:$D$240,"Значение") -> 0 | K10: Сфера | L10: Начальное значение | M10: Базовый годовой прирост | N10: Постоянный эффект на значение | O10: Временный эффект на значение | P10: Постоянный эффект на прирост | Q10: Временный эффект на прирост | R10: От торговли | S10: Реальное значение | T10: От науки | U10: Страна | V10: Код −5…+5 | W10: Статус | X10: Краткое положение
A11: Вода и ресурс отвода тепла | B11: 9 | C11: 0 | D11: 0 | E11: 0 | F11: 0 | G11: 0 | H11: 0 | I11: =MAX(1,MIN(10,B11+D11+E11+H11+J11)) -> 9 | J11: =SUMIFS('Эффекты технологий'!$J$25:$J$240,'Эффекты технологий'!$C$25:$C$240,$A11,'Эффекты технологий'!$D$25:$D$240,"Значение") -> 0 | K11: Производство | L11: 5.5 | M11: 0.35 | N11: 0 | O11: 0 | P11: 0 | Q11: 0 | R11: 0 | S11: =MAX(1,MIN(10,L11+N11+O11+R11+T11)) -> 5.5 | T11: =SUMIFS('Эффекты технологий'!$J$25:$J$240,'Эффекты технологий'!$C$25:$C$240,$K11,'Эффекты технологий'!$D$25:$D$240,"Значение") -> 0 | U11: США | V11: -1.5 | W11: =IF(V11<=-4.1,"Война на уничтожение",IF(V11<=-3.1,"Война",IF(V11<=-2.1,"Вооружённый конфликт",IF(V11<=-1.1,"Конфронтация",IF(V11<0,"Напряжённые отношения",IF(V11=0,"Нейтралитет",IF(V11<=1,"Сотрудничество",IF(V11<=2,"Партнёрство",IF(V11<=3,"Стратегическое партнёрство",IF(V11<=4,"Стратегический союз","Интеграция")))))))))) -> Конфронтация | X11: Санкции и глубокие разногласия сохраняются; дипломатические каналы не разорваны.
A12: Пространственные и природно-географические ресурсы | B12: 9 | C12: 0 | D12: 0 | E12: 0 | F12: 0 | G12: 0 | H12: 0 | I12: =MAX(1,MIN(10,B12+D12+E12+H12+J12)) -> 9 | J12: =SUMIFS('Эффекты технологий'!$J$25:$J$240,'Эффекты технологий'!$C$25:$C$240,$A12,'Эффекты технологий'!$D$25:$D$240,"Значение") -> 0 | K12: Управление | L12: 5.5 | M12: 0.35 | N12: 0 | O12: 0 | P12: 0 | Q12: 0 | R12: 0 | S12: =MAX(1,MIN(10,L12+N12+O12+R12+T12)) -> 5.5 | T12: =SUMIFS('Эффекты технологий'!$J$25:$J$240,'Эффекты технологий'!$C$25:$C$240,$K12,'Эффекты технологий'!$D$25:$D$240,"Значение") -> 0 | U12: Китай | V12: 2.9 | W12: =IF(V12<=-4.1,"Война на уничтожение",IF(V12<=-3.1,"Война",IF(V12<=-2.1,"Вооружённый конфликт",IF(V12<=-1.1,"Конфронтация",IF(V12<0,"Напряжённые отношения",IF(V12=0,"Нейтралитет",IF(V12<=1,"Сотрудничество",IF(V12<=2,"Партнёрство",IF(V12<=3,"Стратегическое партнёрство",IF(V12<=4,"Стратегический союз","Интеграция")))))))))) -> Стратегическое партнёрство | X12: Всеобъемлющее партнёрство и стратегическое взаимодействие; формально не военный союз.
A13: Мощности производства полупроводников | B13: 3 | C13: 0.25 | D13: 0 | E13: 0 | F13: 0 | G13: 0 | H13: 0 | I13: =MAX(1,MIN(10,B13+D13+E13+H13+J13)) -> 3 | J13: =SUMIFS('Эффекты технологий'!$J$25:$J$240,'Эффекты технологий'!$C$25:$C$240,$A13,'Эффекты технологий'!$D$25:$D$240,"Значение") -> 0 | K13: Познание | L13: 6.5 | M13: 0.35 | N13: 0 | O13: 0 | P13: 0 | Q13: 0 | R13: 0 | S13: =MAX(1,MIN(10,L13+N13+O13+R13+T13)) -> 6.5 | T13: =SUMIFS('Эффекты технологий'!$J$25:$J$240,'Эффекты технологий'!$C$25:$C$240,$K13,'Эффекты технологий'!$D$25:$D$240,"Значение") -> 0 | U13: Индия | V13: 2.8 | W13: =IF(V13<=-4.1,"Война на уничтожение",IF(V13<=-3.1,"Война",IF(V13<=-2.1,"Вооружённый конфликт",IF(V13<=-1.1,"Конфронтация",IF(V13<0,"Напряжённые отношения",IF(V13=0,"Нейтралитет",IF(V13<=1,"Сотрудничество",IF(V13<=2,"Партнёрство",IF(V13<=3,"Стратегическое партнёрство",IF(V13<=4,"Стратегический союз","Интеграция")))))))))) -> Стратегическое партнёрство | X13: Особо привилегированное стратегическое партнёрство.
A14: Вычислительные компоненты | B14: 3 | C14: 0.2 | D14: 0 | E14: 0 | F14: 0 | G14: 0 | H14: 0 | I14: =MAX(1,MIN(10,B14+D14+E14+H14+J14)) -> 3 | J14: =SUMIFS('Эффекты технологий'!$J$25:$J$240,'Эффекты технологий'!$C$25:$C$240,$A14,'Эффекты технологий'!$D$25:$D$240,"Значение") -> 0 | K14: Обучение | L14: 5.5 | M14: 0.4 | N14: 0 | O14: 0 | P14: 0 | Q14: 0 | R14: 0 | S14: =MAX(1,MIN(10,L14+N14+O14+R14+T14)) -> 5.5 | T14: =SUMIFS('Эффекты технологий'!$J$25:$J$240,'Эффекты технологий'!$C$25:$C$240,$K14,'Эффекты технологий'!$D$25:$D$240,"Значение") -> 0 | U14: Великобритания | V14: -1.8 | W14: =IF(V14<=-4.1,"Война на уничтожение",IF(V14<=-3.1,"Война",IF(V14<=-2.1,"Вооружённый конфликт",IF(V14<=-1.1,"Конфронтация",IF(V14<0,"Напряжённые отношения",IF(V14=0,"Нейтралитет",IF(V14<=1,"Сотрудничество",IF(V14<=2,"Партнёрство",IF(V14<=3,"Стратегическое партнёрство",IF(V14<=4,"Стратегический союз","Интеграция")))))))))) -> Конфронтация | X14: Широкий санкционный режим и жёсткое политико-безопасностное противостояние.
A15: ЦОД и вычислительная инфраструктура | B15: 6 | C15: 0.4 | D15: 0 | E15: 0 | F15: 0 | G15: 0 | H15: 0 | I15: =MAX(1,MIN(10,B15+D15+E15+H15+J15)) -> 6 | J15: =SUMIFS('Эффекты технологий'!$J$25:$J$240,'Эффекты технологий'!$C$25:$C$240,$A15,'Эффекты технологий'!$D$25:$D$240,"Значение") -> 0 | K15: Война | L15: 6 | M15: 0.25 | N15: 0 | O15: 0 | P15: 0 | Q15: 0 | R15: 0 | S15: =MAX(1,MIN(10,L15+N15+O15+R15+T15)) -> 6 | T15: =SUMIFS('Эффекты технологий'!$J$25:$J$240,'Эффекты технологий'!$C$25:$C$240,$K15,'Эффекты технологий'!$D$25:$D$240,"Значение") -> 0 | U15: Франция | V15: -1.4 | W15: =IF(V15<=-4.1,"Война на уничтожение",IF(V15<=-3.1,"Война",IF(V15<=-2.1,"Вооружённый конфликт",IF(V15<=-1.1,"Конфронтация",IF(V15<0,"Напряжённые отношения",IF(V15=0,"Нейтралитет",IF(V15<=1,"Сотрудничество",IF(V15<=2,"Партнёрство",IF(V15<=3,"Стратегическое партнёрство",IF(V15<=4,"Стратегический союз","Интеграция")))))))))) -> Конфронтация | X15: Санкции и поддержка Украины сочетаются с сохранением отдельных каналов диалога.
A16: Сетевые ресурсы | B16: 8 | C16: 0.2 | D16: 0 | E16: 0 | F16: 0 | G16: 0 | H16: 0 | I16: =MAX(1,MIN(10,B16+D16+E16+H16+J16)) -> 8 | J16: =SUMIFS('Эффекты технологий'!$J$25:$J$240,'Эффекты технологий'!$C$25:$C$240,$A16,'Эффекты технологий'!$D$25:$D$240,"Значение") -> 0 | K16: Экономика | L16: 6.5 | M16: 0.45 | N16: 0 | O16: 0 | P16: 0 | Q16: 0 | R16: 0 | S16: =MAX(1,MIN(10,L16+N16+O16+R16+T16)) -> 6.5 | T16: =SUMIFS('Эффекты технологий'!$J$25:$J$240,'Эффекты технологий'!$C$25:$C$240,$K16,'Эффекты технологий'!$D$25:$D$240,"Значение") -> 0 | U16: Германия | V16: -1.7 | W16: =IF(V16<=-4.1,"Война на уничтожение",IF(V16<=-3.1,"Война",IF(V16<=-2.1,"Вооружённый конфликт",IF(V16<=-1.1,"Конфронтация",IF(V16<0,"Напряжённые отношения",IF(V16=0,"Нейтралитет",IF(V16<=1,"Сотрудничество",IF(V16<=2,"Партнёрство",IF(V16<=3,"Стратегическое партнёрство",IF(V16<=4,"Стратегический союз","Интеграция")))))))))) -> Конфронтация | X16: Участие в санкциях ЕС и поддержке Украины; политические отношения существенно ухудшены.
A17: Конечные устройства | B17: 7 | C17: 0.15 | D17: 0 | E17: 0 | F17: 0 | G17: 0 | H17: 0 | I17: =MAX(1,MIN(10,B17+D17+E17+H17+J17)) -> 7 | J17: =SUMIFS('Эффекты технологий'!$J$25:$J$240,'Эффекты технологий'!$C$25:$C$240,$A17,'Эффекты технологий'!$D$25:$D$240,"Значение") -> 0 | K17: Государственное управление | L17: 6.5 | M17: 0.4 | N17: 0 | O17: 0 | P17: 0 | Q17: 0 | R17: 0 | S17: =MAX(1,MIN(10,L17+N17+O17+R17+T17)) -> 6.5 | T17: =SUMIFS('Эффекты технологий'!$J$25:$J$240,'Эффекты технологий'!$C$25:$C$240,$K17,'Эффекты технологий'!$D$25:$D$240,"Значение") -> 0 | U17: Япония | V17: -1.3 | W17: =IF(V17<=-4.1,"Война на уничтожение",IF(V17<=-3.1,"Война",IF(V17<=-2.1,"Вооружённый конфликт",IF(V17<=-1.1,"Конфронтация",IF(V17<0,"Напряжённые отношения",IF(V17=0,"Нейтралитет",IF(V17<=1,"Сотрудничество",IF(V17<=2,"Партнёрство",IF(V17<=3,"Стратегическое партнёрство",IF(V17<=4,"Стратегический союз","Интеграция")))))))))) -> Конфронтация | X17: Санкции и замороженное экономическое сотрудничество; сохраняются необходимые двусторонние контакты.
A18: II. Программно-алгоритмический потенциал | K18: Принятие ИИ | L18: 6 | M18: 0.35 | N18: 0 | O18: 0 | P18: 0 | Q18: 0 | R18: 0 | S18: =MAX(1,MIN(10,L18+N18+O18+R18+T18)) -> 6 | T18: =SUMIFS('Эффекты технологий'!$J$25:$J$240,'Эффекты технологий'!$C$25:$C$240,$K18,'Эффекты технологий'!$D$25:$D$240,"Значение") -> 0 | U18: Южная Корея | V18: -1.2 | W18: =IF(V18<=-4.1,"Война на уничтожение",IF(V18<=-3.1,"Война",IF(V18<=-2.1,"Вооружённый конфликт",IF(V18<=-1.1,"Конфронтация",IF(V18<0,"Напряжённые отношения",IF(V18=0,"Нейтралитет",IF(V18<=1,"Сотрудничество",IF(V18<=2,"Партнёрство",IF(V18<=3,"Стратегическое партнёрство",IF(V18<=4,"Стратегический союз","Интеграция")))))))))) -> Конфронтация | X18: Санкционное давление и серьёзные разногласия по вопросам Украины и российско-корейского военного сотрудничества.
A19: Базовый программный стек вычислений | B19: 7 | C19: 0.25 | D19: 0 | E19: 0 | F19: 0 | G19: 0 | H19: 0 | I19: =MAX(1,MIN(10,B19+D19+E19+H19+J19)) -> 7 | J19: =SUMIFS('Эффекты технологий'!$J$25:$J$240,'Эффекты технологий'!$C$25:$C$240,$A19,'Эффекты технологий'!$D$25:$D$240,"Значение") -> 0 | U19: Турция | V19: 1.3 | W19: =IF(V19<=-4.1,"Война на уничтожение",IF(V19<=-3.1,"Война",IF(V19<=-2.1,"Вооружённый конфликт",IF(V19<=-1.1,"Конфронтация",IF(V19<0,"Напряжённые отношения",IF(V19=0,"Нейтралитет",IF(V19<=1,"Сотрудничество",IF(V19<=2,"Партнёрство",IF(V19<=3,"Стратегическое партнёрство",IF(V19<=4,"Стратегический союз","Интеграция")))))))))) -> Партнёрство | X19: Плотный политический и экономический контакт при существенных разногласиях по отдельным региональным вопросам.
A20: Стек разработки ИИ | B20: 8 | C20: 0.3 | D20: 0 | E20: 0 | F20: 0 | G20: 0 | H20: 0 | I20: =MAX(1,MIN(10,B20+D20+E20+H20+J20)) -> 8 | J20: =SUMIFS('Эффекты технологий'!$J$25:$J$240,'Эффекты технологий'!$C$25:$C$240,$A20,'Эффекты технологий'!$D$25:$D$240,"Значение") -> 0 | U20: Саудовская Аравия | V20: 1.2 | W20: =IF(V20<=-4.1,"Война на уничтожение",IF(V20<=-3.1,"Война",IF(V20<=-2.1,"Вооружённый конфликт",IF(V20<=-1.1,"Конфронтация",IF(V20<0,"Напряжённые отношения",IF(V20=0,"Нейтралитет",IF(V20<=1,"Сотрудничество",IF(V20<=2,"Партнёрство",IF(V20<=3,"Стратегическое партнёрство",IF(V20<=4,"Стратегический союз","Интеграция")))))))))) -> Партнёрство | X20: Активное энергетическое и экономическое сотрудничество; союзных обязательств нет.
A21: Стек эксплуатации ИИ | B21: 7 | C21: 0.35 | D21: 0 | E21: 0 | F21: 0 | G21: 0 | H21: 0 | I21: =MAX(1,MIN(10,B21+D21+E21+H21+J21)) -> 7 | J21: =SUMIFS('Эффекты технологий'!$J$25:$J$240,'Эффекты технологий'!$C$25:$C$240,$A21,'Эффекты технологий'!$D$25:$D$240,"Значение") -> 0 | U21: Иран | V21: 2.7 | W21: =IF(V21<=-4.1,"Война на уничтожение",IF(V21<=-3.1,"Война",IF(V21<=-2.1,"Вооружённый конфликт",IF(V21<=-1.1,"Конфронтация",IF(V21<0,"Напряжённые отношения",IF(V21=0,"Нейтралитет",IF(V21<=1,"Сотрудничество",IF(V21<=2,"Партнёрство",IF(V21<=3,"Стратегическое партнёрство",IF(V21<=4,"Стратегический союз","Интеграция")))))))))) -> Стратегическое партнёрство | X21: Действует договор о всеобъемлющем стратегическом партнёрстве.
A22: Математико-алгоритмические ресурсы | B22: 9 | C22: 0.15 | D22: 0 | E22: 0 | F22: 0 | G22: 0 | H22: 0 | I22: =MAX(1,MIN(10,B22+D22+E22+H22+J22)) -> 9 | J22: =SUMIFS('Эффекты технологий'!$J$25:$J$240,'Эффекты технологий'!$C$25:$C$240,$A22,'Эффекты технологий'!$D$25:$D$240,"Значение") -> 0 | U22: Израиль | V22: -0.2 | W22: =IF(V22<=-4.1,"Война на уничтожение",IF(V22<=-3.1,"Война",IF(V22<=-2.1,"Вооружённый конфликт",IF(V22<=-1.1,"Конфронтация",IF(V22<0,"Напряжённые отношения",IF(V22=0,"Нейтралитет",IF(V22<=1,"Сотрудничество",IF(V22<=2,"Партнёрство",IF(V22<=3,"Стратегическое партнёрство",IF(V22<=4,"Стратегический союз","Интеграция")))))))))) -> Напряжённые отношения | X22: Дипломатические контакты сохраняются, но по ряду ближневосточных вопросов позиции расходятся.
A23: Методы построения и совершенствования моделей | B23: 8 | C23: 0.3 | D23: 0 | E23: 0 | F23: 0 | G23: 0 | H23: 0 | I23: =MAX(1,MIN(10,B23+D23+E23+H23+J23)) -> 8 | J23: =SUMIFS('Эффекты технологий'!$J$25:$J$240,'Эффекты технологий'!$C$25:$C$240,$A23,'Эффекты технологий'!$D$25:$D$240,"Значение") -> 0 | U23: Бразилия | V23: 1.7 | W23: =IF(V23<=-4.1,"Война на уничтожение",IF(V23<=-3.1,"Война",IF(V23<=-2.1,"Вооружённый конфликт",IF(V23<=-1.1,"Конфронтация",IF(V23<0,"Напряжённые отношения",IF(V23=0,"Нейтралитет",IF(V23<=1,"Сотрудничество",IF(V23<=2,"Партнёрство",IF(V23<=3,"Стратегическое партнёрство",IF(V23<=4,"Стратегический союз","Интеграция")))))))))) -> Партнёрство | X23: Активное взаимодействие в БРИКС и устойчивый политический диалог.
A24: III. Данные, модели и информационная безопасность | U24: ОАЭ | V24: 1.8 | W24: =IF(V24<=-4.1,"Война на уничтожение",IF(V24<=-3.1,"Война",IF(V24<=-2.1,"Вооружённый конфликт",IF(V24<=-1.1,"Конфронтация",IF(V24<0,"Напряжённые отношения",IF(V24=0,"Нейтралитет",IF(V24<=1,"Сотрудничество",IF(V24<=2,"Партнёрство",IF(V24<=3,"Стратегическое партнёрство",IF(V24<=4,"Стратегический союз","Интеграция")))))))))) -> Партнёрство | X24: Стратегическое партнёрство и развитые экономические связи.
A25: Исходные данные | B25: 8 | C25: 0.25 | D25: 0 | E25: 0 | F25: 0 | G25: 0 | H25: 0 | I25: =MAX(1,MIN(10,B25+D25+E25+H25+J25)) -> 8 | J25: =SUMIFS('Эффекты технологий'!$J$25:$J$240,'Эффекты технологий'!$C$25:$C$240,$A25,'Эффекты технологий'!$D$25:$D$240,"Значение") -> 0 | U25: Индонезия | V25: 1.8 | W25: =IF(V25<=-4.1,"Война на уничтожение",IF(V25<=-3.1,"Война",IF(V25<=-2.1,"Вооружённый конфликт",IF(V25<=-1.1,"Конфронтация",IF(V25<0,"Напряжённые отношения",IF(V25=0,"Нейтралитет",IF(V25<=1,"Сотрудничество",IF(V25<=2,"Партнёрство",IF(V25<=3,"Стратегическое партнёрство",IF(V25<=4,"Стратегический союз","Интеграция")))))))))) -> Партнёрство | X25: В 2025 году подтверждено развитие стратегического партнёрства.
A26: Производные данные | B26: 6 | C26: 0.3 | D26: 0 | E26: 0 | F26: 0 | G26: 0 | H26: 0 | I26: =MAX(1,MIN(10,B26+D26+E26+H26+J26)) -> 6 | J26: =SUMIFS('Эффекты технологий'!$J$25:$J$240,'Эффекты технологий'!$C$25:$C$240,$A26,'Эффекты технологий'!$D$25:$D$240,"Значение") -> 0 | U26: Прочее | V26: 0 | W26: =IF(V26<=-4.1,"Война на уничтожение",IF(V26<=-3.1,"Война",IF(V26<=-2.1,"Вооружённый конфликт",IF(V26<=-1.1,"Конфронтация",IF(V26<0,"Напряжённые отношения",IF(V26=0,"Нейтралитет",IF(V26<=1,"Сотрудничество",IF(V26<=2,"Партнёрство",IF(V26<=3,"Стратегическое партнёрство",IF(V26<=4,"Стратегический союз","Интеграция")))))))))) -> Нейтралитет | X26: Агрегированная строка для остальных государств; базовое состояние — нейтралитет.
A27: Контекстные информационные ресурсы | B27: 7 | C27: 0.25 | D27: 0 | E27: 0 | F27: 0 | G27: 0 | H27: 0 | I27: =MAX(1,MIN(10,B27+D27+E27+H27+J27)) -> 7 | J27: =SUMIFS('Эффекты технологий'!$J$25:$J$240,'Эффекты технологий'!$C$25:$C$240,$A27,'Эффекты технологий'!$D$25:$D$240,"Значение") -> 0
A28: Модельные ресурсы | B28: 7 | C28: 0.4 | D28: 0 | E28: 0 | F28: 0 | G28: 0 | H28: 0 | I28: =MAX(1,MIN(10,B28+D28+E28+H28+J28)) -> 7 | J28: =SUMIFS('Эффекты технологий'!$J$25:$J$240,'Эффекты технологий'!$C$25:$C$240,$A28,'Эффекты технологий'!$D$25:$D$240,"Значение") -> 0
A29: Ресурсы оценки | B29: 6 | C29: 0.3 | D29: 0 | E29: 0 | F29: 0 | G29: 0 | H29: 0 | I29: =MAX(1,MIN(10,B29+D29+E29+H29+J29)) -> 6 | J29: =SUMIFS('Эффекты технологий'!$J$25:$J$240,'Эффекты технологий'!$C$25:$C$240,$A29,'Эффекты технологий'!$D$25:$D$240,"Значение") -> 0
A30: Документационные ресурсы | B30: 6 | C30: 0.2 | D30: 0 | E30: 0 | F30: 0 | G30: 0 | H30: 0 | I30: =MAX(1,MIN(10,B30+D30+E30+H30+J30)) -> 6 | J30: =SUMIFS('Эффекты технологий'!$J$25:$J$240,'Эффекты технологий'!$C$25:$C$240,$A30,'Эффекты технологий'!$D$25:$D$240,"Значение") -> 0
A31: Права доступа к информационным ресурсам | B31: 5 | C31: 0.1 | D31: 0 | E31: 0 | F31: 0 | G31: 0 | H31: 0 | I31: =MAX(1,MIN(10,B31+D31+E31+H31+J31)) -> 5 | J31: =SUMIFS('Эффекты технологий'!$J$25:$J$240,'Эффекты технологий'!$C$25:$C$240,$A31,'Эффекты технологий'!$D$25:$D$240,"Значение") -> 0
A32: Кибербезопасностные ресурсы | B32: 9 | C32: 0.1 | D32: 0 | E32: 0 | F32: 0 | G32: 0 | H32: 0 | I32: =MAX(1,MIN(10,B32+D32+E32+H32+J32)) -> 9 | J32: =SUMIFS('Эффекты технологий'!$J$25:$J$240,'Эффекты технологий'!$C$25:$C$240,$A32,'Эффекты технологий'!$D$25:$D$240,"Значение") -> 0
A33: IV. Люди, организация и экономика внедрения
A34: Квалифицированный человеческий ресурс | B34: 8 | C34: 0.15 | D34: 0 | E34: 0 | F34: 0 | G34: 0 | H34: 0 | I34: =MAX(1,MIN(10,B34+D34+E34+H34+J34)) -> 8 | J34: =SUMIFS('Эффекты технологий'!$J$25:$J$240,'Эффекты технологий'!$C$25:$C$240,$A34,'Эффекты технологий'!$D$25:$D$240,"Значение") -> 0
A35: Предметная экспертиза | B35: 9 | C35: 0.05 | D35: 0 | E35: 0 | F35: 0 | G35: 0 | H35: 0 | I35: =MAX(1,MIN(10,B35+D35+E35+H35+J35)) -> 9 | J35: =SUMIFS('Эффекты технологий'!$J$25:$J$240,'Эффекты технологий'!$C$25:$C$240,$A35,'Эффекты технологий'!$D$25:$D$240,"Значение") -> 0
A36: Оцифрованность деятельности | B36: 8 | C36: 0.25 | D36: 0 | E36: 0 | F36: 0 | G36: 0 | H36: 0 | I36: =MAX(1,MIN(10,B36+D36+E36+H36+J36)) -> 8 | J36: =SUMIFS('Эффекты технологий'!$J$25:$J$240,'Эффекты технологий'!$C$25:$C$240,$A36,'Эффекты технологий'!$D$25:$D$240,"Значение") -> 0
A37: Интеграционные ресурсы | B37: 6 | C37: 0.3 | D37: 0 | E37: 0 | F37: 0 | G37: 0 | H37: 0 | I37: =MAX(1,MIN(10,B37+D37+E37+H37+J37)) -> 6 | J37: =SUMIFS('Эффекты технологий'!$J$25:$J$240,'Эффекты технологий'!$C$25:$C$240,$A37,'Эффекты технологий'!$D$25:$D$240,"Значение") -> 0
A38: Организационная архитектура внедрения | B38: 6 | C38: 0.25 | D38: 0 | E38: 0 | F38: 0 | G38: 0 | H38: 0 | I38: =MAX(1,MIN(10,B38+D38+E38+H38+J38)) -> 6 | J38: =SUMIFS('Эффекты технологий'!$J$25:$J$240,'Эффекты технологий'!$C$25:$C$240,$A38,'Эффекты технологий'!$D$25:$D$240,"Значение") -> 0
A39: Организационная способность к изменению | B39: 6 | C39: 0.2 | D39: 0 | E39: 0 | F39: 0 | G39: 0 | H39: 0 | I39: =MAX(1,MIN(10,B39+D39+E39+H39+J39)) -> 6 | J39: =SUMIFS('Эффекты технологий'!$J$25:$J$240,'Эффекты технологий'!$C$25:$C$240,$A39,'Эффекты технологий'!$D$25:$D$240,"Значение") -> 0
A40: Финансовые ресурсы | B40: 7 | C40: 0.1 | D40: 0 | E40: 0 | F40: 0 | G40: 0 | H40: 0 | I40: =MAX(1,MIN(10,B40+D40+E40+H40+J40)) -> 7 | J40: =SUMIFS('Эффекты технологий'!$J$25:$J$240,'Эффекты технологий'!$C$25:$C$240,$A40,'Эффекты технологий'!$D$25:$D$240,"Значение") -> 0
A41: Поставщики и рынок технологических услуг | B41: 7 | C41: 0.25 | D41: 0 | E41: 0 | F41: 0 | G41: 0 | H41: 0 | I41: =MAX(1,MIN(10,B41+D41+E41+H41+J41)) -> 7 | J41: =SUMIFS('Эффекты технологий'!$J$25:$J$240,'Эффекты технологий'!$C$25:$C$240,$A41,'Эффекты технологий'!$D$25:$D$240,"Значение") -> 0
A42: Экономическая целесообразность | B42: 8 | C42: 0.2 | D42: 0 | E42: 0 | F42: 0 | G42: 0 | H42: 0 | I42: =MAX(1,MIN(10,B42+D42+E42+H42+J42)) -> 8 | J42: =SUMIFS('Эффекты технологий'!$J$25:$J$240,'Эффекты технологий'!$C$25:$C$240,$A42,'Эффекты технологий'!$D$25:$D$240,"Значение") -> 0
A43: V. Правовая, институциональная и социальная среда
A44: Правовая среда | B44: 6 | C44: 0.2 | D44: 0 | E44: 0 | F44: 0 | G44: 0 | H44: 0 | I44: =MAX(1,MIN(10,B44+D44+E44+H44+J44)) -> 6 | J44: =SUMIFS('Эффекты технологий'!$J$25:$J$240,'Эффекты технологий'!$C$25:$C$240,$A44,'Эффекты технологий'!$D$25:$D$240,"Значение") -> 0
A45: Регуляторная и стандартная среда | B45: 6 | C45: 0.3 | D45: 0 | E45: 0 | F45: 0 | G45: 0 | H45: 0 | I45: =MAX(1,MIN(10,B45+D45+E45+H45+J45)) -> 6 | J45: =SUMIFS('Эффекты технологий'!$J$25:$J$240,'Эффекты технологий'!$C$25:$C$240,$A45,'Эффекты технологий'!$D$25:$D$240,"Значение") -> 0
A46: Институциональная инфраструктура | B46: 5 | C46: 0.1 | D46: 0 | E46: 0 | F46: 0 | G46: 0 | H46: 0 | I46: =MAX(1,MIN(10,B46+D46+E46+H46+J46)) -> 5 | J46: =SUMIFS('Эффекты технологий'!$J$25:$J$240,'Эффекты технологий'!$C$25:$C$240,$A46,'Эффекты технологий'!$D$25:$D$240,"Значение") -> 0
A47: Конкурентная и торговая среда | B47: 3 | C47: -0.1 | D47: 0 | E47: 0 | F47: 0 | G47: 0 | H47: 0 | I47: =MAX(1,MIN(10,B47+D47+E47+H47+J47)) -> 3 | J47: =SUMIFS('Эффекты технологий'!$J$25:$J$240,'Эффекты технологий'!$C$25:$C$240,$A47,'Эффекты технологий'!$D$25:$D$240,"Значение") -> 0
A48: Социальное доверие | B48: 6 | C48: 0.15 | D48: 0 | E48: 0 | F48: 0 | G48: 0 | H48: 0 | I48: =MAX(1,MIN(10,B48+D48+E48+H48+J48)) -> 6 | J48: =SUMIFS('Эффекты технологий'!$J$25:$J$240,'Эффекты технологий'!$C$25:$C$240,$A48,'Эффекты технологий'!$D$25:$D$240,"Значение") -> 0
A49: Готовность работников к использованию ИИ | B49: 7 | C49: 0.3 | D49: 0 | E49: 0 | F49: 0 | G49: 0 | H49: 0 | I49: =MAX(1,MIN(10,B49+D49+E49+H49+J49)) -> 7 | J49: =SUMIFS('Эффекты технологий'!$J$25:$J$240,'Эффекты технологий'!$C$25:$C$240,$A49,'Эффекты технологий'!$D$25:$D$240,"Значение") -> 0
A50: Локальная социально-культурная применимость | B50: 9 | C50: 0.1 | D50: 0 | E50: 0 | F50: 0 | G50: 0 | H50: 0 | I50: =MAX(1,MIN(10,B50+D50+E50+H50+J50)) -> 9 | J50: =SUMIFS('Эффекты технологий'!$J$25:$J$240,'Эффекты технологий'!$C$25:$C$240,$A50,'Эффекты технологий'!$D$25:$D$240,"Значение") -> 0
A51: Система управления ИИ | B51: 6 | C51: 0.3 | D51: 0 | E51: 0 | F51: 0 | G51: 0 | H51: 0 | I51: =MAX(1,MIN(10,B51+D51+E51+H51+J51)) -> 6 | J51: =SUMIFS('Эффекты технологий'!$J$25:$J$240,'Эффекты технологий'!$C$25:$C$240,$A51,'Эффекты технологий'!$D$25:$D$240,"Значение") -> 0
A52: VI. Устойчивость жизненного цикла
A53: Поствнедренческий мониторинг | B53: 6 | C53: 0.3 | D53: 0 | E53: 0 | F53: 0 | G53: 0 | H53: 0 | I53: =MAX(1,MIN(10,B53+D53+E53+H53+J53)) -> 6 | J53: =SUMIFS('Эффекты технологий'!$J$25:$J$240,'Эффекты технологий'!$C$25:$C$240,$A53,'Эффекты технологий'!$D$25:$D$240,"Значение") -> 0
A54: Ресурс обновления и восстановления | B54: 6 | C54: 0.15 | D54: 0 | E54: 0 | F54: 0 | G54: 0 | H54: 0 | I54: =MAX(1,MIN(10,B54+D54+E54+H54+J54)) -> 6 | J54: =SUMIFS('Эффекты технологий'!$J$25:$J$240,'Эффекты технологий'!$C$25:$C$240,$A54,'Эффекты технологий'!$D$25:$D$240,"Значение") -> 0
A55: Ресурс утилизации и воспроизводства физической базы | B55: 5 | C55: 0.15 | D55: 0 | E55: 0 | F55: 0 | G55: 0 | H55: 0 | I55: =MAX(1,MIN(10,B55+D55+E55+H55+J55)) -> 5 | J55: =SUMIFS('Эффекты технологий'!$J$25:$J$240,'Эффекты технологий'!$C$25:$C$240,$A55,'Эффекты технологий'!$D$25:$D$240,"Значение") -> 0

Sheet Ход 2026
A1: ХОД 2026 — РАСПРЕДЕЛЕНИЕ ОЧКОВ
A3: Жёлтые ячейки — ввод игрока.
A5: ОЧКИ ТРАНСФОРМАЦИИ | E5: ОЧКИ ИИ | I5: ОЧКИ НАУКИ | M5: ВНЕШНЕПОЛИТИЧЕСКИЕ ОЧКИ
A6: Доступно | B6: ='Россия 2026'!U6 -> 83.126867 | E6: Доступно | F6: ='Россия 2026'!K6 -> 72.313822 | I6: Доступно | J6: ='Россия 2026'!N6 -> 73.933944 | M6: Доступно | N6: ='Россия 2026'!Q6 -> 58.945692
A7: Распределено | B7: =SUM(B14:C14)+SUM(B15:C15)+SUM(B16:C16)+SUM(B17:C17)+SUM(B18:C18)+SUM(B19:C19)+SUM(B20:C20)+SUM(B21:C21)+SUM(B22:C22)+SUM(B23:C23)+SUM(B25:C25)+SUM(B26:C26)+SUM(B27:C27)+SUM(B28:C28)+SUM(B29:C29)+SUM(B31:C31)+SUM(B32:C32)+SUM(B33:C33)+SUM(B34:C34)+SUM(B35:C35)+SUM(B36:C36)+SUM(B37:C37)+SUM(B38:C38)+SUM(B40:C40)+SUM(B41:C41)+SUM(B42:C42)+SUM(B43:C43)+SUM(B44:C44)+SUM(B45:C45)+SUM(B46:C46)+SUM(B47:C47)+SUM(B48:C48)+SUM(B50:C50)+SUM(B51:C51)+SUM(B52:C52)+SUM(B53:C53)+SUM(B54:C54)+SUM(B55:C55)+SUM(B56:C56)+SUM(B57:C57)+SUM(B59:C59)+SUM(B60:C60)+SUM(B61:C61) -> 83.1 | E7: Распределено | F7: =SUM(H13:H20) -> 72.3 | I7: Распределено | J7: =SUM(I29:I38) -> 73.9 | M7: Распределено | N7: =SUM(N13:Q28)+J24 -> 58.9
A8: Остаток | B8: =B6-B7 -> 0.026866998 | C8: =IF(B8<0,"ПРЕВЫШЕНИЕ","OK") -> OK | E8: Остаток | F8: =F6-F7 -> 0.013822485 | G8: =IF(F8<0,"ПРЕВЫШЕНИЕ","OK") -> OK | I8: Остаток | J8: =J6-J7 -> 0.033943738 | K8: =IF(J8<0,"ПРЕВЫШЕНИЕ","OK") -> OK | M8: Остаток | N8: =N6-N7 -> 0.045692232 | O8: =IF(N8<0,"ПРЕВЫШЕНИЕ","OK") -> OK
A11: 1. РАСПРЕДЕЛЕНИЕ ОЧКОВ ТРАНСФОРМАЦИИ | G11: 2. РАСПРЕДЕЛЕНИЕ ОЧКОВ ИИ | L11: 4. РАСПРЕДЕЛЕНИЕ ВНЕШНЕПОЛИТИЧЕСКИХ ОЧКОВ
A12: Ресурс | B12: В значение | C12: В прирост | G12: Сфера | H12: Очки ИИ в прирост | L12: Страна | M12: Текущий код отношений | N12: Улучшение отношений | O12: Вклад в войну Ареса | P12: Вклад в войну Афины | Q12: Вклад в войну Аполлона
A13: I. Материально-физическая и вычислительная база | G13: Производство | H13: 12 | L13: США | M13: ='Россия 2026'!V11 -> -1.5 | N13: 10 | O13: 0.9 | P13: 0 | Q13: 0
A14: Минерально-сырьевые ресурсы | B14: 0 | C14: 0 | G14: Управление | H14: 9 | L14: Китай | M14: ='Россия 2026'!V12 -> 2.9 | N14: 0 | O14: 0 | P14: 0 | Q14: 0
A15: Химические и технологические материалы | B15: 0 | C15: 0 | G15: Познание | H15: 6 | L15: Индия | M15: ='Россия 2026'!V13 -> 2.8 | N15: 0 | O15: 0 | P15: 0 | Q15: 0
A16: Энергетические ресурсы | B16: 4.1 | C16: 0 | G16: Обучение | H16: 11 | L16: Великобритания | M16: ='Россия 2026'!V14 -> -1.8 | N16: 0 | O16: 0 | P16: 0 | Q16: 0
A17: Вода и ресурс отвода тепла | B17: 9 | C17: 0 | G17: Война | H17: 5 | L17: Франция | M17: ='Россия 2026'!V15 -> -1.4 | N17: 0 | O17: 0 | P17: 5 | Q17: 0
A18: Пространственные и природно-географические ресурсы | B18: 5 | C18: 0 | G18: Экономика | H18: 15 | L18: Германия | M18: ='Россия 2026'!V16 -> -1.7 | N18: 0 | O18: 0 | P18: 5 | Q18: 0
A19: Мощности производства полупроводников | B19: 0 | C19: 5 | G19: Государственное управление | H19: 12.3 | L19: Япония | M19: ='Россия 2026'!V17 -> -1.3 | N19: 0 | O19: 0 | P19: 0 | Q19: 10
A20: Вычислительные компоненты | B20: 0 | C20: 5 | G20: Принятие ИИ | H20: 2 | L20: Южная Корея | M20: ='Россия 2026'!V18 -> -1.2 | N20: 0 | O20: 0 | P20: 0 | Q20: 0
A21: ЦОД и вычислительная инфраструктура | B21: 0 | C21: 5 | L21: Турция | M21: ='Россия 2026'!V19 -> 1.3 | N21: 0 | O21: 0 | P21: 0 | Q21: 0
A22: Сетевые ресурсы | B22: 0 | C22: 5 | G22: ОБОРОНА — ВНЕШНЕПОЛИТИЧЕСКИЕ ОЧКИ | L22: Саудовская Аравия | M22: ='Россия 2026'!V20 -> 1.2 | N22: 0 | O22: 0 | P22: 0 | Q22: 0
A23: Конечные устройства | B23: 0 | C23: 5 | G23: Защита от войны Ареса | H23: Защита от войны Афины | I23: Защита от войны Аполлона | J23: Всего в оборону | L23: Иран | M23: ='Россия 2026'!V21 -> 2.7 | N23: 0 | O23: 0 | P23: 0 | Q23: 0
A24: II. Программно-алгоритмический потенциал | G24: 10 | H24: 10 | I24: 8 | J24: =SUM(G24:I24) -> 28 | L24: Израиль | M24: ='Россия 2026'!V22 -> -0.2 | N24: 0 | O24: 0 | P24: 0 | Q24: 0
A25: Базовый программный стек вычислений | B25: 0 | C25: 15 | F25: Эффект науки | G25: ='Эффекты технологий'!J$16 -> 0 | H25: ='Эффекты технологий'!J$17 -> 0 | I25: ='Эффекты технологий'!J$18 -> 0 | L25: Бразилия | M25: ='Россия 2026'!V23 -> 1.7 | N25: 0 | O25: 0 | P25: 0 | Q25: 0
A26: Стек разработки ИИ | B26: 5 | C26: 2 | F26: Защита с бонусом | G26: =G24*(1+G25) -> 10 | H26: =H24*(1+H25) -> 10 | I26: =I24*(1+I25) -> 8 | J26: =SUM(G26:I26) -> 28 | L26: ОАЭ | M26: ='Россия 2026'!V24 -> 1.8 | N26: 0 | O26: 0 | P26: 0 | Q26: 0
A27: Стек эксплуатации ИИ | B27: 0 | C27: 0 | G27: 3. РАСПРЕДЕЛЕНИЕ ОЧКОВ НАУКИ | L27: Индонезия | M27: ='Россия 2026'!V25 -> 1.8 | N27: 0 | O27: 0 | P27: 0 | Q27: 0
A28: Математико-алгоритмические ресурсы | B28: 0 | C28: 0 | G28: ID технологии | H28: Технология | I28: Очки науки | J28: Примечание | K28: Статус после хода | L28: Прочее | M28: ='Россия 2026'!V26 -> 0 | N28: 0 | O28: 0 | P28: 0 | Q28: 0
A29: Методы построения и совершенствования моделей | B29: 0 | C29: 0 | G29: C1 | H29: =IF(G29="","",VLOOKUP(G29,'Технологии'!$A$11:$D$50,4,FALSE)) -> GPU-узлы с тензорными ядрами | I29: 20 | K29: =IF(G29="","",VLOOKUP(G29,'Технологии'!$A$11:$BF$50,44,FALSE)) -> ИЗУЧЕНО | N29: Итого вложено | O29: =SUM(O13:O28) -> 0.9 | P29: =SUM(P13:P28) -> 10 | Q29: =SUM(Q13:Q28) -> 10
A30: III. Данные, модели и информационная безопасность | G30: A1 | H30: =IF(G30="","",VLOOKUP(G30,'Технологии'!$A$11:$D$50,4,FALSE)) -> Программные ИИ-агенты с вызовом внешних инструментов через API | I30: 20 | K30: =IF(G30="","",VLOOKUP(G30,'Технологии'!$A$11:$BF$50,44,FALSE)) -> ИЗУЧЕНО | N30: Эффект науки | O30: ='Эффекты технологий'!J$13 -> 0 | P30: ='Эффекты технологий'!J$14 -> 0 | Q30: ='Эффекты технологий'!J$15 -> 0
A31: Исходные данные | B31: 0 | C31: 8 | G31: R1 | H31: =IF(G31="","",VLOOKUP(G31,'Технологии'!$A$11:$D$50,4,FALSE)) -> Машинное зрение для промышленного контроля качества | I31: 20 | K31: =IF(G31="","",VLOOKUP(G31,'Технологии'!$A$11:$BF$50,44,FALSE)) -> ИЗУЧЕНО | N31: Атака с бонусом | O31: =O29*(1+O30) -> 0.9 | P31: =P29*(1+P30) -> 10 | Q31: =Q29*(1+Q30) -> 10
A32: Производные данные | B32: 0 | C32: 0 | G32: S1 | H32: =IF(G32="","",VLOOKUP(G32,'Технологии'!$A$11:$D$50,4,FALSE)) -> Автоматизированные наборы тестов и бенчмарков качества ИИ | I32: 13.9 | K32: =IF(G32="","",VLOOKUP(G32,'Технологии'!$A$11:$BF$50,44,FALSE)) -> ОТКРЫТО
A33: Контекстные информационные ресурсы | B33: 0 | C33: 0 | H33: =IF(G33="","",VLOOKUP(G33,'Технологии'!$A$11:$D$50,4,FALSE)) | I33: 0 | K33: =IF(G33="","",VLOOKUP(G33,'Технологии'!$A$11:$BF$50,44,FALSE))
A34: Модельные ресурсы | B34: 0 | C34: 0 | H34: =IF(G34="","",VLOOKUP(G34,'Технологии'!$A$11:$D$50,4,FALSE)) | I34: 0 | K34: =IF(G34="","",VLOOKUP(G34,'Технологии'!$A$11:$BF$50,44,FALSE))
A35: Ресурсы оценки | B35: 0 | C35: 0 | H35: =IF(G35="","",VLOOKUP(G35,'Технологии'!$A$11:$D$50,4,FALSE)) | I35: 0 | K35: =IF(G35="","",VLOOKUP(G35,'Технологии'!$A$11:$BF$50,44,FALSE))
A36: Документационные ресурсы | B36: 0 | C36: 0 | H36: =IF(G36="","",VLOOKUP(G36,'Технологии'!$A$11:$D$50,4,FALSE)) | I36: 0 | K36: =IF(G36="","",VLOOKUP(G36,'Технологии'!$A$11:$BF$50,44,FALSE))
A37: Права доступа к информационным ресурсам | B37: 0 | C37: 0 | H37: =IF(G37="","",VLOOKUP(G37,'Технологии'!$A$11:$D$50,4,FALSE)) | I37: 0 | K37: =IF(G37="","",VLOOKUP(G37,'Технологии'!$A$11:$BF$50,44,FALSE))
A38: Кибербезопасностные ресурсы | B38: 0 | C38: 0 | H38: =IF(G38="","",VLOOKUP(G38,'Технологии'!$A$11:$D$50,4,FALSE)) | I38: 0 | K38: =IF(G38="","",VLOOKUP(G38,'Технологии'!$A$11:$BF$50,44,FALSE))
A39: IV. Люди, организация и экономика внедрения
A40: Квалифицированный человеческий ресурс | B40: 3 | C40: 0
A41: Предметная экспертиза | B41: 0 | C41: 0
A42: Оцифрованность деятельности | B42: 2 | C42: 0
A43: Интеграционные ресурсы | B43: 0 | C43: 0
A44: Организационная архитектура внедрения | B44: 0 | C44: 0
A45: Организационная способность к изменению | B45: 0 | C45: 0
A46: Финансовые ресурсы | B46: 1 | C46: 0
A47: Поставщики и рынок технологических услуг | B47: 0 | C47: 0
A48: Экономическая целесообразность | B48: 0 | C48: 0
A49: V. Правовая, институциональная и социальная среда
A50: Правовая среда | B50: 0 | C50: 0
A51: Регуляторная и стандартная среда | B51: 0 | C51: 0
A52: Институциональная инфраструктура | B52: 0 | C52: 0
A53: Конкурентная и торговая среда | B53: 0 | C53: 0
A54: Социальное доверие | B54: 0 | C54: 0
A55: Готовность работников к использованию ИИ | B55: 0 | C55: 1
A56: Локальная социально-культурная применимость | B56: 2 | C56: 1
A57: Система управления ИИ | B57: 0 | C57: 0
A58: VI. Устойчивость жизненного цикла
A59: Поствнедренческий мониторинг | B59: 0 | C59: 0
A60: Ресурс обновления и восстановления | B60: 0 | C60: 0
A61: Ресурс утилизации и воспроизводства физической базы | B61: 0 | C61: 0

Sheet Россия 2027
A1: РОССИЯ — СОСТОЯНИЕ НА НАЧАЛО 2027 ГОДА
A3: Жёлтые поля заполняются вручную. Четыре колонки эффектов всегда создаются с нулём и не содержат формул.
A5: 1. РЕСУРСНАЯ БАЗА ИИ | K5: ОЧКИ ИИ | N5: ОЧКИ НАУКИ | Q5: ВНЕШНЕПОЛИТИЧЕСКИЕ ОЧКИ | U5: ОЧКИ ТРАНСФОРМАЦИИ
A6: Ресурс | B6: Начальное значение | C6: Базовый годовой прирост | D6: Постоянный эффект на значение | E6: Временный эффект на значение | F6: Постоянный эффект на прирост | G6: Временный эффект на прирост | H6: От торговли | I6: Реальное значение | J6: От науки | K6: =MIN(100,(100*POWER((POWER(POWER((POWER(I8/10,-1)+POWER(I9/10,-1)+POWER(I10/10,-1)+POWER(I11/10,-1)+POWER(I12/10,-1)+POWER(I13/10,-1)+POWER(I14/10,-1)+POWER(I15/10,-1)+POWER(I16/10,-1)+POWER(I17/10,-1))/10,1/-1),0.3)*POWER(POWER((POWER(I19/10,-0.5)+POWER(I20/10,-0.5)+POWER(I21/10,-0.5)+POWER(I22/10,-0.5)+POWER(I23/10,-0.5))/5,1/-0.5),0.2)*POWER(POWER((POWER(I25/10,-0.5)+POWER(I26/10,-0.5)+POWER(I27/10,-0.5)+POWER(I28/10,-0.5)+POWER(I29/10,-0.5)+POWER(I30/10,-0.5)+POWER(I31/10,-0.5)+POWER(I32/10,-0.5))/8,1/-0.5),0.2)*POWER(POWER((POWER(I34/10,-0.25)+POWER(I35/10,-0.25)+POWER(I36/10,-0.25)+POWER(I37/10,-0.25)+POWER(I38/10,-0.25)+POWER(I39/10,-0.25)+POWER(I40/10,-0.25)+POWER(I41/10,-0.25)+POWER(I42/10,-0.25))/9,1/-0.25),0.15)*POWER(POWER((POWER(I44/10,0.25)+POWER(I45/10,0.25)+POWER(I46/10,0.25)+POWER(I47/10,0.25)+POWER(I48/10,0.25)+POWER(I49/10,0.25)+POWER(I50/10,0.25)+POWER(I51/10,0.25))/8,1/0.25),0.1)*POWER(POWER((I53/10)*(I54/10)*(I55/10),1/3),0.05)),3)/(POWER(0.55,3)+POWER((POWER(POWER((POWER(I8/10,-1)+POWER(I9/10,-1)+POWER(I10/10,-1)+POWER(I11/10,-1)+POWER(I12/10,-1)+POWER(I13/10,-1)+POWER(I14/10,-1)+POWER(I15/10,-1)+POWER(I16/10,-1)+POWER(I17/10,-1))/10,1/-1),0.3)*POWER(POWER((POWER(I19/10,-0.5)+POWER(I20/10,-0.5)+POWER(I21/10,-0.5)+POWER(I22/10,-0.5)+POWER(I23/10,-0.5))/5,1/-0.5),0.2)*POWER(POWER((POWER(I25/10,-0.5)+POWER(I26/10,-0.5)+POWER(I27/10,-0.5)+POWER(I28/10,-0.5)+POWER(I29/10,-0.5)+POWER(I30/10,-0.5)+POWER(I31/10,-0.5)+POWER(I32/10,-0.5))/8,1/-0.5),0.2)*POWER(POWER((POWER(I34/10,-0.25)+POWER(I35/10,-0.25)+POWER(I36/10,-0.25)+POWER(I37/10,-0.25)+POWER(I38/10,-0.25)+POWER(I39/10,-0.25)+POWER(I40/10,-0.25)+POWER(I41/10,-0.25)+POWER(I42/10,-0.25))/9,1/-0.25),0.15)*POWER(POWER((POWER(I44/10,0.25)+POWER(I45/10,0.25)+POWER(I46/10,0.25)+POWER(I47/10,0.25)+POWER(I48/10,0.25)+POWER(I49/10,0.25)+POWER(I50/10,0.25)+POWER(I51/10,0.25))/8,1/0.25),0.1)*POWER(POWER((I53/10)*(I54/10)*(I55/10),1/3),0.05)),3)))*(1+POWER(0.55,3))) -> 75.65183 | N6: =MIN(100,(100*POWER((POWER((POWER(S13/10,0.45)*POWER(S14/10,0.25)*POWER(S12/10,0.1)*POWER(S17/10,0.1)*POWER(S16/10,0.05)*POWER(S18/10,0.05)),0.8)*POWER((POWER(I34/10,0.2)*POWER(I22/10,0.15)*POWER(I25/10,0.1)*POWER(I27/10,0.1)*POWER(I15/10,0.15)*POWER(I28/10,0.1)*POWER(I40/10,0.1)*POWER(I31/10,0.1)),0.2)),2)/(POWER(0.55,2)+POWER((POWER((POWER(S13/10,0.45)*POWER(S14/10,0.25)*POWER(S12/10,0.1)*POWER(S17/10,0.1)*POWER(S16/10,0.05)*POWER(S18/10,0.05)),0.8)*POWER((POWER(I34/10,0.2)*POWER(I22/10,0.15)*POWER(I25/10,0.1)*POWER(I27/10,0.1)*POWER(I15/10,0.15)*POWER(I28/10,0.1)*POWER(I40/10,0.1)*POWER(I31/10,0.1)),0.2)),2)))*(1+POWER(0.55,2))) -> 77.397667 | Q6: =100*POWER(((AVERAGE(V11:V25)+5)/10),0.3)*POWER((POWER(I16/10,0.15)*POWER(I32/10,0.15)*POWER(I40/10,0.2)*POWER(I41/10,0.15)*POWER(I46/10,0.15)*POWER(I47/10,0.2)),0.3)*POWER((POWER(S12/10,0.2)*POWER(S15/10,0.2)*POWER(S16/10,0.3)*POWER(S17/10,0.3)),0.4) -> 60.552332 | U6: =100*LN(1+20*(POWER((POWER(S11/10,0.2)*POWER(S12/10,0.15)*POWER(S13/10,0.1)*POWER(S14/10,0.1)*POWER(S15/10,0.05)*POWER(S16/10,0.15)*POWER(S17/10,0.15)*POWER(S18/10,0.1)),0.65)*POWER((POWER(I8/10,0.06)*POWER(I9/10,0.1)*POWER(I10/10,0.12)*POWER(I11/10,0.05)*POWER(I12/10,0.04)*POWER(I13/10,0.17)*POWER(I14/10,0.15)*POWER(I15/10,0.15)*POWER(I16/10,0.1)*POWER(I17/10,0.06)),0.35)))/LN(21) -> 84.888879
A7: I. Материально-физическая и вычислительная база
A8: Минерально-сырьевые ресурсы | B8: =MAX(1,MIN(10,'Россия 2026'!B8+'Россия 2026'!D8+('Россия 2026'!C8+'Россия 2026'!F8+'Россия 2026'!G8)+(0.35*LN(1+0.6*('Ход 2026'!B14*(1+'Эффекты технологий'!J$12)))*POWER(MAX(0,1-'Россия 2026'!I8/10),0.7)))) -> 9.05 | C8: =MIN(1,(MIN(1,'Россия 2026'!C8+'Россия 2026'!F8+(0.08*LN(1+0.5*('Ход 2026'!C14*(1+'Эффекты технологий'!J$12)))*MAX(0,1-('Россия 2026'!C8+'Россия 2026'!F8)))))+(SUMIFS('Эффекты технологий'!$K$25:$K$240,'Эффекты технологий'!$C$25:$C$240,$A8,'Эффекты технологий'!$D$25:$D$240,"Прирост")-SUMIFS('Эффекты технологий'!$J$25:$J$240,'Эффекты технологий'!$C$25:$C$240,$A8,'Эффекты технологий'!$D$25:$D$240,"Прирост"))) -> 0.05 | D8: 0 | E8: 0 | F8: 0 | G8: 0 | H8: 0 | I8: =MAX(1,MIN(10,B8+D8+E8+H8+J8)) -> 9.05 | J8: =SUMIFS('Эффекты технологий'!$K$25:$K$240,'Эффекты технологий'!$C$25:$C$240,$A8,'Эффекты технологий'!$D$25:$D$240,"Значение") -> 0
A9: Химические и технологические материалы | B9: =MAX(1,MIN(10,'Россия 2026'!B9+'Россия 2026'!D9+('Россия 2026'!C9+'Россия 2026'!F9+'Россия 2026'!G9)+(0.35*LN(1+0.6*('Ход 2026'!B15*(1+'Эффекты технологий'!J$12)))*POWER(MAX(0,1-'Россия 2026'!I9/10),0.7)))) -> 5.2 | C9: =MIN(1,(MIN(1,'Россия 2026'!C9+'Россия 2026'!F9+(0.08*LN(1+0.5*('Ход 2026'!C15*(1+'Эффекты технологий'!J$12)))*MAX(0,1-('Россия 2026'!C9+'Россия 2026'!F9)))))+(SUMIFS('Эффекты технологий'!$K$25:$K$240,'Эффекты технологий'!$C$25:$C$240,$A9,'Эффекты технологий'!$D$25:$D$240,"Прирост")-SUMIFS('Эффекты технологий'!$J$25:$J$240,'Эффекты технологий'!$C$25:$C$240,$A9,'Эффекты технологий'!$D$25:$D$240,"Прирост"))) -> 0.2 | D9: 0 | E9: 0 | F9: 0 | G9: 0 | H9: 0 | I9: =MAX(1,MIN(10,B9+D9+E9+H9+J9)) -> 5.2 | J9: =SUMIFS('Эффекты технологий'!$K$25:$K$240,'Эффекты технологий'!$C$25:$C$240,$A9,'Эффекты технологий'!$D$25:$D$240,"Значение") -> 0 | K9: 2. СФЕРЫ ВНЕДРЕНИЯ ИИ | U9: 3. МЕЖДУНАРОДНЫЕ ОТНОШЕНИЯ
A10: Энергетические ресурсы | B10: =MAX(1,MIN(10,'Россия 2026'!B10+'Россия 2026'!D10+('Россия 2026'!C10+'Россия 2026'!F10+'Россия 2026'!G10)+(0.35*LN(1+0.6*('Ход 2026'!B16*(1+'Эффекты технологий'!J$12)))*POWER(MAX(0,1-'Россия 2026'!I10/10),0.7)))) -> 9.186683 | C10: =MIN(1,(MIN(1,'Россия 2026'!C10+'Россия 2026'!F10+(0.08*LN(1+0.5*('Ход 2026'!C16*(1+'Эффекты технологий'!J$12)))*MAX(0,1-('Россия 2026'!C10+'Россия 2026'!F10)))))+(SUMIFS('Эффекты технологий'!$K$25:$K$240,'Эффекты технологий'!$C$25:$C$240,$A10,'Эффекты технологий'!$D$25:$D$240,"Прирост")-SUMIFS('Эффекты технологий'!$J$25:$J$240,'Эффекты технологий'!$C$25:$C$240,$A10,'Эффекты технологий'!$D$25:$D$240,"Прирост"))) -> 0.1 | D10: 0 | E10: 0 | F10: 0 | G10: 0 | H10: 0 | I10: =MAX(1,MIN(10,B10+D10+E10+H10+J10)) -> 9.186683 | J10: =SUMIFS('Эффекты технологий'!$K$25:$K$240,'Эффекты технологий'!$C$25:$C$240,$A10,'Эффекты технологий'!$D$25:$D$240,"Значение") -> 0 | K10: Сфера | L10: Начальное значение | M10: Базовый годовой прирост | N10: Постоянный эффект на значение | O10: Временный эффект на значение | P10: Постоянный эффект на прирост | Q10: Временный эффект на прирост | R10: От торговли | S10: Реальное значение | T10: От науки | U10: Страна | V10: Код −5…+5 | W10: Статус
A11: Вода и ресурс отвода тепла | B11: =MAX(1,MIN(10,'Россия 2026'!B11+'Россия 2026'!D11+('Россия 2026'!C11+'Россия 2026'!F11+'Россия 2026'!G11)+(0.35*LN(1+0.6*('Ход 2026'!B17*(1+'Эффекты технологий'!J$12)))*POWER(MAX(0,1-'Россия 2026'!I11/10),0.7)))) -> 9.1296331 | C11: =MIN(1,(MIN(1,'Россия 2026'!C11+'Россия 2026'!F11+(0.08*LN(1+0.5*('Ход 2026'!C17*(1+'Эффекты технологий'!J$12)))*MAX(0,1-('Россия 2026'!C11+'Россия 2026'!F11)))))+(SUMIFS('Эффекты технологий'!$K$25:$K$240,'Эффекты технологий'!$C$25:$C$240,$A11,'Эффекты технологий'!$D$25:$D$240,"Прирост")-SUMIFS('Эффекты технологий'!$J$25:$J$240,'Эффекты технологий'!$C$25:$C$240,$A11,'Эффекты технологий'!$D$25:$D$240,"Прирост"))) -> 0 | D11: 0 | E11: 0 | F11: 0 | G11: 0 | H11: 0 | I11: =MAX(1,MIN(10,B11+D11+E11+H11+J11)) -> 9.1296331 | J11: =SUMIFS('Эффекты технологий'!$K$25:$K$240,'Эффекты технологий'!$C$25:$C$240,$A11,'Эффекты технологий'!$D$25:$D$240,"Значение") -> 0 | K11: Производство | L11: =MAX(1,MIN(10,'Россия 2026'!L11+'Россия 2026'!N11+('Россия 2026'!M11+'Россия 2026'!P11+'Россия 2026'!Q11))) -> 5.85 | M11: =MIN(1,(MIN(1,'Россия 2026'!M11+'Россия 2026'!P11+(0.1*LN(1+0.5*('Ход 2026'!H13*(1+'Эффекты технологий'!J$10)))*POWER(MAX(0,1-'Россия 2026'!S11/10),0.8))))+(SUMIFS('Эффекты технологий'!$K$25:$K$240,'Эффекты технологий'!$C$25:$C$240,$K11,'Эффекты технологий'!$D$25:$D$240,"Прирост")-SUMIFS('Эффекты технологий'!$J$25:$J$240,'Эффекты технологий'!$C$25:$C$240,$K11,'Эффекты технологий'!$D$25:$D$240,"Прирост"))) -> 0.45272894 | N11: 0 | O11: 0 | P11: 0 | Q11: 0 | R11: 0 | S11: =MAX(1,MIN(10,L11+N11+O11+R11+T11)) -> 5.85 | T11: =SUMIFS('Эффекты технологий'!$K$25:$K$240,'Эффекты технологий'!$C$25:$C$240,$K11,'Эффекты технологий'!$D$25:$D$240,"Значение") -> 0 | U11: США | V11: ='Россия 2026'!V11 -> -1.5 | W11: =IF(V11<=-4.1,"Война на уничтожение",IF(V11<=-3.1,"Война",IF(V11<=-2.1,"Вооружённый конфликт",IF(V11<=-1.1,"Конфронтация",IF(V11<0,"Напряжённые отношения",IF(V11=0,"Нейтралитет",IF(V11<=1,"Сотрудничество",IF(V11<=2,"Партнёрство",IF(V11<=3,"Стратегическое партнёрство",IF(V11<=4,"Стратегический союз","Интеграция")))))))))) -> Конфронтация
A12: Пространственные и природно-географические ресурсы | B12: =MAX(1,MIN(10,'Россия 2026'!B12+'Россия 2026'!D12+('Россия 2026'!C12+'Россия 2026'!F12+'Россия 2026'!G12)+(0.35*LN(1+0.6*('Ход 2026'!B18*(1+'Эффекты технологий'!J$12)))*POWER(MAX(0,1-'Россия 2026'!I12/10),0.7)))) -> 9.0968107 | C12: =MIN(1,(MIN(1,'Россия 2026'!C12+'Россия 2026'!F12+(0.08*LN(1+0.5*('Ход 2026'!C18*(1+'Эффекты технологий'!J$12)))*MAX(0,1-('Россия 2026'!C12+'Россия 2026'!F12)))))+(SUMIFS('Эффекты технологий'!$K$25:$K$240,'Эффекты технологий'!$C$25:$C$240,$A12,'Эффекты технологий'!$D$25:$D$240,"Прирост")-SUMIFS('Эффекты технологий'!$J$25:$J$240,'Эффекты технологий'!$C$25:$C$240,$A12,'Эффекты технологий'!$D$25:$D$240,"Прирост"))) -> 0 | D12: 0 | E12: 0 | F12: 0 | G12: 0 | H12: 0 | I12: =MAX(1,MIN(10,B12+D12+E12+H12+J12)) -> 9.0968107 | J12: =SUMIFS('Эффекты технологий'!$K$25:$K$240,'Эффекты технологий'!$C$25:$C$240,$A12,'Эффекты технологий'!$D$25:$D$240,"Значение") -> 0 | K12: Управление | L12: =MAX(1,MIN(10,'Россия 2026'!L12+'Россия 2026'!N12+('Россия 2026'!M12+'Россия 2026'!P12+'Россия 2026'!Q12))) -> 5.85 | M12: =MIN(1,(MIN(1,'Россия 2026'!M12+'Россия 2026'!P12+(0.1*LN(1+0.5*('Ход 2026'!H14*(1+'Эффекты технологий'!J$10)))*POWER(MAX(0,1-'Россия 2026'!S12/10),0.8))))+(SUMIFS('Эффекты технологий'!$K$25:$K$240,'Эффекты технологий'!$C$25:$C$240,$K12,'Эффекты технологий'!$D$25:$D$240,"Прирост")-SUMIFS('Эффекты технологий'!$J$25:$J$240,'Эффекты технологий'!$C$25:$C$240,$K12,'Эффекты технологий'!$D$25:$D$240,"Прирост"))) -> 0.48999745 | N12: 0 | O12: 0 | P12: 0 | Q12: 0 | R12: 0 | S12: =MAX(1,MIN(10,L12+N12+O12+R12+T12)) -> 5.85 | T12: =SUMIFS('Эффекты технологий'!$K$25:$K$240,'Эффекты технологий'!$C$25:$C$240,$K12,'Эффекты технологий'!$D$25:$D$240,"Значение") -> 0 | U12: Китай | V12: ='Россия 2026'!V12 -> 2.9 | W12: =IF(V12<=-4.1,"Война на уничтожение",IF(V12<=-3.1,"Война",IF(V12<=-2.1,"Вооружённый конфликт",IF(V12<=-1.1,"Конфронтация",IF(V12<0,"Напряжённые отношения",IF(V12=0,"Нейтралитет",IF(V12<=1,"Сотрудничество",IF(V12<=2,"Партнёрство",IF(V12<=3,"Стратегическое партнёрство",IF(V12<=4,"Стратегический союз","Интеграция")))))))))) -> Стратегическое партнёрство
A13: Мощности производства полупроводников | B13: =MAX(1,MIN(10,'Россия 2026'!B13+'Россия 2026'!D13+('Россия 2026'!C13+'Россия 2026'!F13+'Россия 2026'!G13)+(0.35*LN(1+0.6*('Ход 2026'!B19*(1+'Эффекты технологий'!J$12)))*POWER(MAX(0,1-'Россия 2026'!I13/10),0.7)))) -> 3.25 | C13: =MIN(1,(MIN(1,'Россия 2026'!C13+'Россия 2026'!F13+(0.08*LN(1+0.5*('Ход 2026'!C19*(1+'Эффекты технологий'!J$12)))*MAX(0,1-('Россия 2026'!C13+'Россия 2026'!F13)))))+(SUMIFS('Эффекты технологий'!$K$25:$K$240,'Эффекты технологий'!$C$25:$C$240,$A13,'Эффекты технологий'!$D$25:$D$240,"Прирост")-SUMIFS('Эффекты технологий'!$J$25:$J$240,'Эффекты технологий'!$C$25:$C$240,$A13,'Эффекты технологий'!$D$25:$D$240,"Прирост"))) -> 0.32516578 | D13: 0 | E13: 0 | F13: 0 | G13: 0 | H13: 0 | I13: =MAX(1,MIN(10,B13+D13+E13+H13+J13)) -> 3.25 | J13: =SUMIFS('Эффекты технологий'!$K$25:$K$240,'Эффекты технологий'!$C$25:$C$240,$A13,'Эффекты технологий'!$D$25:$D$240,"Значение") -> 0 | K13: Познание | L13: =MAX(1,MIN(10,'Россия 2026'!L13+'Россия 2026'!N13+('Россия 2026'!M13+'Россия 2026'!P13+'Россия 2026'!Q13))) -> 6.85 | M13: =MIN(1,(MIN(1,'Россия 2026'!M13+'Россия 2026'!P13+(0.1*LN(1+0.5*('Ход 2026'!H15*(1+'Эффекты технологий'!J$10)))*POWER(MAX(0,1-'Россия 2026'!S13/10),0.8))))+(SUMIFS('Эффекты технологий'!$K$25:$K$240,'Эффекты технологий'!$C$25:$C$240,$K13,'Эффекты технологий'!$D$25:$D$240,"Прирост")-SUMIFS('Эффекты технологий'!$J$25:$J$240,'Эффекты технологий'!$C$25:$C$240,$K13,'Эффекты технологий'!$D$25:$D$240,"Прирост"))) -> 0.4098563 | N13: 0 | O13: 0 | P13: 0 | Q13: 0 | R13: 0 | S13: =MAX(1,MIN(10,L13+N13+O13+R13+T13)) -> 6.85 | T13: =SUMIFS('Эффекты технологий'!$K$25:$K$240,'Эффекты технологий'!$C$25:$C$240,$K13,'Эффекты технологий'!$D$25:$D$240,"Значение") -> 0 | U13: Индия | V13: ='Россия 2026'!V13 -> 2.8 | W13: =IF(V13<=-4.1,"Война на уничтожение",IF(V13<=-3.1,"Война",IF(V13<=-2.1,"Вооружённый конфликт",IF(V13<=-1.1,"Конфронтация",IF(V13<0,"Напряжённые отношения",IF(V13=0,"Нейтралитет",IF(V13<=1,"Сотрудничество",IF(V13<=2,"Партнёрство",IF(V13<=3,"Стратегическое партнёрство",IF(V13<=4,"Стратегический союз","Интеграция")))))))))) -> Стратегическое партнёрство
