Workbook

Sheet Технологии
A1: ДЕРЕВО ТЕХНОЛОГИЙ — 15 ХОДОВ
A3: Вложения автоматически собираются с листов Ход 2026–2040. Незавершённые исследования накапливаются; prerequisites проверяются по накопленному прогрессу. Игровые эффекты технологий в состояние страны вносятся вручную.
A5: ВСЕГО ТЕХНОЛОГИЙ | E5: ОСНОВНЫХ ВЕТВЕЙ | I5: МЕЖВЕТВЕВЫХ | M5: СТАРТОВО ОТКРЫТО
A6: 40 | E6: 6 | I6: 4 | M6: 6
A10: ID | B10: Ветвь | C10: Уровень | D10: Технология | E10: Цена науки | F10: Требование 1 | G10: Требование 2 | H10: Требование 3 | I10: Суть | J10: Игровой эффект | K10: Вложено 2026 | L10: Вложено 2027 | M10: Вложено 2028 | N10: Вложено 2029 | O10: Вложено 2030 | P10: Вложено 2031 | Q10: Вложено 2032 | R10: Вложено 2033 | S10: Вложено 2034 | T10: Вложено 2035 | U10: Вложено 2036 | V10: Вложено 2037 | W10: Вложено 2038 | X10: Вложено 2039 | Y10: Вложено 2040 | Z10: Накоплено всего | AA10: Осталось | AB10: Текущий статус | AC10: Σ 2026 | AD10: Σ 2027 | AE10: Σ 2028 | AF10: Σ 2029 | AG10: Σ 2030 | AH10: Σ 2031 | AI10: Σ 2032 | AJ10: Σ 2033 | AK10: Σ 2034 | AL10: Σ 2035 | AM10: Σ 2036 | AN10: Σ 2037 | AO10: Σ 2038 | AP10: Σ 2039 | AQ10: Σ 2040 | AR10: Статус 2026 | AS10: Статус 2027 | AT10: Статус 2028 | AU10: Статус 2029 | AV10: Статус 2030 | AW10: Статус 2031 | AX10: Статус 2032 | AY10: Статус 2033 | AZ10: Статус 2034 | BA10: Статус 2035 | BB10: Статус 2036 | BC10: Статус 2037 | BD10: Статус 2038 | BE10: Статус 2039 | BF10: Статус 2040
A11: C1 | B11: Вычисления и аппаратная база | C11: I | D11: Энергоэффективные ИИ-ускорители | E11: 20 | I11: Специализированные ускорители с лучшим отношением вычислений к энергопотреблению. | J11: Вычислительные компоненты +0,2; прирост ЦОД +0,05/год | K11: =SUMIF('Ход 2026'!$G$29:$G$38,$A11,'Ход 2026'!$I$29:$I$38) -> 0 | L11: =SUMIF('Ход 2027'!$G$29:$G$38,$A11,'Ход 2027'!$I$29:$I$38) -> 0 | M11: =SUMIF('Ход 2028'!$G$29:$G$38,$A11,'Ход 2028'!$I$29:$I$38) -> 0 | N11: =SUMIF('Ход 2029'!$G$29:$G$38,$A11,'Ход 2029'!$I$29:$I$38) -> 0 | O11: =SUMIF('Ход 2030'!$G$29:$G$38,$A11,'Ход 2030'!$I$29:$I$38) -> 0 | P11: =SUMIF('Ход 2031'!$G$29:$G$38,$A11,'Ход 2031'!$I$29:$I$38) -> 0 | Q11: =SUMIF('Ход 2032'!$G$29:$G$38,$A11,'Ход 2032'!$I$29:$I$38) -> 0 | R11: =SUMIF('Ход 2033'!$G$29:$G$38,$A11,'Ход 2033'!$I$29:$I$38) -> 0 | S11: =SUMIF('Ход 2034'!$G$29:$G$38,$A11,'Ход 2034'!$I$29:$I$38) -> 0 | T11: =SUMIF('Ход 2035'!$G$29:$G$38,$A11,'Ход 2035'!$I$29:$I$38) -> 0 | U11: =SUMIF('Ход 2036'!$G$29:$G$38,$A11,'Ход 2036'!$I$29:$I$38) -> 0 | V11: =SUMIF('Ход 2037'!$G$29:$G$38,$A11,'Ход 2037'!$I$29:$I$38) -> 0 | W11: =SUMIF('Ход 2038'!$G$29:$G$38,$A11,'Ход 2038'!$I$29:$I$38) -> 0 | X11: =SUMIF('Ход 2039'!$G$29:$G$38,$A11,'Ход 2039'!$I$29:$I$38) -> 0 | Y11: =SUMIF('Ход 2040'!$G$29:$G$38,$A11,'Ход 2040'!$I$29:$I$38) -> 0 | Z11: =SUM(K11:Y11) -> 0 | AA11: =MAX(0,E11-Z11) -> 20 | AB11: =BF11 -> ОТКРЫТО | AC11: =SUM($K11:K11) -> 0 | AD11: =SUM($K11:L11) -> 0 | AE11: =SUM($K11:M11) -> 0 | AF11: =SUM($K11:N11) -> 0 | AG11: =SUM($K11:O11) -> 0 | AH11: =SUM($K11:P11) -> 0 | AI11: =SUM($K11:Q11) -> 0 | AJ11: =SUM($K11:R11) -> 0 | ... AQ11: =SUM($K11:Y11) -> 0 | AR11: =IF(AC11>=E11,"ИЗУЧЕНО",IF(AND(OR(F11="",SUMIF($A$11:$A$50,F11,AC$11:AC$50)>=SUMIF($A$11:$A$50,F11,$E$11:$E$50)),OR(G11="",SUMIF($A$11:$A$50,G11,AC$11:AC$50)>=SUMIF($A$11:$A$50,G11,$E$11:$E$50)),OR(H11="",SUMIF($A$11:$A$50,H11,AC$11:AC$50)>=SUMIF($A$11:$A$50,H11,$E$11:$E$50))),"ОТКРЫТО","ЗАКРЫТО")) -> ОТКРЫТО | AS11: =IF(AD11>=E11,"ИЗУЧЕНО",IF(AND(OR(F11="",SUMIF($A$11:$A$50,F11,AD$11:AD$50)>=SUMIF($A$11:$A$50,F11,$E$11:$E$50)),OR(G11="",SUMIF($A$11:$A$50,G11,AD$11:AD$50)>=SUMIF($A$11:$A$50,G11,$E$11:$E$50)),OR(H11="",SUMIF($A$11:$A$50,H11,AD$11:AD$50)>=SUMIF($A$11:$A$50,H11,$E$11:$E$50))),"ОТКРЫТО","ЗАКРЫТО")) -> ОТКРЫТО | AT11: =IF(AE11>=E11,"ИЗУЧЕНО",IF(AND(OR(F11="",SUMIF($A$11:$A$50,F11,AE$11:AE$50)>=SUMIF($A$11:$A$50,F11,$E$11:$E$50)),OR(G11="",SUMIF($A$11:$A$50,G11,AE$11:AE$50)>=SUMIF($A$11:$A$50,G11,$E$11:$E$50)),OR(H11="",SUMIF($A$11:$A$50,H11,AE$11:AE$50)>=SUMIF($A$11:$A$50,H11,$E$11:$E$50))),"ОТКРЫТО","ЗАКРЫТО")) -> ОТКРЫТО | AU11: =IF(AF11>=E11,"ИЗУЧЕНО",IF(AND(OR(F11="",SUMIF($A$11:$A$50,F11,AF$11:AF$50)>=SUMIF($A$11:$A$50,F11,$E$11:$E$50)),OR(G11="",SUMIF($A$11:$A$50,G11,AF$11:AF$50)>=SUMIF($A$11:$A$50,G11,$E$11:$E$50)),OR(H11="",SUMIF($A$11:$A$50,H11,AF$11:AF$50)>=SUMIF($A$11:$A$50,H11,$E$11:$E$50))),"ОТКРЫТО","ЗАКРЫТО")) -> ОТКРЫТО | AV11: =IF(AG11>=E11,"ИЗУЧЕНО",IF(AND(OR(F11="",SUMIF($A$11:$A$50,F11,AG$11:AG$50)>=SUMIF($A$11:$A$50,F11,$E$11:$E$50)),OR(G11="",SUMIF($A$11:$A$50,G11,AG$11:AG$50)>=SUMIF($A$11:$A$50,G11,$E$11:$E$50)),OR(H11="",SUMIF($A$11:$A$50,H11,AG$11:AG$50)>=SUMIF($A$11:$A$50,H11,$E$11:$E$50))),"ОТКРЫТО","ЗАКРЫТО")) -> ОТКРЫТО | AW11: =IF(AH11>=E11,"ИЗУЧЕНО",IF(AND(OR(F11="",SUMIF($A$11:$A$50,F11,AH$11:AH$50)>=SUMIF($A$11:$A$50,F11,$E$11:$E$50)),OR(G11="",SUMIF($A$11:$A$50,G11,AH$11:AH$50)>=SUMIF($A$11:$A$50,G11,$E$11:$E$50)),OR(H11="",SUMIF($A$11:$A$50,H11,AH$11:AH$50)>=SUMIF($A$11:$A$50,H11,$E$11:$E$50))),"ОТКРЫТО","ЗАКРЫТО")) -> ОТКРЫТО | AX11: =IF(AI11>=E11,"ИЗУЧЕНО",IF(AND(OR(F11="",SUMIF($A$11:$A$50,F11,AI$11:AI$50)>=SUMIF($A$11:$A$50,F11,$E$11:$E$50)),OR(G11="",SUMIF($A$11:$A$50,G11,AI$11:AI$50)>=SUMIF($A$11:$A$50,G11,$E$11:$E$50)),OR(H11="",SUMIF($A$11:$A$50,H11,AI$11:AI$50)>=SUMIF($A$11:$A$50,H11,$E$11:$E$50))),"ОТКРЫТО","ЗАКРЫТО")) -> ОТКРЫТО | AY11: =IF(AJ11>=E11,"ИЗУЧЕНО",IF(AND(OR(F11="",SUMIF($A$11:$A$50,F11,AJ$11:AJ$50)>=SUMIF($A$11:$A$50,F11,$E$11:$E$50)),OR(G11="",SUMIF($A$11:$A$50,G11,AJ$11:AJ$50)>=SUMIF($A$11:$A$50,G11,$E$11:$E$50)),OR(H11="",SUMIF($A$11:$A$50,H11,AJ$11:AJ$50)>=SUMIF($A$11:$A$50,H11,$E$11:$E$50))),"ОТКРЫТО","ЗАКРЫТО")) -> ОТКРЫТО | AZ11: =IF(AK11>=E11,"ИЗУЧЕНО",IF(AND(OR(F11="",SUMIF($A$11:$A$50,F11,AK$11:AK$50)>=SUMIF($A$11:$A$50,F11,$E$11:$E$50)),OR(G11="",SUMIF($A$11:$A$50,G11,AK$11:AK$50)>=SUMIF($A$11:$A$50,G11,$E$11:$E$50)),OR(H11="",SUMIF($A$11:$A$50,H11,AK$11:AK$50)>=SUMIF($A$11:$A$50,H11,$E$11:$E$50))),"ОТКРЫТО","ЗАКРЫТО")) -> ОТКРЫТО | BA11: =IF(AL11>=E11,"ИЗУЧЕНО",IF(AND(OR(F11="",SUMIF($A$11:$A$50,F11,AL$11:AL$50)>=SUMIF($A$11:$A$50,F11,$E$11:$E$50)),OR(G11="",SUMIF($A$11:$A$50,G11,AL$11:AL$50)>=SUMIF($A$11:$A$50,G11,$E$11:$E$50)),OR(H11="",SUMIF($A$11:$A$50,H11,AL$11:AL$50)>=SUMIF($A$11:$A$50,H11,$E$11:$E$50))),"ОТКРЫТО","ЗАКРЫТО")) -> ОТКРЫТО | BB11: =IF(AM11>=E11,"ИЗУЧЕНО",IF(AND(OR(F11="",SUMIF($A$11:$A$50,F11,AM$11:AM$50)>=SUMIF($A$11:$A$50,F11,$E$11:$E$50)),OR(G11="",SUMIF($A$11:$A$50,G11,AM$11:AM$50)>=SUMIF($A$11:$A$50,G11,$E$11:$E$50)),OR(H11="",SUMIF($A$11:$A$50,H11,AM$11:AM$50)>=SUMIF($A$11:$A$50,H11,$E$11:$E$50))),"ОТКРЫТО","ЗАКРЫТО")) -> ОТКРЫТО | BC11: =IF(AN11>=E11,"ИЗУЧЕНО",IF(AND(OR(F11="",SUMIF($A$11:$A$50,F11,AN$11:AN$50)>=SUMIF($A$11:$A$50,F11,$E$11:$E$50)),OR(G11="",SUMIF($A$11:$A$50,G11,AN$11:AN$50)>=SUMIF($A$11:$A$50,G11,$E$11:$E$50)),OR(H11="",SUMIF($A$11:$A$50,H11,AN$11:AN$50)>=SUMIF($A$11:$A$50,H11,$E$11:$E$50))),"ОТКРЫТО","ЗАКРЫТО")) -> ОТКРЫТО | BD11: =IF(AO11>=E11,"ИЗУЧЕНО",IF(AND(OR(F11="",SUMIF($A$11:$A$50,F11,AO$11:AO$50)>=SUMIF($A$11:$A$50,F11,$E$11:$E$50)),OR(G11="",SUMIF($A$11:$A$50,G11,AO$11:AO$50)>=SUMIF($A$11:$A$50,G11,$E$11:$E$50)),OR(H11="",SUMIF($A$11:$A$50,H11,AO$11:AO$50)>=SUMIF($A$11:$A$50,H11,$E$11:$E$50))),"ОТКРЫТО","ЗАКРЫТО")) -> ОТКРЫТО | BE11: =IF(AP11>=E11,"ИЗУЧЕНО",IF(AND(OR(F11="",SUMIF($A$11:$A$50,F11,AP$11:AP$50)>=SUMIF($A$11:$A$50,F11,$E$11:$E$50)),OR(G11="",SUMIF($A$11:$A$50,G11,AP$11:AP$50)>=SUMIF($A$11:$A$50,G11,$E$11:$E$50)),OR(H11="",SUMIF($A$11:$A$50,H11,AP$11:AP$50)>=SUMIF($A$11:$A$50,H11,$E$11:$E$50))),"ОТКРЫТО","ЗАКРЫТО")) -> ОТКРЫТО | BF11: =IF(AQ11>=E11,"ИЗУЧЕНО",IF(AND(OR(F11="",SUMIF($A$11:$A$50,F11,AQ$11:AQ$50)>=SUMIF($A$11:$A$50,F11,$E$11:$E$50)),OR(G11="",SUMIF($A$11:$A$50,G11,AQ$11:AQ$50)>=SUMIF($A$11:$A$50,G11,$E$11:$E$50)),OR(H11="",SUMIF($A$11:$A$50,H11,AQ$11:AQ$50)>=SUMIF($A$11:$A$50,H11,$E$11:$E$50))),"ОТКРЫТО","ЗАКРЫТО")) -> ОТКРЫТО
A12: C2 | B12: Вычисления и аппаратная база | C12: II | D12: Проектирование специализированных ускорителей | E12: 40 | F12: C1 | I12: Собственные архитектуры ускорителей и средств их проектирования. | J12: Вычислительные компоненты +0,3; их прирост +0,08/год | K12: =SUMIF('Ход 2026'!$G$29:$G$38,$A12,'Ход 2026'!$I$29:$I$38) -> 0 | L12: =SUMIF('Ход 2027'!$G$29:$G$38,$A12,'Ход 2027'!$I$29:$I$38) -> 0 | M12: =SUMIF('Ход 2028'!$G$29:$G$38,$A12,'Ход 2028'!$I$29:$I$38) -> 0 | N12: =SUMIF('Ход 2029'!$G$29:$G$38,$A12,'Ход 2029'!$I$29:$I$38) -> 0 | O12: =SUMIF('Ход 2030'!$G$29:$G$38,$A12,'Ход 2030'!$I$29:$I$38) -> 0 | P12: =SUMIF('Ход 2031'!$G$29:$G$38,$A12,'Ход 2031'!$I$29:$I$38) -> 0 | Q12: =SUMIF('Ход 2032'!$G$29:$G$38,$A12,'Ход 2032'!$I$29:$I$38) -> 0 | R12: =SUMIF('Ход 2033'!$G$29:$G$38,$A12,'Ход 2033'!$I$29:$I$38) -> 0 | S12: =SUMIF('Ход 2034'!$G$29:$G$38,$A12,'Ход 2034'!$I$29:$I$38) -> 0 | T12: =SUMIF('Ход 2035'!$G$29:$G$38,$A12,'Ход 2035'!$I$29:$I$38) -> 0 | U12: =SUMIF('Ход 2036'!$G$29:$G$38,$A12,'Ход 2036'!$I$29:$I$38) -> 0 | V12: =SUMIF('Ход 2037'!$G$29:$G$38,$A12,'Ход 2037'!$I$29:$I$38) -> 0 | W12: =SUMIF('Ход 2038'!$G$29:$G$38,$A12,'Ход 2038'!$I$29:$I$38) -> 0 | X12: =SUMIF('Ход 2039'!$G$29:$G$38,$A12,'Ход 2039'!$I$29:$I$38) -> 0 | Y12: =SUMIF('Ход 2040'!$G$29:$G$38,$A12,'Ход 2040'!$I$29:$I$38) -> 0 | Z12: =SUM(K12:Y12) -> 0 | AA12: =MAX(0,E12-Z12) -> 40 | AB12: =BF12 -> ЗАКРЫТО | AC12: =SUM($K12:K12) -> 0 | AD12: =SUM($K12:L12) -> 0 | AE12: =SUM($K12:M12) -> 0 | AF12: =SUM($K12:N12) -> 0 | AG12: =SUM($K12:O12) -> 0 | AH12: =SUM($K12:P12) -> 0 | AI12: =SUM($K12:Q12) -> 0 | AJ12: =SUM($K12:R12) -> 0 | ... AQ12: =SUM($K12:Y12) -> 0 | AR12: =IF(AC12>=E12,"ИЗУЧЕНО",IF(AND(OR(F12="",SUMIF($A$11:$A$50,F12,AC$11:AC$50)>=SUMIF($A$11:$A$50,F12,$E$11:$E$50)),OR(G12="",SUMIF($A$11:$A$50,G12,AC$11:AC$50)>=SUMIF($A$11:$A$50,G12,$E$11:$E$50)),OR(H12="",SUMIF($A$11:$A$50,H12,AC$11:AC$50)>=SUMIF($A$11:$A$50,H12,$E$11:$E$50))),"ОТКРЫТО","ЗАКРЫТО")) -> ЗАКРЫТО | AS12: =IF(AD12>=E12,"ИЗУЧЕНО",IF(AND(OR(F12="",SUMIF($A$11:$A$50,F12,AD$11:AD$50)>=SUMIF($A$11:$A$50,F12,$E$11:$E$50)),OR(G12="",SUMIF($A$11:$A$50,G12,AD$11:AD$50)>=SUMIF($A$11:$A$50,G12,$E$11:$E$50)),OR(H12="",SUMIF($A$11:$A$50,H12,AD$11:AD$50)>=SUMIF($A$11:$A$50,H12,$E$11:$E$50))),"ОТКРЫТО","ЗАКРЫТО")) -> ЗАКРЫТО | AT12: =IF(AE12>=E12,"ИЗУЧЕНО",IF(AND(OR(F12="",SUMIF($A$11:$A$50,F12,AE$11:AE$50)>=SUMIF($A$11:$A$50,F12,$E$11:$E$50)),OR(G12="",SUMIF($A$11:$A$50,G12,AE$11:AE$50)>=SUMIF($A$11:$A$50,G12,$E$11:$E$50)),OR(H12="",SUMIF($A$11:$A$50,H12,AE$11:AE$50)>=SUMIF($A$11:$A$50,H12,$E$11:$E$50))),"ОТКРЫТО","ЗАКРЫТО")) -> ЗАКРЫТО | AU12: =IF(AF12>=E12,"ИЗУЧЕНО",IF(AND(OR(F12="",SUMIF($A$11:$A$50,F12,AF$11:AF$50)>=SUMIF($A$11:$A$50,F12,$E$11:$E$50)),OR(G12="",SUMIF($A$11:$A$50,G12,AF$11:AF$50)>=SUMIF($A$11:$A$50,G12,$E$11:$E$50)),OR(H12="",SUMIF($A$11:$A$50,H12,AF$11:AF$50)>=SUMIF($A$11:$A$50,H12,$E$11:$E$50))),"ОТКРЫТО","ЗАКРЫТО")) -> ЗАКРЫТО | AV12: =IF(AG12>=E12,"ИЗУЧЕНО",IF(AND(OR(F12="",SUMIF($A$11:$A$50,F12,AG$11:AG$50)>=SUMIF($A$11:$A$50,F12,$E$11:$E$50)),OR(G12="",SUMIF($A$11:$A$50,G12,AG$11:AG$50)>=SUMIF($A$11:$A$50,G12,$E$11:$E$50)),OR(H12="",SUMIF($A$11:$A$50,H12,AG$11:AG$50)>=SUMIF($A$11:$A$50,H12,$E$11:$E$50))),"ОТКРЫТО","ЗАКРЫТО")) -> ЗАКРЫТО | AW12: =IF(AH12>=E12,"ИЗУЧЕНО",IF(AND(OR(F12="",SUMIF($A$11:$A$50,F12,AH$11:AH$50)>=SUMIF($A$11:$A$50,F12,$E$11:$E$50)),OR(G12="",SUMIF($A$11:$A$50,G12,AH$11:AH$50)>=SUMIF($A$11:$A$50,G12,$E$11:$E$50)),OR(H12="",SUMIF($A$11:$A$50,H12,AH$11:AH$50)>=SUMIF($A$11:$A$50,H12,$E$11:$E$50))),"ОТКРЫТО","ЗАКРЫТО")) -> ЗАКРЫТО | AX12: =IF(AI12>=E12,"ИЗУЧЕНО",IF(AND(OR(F12="",SUMIF($A$11:$A$50,F12,AI$11:AI$50)>=SUMIF($A$11:$A$50,F12,$E$11:$E$50)),OR(G12="",SUMIF($A$11:$A$50,G12,AI$11:AI$50)>=SUMIF($A$11:$A$50,G12,$E$11:$E$50)),OR(H12="",SUMIF($A$11:$A$50,H12,AI$11:AI$50)>=SUMIF($A$11:$A$50,H12,$E$11:$E$50))),"ОТКРЫТО","ЗАКРЫТО")) -> ЗАКРЫТО | AY12: =IF(AJ12>=E12,"ИЗУЧЕНО",IF(AND(OR(F12="",SUMIF($A$11:$A$50,F12,AJ$11:AJ$50)>=SUMIF($A$11:$A$50,F12,$E$11:$E$50)),OR(G12="",SUMIF($A$11:$A$50,G12,AJ$11:AJ$50)>=SUMIF($A$11:$A$50,G12,$E$11:$E$50)),OR(H12="",SUMIF($A$11:$A$50,H12,AJ$11:AJ$50)>=SUMIF($A$11:$A$50,H12,$E$11:$E$50))),"ОТКРЫТО","ЗАКРЫТО")) -> ЗАКРЫТО | AZ12: =IF(AK12>=E12,"ИЗУЧЕНО",IF(AND(OR(F12="",SUMIF($A$11:$A$50,F12,AK$11:AK$50)>=SUMIF($A$11:$A$50,F12,$E$11:$E$50)),OR(G12="",SUMIF($A$11:$A$50,G12,AK$11:AK$50)>=SUMIF($A$11:$A$50,G12,$E$11:$E$50)),OR(H12="",SUMIF($A$11:$A$50,H12,AK$11:AK$50)>=SUMIF($A$11:$A$50,H12,$E$11:$E$50))),"ОТКРЫТО","ЗАКРЫТО")) -> ЗАКРЫТО | BA12: =IF(AL12>=E12,"ИЗУЧЕНО",IF(AND(OR(F12="",SUMIF($A$11:$A$50,F12,AL$11:AL$50)>=SUMIF($A$11:$A$50,F12,$E$11:$E$50)),OR(G12="",SUMIF($A$11:$A$50,G12,AL$11:AL$50)>=SUMIF($A$11:$A$50,G12,$E$11:$E$50)),OR(H12="",SUMIF($A$11:$A$50,H12,AL$11:AL$50)>=SUMIF($A$11:$A$50,H12,$E$11:$E$50))),"ОТКРЫТО","ЗАКРЫТО")) -> ЗАКРЫТО | BB12: =IF(AM12>=E12,"ИЗУЧЕНО",IF(AND(OR(F12="",SUMIF($A$11:$A$50,F12,AM$11:AM$50)>=SUMIF($A$11:$A$50,F12,$E$11:$E$50)),OR(G12="",SUMIF($A$11:$A$50,G12,AM$11:AM$50)>=SUMIF($A$11:$A$50,G12,$E$11:$E$50)),OR(H12="",SUMIF($A$11:$A$50,H12,AM$11:AM$50)>=SUMIF($A$11:$A$50,H12,$E$11:$E$50))),"ОТКРЫТО","ЗАКРЫТО")) -> ЗАКРЫТО | BC12: =IF(AN12>=E12,"ИЗУЧЕНО",IF(AND(OR(F12="",SUMIF($A$11:$A$50,F12,AN$11:AN$50)>=SUMIF($A$11:$A$50,F12,$E$11:$E$50)),OR(G12="",SUMIF($A$11:$A$50,G12,AN$11:AN$50)>=SUMIF($A$11:$A$50,G12,$E$11:$E$50)),OR(H12="",SUMIF($A$11:$A$50,H12,AN$11:AN$50)>=SUMIF($A$11:$A$50,H12,$E$11:$E$50))),"ОТКРЫТО","ЗАКРЫТО")) -> ЗАКРЫТО | BD12: =IF(AO12>=E12,"ИЗУЧЕНО",IF(AND(OR(F12="",SUMIF($A$11:$A$50,F12,AO$11:AO$50)>=SUMIF($A$11:$A$50,F12,$E$11:$E$50)),OR(G12="",SUMIF($A$11:$A$50,G12,AO$11:AO$50)>=SUMIF($A$11:$A$50,G12,$E$11:$E$50)),OR(H12="",SUMIF($A$11:$A$50,H12,AO$11:AO$50)>=SUMIF($A$11:$A$50,H12,$E$11:$E$50))),"ОТКРЫТО","ЗАКРЫТО")) -> ЗАКРЫТО | BE12: =IF(AP12>=E12,"ИЗУЧЕНО",IF(AND(OR(F12="",SUMIF($A$11:$A$50,F12,AP$11:AP$50)>=SUMIF($A$11:$A$50,F12,$E$11:$E$50)),OR(G12="",SUMIF($A$11:$A$50,G12,AP$11:AP$50)>=SUMIF($A$11:$A$50,G12,$E$11:$E$50)),OR(H12="",SUMIF($A$11:$A$50,H12,AP$11:AP$50)>=SUMIF($A$11:$A$50,H12,$E$11:$E$50))),"ОТКРЫТО","ЗАКРЫТО")) -> ЗАКРЫТО | BF12: =IF(AQ12>=E12,"ИЗУЧЕНО",IF(AND(OR(F12="",SUMIF($A$11:$A$50,F12,AQ$11:AQ$50)>=SUMIF($A$11:$A$50,F12,$E$11:$E$50)),OR(G12="",SUMIF($A$11:$A$50,G12,AQ$11:AQ$50)>=SUMIF($A$11:$A$50,G12,$E$11:$E$50)),OR(H12="",SUMIF($A$11:$A$50,H12,AQ$11:AQ$50)>=SUMIF($A$11:$A$50,H12,$E$11:$E$50))),"ОТКРЫТО","ЗАКРЫТО")) -> ЗАКРЫТО
A13: C3 | B13: Вычисления и аппаратная база | C13: II | D13: Передовая микроэлектроника для ИИ | E13: 45 | F13: C1 | I13: Технологическая база для специализированных чипов, памяти и упаковки. | J13: Полупроводниковое производство +0,4; его прирост +0,08/год | K13: =SUMIF('Ход 2026'!$G$29:$G$38,$A13,'Ход 2026'!$I$29:$I$38) -> 0 | L13: =SUMIF('Ход 2027'!$G$29:$G$38,$A13,'Ход 2027'!$I$29:$I$38) -> 0 | M13: =SUMIF('Ход 2028'!$G$29:$G$38,$A13,'Ход 2028'!$I$29:$I$38) -> 0 | N13: =SUMIF('Ход 2029'!$G$29:$G$38,$A13,'Ход 2029'!$I$29:$I$38) -> 0 | O13: =SUMIF('Ход 2030'!$G$29:$G$38,$A13,'Ход 2030'!$I$29:$I$38) -> 0 | P13: =SUMIF('Ход 2031'!$G$29:$G$38,$A13,'Ход 2031'!$I$29:$I$38) -> 0 | Q13: =SUMIF('Ход 2032'!$G$29:$G$38,$A13,'Ход 2032'!$I$29:$I$38) -> 0 | R13: =SUMIF('Ход 2033'!$G$29:$G$38,$A13,'Ход 2033'!$I$29:$I$38) -> 0 | S13: =SUMIF('Ход 2034'!$G$29:$G$38,$A13,'Ход 2034'!$I$29:$I$38) -> 0 | T13: =SUMIF('Ход 2035'!$G$29:$G$38,$A13,'Ход 2035'!$I$29:$I$38) -> 0 | U13: =SUMIF('Ход 2036'!$G$29:$G$38,$A13,'Ход 2036'!$I$29:$I$38) -> 0 | V13: =SUMIF('Ход 2037'!$G$29:$G$38,$A13,'Ход 2037'!$I$29:$I$38) -> 0 | W13: =SUMIF('Ход 2038'!$G$29:$G$38,$A13,'Ход 2038'!$I$29:$I$38) -> 0 | X13: =SUMIF('Ход 2039'!$G$29:$G$38,$A13,'Ход 2039'!$I$29:$I$38) -> 0 | Y13: =SUMIF('Ход 2040'!$G$29:$G$38,$A13,'Ход 2040'!$I$29:$I$38) -> 0 | Z13: =SUM(K13:Y13) -> 0 | AA13: =MAX(0,E13-Z13) -> 45 | AB13: =BF13 -> ЗАКРЫТО | AC13: =SUM($K13:K13) -> 0 | AD13: =SUM($K13:L13) -> 0 | AE13: =SUM($K13:M13) -> 0 | AF13: =SUM($K13:N13) -> 0 | AG13: =SUM($K13:O13) -> 0 | AH13: =SUM($K13:P13) -> 0 | AI13: =SUM($K13:Q13) -> 0 | AJ13: =SUM($K13:R13) -> 0 | ... AQ13: =SUM($K13:Y13) -> 0 | AR13: =IF(AC13>=E13,"ИЗУЧЕНО",IF(AND(OR(F13="",SUMIF($A$11:$A$50,F13,AC$11:AC$50)>=SUMIF($A$11:$A$50,F13,$E$11:$E$50)),OR(G13="",SUMIF($A$11:$A$50,G13,AC$11:AC$50)>=SUMIF($A$11:$A$50,G13,$E$11:$E$50)),OR(H13="",SUMIF($A$11:$A$50,H13,AC$11:AC$50)>=SUMIF($A$11:$A$50,H13,$E$11:$E$50))),"ОТКРЫТО","ЗАКРЫТО")) -> ЗАКРЫТО | AS13: =IF(AD13>=E13,"ИЗУЧЕНО",IF(AND(OR(F13="",SUMIF($A$11:$A$50,F13,AD$11:AD$50)>=SUMIF($A$11:$A$50,F13,$E$11:$E$50)),OR(G13="",SUMIF($A$11:$A$50,G13,AD$11:AD$50)>=SUMIF($A$11:$A$50,G13,$E$11:$E$50)),OR(H13="",SUMIF($A$11:$A$50,H13,AD$11:AD$50)>=SUMIF($A$11:$A$50,H13,$E$11:$E$50))),"ОТКРЫТО","ЗАКРЫТО")) -> ЗАКРЫТО | AT13: =IF(AE13>=E13,"ИЗУЧЕНО",IF(AND(OR(F13="",SUMIF($A$11:$A$50,F13,AE$11:AE$50)>=SUMIF($A$11:$A$50,F13,$E$11:$E$50)),OR(G13="",SUMIF($A$11:$A$50,G13,AE$11:AE$50)>=SUMIF($A$11:$A$50,G13,$E$11:$E$50)),OR(H13="",SUMIF($A$11:$A$50,H13,AE$11:AE$50)>=SUMIF($A$11:$A$50,H13,$E$11:$E$50))),"ОТКРЫТО","ЗАКРЫТО")) -> ЗАКРЫТО | AU13: =IF(AF13>=E13,"ИЗУЧЕНО",IF(AND(OR(F13="",SUMIF($A$11:$A$50,F13,AF$11:AF$50)>=SUMIF($A$11:$A$50,F13,$E$11:$E$50)),OR(G13="",SUMIF($A$11:$A$50,G13,AF$11:AF$50)>=SUMIF($A$11:$A$50,G13,$E$11:$E$50)),OR(H13="",SUMIF($A$11:$A$50,H13,AF$11:AF$50)>=SUMIF($A$11:$A$50,H13,$E$11:$E$50))),"ОТКРЫТО","ЗАКРЫТО")) -> ЗАКРЫТО | AV13: =IF(AG13>=E13,"ИЗУЧЕНО",IF(AND(OR(F13="",SUMIF($A$11:$A$50,F13,AG$11:AG$50)>=SUMIF($A$11:$A$50,F13,$E$11:$E$50)),OR(G13="",SUMIF($A$11:$A$50,G13,AG$11:AG$50)>=SUMIF($A$11:$A$50,G13,$E$11:$E$50)),OR(H13="",SUMIF($A$11:$A$50,H13,AG$11:AG$50)>=SUMIF($A$11:$A$50,H13,$E$11:$E$50))),"ОТКРЫТО","ЗАКРЫТО")) -> ЗАКРЫТО | AW13: =IF(AH13>=E13,"ИЗУЧЕНО",IF(AND(OR(F13="",SUMIF($A$11:$A$50,F13,AH$11:AH$50)>=SUMIF($A$11:$A$50,F13,$E$11:$E$50)),OR(G13="",SUMIF($A$11:$A$50,G13,AH$11:AH$50)>=SUMIF($A$11:$A$50,G13,$E$11:$E$50)),OR(H13="",SUMIF($A$11:$A$50,H13,AH$11:AH$50)>=SUMIF($A$11:$A$50,H13,$E$11:$E$50))),"ОТКРЫТО","ЗАКРЫТО")) -> ЗАКРЫТО | AX13: =IF(AI13>=E13,"ИЗУЧЕНО",IF(AND(OR(F13="",SUMIF($A$11:$A$50,F13,AI$11:AI$50)>=SUMIF($A$11:$A$50,F13,$E$11:$E$50)),OR(G13="",SUMIF($A$11:$A$50,G13,AI$11:AI$50)>=SUMIF($A$11:$A$50,G13,$E$11:$E$50)),OR(H13="",SUMIF($A$11:$A$50,H13,AI$11:AI$50)>=SUMIF($A$11:$A$50,H13,$E$11:$E$50))),"ОТКРЫТО","ЗАКРЫТО")) -> ЗАКРЫТО | AY13: =IF(AJ13>=E13,"ИЗУЧЕНО",IF(AND(OR(F13="",SUMIF($A$11:$A$50,F13,AJ$11:AJ$50)>=SUMIF($A$11:$A$50,F13,$E$11:$E$50)),OR(G13="",SUMIF($A$11:$A$50,G13,AJ$11:AJ$50)>=SUMIF($A$11:$A$50,G13,$E$11:$E$50)),OR(H13="",SUMIF($A$11:$A$50,H13,AJ$11:AJ$50)>=SUMIF($A$11:$A$50,H13,$E$11:$E$50))),"ОТКРЫТО","ЗАКРЫТО")) -> ЗАКРЫТО | AZ13: =IF(AK13>=E13,"ИЗУЧЕНО",IF(AND(OR(F13="",SUMIF($A$11:$A$50,F13,AK$11:AK$50)>=SUMIF($A$11:$A$50,F13,$E$11:$E$50)),OR(G13="",SUMIF($A$11:$A$50,G13,AK$11:AK$50)>=SUMIF($A$11:$A$50,G13,$E$11:$E$50)),OR(H13="",SUMIF($A$11:$A$50,H13,AK$11:AK$50)>=SUMIF($A$11:$A$50,H13,$E$11:$E$50))),"ОТКРЫТО","ЗАКРЫТО")) -> ЗАКРЫТО | BA13: =IF(AL13>=E13,"ИЗУЧЕНО",IF(AND(OR(F13="",SUMIF($A$11:$A$50,F13,AL$11:AL$50)>=SUMIF($A$11:$A$50,F13,$E$11:$E$50)),OR(G13="",SUMIF($A$11:$A$50,G13,AL$11:AL$50)>=SUMIF($A$11:$A$50,G13,$E$11:$E$50)),OR(H13="",SUMIF($A$11:$A$50,H13,AL$11:AL$50)>=SUMIF($A$11:$A$50,H13,$E$11:$E$50))),"ОТКРЫТО","ЗАКРЫТО")) -> ЗАКРЫТО | BB13: =IF(AM13>=E13,"ИЗУЧЕНО",IF(AND(OR(F13="",SUMIF($A$11:$A$50,F13,AM$11:AM$50)>=SUMIF($A$11:$A$50,F13,$E$11:$E$50)),OR(G13="",SUMIF($A$11:$A$50,G13,AM$11:AM$50)>=SUMIF($A$11:$A$50,G13,$E$11:$E$50)),OR(H13="",SUMIF($A$11:$A$50,H13,AM$11:AM$50)>=SUMIF($A$11:$A$50,H13,$E$11:$E$50))),"ОТКРЫТО","ЗАКРЫТО")) -> ЗАКРЫТО | BC13: =IF(AN13>=E13,"ИЗУЧЕНО",IF(AND(OR(F13="",SUMIF($A$11:$A$50,F13,AN$11:AN$50)>=SUMIF($A$11:$A$50,F13,$E$11:$E$50)),OR(G13="",SUMIF($A$11:$A$50,G13,AN$11:AN$50)>=SUMIF($A$11:$A$50,G13,$E$11:$E$50)),OR(H13="",SUMIF($A$11:$A$50,H13,AN$11:AN$50)>=SUMIF($A$11:$A$50,H13,$E$11:$E$50))),"ОТКРЫТО","ЗАКРЫТО")) -> ЗАКРЫТО | BD13: =IF(AO13>=E13,"ИЗУЧЕНО",IF(AND(OR(F13="",SUMIF($A$11:$A$50,F13,AO$11:AO$50)>=SUMIF($A$11:$A$50,F13,$E$11:$E$50)),OR(G13="",SUMIF($A$11:$A$50,G13,AO$11:AO$50)>=SUMIF($A$11:$A$50,G13,$E$11:$E$50)),OR(H13="",SUMIF($A$11:$A$50,H13,AO$11:AO$50)>=SUMIF($A$11:$A$50,H13,$E$11:$E$50))),"ОТКРЫТО","ЗАКРЫТО")) -> ЗАКРЫТО | BE13: =IF(AP13>=E13,"ИЗУЧЕНО",IF(AND(OR(F13="",SUMIF($A$11:$A$50,F13,AP$11:AP$50)>=SUMIF($A$11:$A$50,F13,$E$11:$E$50)),OR(G13="",SUMIF($A$11:$A$50,G13,AP$11:AP$50)>=SUMIF($A$11:$A$50,G13,$E$11:$E$50)),OR(H13="",SUMIF($A$11:$A$50,H13,AP$11:AP$50)>=SUMIF($A$11:$A$50,H13,$E$11:$E$50))),"ОТКРЫТО","ЗАКРЫТО")) -> ЗАКРЫТО | BF13: =IF(AQ13>=E13,"ИЗУЧЕНО",IF(AND(OR(F13="",SUMIF($A$11:$A$50,F13,AQ$11:AQ$50)>=SUMIF($A$11:$A$50,F13,$E$11:$E$50)),OR(G13="",SUMIF($A$11:$A$50,G13,AQ$11:AQ$50)>=SUMIF($A$11:$A$50,G13,$E$11:$E$50)),OR(H13="",SUMIF($A$11:$A$50,H13,AQ$11:AQ$50)>=SUMIF($A$11:$A$50,H13,$E$11:$E$50))),"ОТКРЫТО","ЗАКРЫТО")) -> ЗАКРЫТО
A14: C4 | B14: Вычисления и аппаратная база | C14: III | D14: Гетерогенные вычислительные кластеры | E14: 65 | F14: C2 | G14: C3 | I14: Совместное использование CPU, GPU, специализированных ускорителей и распределённой памяти. | J14: ЦОД +0,4; Стек эксплуатации ИИ +0,2; прирост ЦОД +0,05/год | K14: =SUMIF('Ход 2026'!$G$29:$G$38,$A14,'Ход 2026'!$I$29:$I$38) -> 0 | L14: =SUMIF('Ход 2027'!$G$29:$G$38,$A14,'Ход 2027'!$I$29:$I$38) -> 0 | M14: =SUMIF('Ход 2028'!$G$29:$G$38,$A14,'Ход 2028'!$I$29:$I$38) -> 0 | N14: =SUMIF('Ход 2029'!$G$29:$G$38,$A14,'Ход 2029'!$I$29:$I$38) -> 0 | O14: =SUMIF('Ход 2030'!$G$29:$G$38,$A14,'Ход 2030'!$I$29:$I$38) -> 0 | P14: =SUMIF('Ход 2031'!$G$29:$G$38,$A14,'Ход 2031'!$I$29:$I$38) -> 0 | Q14: =SUMIF('Ход 2032'!$G$29:$G$38,$A14,'Ход 2032'!$I$29:$I$38) -> 0 | R14: =SUMIF('Ход 2033'!$G$29:$G$38,$A14,'Ход 2033'!$I$29:$I$38) -> 0 | S14: =SUMIF('Ход 2034'!$G$29:$G$38,$A14,'Ход 2034'!$I$29:$I$38) -> 0 | T14: =SUMIF('Ход 2035'!$G$29:$G$38,$A14,'Ход 2035'!$I$29:$I$38) -> 0 | U14: =SUMIF('Ход 2036'!$G$29:$G$38,$A14,'Ход 2036'!$I$29:$I$38) -> 0 | V14: =SUMIF('Ход 2037'!$G$29:$G$38,$A14,'Ход 2037'!$I$29:$I$38) -> 0 | W14: =SUMIF('Ход 2038'!$G$29:$G$38,$A14,'Ход 2038'!$I$29:$I$38) -> 0 | X14: =SUMIF('Ход 2039'!$G$29:$G$38,$A14,'Ход 2039'!$I$29:$I$38) -> 0 | Y14: =SUMIF('Ход 2040'!$G$29:$G$38,$A14,'Ход 2040'!$I$29:$I$38) -> 0 | Z14: =SUM(K14:Y14) -> 0 | AA14: =MAX(0,E14-Z14) -> 65 | AB14: =BF14 -> ЗАКРЫТО | AC14: =SUM($K14:K14) -> 0 | AD14: =SUM($K14:L14) -> 0 | AE14: =SUM($K14:M14) -> 0 | AF14: =SUM($K14:N14) -> 0 | AG14: =SUM($K14:O14) -> 0 | AH14: =SUM($K14:P14) -> 0 | AI14: =SUM($K14:Q14) -> 0 | AJ14: =SUM($K14:R14) -> 0 | ... AQ14: =SUM($K14:Y14) -> 0 | AR14: =IF(AC14>=E14,"ИЗУЧЕНО",IF(AND(OR(F14="",SUMIF($A$11:$A$50,F14,AC$11:AC$50)>=SUMIF($A$11:$A$50,F14,$E$11:$E$50)),OR(G14="",SUMIF($A$11:$A$50,G14,AC$11:AC$50)>=SUMIF($A$11:$A$50,G14,$E$11:$E$50)),OR(H14="",SUMIF($A$11:$A$50,H14,AC$11:AC$50)>=SUMIF($A$11:$A$50,H14,$E$11:$E$50))),"ОТКРЫТО","ЗАКРЫТО")) -> ЗАКРЫТО | AS14: =IF(AD14>=E14,"ИЗУЧЕНО",IF(AND(OR(F14="",SUMIF($A$11:$A$50,F14,AD$11:AD$50)>=SUMIF($A$11:$A$50,F14,$E$11:$E$50)),OR(G14="",SUMIF($A$11:$A$50,G14,AD$11:AD$50)>=SUMIF($A$11:$A$50,G14,$E$11:$E$50)),OR(H14="",SUMIF($A$11:$A$50,H14,AD$11:AD$50)>=SUMIF($A$11:$A$50,H14,$E$11:$E$50))),"ОТКРЫТО","ЗАКРЫТО")) -> ЗАКРЫТО | AT14: =IF(AE14>=E14,"ИЗУЧЕНО",IF(AND(OR(F14="",SUMIF($A$11:$A$50,F14,AE$11:AE$50)>=SUMIF($A$11:$A$50,F14,$E$11:$E$50)),OR(G14="",SUMIF($A$11:$A$50,G14,AE$11:AE$50)>=SUMIF($A$11:$A$50,G14,$E$11:$E$50)),OR(H14="",SUMIF($A$11:$A$50,H14,AE$11:AE$50)>=SUMIF($A$11:$A$50,H14,$E$11:$E$50))),"ОТКРЫТО","ЗАКРЫТО")) -> ЗАКРЫТО | AU14: =IF(AF14>=E14,"ИЗУЧЕНО",IF(AND(OR(F14="",SUMIF($A$11:$A$50,F14,AF$11:AF$50)>=SUMIF($A$11:$A$50,F14,$E$11:$E$50)),OR(G14="",SUMIF($A$11:$A$50,G14,AF$11:AF$50)>=SUMIF($A$11:$A$50,G14,$E$11:$E$50)),OR(H14="",SUMIF($A$11:$A$50,H14,AF$11:AF$50)>=SUMIF($A$11:$A$50,H14,$E$11:$E$50))),"ОТКРЫТО","ЗАКРЫТО")) -> ЗАКРЫТО | AV14: =IF(AG14>=E14,"ИЗУЧЕНО",IF(AND(OR(F14="",SUMIF($A$11:$A$50,F14,AG$11:AG$50)>=SUMIF($A$11:$A$50,F14,$E$11:$E$50)),OR(G14="",SUMIF($A$11:$A$50,G14,AG$11:AG$50)>=SUMIF($A$11:$A$50,G14,$E$11:$E$50)),OR(H14="",SUMIF($A$11:$A$50,H14,AG$11:AG$50)>=SUMIF($A$11:$A$50,H14,$E$11:$E$50))),"ОТКРЫТО","ЗАКРЫТО")) -> ЗАКРЫТО | AW14: =IF(AH14>=E14,"ИЗУЧЕНО",IF(AND(OR(F14="",SUMIF($A$11:$A$50,F14,AH$11:AH$50)>=SUMIF($A$11:$A$50,F14,$E$11:$E$50)),OR(G14="",SUMIF($A$11:$A$50,G14,AH$11:AH$50)>=SUMIF($A$11:$A$50,G14,$E$11:$E$50)),OR(H14="",SUMIF($A$11:$A$50,H14,AH$11:AH$50)>=SUMIF($A$11:$A$50,H14,$E$11:$E$50))),"ОТКРЫТО","ЗАКРЫТО")) -> ЗАКРЫТО | AX14: =IF(AI14>=E14,"ИЗУЧЕНО",IF(AND(OR(F14="",SUMIF($A$11:$A$50,F14,AI$11:AI$50)>=SUMIF($A$11:$A$50,F14,$E$11:$E$50)),OR(G14="",SUMIF($A$11:$A$50,G14,AI$11:AI$50)>=SUMIF($A$11:$A$50,G14,$E$11:$E$50)),OR(H14="",SUMIF($A$11:$A$50,H14,AI$11:AI$50)>=SUMIF($A$11:$A$50,H14,$E$11:$E$50))),"ОТКРЫТО","ЗАКРЫТО")) -> ЗАКРЫТО | AY14: =IF(AJ14>=E14,"ИЗУЧЕНО",IF(AND(OR(F14="",SUMIF($A$11:$A$50,F14,AJ$11:AJ$50)>=SUMIF($A$11:$A$50,F14,$E$11:$E$50)),OR(G14="",SUMIF($A$11:$A$50,G14,AJ$11:AJ$50)>=SUMIF($A$11:$A$50,G14,$E$11:$E$50)),OR(H14="",SUMIF($A$11:$A$50,H14,AJ$11:AJ$50)>=SUMIF($A$11:$A$50,H14,$E$11:$E$50))),"ОТКРЫТО","ЗАКРЫТО")) -> ЗАКРЫТО | AZ14: =IF(AK14>=E14,"ИЗУЧЕНО",IF(AND(OR(F14="",SUMIF($A$11:$A$50,F14,AK$11:AK$50)>=SUMIF($A$11:$A$50,F14,$E$11:$E$50)),OR(G14="",SUMIF($A$11:$A$50,G14,AK$11:AK$50)>=SUMIF($A$11:$A$50,G14,$E$11:$E$50)),OR(H14="",SUMIF($A$11:$A$50,H14,AK$11:AK$50)>=SUMIF($A$11:$A$50,H14,$E$11:$E$50))),"ОТКРЫТО","ЗАКРЫТО")) -> ЗАКРЫТО | BA14: =IF(AL14>=E14,"ИЗУЧЕНО",IF(AND(OR(F14="",SUMIF($A$11:$A$50,F14,AL$11:AL$50)>=SUMIF($A$11:$A$50,F14,$E$11:$E$50)),OR(G14="",SUMIF($A$11:$A$50,G14,AL$11:AL$50)>=SUMIF($A$11:$A$50,G14,$E$11:$E$50)),OR(H14="",SUMIF($A$11:$A$50,H14,AL$11:AL$50)>=SUMIF($A$11:$A$50,H14,$E$11:$E$50))),"ОТКРЫТО","ЗАКРЫТО")) -> ЗАКРЫТО | BB14: =IF(AM14>=E14,"ИЗУЧЕНО",IF(AND(OR(F14="",SUMIF($A$11:$A$50,F14,AM$11:AM$50)>=SUMIF($A$11:$A$50,F14,$E$11:$E$50)),OR(G14="",SUMIF($A$11:$A$50,G14,AM$11:AM$50)>=SUMIF($A$11:$A$50,G14,$E$11:$E$50)),OR(H14="",SUMIF($A$11:$A$50,H14,AM$11:AM$50)>=SUMIF($A$11:$A$50,H14,$E$11:$E$50))),"ОТКРЫТО","ЗАКРЫТО")) -> ЗАКРЫТО | BC14: =IF(AN14>=E14,"ИЗУЧЕНО",IF(AND(OR(F14="",SUMIF($A$11:$A$50,F14,AN$11:AN$50)>=SUMIF($A$11:$A$50,F14,$E$11:$E$50)),OR(G14="",SUMIF($A$11:$A$50,G14,AN$11:AN$50)>=SUMIF($A$11:$A$50,G14,$E$11:$E$50)),OR(H14="",SUMIF($A$11:$A$50,H14,AN$11:AN$50)>=SUMIF($A$11:$A$50,H14,$E$11:$E$50))),"ОТКРЫТО","ЗАКРЫТО")) -> ЗАКРЫТО | BD14: =IF(AO14>=E14,"ИЗУЧЕНО",IF(AND(OR(F14="",SUMIF($A$11:$A$50,F14,AO$11:AO$50)>=SUMIF($A$11:$A$50,F14,$E$11:$E$50)),OR(G14="",SUMIF($A$11:$A$50,G14,AO$11:AO$50)>=SUMIF($A$11:$A$50,G14,$E$11:$E$50)),OR(H14="",SUMIF($A$11:$A$50,H14,AO$11:AO$50)>=SUMIF($A$11:$A$50,H14,$E$11:$E$50))),"ОТКРЫТО","ЗАКРЫТО")) -> ЗАКРЫТО | BE14: =IF(AP14>=E14,"ИЗУЧЕНО",IF(AND(OR(F14="",SUMIF($A$11:$A$50,F14,AP$11:AP$50)>=SUMIF($A$11:$A$50,F14,$E$11:$E$50)),OR(G14="",SUMIF($A$11:$A$50,G14,AP$11:AP$50)>=SUMIF($A$11:$A$50,G14,$E$11:$E$50)),OR(H14="",SUMIF($A$11:$A$50,H14,AP$11:AP$50)>=SUMIF($A$11:$A$50,H14,$E$11:$E$50))),"ОТКРЫТО","ЗАКРЫТО")) -> ЗАКРЫТО | BF14: =IF(AQ14>=E14,"ИЗУЧЕНО",IF(AND(OR(F14="",SUMIF($A$11:$A$50,F14,AQ$11:AQ$50)>=SUMIF($A$11:$A$50,F14,$E$11:$E$50)),OR(G14="",SUMIF($A$11:$A$50,G14,AQ$11:AQ$50)>=SUMIF($A$11:$A$50,G14,$E$11:$E$50)),OR(H14="",SUMIF($A$11:$A$50,H14,AQ$11:AQ$50)>=SUMIF($A$11:$A$50,H14,$E$11:$E$50))),"ОТКРЫТО","ЗАКРЫТО")) -> ЗАКРЫТО
A15: C5 | B15: Вычисления и аппаратная база | C15: IV | D15: Суверенная распределённая вычислительная сеть | E15: 100 | F15: C4 | I15: Национальная сеть взаимозаменяемых ЦОД и вычислительных узлов. | J15: Сетевые ресурсы +0,4; прирост ЦОД +0,10/год; защита Афины +15% | K15: =SUMIF('Ход 2026'!$G$29:$G$38,$A15,'Ход 2026'!$I$29:$I$38) -> 0 | L15: =SUMIF('Ход 2027'!$G$29:$G$38,$A15,'Ход 2027'!$I$29:$I$38) -> 0 | M15: =SUMIF('Ход 2028'!$G$29:$G$38,$A15,'Ход 2028'!$I$29:$I$38) -> 0 | N15: =SUMIF('Ход 2029'!$G$29:$G$38,$A15,'Ход 2029'!$I$29:$I$38) -> 0 | O15: =SUMIF('Ход 2030'!$G$29:$G$38,$A15,'Ход 2030'!$I$29:$I$38) -> 0 | P15: =SUMIF('Ход 2031'!$G$29:$G$38,$A15,'Ход 2031'!$I$29:$I$38) -> 0 | Q15: =SUMIF('Ход 2032'!$G$29:$G$38,$A15,'Ход 2032'!$I$29:$I$38) -> 0 | R15: =SUMIF('Ход 2033'!$G$29:$G$38,$A15,'Ход 2033'!$I$29:$I$38) -> 0 | S15: =SUMIF('Ход 2034'!$G$29:$G$38,$A15,'Ход 2034'!$I$29:$I$38) -> 0 | T15: =SUMIF('Ход 2035'!$G$29:$G$38,$A15,'Ход 2035'!$I$29:$I$38) -> 0 | U15: =SUMIF('Ход 2036'!$G$29:$G$38,$A15,'Ход 2036'!$I$29:$I$38) -> 0 | V15: =SUMIF('Ход 2037'!$G$29:$G$38,$A15,'Ход 2037'!$I$29:$I$38) -> 0 | W15: =SUMIF('Ход 2038'!$G$29:$G$38,$A15,'Ход 2038'!$I$29:$I$38) -> 0 | X15: =SUMIF('Ход 2039'!$G$29:$G$38,$A15,'Ход 2039'!$I$29:$I$38) -> 0 | Y15: =SUMIF('Ход 2040'!$G$29:$G$38,$A15,'Ход 2040'!$I$29:$I$38) -> 0 | Z15: =SUM(K15:Y15) -> 0 | AA15: =MAX(0,E15-Z15) -> 100 | AB15: =BF15 -> ЗАКРЫТО | AC15: =SUM($K15:K15) -> 0 | AD15: =SUM($K15:L15) -> 0 | AE15: =SUM($K15:M15) -> 0 | AF15: =SUM($K15:N15) -> 0 | AG15: =SUM($K15:O15) -> 0 | AH15: =SUM($K15:P15) -> 0 | AI15: =SUM($K15:Q15) -> 0 | AJ15: =SUM($K15:R15) -> 0 | ... AQ15: =SUM($K15:Y15) -> 0 | AR15: =IF(AC15>=E15,"ИЗУЧЕНО",IF(AND(OR(F15="",SUMIF($A$11:$A$50,F15,AC$11:AC$50)>=SUMIF($A$11:$A$50,F15,$E$11:$E$50)),OR(G15="",SUMIF($A$11:$A$50,G15,AC$11:AC$50)>=SUMIF($A$11:$A$50,G15,$E$11:$E$50)),OR(H15="",SUMIF($A$11:$A$50,H15,AC$11:AC$50)>=SUMIF($A$11:$A$50,H15,$E$11:$E$50))),"ОТКРЫТО","ЗАКРЫТО")) -> ЗАКРЫТО | AS15: =IF(AD15>=E15,"ИЗУЧЕНО",IF(AND(OR(F15="",SUMIF($A$11:$A$50,F15,AD$11:AD$50)>=SUMIF($A$11:$A$50,F15,$E$11:$E$50)),OR(G15="",SUMIF($A$11:$A$50,G15,AD$11:AD$50)>=SUMIF($A$11:$A$50,G15,$E$11:$E$50)),OR(H15="",SUMIF($A$11:$A$50,H15,AD$11:AD$50)>=SUMIF($A$11:$A$50,H15,$E$11:$E$50))),"ОТКРЫТО","ЗАКРЫТО")) -> ЗАКРЫТО | AT15: =IF(AE15>=E15,"ИЗУЧЕНО",IF(AND(OR(F15="",SUMIF($A$11:$A$50,F15,AE$11:AE$50)>=SUMIF($A$11:$A$50,F15,$E$11:$E$50)),OR(G15="",SUMIF($A$11:$A$50,G15,AE$11:AE$50)>=SUMIF($A$11:$A$50,G15,$E$11:$E$50)),OR(H15="",SUMIF($A$11:$A$50,H15,AE$11:AE$50)>=SUMIF($A$11:$A$50,H15,$E$11:$E$50))),"ОТКРЫТО","ЗАКРЫТО")) -> ЗАКРЫТО | AU15: =IF(AF15>=E15,"ИЗУЧЕНО",IF(AND(OR(F15="",SUMIF($A$11:$A$50,F15,AF$11:AF$50)>=SUMIF($A$11:$A$50,F15,$E$11:$E$50)),OR(G15="",SUMIF($A$11:$A$50,G15,AF$11:AF$50)>=SUMIF($A$11:$A$50,G15,$E$11:$E$50)),OR(H15="",SUMIF($A$11:$A$50,H15,AF$11:AF$50)>=SUMIF($A$11:$A$50,H15,$E$11:$E$50))),"ОТКРЫТО","ЗАКРЫТО")) -> ЗАКРЫТО | AV15: =IF(AG15>=E15,"ИЗУЧЕНО",IF(AND(OR(F15="",SUMIF($A$11:$A$50,F15,AG$11:AG$50)>=SUMIF($A$11:$A$50,F15,$E$11:$E$50)),OR(G15="",SUMIF($A$11:$A$50,G15,AG$11:AG$50)>=SUMIF($A$11:$A$50,G15,$E$11:$E$50)),OR(H15="",SUMIF($A$11:$A$50,H15,AG$11:AG$50)>=SUMIF($A$11:$A$50,H15,$E$11:$E$50))),"ОТКРЫТО","ЗАКРЫТО")) -> ЗАКРЫТО | AW15: =IF(AH15>=E15,"ИЗУЧЕНО",IF(AND(OR(F15="",SUMIF($A$11:$A$50,F15,AH$11:AH$50)>=SUMIF($A$11:$A$50,F15,$E$11:$E$50)),OR(G15="",SUMIF($A$11:$A$50,G15,AH$11:AH$50)>=SUMIF($A$11:$A$50,G15,$E$11:$E$50)),OR(H15="",SUMIF($A$11:$A$50,H15,AH$11:AH$50)>=SUMIF($A$11:$A$50,H15,$E$11:$E$50))),"ОТКРЫТО","ЗАКРЫТО")) -> ЗАКРЫТО | AX15: =IF(AI15>=E15,"ИЗУЧЕНО",IF(AND(OR(F15="",SUMIF($A$11:$A$50,F15,AI$11:AI$50)>=SUMIF($A$11:$A$50,F15,$E$11:$E$50)),OR(G15="",SUMIF($A$11:$A$50,G15,AI$11:AI$50)>=SUMIF($A$11:$A$50,G15,$E$11:$E$50)),OR(H15="",SUMIF($A$11:$A$50,H15,AI$11:AI$50)>=SUMIF($A$11:$A$50,H15,$E$11:$E$50))),"ОТКРЫТО","ЗАКРЫТО")) -> ЗАКРЫТО | AY15: =IF(AJ15>=E15,"ИЗУЧЕНО",IF(AND(OR(F15="",SUMIF($A$11:$A$50,F15,AJ$11:AJ$50)>=SUMIF($A$11:$A$50,F15,$E$11:$E$50)),OR(G15="",SUMIF($A$11:$A$50,G15,AJ$11:AJ$50)>=SUMIF($A$11:$A$50,G15,$E$11:$E$50)),OR(H15="",SUMIF($A$11:$A$50,H15,AJ$11:AJ$50)>=SUMIF($A$11:$A$50,H15,$E$11:$E$50))),"ОТКРЫТО","ЗАКРЫТО")) -> ЗАКРЫТО | AZ15: =IF(AK15>=E15,"ИЗУЧЕНО",IF(AND(OR(F15="",SUMIF($A$11:$A$50,F15,AK$11:AK$50)>=SUMIF($A$11:$A$50,F15,$E$11:$E$50)),OR(G15="",SUMIF($A$11:$A$50,G15,AK$11:AK$50)>=SUMIF($A$11:$A$50,G15,$E$11:$E$50)),OR(H15="",SUMIF($A$11:$A$50,H15,AK$11:AK$50)>=SUMIF($A$11:$A$50,H15,$E$11:$E$50))),"ОТКРЫТО","ЗАКРЫТО")) -> ЗАКРЫТО | BA15: =IF(AL15>=E15,"ИЗУЧЕНО",IF(AND(OR(F15="",SUMIF($A$11:$A$50,F15,AL$11:AL$50)>=SUMIF($A$11:$A$50,F15,$E$11:$E$50)),OR(G15="",SUMIF($A$11:$A$50,G15,AL$11:AL$50)>=SUMIF($A$11:$A$50,G15,$E$11:$E$50)),OR(H15="",SUMIF($A$11:$A$50,H15,AL$11:AL$50)>=SUMIF($A$11:$A$50,H15,$E$11:$E$50))),"ОТКРЫТО","ЗАКРЫТО")) -> ЗАКРЫТО | BB15: =IF(AM15>=E15,"ИЗУЧЕНО",IF(AND(OR(F15="",SUMIF($A$11:$A$50,F15,AM$11:AM$50)>=SUMIF($A$11:$A$50,F15,$E$11:$E$50)),OR(G15="",SUMIF($A$11:$A$50,G15,AM$11:AM$50)>=SUMIF($A$11:$A$50,G15,$E$11:$E$50)),OR(H15="",SUMIF($A$11:$A$50,H15,AM$11:AM$50)>=SUMIF($A$11:$A$50,H15,$E$11:$E$50))),"ОТКРЫТО","ЗАКРЫТО")) -> ЗАКРЫТО | BC15: =IF(AN15>=E15,"ИЗУЧЕНО",IF(AND(OR(F15="",SUMIF($A$11:$A$50,F15,AN$11:AN$50)>=SUMIF($A$11:$A$50,F15,$E$11:$E$50)),OR(G15="",SUMIF($A$11:$A$50,G15,AN$11:AN$50)>=SUMIF($A$11:$A$50,G15,$E$11:$E$50)),OR(H15="",SUMIF($A$11:$A$50,H15,AN$11:AN$50)>=SUMIF($A$11:$A$50,H15,$E$11:$E$50))),"ОТКРЫТО","ЗАКРЫТО")) -> ЗАКРЫТО | BD15: =IF(AO15>=E15,"ИЗУЧЕНО",IF(AND(OR(F15="",SUMIF($A$11:$A$50,F15,AO$11:AO$50)>=SUMIF($A$11:$A$50,F15,$E$11:$E$50)),OR(G15="",SUMIF($A$11:$A$50,G15,AO$11:AO$50)>=SUMIF($A$11:$A$50,G15,$E$11:$E$50)),OR(H15="",SUMIF($A$11:$A$50,H15,AO$11:AO$50)>=SUMIF($A$11:$A$50,H15,$E$11:$E$50))),"ОТКРЫТО","ЗАКРЫТО")) -> ЗАКРЫТО | BE15: =IF(AP15>=E15,"ИЗУЧЕНО",IF(AND(OR(F15="",SUMIF($A$11:$A$50,F15,AP$11:AP$50)>=SUMIF($A$11:$A$50,F15,$E$11:$E$50)),OR(G15="",SUMIF($A$11:$A$50,G15,AP$11:AP$50)>=SUMIF($A$11:$A$50,G15,$E$11:$E$50)),OR(H15="",SUMIF($A$11:$A$50,H15,AP$11:AP$50)>=SUMIF($A$11:$A$50,H15,$E$11:$E$50))),"ОТКРЫТО","ЗАКРЫТО")) -> ЗАКРЫТО | BF15: =IF(AQ15>=E15,"ИЗУЧЕНО",IF(AND(OR(F15="",SUMIF($A$11:$A$50,F15,AQ$11:AQ$50)>=SUMIF($A$11:$A$50,F15,$E$11:$E$50)),OR(G15="",SUMIF($A$11:$A$50,G15,AQ$11:AQ$50)>=SUMIF($A$11:$A$50,G15,$E$11:$E$50)),OR(H15="",SUMIF($A$11:$A$50,H15,AQ$11:AQ$50)>=SUMIF($A$11:$A$50,H15,$E$11:$E$50))),"ОТКРЫТО","ЗАКРЫТО")) -> ЗАКРЫТО
A16: C6 | B16: Вычисления и аппаратная база | C16: V | D16: Новые вычислительные архитектуры | E16: 150 | F16: C5 | I16: Нейроморфные, вычислительно-памятные и иные постфоннеймановские архитектуры. | J16: Вычислительные компоненты +0,5; Математико-алгоритмические ресурсы +0,3; исследования ветви Модели +10% | K16: =SUMIF('Ход 2026'!$G$29:$G$38,$A16,'Ход 2026'!$I$29:$I$38) -> 0 | L16: =SUMIF('Ход 2027'!$G$29:$G$38,$A16,'Ход 2027'!$I$29:$I$38) -> 0 | M16: =SUMIF('Ход 2028'!$G$29:$G$38,$A16,'Ход 2028'!$I$29:$I$38) -> 0 | N16: =SUMIF('Ход 2029'!$G$29:$G$38,$A16,'Ход 2029'!$I$29:$I$38) -> 0 | O16: =SUMIF('Ход 2030'!$G$29:$G$38,$A16,'Ход 2030'!$I$29:$I$38) -> 0 | P16: =SUMIF('Ход 2031'!$G$29:$G$38,$A16,'Ход 2031'!$I$29:$I$38) -> 0 | Q16: =SUMIF('Ход 2032'!$G$29:$G$38,$A16,'Ход 2032'!$I$29:$I$38) -> 0 | R16: =SUMIF('Ход 2033'!$G$29:$G$38,$A16,'Ход 2033'!$I$29:$I$38) -> 0 | S16: =SUMIF('Ход 2034'!$G$29:$G$38,$A16,'Ход 2034'!$I$29:$I$38) -> 0 | T16: =SUMIF('Ход 2035'!$G$29:$G$38,$A16,'Ход 2035'!$I$29:$I$38) -> 0 | U16: =SUMIF('Ход 2036'!$G$29:$G$38,$A16,'Ход 2036'!$I$29:$I$38) -> 0 | V16: =SUMIF('Ход 2037'!$G$29:$G$38,$A16,'Ход 2037'!$I$29:$I$38) -> 0 | W16: =SUMIF('Ход 2038'!$G$29:$G$38,$A16,'Ход 2038'!$I$29:$I$38) -> 0 | X16: =SUMIF('Ход 2039'!$G$29:$G$38,$A16,'Ход 2039'!$I$29:$I$38) -> 0 | Y16: =SUMIF('Ход 2040'!$G$29:$G$38,$A16,'Ход 2040'!$I$29:$I$38) -> 0 | Z16: =SUM(K16:Y16) -> 0 | AA16: =MAX(0,E16-Z16) -> 150 | AB16: =BF16 -> ЗАКРЫТО | AC16: =SUM($K16:K16) -> 0 | AD16: =SUM($K16:L16) -> 0 | AE16: =SUM($K16:M16) -> 0 | AF16: =SUM($K16:N16) -> 0 | AG16: =SUM($K16:O16) -> 0 | AH16: =SUM($K16:P16) -> 0 | AI16: =SUM($K16:Q16) -> 0 | AJ16: =SUM($K16:R16) -> 0 | ... AQ16: =SUM($K16:Y16) -> 0 | AR16: =IF(AC16>=E16,"ИЗУЧЕНО",IF(AND(OR(F16="",SUMIF($A$11:$A$50,F16,AC$11:AC$50)>=SUMIF($A$11:$A$50,F16,$E$11:$E$50)),OR(G16="",SUMIF($A$11:$A$50,G16,AC$11:AC$50)>=SUMIF($A$11:$A$50,G16,$E$11:$E$50)),OR(H16="",SUMIF($A$11:$A$50,H16,AC$11:AC$50)>=SUMIF($A$11:$A$50,H16,$E$11:$E$50))),"ОТКРЫТО","ЗАКРЫТО")) -> ЗАКРЫТО | AS16: =IF(AD16>=E16,"ИЗУЧЕНО",IF(AND(OR(F16="",SUMIF($A$11:$A$50,F16,AD$11:AD$50)>=SUMIF($A$11:$A$50,F16,$E$11:$E$50)),OR(G16="",SUMIF($A$11:$A$50,G16,AD$11:AD$50)>=SUMIF($A$11:$A$50,G16,$E$11:$E$50)),OR(H16="",SUMIF($A$11:$A$50,H16,AD$11:AD$50)>=SUMIF($A$11:$A$50,H16,$E$11:$E$50))),"ОТКРЫТО","ЗАКРЫТО")) -> ЗАКРЫТО | AT16: =IF(AE16>=E16,"ИЗУЧЕНО",IF(AND(OR(F16="",SUMIF($A$11:$A$50,F16,AE$11:AE$50)>=SUMIF($A$11:$A$50,F16,$E$11:$E$50)),OR(G16="",SUMIF($A$11:$A$50,G16,AE$11:AE$50)>=SUMIF($A$11:$A$50,G16,$E$11:$E$50)),OR(H16="",SUMIF($A$11:$A$50,H16,AE$11:AE$50)>=SUMIF($A$11:$A$50,H16,$E$11:$E$50))),"ОТКРЫТО","ЗАКРЫТО")) -> ЗАКРЫТО | AU16: =IF(AF16>=E16,"ИЗУЧЕНО",IF(AND(OR(F16="",SUMIF($A$11:$A$50,F16,AF$11:AF$50)>=SUMIF($A$11:$A$50,F16,$E$11:$E$50)),OR(G16="",SUMIF($A$11:$A$50,G16,AF$11:AF$50)>=SUMIF($A$11:$A$50,G16,$E$11:$E$50)),OR(H16="",SUMIF($A$11:$A$50,H16,AF$11:AF$50)>=SUMIF($A$11:$A$50,H16,$E$11:$E$50))),"ОТКРЫТО","ЗАКРЫТО")) -> ЗАКРЫТО | AV16: =IF(AG16>=E16,"ИЗУЧЕНО",IF(AND(OR(F16="",SUMIF($A$11:$A$50,F16,AG$11:AG$50)>=SUMIF($A$11:$A$50,F16,$E$11:$E$50)),OR(G16="",SUMIF($A$11:$A$50,G16,AG$11:AG$50)>=SUMIF($A$11:$A$50,G16,$E$11:$E$50)),OR(H16="",SUMIF($A$11:$A$50,H16,AG$11:AG$50)>=SUMIF($A$11:$A$50,H16,$E$11:$E$50))),"ОТКРЫТО","ЗАКРЫТО")) -> ЗАКРЫТО | AW16: =IF(AH16>=E16,"ИЗУЧЕНО",IF(AND(OR(F16="",SUMIF($A$11:$A$50,F16,AH$11:AH$50)>=SUMIF($A$11:$A$50,F16,$E$11:$E$50)),OR(G16="",SUMIF($A$11:$A$50,G16,AH$11:AH$50)>=SUMIF($A$11:$A$50,G16,$E$11:$E$50)),OR(H16="",SUMIF($A$11:$A$50,H16,AH$11:AH$50)>=SUMIF($A$11:$A$50,H16,$E$11:$E$50))),"ОТКРЫТО","ЗАКРЫТО")) -> ЗАКРЫТО | AX16: =IF(AI16>=E16,"ИЗУЧЕНО",IF(AND(OR(F16="",SUMIF($A$11:$A$50,F16,AI$11:AI$50)>=SUMIF($A$11:$A$50,F16,$E$11:$E$50)),OR(G16="",SUMIF($A$11:$A$50,G16,AI$11:AI$50)>=SUMIF($A$11:$A$50,G16,$E$11:$E$50)),OR(H16="",SUMIF($A$11:$A$50,H16,AI$11:AI$50)>=SUMIF($A$11:$A$50,H16,$E$11:$E$50))),"ОТКРЫТО","ЗАКРЫТО")) -> ЗАКРЫТО | AY16: =IF(AJ16>=E16,"ИЗУЧЕНО",IF(AND(OR(F16="",SUMIF($A$11:$A$50,F16,AJ$11:AJ$50)>=SUMIF($A$11:$A$50,F16,$E$11:$E$50)),OR(G16="",SUMIF($A$11:$A$50,G16,AJ$11:AJ$50)>=SUMIF($A$11:$A$50,G16,$E$11:$E$50)),OR(H16="",SUMIF($A$11:$A$50,H16,AJ$11:AJ$50)>=SUMIF($A$11:$A$50,H16,$E$11:$E$50))),"ОТКРЫТО","ЗАКРЫТО")) -> ЗАКРЫТО | AZ16: =IF(AK16>=E16,"ИЗУЧЕНО",IF(AND(OR(F16="",SUMIF($A$11:$A$50,F16,AK$11:AK$50)>=SUMIF($A$11:$A$50,F16,$E$11:$E$50)),OR(G16="",SUMIF($A$11:$A$50,G16,AK$11:AK$50)>=SUMIF($A$11:$A$50,G16,$E$11:$E$50)),OR(H16="",SUMIF($A$11:$A$50,H16,AK$11:AK$50)>=SUMIF($A$11:$A$50,H16,$E$11:$E$50))),"ОТКРЫТО","ЗАКРЫТО")) -> ЗАКРЫТО | BA16: =IF(AL16>=E16,"ИЗУЧЕНО",IF(AND(OR(F16="",SUMIF($A$11:$A$50,F16,AL$11:AL$50)>=SUMIF($A$11:$A$50,F16,$E$11:$E$50)),OR(G16="",SUMIF($A$11:$A$50,G16,AL$11:AL$50)>=SUMIF($A$11:$A$50,G16,$E$11:$E$50)),OR(H16="",SUMIF($A$11:$A$50,H16,AL$11:AL$50)>=SUMIF($A$11:$A$50,H16,$E$11:$E$50))),"ОТКРЫТО","ЗАКРЫТО")) -> ЗАКРЫТО | BB16: =IF(AM16>=E16,"ИЗУЧЕНО",IF(AND(OR(F16="",SUMIF($A$11:$A$50,F16,AM$11:AM$50)>=SUMIF($A$11:$A$50,F16,$E$11:$E$50)),OR(G16="",SUMIF($A$11:$A$50,G16,AM$11:AM$50)>=SUMIF($A$11:$A$50,G16,$E$11:$E$50)),OR(H16="",SUMIF($A$11:$A$50,H16,AM$11:AM$50)>=SUMIF($A$11:$A$50,H16,$E$11:$E$50))),"ОТКРЫТО","ЗАКРЫТО")) -> ЗАКРЫТО | BC16: =IF(AN16>=E16,"ИЗУЧЕНО",IF(AND(OR(F16="",SUMIF($A$11:$A$50,F16,AN$11:AN$50)>=SUMIF($A$11:$A$50,F16,$E$11:$E$50)),OR(G16="",SUMIF($A$11:$A$50,G16,AN$11:AN$50)>=SUMIF($A$11:$A$50,G16,$E$11:$E$50)),OR(H16="",SUMIF($A$11:$A$50,H16,AN$11:AN$50)>=SUMIF($A$11:$A$50,H16,$E$11:$E$50))),"ОТКРЫТО","ЗАКРЫТО")) -> ЗАКРЫТО | BD16: =IF(AO16>=E16,"ИЗУЧЕНО",IF(AND(OR(F16="",SUMIF($A$11:$A$50,F16,AO$11:AO$50)>=SUMIF($A$11:$A$50,F16,$E$11:$E$50)),OR(G16="",SUMIF($A$11:$A$50,G16,AO$11:AO$50)>=SUMIF($A$11:$A$50,G16,$E$11:$E$50)),OR(H16="",SUMIF($A$11:$A$50,H16,AO$11:AO$50)>=SUMIF($A$11:$A$50,H16,$E$11:$E$50))),"ОТКРЫТО","ЗАКРЫТО")) -> ЗАКРЫТО | BE16: =IF(AP16>=E16,"ИЗУЧЕНО",IF(AND(OR(F16="",SUMIF($A$11:$A$50,F16,AP$11:AP$50)>=SUMIF($A$11:$A$50,F16,$E$11:$E$50)),OR(G16="",SUMIF($A$11:$A$50,G16,AP$11:AP$50)>=SUMIF($A$11:$A$50,G16,$E$11:$E$50)),OR(H16="",SUMIF($A$11:$A$50,H16,AP$11:AP$50)>=SUMIF($A$11:$A$50,H16,$E$11:$E$50))),"ОТКРЫТО","ЗАКРЫТО")) -> ЗАКРЫТО | BF16: =IF(AQ16>=E16,"ИЗУЧЕНО",IF(AND(OR(F16="",SUMIF($A$11:$A$50,F16,AQ$11:AQ$50)>=SUMIF($A$11:$A$50,F16,$E$11:$E$50)),OR(G16="",SUMIF($A$11:$A$50,G16,AQ$11:AQ$50)>=SUMIF($A$11:$A$50,G16,$E$11:$E$50)),OR(H16="",SUMIF($A$11:$A$50,H16,AQ$11:AQ$50)>=SUMIF($A$11:$A$50,H16,$E$11:$E$50))),"ОТКРЫТО","ЗАКРЫТО")) -> ЗАКРЫТО
A17: M1 | B17: Модели и алгоритмы | C17: I | D17: Эффективное обучение моделей | E17: 20 | I17: Улучшенные методы оптимизации, сжатия и обучения моделей. | J17: Методы построения моделей +0,2; их прирост +0,05/год | K17: =SUMIF('Ход 2026'!$G$29:$G$38,$A17,'Ход 2026'!$I$29:$I$38) -> 0 | L17: =SUMIF('Ход 2027'!$G$29:$G$38,$A17,'Ход 2027'!$I$29:$I$38) -> 0 | M17: =SUMIF('Ход 2028'!$G$29:$G$38,$A17,'Ход 2028'!$I$29:$I$38) -> 0 | N17: =SUMIF('Ход 2029'!$G$29:$G$38,$A17,'Ход 2029'!$I$29:$I$38) -> 0 | O17: =SUMIF('Ход 2030'!$G$29:$G$38,$A17,'Ход 2030'!$I$29:$I$38) -> 0 | P17: =SUMIF('Ход 2031'!$G$29:$G$38,$A17,'Ход 2031'!$I$29:$I$38) -> 0 | Q17: =SUMIF('Ход 2032'!$G$29:$G$38,$A17,'Ход 2032'!$I$29:$I$38) -> 0 | R17: =SUMIF('Ход 2033'!$G$29:$G$38,$A17,'Ход 2033'!$I$29:$I$38) -> 0 | S17: =SUMIF('Ход 2034'!$G$29:$G$38,$A17,'Ход 2034'!$I$29:$I$38) -> 0 | T17: =SUMIF('Ход 2035'!$G$29:$G$38,$A17,'Ход 2035'!$I$29:$I$38) -> 0 | U17: =SUMIF('Ход 2036'!$G$29:$G$38,$A17,'Ход 2036'!$I$29:$I$38) -> 0 | V17: =SUMIF('Ход 2037'!$G$29:$G$38,$A17,'Ход 2037'!$I$29:$I$38) -> 0 | W17: =SUMIF('Ход 2038'!$G$29:$G$38,$A17,'Ход 2038'!$I$29:$I$38) -> 0 | X17: =SUMIF('Ход 2039'!$G$29:$G$38,$A17,'Ход 2039'!$I$29:$I$38) -> 0 | Y17: =SUMIF('Ход 2040'!$G$29:$G$38,$A17,'Ход 2040'!$I$29:$I$38) -> 0 | Z17: =SUM(K17:Y17) -> 0 | AA17: =MAX(0,E17-Z17) -> 20 | AB17: =BF17 -> ОТКРЫТО | AC17: =SUM($K17:K17) -> 0 | AD17: =SUM($K17:L17) -> 0 | AE17: =SUM($K17:M17) -> 0 | AF17: =SUM($K17:N17) -> 0 | AG17: =SUM($K17:O17) -> 0 | AH17: =SUM($K17:P17) -> 0 | AI17: =SUM($K17:Q17) -> 0 | AJ17: =SUM($K17:R17) -> 0 | ... AQ17: =SUM($K17:Y17) -> 0 | AR17: =IF(AC17>=E17,"ИЗУЧЕНО",IF(AND(OR(F17="",SUMIF($A$11:$A$50,F17,AC$11:AC$50)>=SUMIF($A$11:$A$50,F17,$E$11:$E$50)),OR(G17="",SUMIF($A$11:$A$50,G17,AC$11:AC$50)>=SUMIF($A$11:$A$50,G17,$E$11:$E$50)),OR(H17="",SUMIF($A$11:$A$50,H17,AC$11:AC$50)>=SUMIF($A$11:$A$50,H17,$E$11:$E$50))),"ОТКРЫТО","ЗАКРЫТО")) -> ОТКРЫТО | AS17: =IF(AD17>=E17,"ИЗУЧЕНО",IF(AND(OR(F17="",SUMIF($A$11:$A$50,F17,AD$11:AD$50)>=SUMIF($A$11:$A$50,F17,$E$11:$E$50)),OR(G17="",SUMIF($A$11:$A$50,G17,AD$11:AD$50)>=SUMIF($A$11:$A$50,G17,$E$11:$E$50)),OR(H17="",SUMIF($A$11:$A$50,H17,AD$11:AD$50)>=SUMIF($A$11:$A$50,H17,$E$11:$E$50))),"ОТКРЫТО","ЗАКРЫТО")) -> ОТКРЫТО | AT17: =IF(AE17>=E17,"ИЗУЧЕНО",IF(AND(OR(F17="",SUMIF($A$11:$A$50,F17,AE$11:AE$50)>=SUMIF($A$11:$A$50,F17,$E$11:$E$50)),OR(G17="",SUMIF($A$11:$A$50,G17,AE$11:AE$50)>=SUMIF($A$11:$A$50,G17,$E$11:$E$50)),OR(H17="",SUMIF($A$11:$A$50,H17,AE$11:AE$50)>=SUMIF($A$11:$A$50,H17,$E$11:$E$50))),"ОТКРЫТО","ЗАКРЫТО")) -> ОТКРЫТО | AU17: =IF(AF17>=E17,"ИЗУЧЕНО",IF(AND(OR(F17="",SUMIF($A$11:$A$50,F17,AF$11:AF$50)>=SUMIF($A$11:$A$50,F17,$E$11:$E$50)),OR(G17="",SUMIF($A$11:$A$50,G17,AF$11:AF$50)>=SUMIF($A$11:$A$50,G17,$E$11:$E$50)),OR(H17="",SUMIF($A$11:$A$50,H17,AF$11:AF$50)>=SUMIF($A$11:$A$50,H17,$E$11:$E$50))),"ОТКРЫТО","ЗАКРЫТО")) -> ОТКРЫТО | AV17: =IF(AG17>=E17,"ИЗУЧЕНО",IF(AND(OR(F17="",SUMIF($A$11:$A$50,F17,AG$11:AG$50)>=SUMIF($A$11:$A$50,F17,$E$11:$E$50)),OR(G17="",SUMIF($A$11:$A$50,G17,AG$11:AG$50)>=SUMIF($A$11:$A$50,G17,$E$11:$E$50)),OR(H17="",SUMIF($A$11:$A$50,H17,AG$11:AG$50)>=SUMIF($A$11:$A$50,H17,$E$11:$E$50))),"ОТКРЫТО","ЗАКРЫТО")) -> ОТКРЫТО | AW17: =IF(AH17>=E17,"ИЗУЧЕНО",IF(AND(OR(F17="",SUMIF($A$11:$A$50,F17,AH$11:AH$50)>=SUMIF($A$11:$A$50,F17,$E$11:$E$50)),OR(G17="",SUMIF($A$11:$A$50,G17,AH$11:AH$50)>=SUMIF($A$11:$A$50,G17,$E$11:$E$50)),OR(H17="",SUMIF($A$11:$A$50,H17,AH$11:AH$50)>=SUMIF($A$11:$A$50,H17,$E$11:$E$50))),"ОТКРЫТО","ЗАКРЫТО")) -> ОТКРЫТО | AX17: =IF(AI17>=E17,"ИЗУЧЕНО",IF(AND(OR(F17="",SUMIF($A$11:$A$50,F17,AI$11:AI$50)>=SUMIF($A$11:$A$50,F17,$E$11:$E$50)),OR(G17="",SUMIF($A$11:$A$50,G17,AI$11:AI$50)>=SUMIF($A$11:$A$50,G17,$E$11:$E$50)),OR(H17="",SUMIF($A$11:$A$50,H17,AI$11:AI$50)>=SUMIF($A$11:$A$50,H17,$E$11:$E$50))),"ОТКРЫТО","ЗАКРЫТО")) -> ОТКРЫТО | AY17: =IF(AJ17>=E17,"ИЗУЧЕНО",IF(AND(OR(F17="",SUMIF($A$11:$A$50,F17,AJ$11:AJ$50)>=SUMIF($A$11:$A$50,F17,$E$11:$E$50)),OR(G17="",SUMIF($A$11:$A$50,G17,AJ$11:AJ$50)>=SUMIF($A$11:$A$50,G17,$E$11:$E$50)),OR(H17="",SUMIF($A$11:$A$50,H17,AJ$11:AJ$50)>=SUMIF($A$11:$A$50,H17,$E$11:$E$50))),"ОТКРЫТО","ЗАКРЫТО")) -> ОТКРЫТО | AZ17: =IF(AK17>=E17,"ИЗУЧЕНО",IF(AND(OR(F17="",SUMIF($A$11:$A$50,F17,AK$11:AK$50)>=SUMIF($A$11:$A$50,F17,$E$11:$E$50)),OR(G17="",SUMIF($A$11:$A$50,G17,AK$11:AK$50)>=SUMIF($A$11:$A$50,G17,$E$11:$E$50)),OR(H17="",SUMIF($A$11:$A$50,H17,AK$11:AK$50)>=SUMIF($A$11:$A$50,H17,$E$11:$E$50))),"ОТКРЫТО","ЗАКРЫТО")) -> ОТКРЫТО | BA17: =IF(AL17>=E17,"ИЗУЧЕНО",IF(AND(OR(F17="",SUMIF($A$11:$A$50,F17,AL$11:AL$50)>=SUMIF($A$11:$A$50,F17,$E$11:$E$50)),OR(G17="",SUMIF($A$11:$A$50,G17,AL$11:AL$50)>=SUMIF($A$11:$A$50,G17,$E$11:$E$50)),OR(H17="",SUMIF($A$11:$A$50,H17,AL$11:AL$50)>=SUMIF($A$11:$A$50,H17,$E$11:$E$50))),"ОТКРЫТО","ЗАКРЫТО")) -> ОТКРЫТО | BB17: =IF(AM17>=E17,"ИЗУЧЕНО",IF(AND(OR(F17="",SUMIF($A$11:$A$50,F17,AM$11:AM$50)>=SUMIF($A$11:$A$50,F17,$E$11:$E$50)),OR(G17="",SUMIF($A$11:$A$50,G17,AM$11:AM$50)>=SUMIF($A$11:$A$50,G17,$E$11:$E$50)),OR(H17="",SUMIF($A$11:$A$50,H17,AM$11:AM$50)>=SUMIF($A$11:$A$50,H17,$E$11:$E$50))),"ОТКРЫТО","ЗАКРЫТО")) -> ОТКРЫТО | BC17: =IF(AN17>=E17,"ИЗУЧЕНО",IF(AND(OR(F17="",SUMIF($A$11:$A$50,F17,AN$11:AN$50)>=SUMIF($A$11:$A$50,F17,$E$11:$E$50)),OR(G17="",SUMIF($A$11:$A$50,G17,AN$11:AN$50)>=SUMIF($A$11:$A$50,G17,$E$11:$E$50)),OR(H17="",SUMIF($A$11:$A$50,H17,AN$11:AN$50)>=SUMIF($A$11:$A$50,H17,$E$11:$E$50))),"ОТКРЫТО","ЗАКРЫТО")) -> ОТКРЫТО | BD17: =IF(AO17>=E17,"ИЗУЧЕНО",IF(AND(OR(F17="",SUMIF($A$11:$A$50,F17,AO$11:AO$50)>=SUMIF($A$11:$A$50,F17,$E$11:$E$50)),OR(G17="",SUMIF($A$11:$A$50,G17,AO$11:AO$50)>=SUMIF($A$11:$A$50,G17,$E$11:$E$50)),OR(H17="",SUMIF($A$11:$A$50,H17,AO$11:AO$50)>=SUMIF($A$11:$A$50,H17,$E$11:$E$50))),"ОТКРЫТО","ЗАКРЫТО")) -> ОТКРЫТО | BE17: =IF(AP17>=E17,"ИЗУЧЕНО",IF(AND(OR(F17="",SUMIF($A$11:$A$50,F17,AP$11:AP$50)>=SUMIF($A$11:$A$50,F17,$E$11:$E$50)),OR(G17="",SUMIF($A$11:$A$50,G17,AP$11:AP$50)>=SUMIF($A$11:$A$50,G17,$E$11:$E$50)),OR(H17="",SUMIF($A$11:$A$50,H17,AP$11:AP$50)>=SUMIF($A$11:$A$50,H17,$E$11:$E$50))),"ОТКРЫТО","ЗАКРЫТО")) -> ОТКРЫТО | BF17: =IF(AQ17>=E17,"ИЗУЧЕНО",IF(AND(OR(F17="",SUMIF($A$11:$A$50,F17,AQ$11:AQ$50)>=SUMIF($A$11:$A$50,F17,$E$11:$E$50)),OR(G17="",SUMIF($A$11:$A$50,G17,AQ$11:AQ$50)>=SUMIF($A$11:$A$50,G17,$E$11:$E$50)),OR(H17="",SUMIF($A$11:$A$50,H17,AQ$11:AQ$50)>=SUMIF($A$11:$A$50,H17,$E$11:$E$50))),"ОТКРЫТО","ЗАКРЫТО")) -> ОТКРЫТО
A18: M2 | B18: Модели и алгоритмы | C18: II | D18: Мультимодальные фундаментальные модели | E18: 40 | F18: M1 | I18: Совместная работа с текстом, изображениями, звуком, видео и другими модальностями. | J18: Модельные ресурсы +0,3; прирост Принятия ИИ +0,05/год; атака Аполлона +10% | K18: =SUMIF('Ход 2026'!$G$29:$G$38,$A18,'Ход 2026'!$I$29:$I$38) -> 0 | L18: =SUMIF('Ход 2027'!$G$29:$G$38,$A18,'Ход 2027'!$I$29:$I$38) -> 0 | M18: =SUMIF('Ход 2028'!$G$29:$G$38,$A18,'Ход 2028'!$I$29:$I$38) -> 0 | N18: =SUMIF('Ход 2029'!$G$29:$G$38,$A18,'Ход 2029'!$I$29:$I$38) -> 0 | O18: =SUMIF('Ход 2030'!$G$29:$G$38,$A18,'Ход 2030'!$I$29:$I$38) -> 0 | P18: =SUMIF('Ход 2031'!$G$29:$G$38,$A18,'Ход 2031'!$I$29:$I$38) -> 0 | Q18: =SUMIF('Ход 2032'!$G$29:$G$38,$A18,'Ход 2032'!$I$29:$I$38) -> 0 | R18: =SUMIF('Ход 2033'!$G$29:$G$38,$A18,'Ход 2033'!$I$29:$I$38) -> 0 | S18: =SUMIF('Ход 2034'!$G$29:$G$38,$A18,'Ход 2034'!$I$29:$I$38) -> 0 | T18: =SUMIF('Ход 2035'!$G$29:$G$38,$A18,'Ход 2035'!$I$29:$I$38) -> 0 | U18: =SUMIF('Ход 2036'!$G$29:$G$38,$A18,'Ход 2036'!$I$29:$I$38) -> 0 | V18: =SUMIF('Ход 2037'!$G$29:$G$38,$A18,'Ход 2037'!$I$29:$I$38) -> 0 | W18: =SUMIF('Ход 2038'!$G$29:$G$38,$A18,'Ход 2038'!$I$29:$I$38) -> 0 | X18: =SUMIF('Ход 2039'!$G$29:$G$38,$A18,'Ход 2039'!$I$29:$I$38) -> 0 | Y18: =SUMIF('Ход 2040'!$G$29:$G$38,$A18,'Ход 2040'!$I$29:$I$38) -> 0 | Z18: =SUM(K18:Y18) -> 0 | AA18: =MAX(0,E18-Z18) -> 40 | AB18: =BF18 -> ЗАКРЫТО | AC18: =SUM($K18:K18) -> 0 | AD18: =SUM($K18:L18) -> 0 | AE18: =SUM($K18:M18) -> 0 | AF18: =SUM($K18:N18) -> 0 | AG18: =SUM($K18:O18) -> 0 | AH18: =SUM($K18:P18) -> 0 | AI18: =SUM($K18:Q18) -> 0 | AJ18: =SUM($K18:R18) -> 0 | ... AQ18: =SUM($K18:Y18) -> 0 | AR18: =IF(AC18>=E18,"ИЗУЧЕНО",IF(AND(OR(F18="",SUMIF($A$11:$A$50,F18,AC$11:AC$50)>=SUMIF($A$11:$A$50,F18,$E$11:$E$50)),OR(G18="",SUMIF($A$11:$A$50,G18,AC$11:AC$50)>=SUMIF($A$11:$A$50,G18,$E$11:$E$50)),OR(H18="",SUMIF($A$11:$A$50,H18,AC$11:AC$50)>=SUMIF($A$11:$A$50,H18,$E$11:$E$50))),"ОТКРЫТО","ЗАКРЫТО")) -> ЗАКРЫТО | AS18: =IF(AD18>=E18,"ИЗУЧЕНО",IF(AND(OR(F18="",SUMIF($A$11:$A$50,F18,AD$11:AD$50)>=SUMIF($A$11:$A$50,F18,$E$11:$E$50)),OR(G18="",SUMIF($A$11:$A$50,G18,AD$11:AD$50)>=SUMIF($A$11:$A$50,G18,$E$11:$E$50)),OR(H18="",SUMIF($A$11:$A$50,H18,AD$11:AD$50)>=SUMIF($A$11:$A$50,H18,$E$11:$E$50))),"ОТКРЫТО","ЗАКРЫТО")) -> ЗАКРЫТО | AT18: =IF(AE18>=E18,"ИЗУЧЕНО",IF(AND(OR(F18="",SUMIF($A$11:$A$50,F18,AE$11:AE$50)>=SUMIF($A$11:$A$50,F18,$E$11:$E$50)),OR(G18="",SUMIF($A$11:$A$50,G18,AE$11:AE$50)>=SUMIF($A$11:$A$50,G18,$E$11:$E$50)),OR(H18="",SUMIF($A$11:$A$50,H18,AE$11:AE$50)>=SUMIF($A$11:$A$50,H18,$E$11:$E$50))),"ОТКРЫТО","ЗАКРЫТО")) -> ЗАКРЫТО | AU18: =IF(AF18>=E18,"ИЗУЧЕНО",IF(AND(OR(F18="",SUMIF($A$11:$A$50,F18,AF$11:AF$50)>=SUMIF($A$11:$A$50,F18,$E$11:$E$50)),OR(G18="",SUMIF($A$11:$A$50,G18,AF$11:AF$50)>=SUMIF($A$11:$A$50,G18,$E$11:$E$50)),OR(H18="",SUMIF($A$11:$A$50,H18,AF$11:AF$50)>=SUMIF($A$11:$A$50,H18,$E$11:$E$50))),"ОТКРЫТО","ЗАКРЫТО")) -> ЗАКРЫТО | AV18: =IF(AG18>=E18,"ИЗУЧЕНО",IF(AND(OR(F18="",SUMIF($A$11:$A$50,F18,AG$11:AG$50)>=SUMIF($A$11:$A$50,F18,$E$11:$E$50)),OR(G18="",SUMIF($A$11:$A$50,G18,AG$11:AG$50)>=SUMIF($A$11:$A$50,G18,$E$11:$E$50)),OR(H18="",SUMIF($A$11:$A$50,H18,AG$11:AG$50)>=SUMIF($A$11:$A$50,H18,$E$11:$E$50))),"ОТКРЫТО","ЗАКРЫТО")) -> ЗАКРЫТО | AW18: =IF(AH18>=E18,"ИЗУЧЕНО",IF(AND(OR(F18="",SUMIF($A$11:$A$50,F18,AH$11:AH$50)>=SUMIF($A$11:$A$50,F18,$E$11:$E$50)),OR(G18="",SUMIF($A$11:$A$50,G18,AH$11:AH$50)>=SUMIF($A$11:$A$50,G18,$E$11:$E$50)),OR(H18="",SUMIF($A$11:$A$50,H18,AH$11:AH$50)>=SUMIF($A$11:$A$50,H18,$E$11:$E$50))),"ОТКРЫТО","ЗАКРЫТО")) -> ЗАКРЫТО | AX18: =IF(AI18>=E18,"ИЗУЧЕНО",IF(AND(OR(F18="",SUMIF($A$11:$A$50,F18,AI$11:AI$50)>=SUMIF($A$11:$A$50,F18,$E$11:$E$50)),OR(G18="",SUMIF($A$11:$A$50,G18,AI$11:AI$50)>=SUMIF($A$11:$A$50,G18,$E$11:$E$50)),OR(H18="",SUMIF($A$11:$A$50,H18,AI$11:AI$50)>=SUMIF($A$11:$A$50,H18,$E$11:$E$50))),"ОТКРЫТО","ЗАКРЫТО")) -> ЗАКРЫТО | AY18: =IF(AJ18>=E18,"ИЗУЧЕНО",IF(AND(OR(F18="",SUMIF($A$11:$A$50,F18,AJ$11:AJ$50)>=SUMIF($A$11:$A$50,F18,$E$11:$E$50)),OR(G18="",SUMIF($A$11:$A$50,G18,AJ$11:AJ$50)>=SUMIF($A$11:$A$50,G18,$E$11:$E$50)),OR(H18="",SUMIF($A$11:$A$50,H18,AJ$11:AJ$50)>=SUMIF($A$11:$A$50,H18,$E$11:$E$50))),"ОТКРЫТО","ЗАКРЫТО")) -> ЗАКРЫТО | AZ18: =IF(AK18>=E18,"ИЗУЧЕНО",IF(AND(OR(F18="",SUMIF($A$11:$A$50,F18,AK$11:AK$50)>=SUMIF($A$11:$A$50,F18,$E$11:$E$50)),OR(G18="",SUMIF($A$11:$A$50,G18,AK$11:AK$50)>=SUMIF($A$11:$A$50,G18,$E$11:$E$50)),OR(H18="",SUMIF($A$11:$A$50,H18,AK$11:AK$50)>=SUMIF($A$11:$A$50,H18,$E$11:$E$50))),"ОТКРЫТО","ЗАКРЫТО")) -> ЗАКРЫТО | BA18: =IF(AL18>=E18,"ИЗУЧЕНО",IF(AND(OR(F18="",SUMIF($A$11:$A$50,F18,AL$11:AL$50)>=SUMIF($A$11:$A$50,F18,$E$11:$E$50)),OR(G18="",SUMIF($A$11:$A$50,G18,AL$11:AL$50)>=SUMIF($A$11:$A$50,G18,$E$11:$E$50)),OR(H18="",SUMIF($A$11:$A$50,H18,AL$11:AL$50)>=SUMIF($A$11:$A$50,H18,$E$11:$E$50))),"ОТКРЫТО","ЗАКРЫТО")) -> ЗАКРЫТО | BB18: =IF(AM18>=E18,"ИЗУЧЕНО",IF(AND(OR(F18="",SUMIF($A$11:$A$50,F18,AM$11:AM$50)>=SUMIF($A$11:$A$50,F18,$E$11:$E$50)),OR(G18="",SUMIF($A$11:$A$50,G18,AM$11:AM$50)>=SUMIF($A$11:$A$50,G18,$E$11:$E$50)),OR(H18="",SUMIF($A$11:$A$50,H18,AM$11:AM$50)>=SUMIF($A$11:$A$50,H18,$E$11:$E$50))),"ОТКРЫТО","ЗАКРЫТО")) -> ЗАКРЫТО | BC18: =IF(AN18>=E18,"ИЗУЧЕНО",IF(AND(OR(F18="",SUMIF($A$11:$A$50,F18,AN$11:AN$50)>=SUMIF($A$11:$A$50,F18,$E$11:$E$50)),OR(G18="",SUMIF($A$11:$A$50,G18,AN$11:AN$50)>=SUMIF($A$11:$A$50,G18,$E$11:$E$50)),OR(H18="",SUMIF($A$11:$A$50,H18,AN$11:AN$50)>=SUMIF($A$11:$A$50,H18,$E$11:$E$50))),"ОТКРЫТО","ЗАКРЫТО")) -> ЗАКРЫТО | BD18: =IF(AO18>=E18,"ИЗУЧЕНО",IF(AND(OR(F18="",SUMIF($A$11:$A$50,F18,AO$11:AO$50)>=SUMIF($A$11:$A$50,F18,$E$11:$E$50)),OR(G18="",SUMIF($A$11:$A$50,G18,AO$11:AO$50)>=SUMIF($A$11:$A$50,G18,$E$11:$E$50)),OR(H18="",SUMIF($A$11:$A$50,H18,AO$11:AO$50)>=SUMIF($A$11:$A$50,H18,$E$11:$E$50))),"ОТКРЫТО","ЗАКРЫТО")) -> ЗАКРЫТО | BE18: =IF(AP18>=E18,"ИЗУЧЕНО",IF(AND(OR(F18="",SUMIF($A$11:$A$50,F18,AP$11:AP$50)>=SUMIF($A$11:$A$50,F18,$E$11:$E$50)),OR(G18="",SUMIF($A$11:$A$50,G18,AP$11:AP$50)>=SUMIF($A$11:$A$50,G18,$E$11:$E$50)),OR(H18="",SUMIF($A$11:$A$50,H18,AP$11:AP$50)>=SUMIF($A$11:$A$50,H18,$E$11:$E$50))),"ОТКРЫТО","ЗАКРЫТО")) -> ЗАКРЫТО | BF18: =IF(AQ18>=E18,"ИЗУЧЕНО",IF(AND(OR(F18="",SUMIF($A$11:$A$50,F18,AQ$11:AQ$50)>=SUMIF($A$11:$A$50,F18,$E$11:$E$50)),OR(G18="",SUMIF($A$11:$A$50,G18,AQ$11:AQ$50)>=SUMIF($A$11:$A$50,G18,$E$11:$E$50)),OR(H18="",SUMIF($A$11:$A$50,H18,AQ$11:AQ$50)>=SUMIF($A$11:$A$50,H18,$E$11:$E$50))),"ОТКРЫТО","ЗАКРЫТО")) -> ЗАКРЫТО
A19: M3 | B19: Модели и алгоритмы | C19: II | D19: Модели рассуждения и планирования | E19: 45 | F19: M1 | I19: Многошаговое решение задач, планирование и проверка промежуточных результатов. | J19: Методы построения моделей +0,3; прирост Познания +0,08/год | K19: =SUMIF('Ход 2026'!$G$29:$G$38,$A19,'Ход 2026'!$I$29:$I$38) -> 0 | L19: =SUMIF('Ход 2027'!$G$29:$G$38,$A19,'Ход 2027'!$I$29:$I$38) -> 0 | M19: =SUMIF('Ход 2028'!$G$29:$G$38,$A19,'Ход 2028'!$I$29:$I$38) -> 0 | N19: =SUMIF('Ход 2029'!$G$29:$G$38,$A19,'Ход 2029'!$I$29:$I$38) -> 0 | O19: =SUMIF('Ход 2030'!$G$29:$G$38,$A19,'Ход 2030'!$I$29:$I$38) -> 0 | P19: =SUMIF('Ход 2031'!$G$29:$G$38,$A19,'Ход 2031'!$I$29:$I$38) -> 0 | Q19: =SUMIF('Ход 2032'!$G$29:$G$38,$A19,'Ход 2032'!$I$29:$I$38) -> 0 | R19: =SUMIF('Ход 2033'!$G$29:$G$38,$A19,'Ход 2033'!$I$29:$I$38) -> 0 | S19: =SUMIF('Ход 2034'!$G$29:$G$38,$A19,'Ход 2034'!$I$29:$I$38) -> 0 | T19: =SUMIF('Ход 2035'!$G$29:$G$38,$A19,'Ход 2035'!$I$29:$I$38) -> 0 | U19: =SUMIF('Ход 2036'!$G$29:$G$38,$A19,'Ход 2036'!$I$29:$I$38) -> 0 | V19: =SUMIF('Ход 2037'!$G$29:$G$38,$A19,'Ход 2037'!$I$29:$I$38) -> 0 | W19: =SUMIF('Ход 2038'!$G$29:$G$38,$A19,'Ход 2038'!$I$29:$I$38) -> 0 | X19: =SUMIF('Ход 2039'!$G$29:$G$38,$A19,'Ход 2039'!$I$29:$I$38) -> 0 | Y19: =SUMIF('Ход 2040'!$G$29:$G$38,$A19,'Ход 2040'!$I$29:$I$38) -> 0 | Z19: =SUM(K19:Y19) -> 0 | AA19: =MAX(0,E19-Z19) -> 45 | AB19: =BF19 -> ЗАКРЫТО | AC19: =SUM($K19:K19) -> 0 | AD19: =SUM($K19:L19) -> 0 | AE19: =SUM($K19:M19) -> 0 | AF19: =SUM($K19:N19) -> 0 | AG19: =SUM($K19:O19) -> 0 | AH19: =SUM($K19:P19) -> 0 | AI19: =SUM($K19:Q19) -> 0 | AJ19: =SUM($K19:R19) -> 0 | ... AQ19: =SUM($K19:Y19) -> 0 | AR19: =IF(AC19>=E19,"ИЗУЧЕНО",IF(AND(OR(F19="",SUMIF($A$11:$A$50,F19,AC$11:AC$50)>=SUMIF($A$11:$A$50,F19,$E$11:$E$50)),OR(G19="",SUMIF($A$11:$A$50,G19,AC$11:AC$50)>=SUMIF($A$11:$A$50,G19,$E$11:$E$50)),OR(H19="",SUMIF($A$11:$A$50,H19,AC$11:AC$50)>=SUMIF($A$11:$A$50,H19,$E$11:$E$50))),"ОТКРЫТО","ЗАКРЫТО")) -> ЗАКРЫТО | AS19: =IF(AD19>=E19,"ИЗУЧЕНО",IF(AND(OR(F19="",SUMIF($A$11:$A$50,F19,AD$11:AD$50)>=SUMIF($A$11:$A$50,F19,$E$11:$E$50)),OR(G19="",SUMIF($A$11:$A$50,G19,AD$11:AD$50)>=SUMIF($A$11:$A$50,G19,$E$11:$E$50)),OR(H19="",SUMIF($A$11:$A$50,H19,AD$11:AD$50)>=SUMIF($A$11:$A$50,H19,$E$11:$E$50))),"ОТКРЫТО","ЗАКРЫТО")) -> ЗАКРЫТО | AT19: =IF(AE19>=E19,"ИЗУЧЕНО",IF(AND(OR(F19="",SUMIF($A$11:$A$50,F19,AE$11:AE$50)>=SUMIF($A$11:$A$50,F19,$E$11:$E$50)),OR(G19="",SUMIF($A$11:$A$50,G19,AE$11:AE$50)>=SUMIF($A$11:$A$50,G19,$E$11:$E$50)),OR(H19="",SUMIF($A$11:$A$50,H19,AE$11:AE$50)>=SUMIF($A$11:$A$50,H19,$E$11:$E$50))),"ОТКРЫТО","ЗАКРЫТО")) -> ЗАКРЫТО | AU19: =IF(AF19>=E19,"ИЗУЧЕНО",IF(AND(OR(F19="",SUMIF($A$11:$A$50,F19,AF$11:AF$50)>=SUMIF($A$11:$A$50,F19,$E$11:$E$50)),OR(G19="",SUMIF($A$11:$A$50,G19,AF$11:AF$50)>=SUMIF($A$11:$A$50,G19,$E$11:$E$50)),OR(H19="",SUMIF($A$11:$A$50,H19,AF$11:AF$50)>=SUMIF($A$11:$A$50,H19,$E$11:$E$50))),"ОТКРЫТО","ЗАКРЫТО")) -> ЗАКРЫТО | AV19: =IF(AG19>=E19,"ИЗУЧЕНО",IF(AND(OR(F19="",SUMIF($A$11:$A$50,F19,AG$11:AG$50)>=SUMIF($A$11:$A$50,F19,$E$11:$E$50)),OR(G19="",SUMIF($A$11:$A$50,G19,AG$11:AG$50)>=SUMIF($A$11:$A$50,G19,$E$11:$E$50)),OR(H19="",SUMIF($A$11:$A$50,H19,AG$11:AG$50)>=SUMIF($A$11:$A$50,H19,$E$11:$E$50))),"ОТКРЫТО","ЗАКРЫТО")) -> ЗАКРЫТО | AW19: =IF(AH19>=E19,"ИЗУЧЕНО",IF(AND(OR(F19="",SUMIF($A$11:$A$50,F19,AH$11:AH$50)>=SUMIF($A$11:$A$50,F19,$E$11:$E$50)),OR(G19="",SUMIF($A$11:$A$50,G19,AH$11:AH$50)>=SUMIF($A$11:$A$50,G19,$E$11:$E$50)),OR(H19="",SUMIF($A$11:$A$50,H19,AH$11:AH$50)>=SUMIF($A$11:$A$50,H19,$E$11:$E$50))),"ОТКРЫТО","ЗАКРЫТО")) -> ЗАКРЫТО | AX19: =IF(AI19>=E19,"ИЗУЧЕНО",IF(AND(OR(F19="",SUMIF($A$11:$A$50,F19,AI$11:AI$50)>=SUMIF($A$11:$A$50,F19,$E$11:$E$50)),OR(G19="",SUMIF($A$11:$A$50,G19,AI$11:AI$50)>=SUMIF($A$11:$A$50,G19,$E$11:$E$50)),OR(H19="",SUMIF($A$11:$A$50,H19,AI$11:AI$50)>=SUMIF($A$11:$A$50,H19,$E$11:$E$50))),"ОТКРЫТО","ЗАКРЫТО")) -> ЗАКРЫТО | AY19: =IF(AJ19>=E19,"ИЗУЧЕНО",IF(AND(OR(F19="",SUMIF($A$11:$A$50,F19,AJ$11:AJ$50)>=SUMIF($A$11:$A$50,F19,$E$11:$E$50)),OR(G19="",SUMIF($A$11:$A$50,G19,AJ$11:AJ$50)>=SUMIF($A$11:$A$50,G19,$E$11:$E$50)),OR(H19="",SUMIF($A$11:$A$50,H19,AJ$11:AJ$50)>=SUMIF($A$11:$A$50,H19,$E$11:$E$50))),"ОТКРЫТО","ЗАКРЫТО")) -> ЗАКРЫТО | AZ19: =IF(AK19>=E19,"ИЗУЧЕНО",IF(AND(OR(F19="",SUMIF($A$11:$A$50,F19,AK$11:AK$50)>=SUMIF($A$11:$A$50,F19,$E$11:$E$50)),OR(G19="",SUMIF($A$11:$A$50,G19,AK$11:AK$50)>=SUMIF($A$11:$A$50,G19,$E$11:$E$50)),OR(H19="",SUMIF($A$11:$A$50,H19,AK$11:AK$50)>=SUMIF($A$11:$A$50,H19,$E$11:$E$50))),"ОТКРЫТО","ЗАКРЫТО")) -> ЗАКРЫТО | BA19: =IF(AL19>=E19,"ИЗУЧЕНО",IF(AND(OR(F19="",SUMIF($A$11:$A$50,F19,AL$11:AL$50)>=SUMIF($A$11:$A$50,F19,$E$11:$E$50)),OR(G19="",SUMIF($A$11:$A$50,G19,AL$11:AL$50)>=SUMIF($A$11:$A$50,G19,$E$11:$E$50)),OR(H19="",SUMIF($A$11:$A$50,H19,AL$11:AL$50)>=SUMIF($A$11:$A$50,H19,$E$11:$E$50))),"ОТКРЫТО","ЗАКРЫТО")) -> ЗАКРЫТО | BB19: =IF(AM19>=E19,"ИЗУЧЕНО",IF(AND(OR(F19="",SUMIF($A$11:$A$50,F19,AM$11:AM$50)>=SUMIF($A$11:$A$50,F19,$E$11:$E$50)),OR(G19="",SUMIF($A$11:$A$50,G19,AM$11:AM$50)>=SUMIF($A$11:$A$50,G19,$E$11:$E$50)),OR(H19="",SUMIF($A$11:$A$50,H19,AM$11:AM$50)>=SUMIF($A$11:$A$50,H19,$E$11:$E$50))),"ОТКРЫТО","ЗАКРЫТО")) -> ЗАКРЫТО | BC19: =IF(AN19>=E19,"ИЗУЧЕНО",IF(AND(OR(F19="",SUMIF($A$11:$A$50,F19,AN$11:AN$50)>=SUMIF($A$11:$A$50,F19,$E$11:$E$50)),OR(G19="",SUMIF($A$11:$A$50,G19,AN$11:AN$50)>=SUMIF($A$11:$A$50,G19,$E$11:$E$50)),OR(H19="",SUMIF($A$11:$A$50,H19,AN$11:AN$50)>=SUMIF($A$11:$A$50,H19,$E$11:$E$50))),"ОТКРЫТО","ЗАКРЫТО")) -> ЗАКРЫТО | BD19: =IF(AO19>=E19,"ИЗУЧЕНО",IF(AND(OR(F19="",SUMIF($A$11:$A$50,F19,AO$11:AO$50)>=SUMIF($A$11:$A$50,F19,$E$11:$E$50)),OR(G19="",SUMIF($A$11:$A$50,G19,AO$11:AO$50)>=SUMIF($A$11:$A$50,G19,$E$11:$E$50)),OR(H19="",SUMIF($A$11:$A$50,H19,AO$11:AO$50)>=SUMIF($A$11:$A$50,H19,$E$11:$E$50))),"ОТКРЫТО","ЗАКРЫТО")) -> ЗАКРЫТО | BE19: =IF(AP19>=E19,"ИЗУЧЕНО",IF(AND(OR(F19="",SUMIF($A$11:$A$50,F19,AP$11:AP$50)>=SUMIF($A$11:$A$50,F19,$E$11:$E$50)),OR(G19="",SUMIF($A$11:$A$50,G19,AP$11:AP$50)>=SUMIF($A$11:$A$50,G19,$E$11:$E$50)),OR(H19="",SUMIF($A$11:$A$50,H19,AP$11:AP$50)>=SUMIF($A$11:$A$50,H19,$E$11:$E$50))),"ОТКРЫТО","ЗАКРЫТО")) -> ЗАКРЫТО | BF19: =IF(AQ19>=E19,"ИЗУЧЕНО",IF(AND(OR(F19="",SUMIF($A$11:$A$50,F19,AQ$11:AQ$50)>=SUMIF($A$11:$A$50,F19,$E$11:$E$50)),OR(G19="",SUMIF($A$11:$A$50,G19,AQ$11:AQ$50)>=SUMIF($A$11:$A$50,G19,$E$11:$E$50)),OR(H19="",SUMIF($A$11:$A$50,H19,AQ$11:AQ$50)>=SUMIF($A$11:$A$50,H19,$E$11:$E$50))),"ОТКРЫТО","ЗАКРЫТО")) -> ЗАКРЫТО
A20: M4 | B20: Модели и алгоритмы | C20: III | D20: Адаптивные модели непрерывного обучения | E20: 65 | F20: M2 | G20: M3 | I20: Модели, способные обновляться при изменении среды и данных. | J20: Модельные ресурсы +0,4; их прирост +0,08/год; прирост Управления +0,05/год | K20: =SUMIF('Ход 2026'!$G$29:$G$38,$A20,'Ход 2026'!$I$29:$I$38) -> 0 | L20: =SUMIF('Ход 2027'!$G$29:$G$38,$A20,'Ход 2027'!$I$29:$I$38) -> 0 | M20: =SUMIF('Ход 2028'!$G$29:$G$38,$A20,'Ход 2028'!$I$29:$I$38) -> 0 | N20: =SUMIF('Ход 2029'!$G$29:$G$38,$A20,'Ход 2029'!$I$29:$I$38) -> 0 | O20: =SUMIF('Ход 2030'!$G$29:$G$38,$A20,'Ход 2030'!$I$29:$I$38) -> 0 | P20: =SUMIF('Ход 2031'!$G$29:$G$38,$A20,'Ход 2031'!$I$29:$I$38) -> 0 | Q20: =SUMIF('Ход 2032'!$G$29:$G$38,$A20,'Ход 2032'!$I$29:$I$38) -> 0 | R20: =SUMIF('Ход 2033'!$G$29:$G$38,$A20,'Ход 2033'!$I$29:$I$38) -> 0 | S20: =SUMIF('Ход 2034'!$G$29:$G$38,$A20,'Ход 2034'!$I$29:$I$38) -> 0 | T20: =SUMIF('Ход 2035'!$G$29:$G$38,$A20,'Ход 2035'!$I$29:$I$38) -> 0 | U20: =SUMIF('Ход 2036'!$G$29:$G$38,$A20,'Ход 2036'!$I$29:$I$38) -> 0 | V20: =SUMIF('Ход 2037'!$G$29:$G$38,$A20,'Ход 2037'!$I$29:$I$38) -> 0 | W20: =SUMIF('Ход 2038'!$G$29:$G$38,$A20,'Ход 2038'!$I$29:$I$38) -> 0 | X20: =SUMIF('Ход 2039'!$G$29:$G$38,$A20,'Ход 2039'!$I$29:$I$38) -> 0 | Y20: =SUMIF('Ход 2040'!$G$29:$G$38,$A20,'Ход 2040'!$I$29:$I$38) -> 0 | Z20: =SUM(K20:Y20) -> 0 | AA20: =MAX(0,E20-Z20) -> 65 | AB20: =BF20 -> ЗАКРЫТО | AC20: =SUM($K20:K20) -> 0 | AD20: =SUM($K20:L20) -> 0 | AE20: =SUM($K20:M20) -> 0 | AF20: =SUM($K20:N20) -> 0 | AG20: =SUM($K20:O20) -> 0 | AH20: =SUM($K20:P20) -> 0 | AI20: =SUM($K20:Q20) -> 0 | AJ20: =SUM($K20:R20) -> 0 | ... AQ20: =SUM($K20:Y20) -> 0 | AR20: =IF(AC20>=E20,"ИЗУЧЕНО",IF(AND(OR(F20="",SUMIF($A$11:$A$50,F20,AC$11:AC$50)>=SUMIF($A$11:$A$50,F20,$E$11:$E$50)),OR(G20="",SUMIF($A$11:$A$50,G20,AC$11:AC$50)>=SUMIF($A$11:$A$50,G20,$E$11:$E$50)),OR(H20="",SUMIF($A$11:$A$50,H20,AC$11:AC$50)>=SUMIF($A$11:$A$50,H20,$E$11:$E$50))),"ОТКРЫТО","ЗАКРЫТО")) -> ЗАКРЫТО | AS20: =IF(AD20>=E20,"ИЗУЧЕНО",IF(AND(OR(F20="",SUMIF($A$11:$A$50,F20,AD$11:AD$50)>=SUMIF($A$11:$A$50,F20,$E$11:$E$50)),OR(G20="",SUMIF($A$11:$A$50,G20,AD$11:AD$50)>=SUMIF($A$11:$A$50,G20,$E$11:$E$50)),OR(H20="",SUMIF($A$11:$A$50,H20,AD$11:AD$50)>=SUMIF($A$11:$A$50,H20,$E$11:$E$50))),"ОТКРЫТО","ЗАКРЫТО")) -> ЗАКРЫТО | AT20: =IF(AE20>=E20,"ИЗУЧЕНО",IF(AND(OR(F20="",SUMIF($A$11:$A$50,F20,AE$11:AE$50)>=SUMIF($A$11:$A$50,F20,$E$11:$E$50)),OR(G20="",SUMIF($A$11:$A$50,G20,AE$11:AE$50)>=SUMIF($A$11:$A$50,G20,$E$11:$E$50)),OR(H20="",SUMIF($A$11:$A$50,H20,AE$11:AE$50)>=SUMIF($A$11:$A$50,H20,$E$11:$E$50))),"ОТКРЫТО","ЗАКРЫТО")) -> ЗАКРЫТО | AU20: =IF(AF20>=E20,"ИЗУЧЕНО",IF(AND(OR(F20="",SUMIF($A$11:$A$50,F20,AF$11:AF$50)>=SUMIF($A$11:$A$50,F20,$E$11:$E$50)),OR(G20="",SUMIF($A$11:$A$50,G20,AF$11:AF$50)>=SUMIF($A$11:$A$50,G20,$E$11:$E$50)),OR(H20="",SUMIF($A$11:$A$50,H20,AF$11:AF$50)>=SUMIF($A$11:$A$50,H20,$E$11:$E$50))),"ОТКРЫТО","ЗАКРЫТО")) -> ЗАКРЫТО | AV20: =IF(AG20>=E20,"ИЗУЧЕНО",IF(AND(OR(F20="",SUMIF($A$11:$A$50,F20,AG$11:AG$50)>=SUMIF($A$11:$A$50,F20,$E$11:$E$50)),OR(G20="",SUMIF($A$11:$A$50,G20,AG$11:AG$50)>=SUMIF($A$11:$A$50,G20,$E$11:$E$50)),OR(H20="",SUMIF($A$11:$A$50,H20,AG$11:AG$50)>=SUMIF($A$11:$A$50,H20,$E$11:$E$50))),"ОТКРЫТО","ЗАКРЫТО")) -> ЗАКРЫТО | AW20: =IF(AH20>=E20,"ИЗУЧЕНО",IF(AND(OR(F20="",SUMIF($A$11:$A$50,F20,AH$11:AH$50)>=SUMIF($A$11:$A$50,F20,$E$11:$E$50)),OR(G20="",SUMIF($A$11:$A$50,G20,AH$11:AH$50)>=SUMIF($A$11:$A$50,G20,$E$11:$E$50)),OR(H20="",SUMIF($A$11:$A$50,H20,AH$11:AH$50)>=SUMIF($A$11:$A$50,H20,$E$11:$E$50))),"ОТКРЫТО","ЗАКРЫТО")) -> ЗАКРЫТО | AX20: =IF(AI20>=E20,"ИЗУЧЕНО",IF(AND(OR(F20="",SUMIF($A$11:$A$50,F20,AI$11:AI$50)>=SUMIF($A$11:$A$50,F20,$E$11:$E$50)),OR(G20="",SUMIF($A$11:$A$50,G20,AI$11:AI$50)>=SUMIF($A$11:$A$50,G20,$E$11:$E$50)),OR(H20="",SUMIF($A$11:$A$50,H20,AI$11:AI$50)>=SUMIF($A$11:$A$50,H20,$E$11:$E$50))),"ОТКРЫТО","ЗАКРЫТО")) -> ЗАКРЫТО | AY20: =IF(AJ20>=E20,"ИЗУЧЕНО",IF(AND(OR(F20="",SUMIF($A$11:$A$50,F20,AJ$11:AJ$50)>=SUMIF($A$11:$A$50,F20,$E$11:$E$50)),OR(G20="",SUMIF($A$11:$A$50,G20,AJ$11:AJ$50)>=SUMIF($A$11:$A$50,G20,$E$11:$E$50)),OR(H20="",SUMIF($A$11:$A$50,H20,AJ$11:AJ$50)>=SUMIF($A$11:$A$50,H20,$E$11:$E$50))),"ОТКРЫТО","ЗАКРЫТО")) -> ЗАКРЫТО | AZ20: =IF(AK20>=E20,"ИЗУЧЕНО",IF(AND(OR(F20="",SUMIF($A$11:$A$50,F20,AK$11:AK$50)>=SUMIF($A$11:$A$50,F20,$E$11:$E$50)),OR(G20="",SUMIF($A$11:$A$50,G20,AK$11:AK$50)>=SUMIF($A$11:$A$50,G20,$E$11:$E$50)),OR(H20="",SUMIF($A$11:$A$50,H20,AK$11:AK$50)>=SUMIF($A$11:$A$50,H20,$E$11:$E$50))),"ОТКРЫТО","ЗАКРЫТО")) -> ЗАКРЫТО | BA20: =IF(AL20>=E20,"ИЗУЧЕНО",IF(AND(OR(F20="",SUMIF($A$11:$A$50,F20,AL$11:AL$50)>=SUMIF($A$11:$A$50,F20,$E$11:$E$50)),OR(G20="",SUMIF($A$11:$A$50,G20,AL$11:AL$50)>=SUMIF($A$11:$A$50,G20,$E$11:$E$50)),OR(H20="",SUMIF($A$11:$A$50,H20,AL$11:AL$50)>=SUMIF($A$11:$A$50,H20,$E$11:$E$50))),"ОТКРЫТО","ЗАКРЫТО")) -> ЗАКРЫТО | BB20: =IF(AM20>=E20,"ИЗУЧЕНО",IF(AND(OR(F20="",SUMIF($A$11:$A$50,F20,AM$11:AM$50)>=SUMIF($A$11:$A$50,F20,$E$11:$E$50)),OR(G20="",SUMIF($A$11:$A$50,G20,AM$11:AM$50)>=SUMIF($A$11:$A$50,G20,$E$11:$E$50)),OR(H20="",SUMIF($A$11:$A$50,H20,AM$11:AM$50)>=SUMIF($A$11:$A$50,H20,$E$11:$E$50))),"ОТКРЫТО","ЗАКРЫТО")) -> ЗАКРЫТО | BC20: =IF(AN20>=E20,"ИЗУЧЕНО",IF(AND(OR(F20="",SUMIF($A$11:$A$50,F20,AN$11:AN$50)>=SUMIF($A$11:$A$50,F20,$E$11:$E$50)),OR(G20="",SUMIF($A$11:$A$50,G20,AN$11:AN$50)>=SUMIF($A$11:$A$50,G20,$E$11:$E$50)),OR(H20="",SUMIF($A$11:$A$50,H20,AN$11:AN$50)>=SUMIF($A$11:$A$50,H20,$E$11:$E$50))),"ОТКРЫТО","ЗАКРЫТО")) -> ЗАКРЫТО | BD20: =IF(AO20>=E20,"ИЗУЧЕНО",IF(AND(OR(F20="",SUMIF($A$11:$A$50,F20,AO$11:AO$50)>=SUMIF($A$11:$A$50,F20,$E$11:$E$50)),OR(G20="",SUMIF($A$11:$A$50,G20,AO$11:AO$50)>=SUMIF($A$11:$A$50,G20,$E$11:$E$50)),OR(H20="",SUMIF($A$11:$A$50,H20,AO$11:AO$50)>=SUMIF($A$11:$A$50,H20,$E$11:$E$50))),"ОТКРЫТО","ЗАКРЫТО")) -> ЗАКРЫТО | BE20: =IF(AP20>=E20,"ИЗУЧЕНО",IF(AND(OR(F20="",SUMIF($A$11:$A$50,F20,AP$11:AP$50)>=SUMIF($A$11:$A$50,F20,$E$11:$E$50)),OR(G20="",SUMIF($A$11:$A$50,G20,AP$11:AP$50)>=SUMIF($A$11:$A$50,G20,$E$11:$E$50)),OR(H20="",SUMIF($A$11:$A$50,H20,AP$11:AP$50)>=SUMIF($A$11:$A$50,H20,$E$11:$E$50))),"ОТКРЫТО","ЗАКРЫТО")) -> ЗАКРЫТО | BF20: =IF(AQ20>=E20,"ИЗУЧЕНО",IF(AND(OR(F20="",SUMIF($A$11:$A$50,F20,AQ$11:AQ$50)>=SUMIF($A$11:$A$50,F20,$E$11:$E$50)),OR(G20="",SUMIF($A$11:$A$50,G20,AQ$11:AQ$50)>=SUMIF($A$11:$A$50,G20,$E$11:$E$50)),OR(H20="",SUMIF($A$11:$A$50,H20,AQ$11:AQ$50)>=SUMIF($A$11:$A$50,H20,$E$11:$E$50))),"ОТКРЫТО","ЗАКРЫТО")) -> ЗАКРЫТО
A21: M5 | B21: Модели и алгоритмы | C21: IV | D21: Модели мира и причинного прогнозирования | E21: 100 | F21: M4 | I21: Моделирование среды, сценариев и последствий решений. | J21: Познание +0,3; прирост Познания +0,10/год; атака Афины +10% | K21: =SUMIF('Ход 2026'!$G$29:$G$38,$A21,'Ход 2026'!$I$29:$I$38) -> 0 | L21: =SUMIF('Ход 2027'!$G$29:$G$38,$A21,'Ход 2027'!$I$29:$I$38) -> 0 | M21: =SUMIF('Ход 2028'!$G$29:$G$38,$A21,'Ход 2028'!$I$29:$I$38) -> 0 | N21: =SUMIF('Ход 2029'!$G$29:$G$38,$A21,'Ход 2029'!$I$29:$I$38) -> 0 | O21: =SUMIF('Ход 2030'!$G$29:$G$38,$A21,'Ход 2030'!$I$29:$I$38) -> 0 | P21: =SUMIF('Ход 2031'!$G$29:$G$38,$A21,'Ход 2031'!$I$29:$I$38) -> 0 | Q21: =SUMIF('Ход 2032'!$G$29:$G$38,$A21,'Ход 2032'!$I$29:$I$38) -> 0 | R21: =SUMIF('Ход 2033'!$G$29:$G$38,$A21,'Ход 2033'!$I$29:$I$38) -> 0 | S21: =SUMIF('Ход 2034'!$G$29:$G$38,$A21,'Ход 2034'!$I$29:$I$38) -> 0 | T21: =SUMIF('Ход 2035'!$G$29:$G$38,$A21,'Ход 2035'!$I$29:$I$38) -> 0 | U21: =SUMIF('Ход 2036'!$G$29:$G$38,$A21,'Ход 2036'!$I$29:$I$38) -> 0 | V21: =SUMIF('Ход 2037'!$G$29:$G$38,$A21,'Ход 2037'!$I$29:$I$38) -> 0 | W21: =SUMIF('Ход 2038'!$G$29:$G$38,$A21,'Ход 2038'!$I$29:$I$38) -> 0 | X21: =SUMIF('Ход 2039'!$G$29:$G$38,$A21,'Ход 2039'!$I$29:$I$38) -> 0 | Y21: =SUMIF('Ход 2040'!$G$29:$G$38,$A21,'Ход 2040'!$I$29:$I$38) -> 0 | Z21: =SUM(K21:Y21) -> 0 | AA21: =MAX(0,E21-Z21) -> 100 | AB21: =BF21 -> ЗАКРЫТО | AC21: =SUM($K21:K21) -> 0 | AD21: =SUM($K21:L21) -> 0 | AE21: =SUM($K21:M21) -> 0 | AF21: =SUM($K21:N21) -> 0 | AG21: =SUM($K21:O21) -> 0 | AH21: =SUM($K21:P21) -> 0 | AI21: =SUM($K21:Q21) -> 0 | AJ21: =SUM($K21:R21) -> 0 | ... AQ21: =SUM($K21:Y21) -> 0 | AR21: =IF(AC21>=E21,"ИЗУЧЕНО",IF(AND(OR(F21="",SUMIF($A$11:$A$50,F21,AC$11:AC$50)>=SUMIF($A$11:$A$50,F21,$E$11:$E$50)),OR(G21="",SUMIF($A$11:$A$50,G21,AC$11:AC$50)>=SUMIF($A$11:$A$50,G21,$E$11:$E$50)),OR(H21="",SUMIF($A$11:$A$50,H21,AC$11:AC$50)>=SUMIF($A$11:$A$50,H21,$E$11:$E$50))),"ОТКРЫТО","ЗАКРЫТО")) -> ЗАКРЫТО | AS21: =IF(AD21>=E21,"ИЗУЧЕНО",IF(AND(OR(F21="",SUMIF($A$11:$A$50,F21,AD$11:AD$50)>=SUMIF($A$11:$A$50,F21,$E$11:$E$50)),OR(G21="",SUMIF($A$11:$A$50,G21,AD$11:AD$50)>=SUMIF($A$11:$A$50,G21,$E$11:$E$50)),OR(H21="",SUMIF($A$11:$A$50,H21,AD$11:AD$50)>=SUMIF($A$11:$A$50,H21,$E$11:$E$50))),"ОТКРЫТО","ЗАКРЫТО")) -> ЗАКРЫТО | AT21: =IF(AE21>=E21,"ИЗУЧЕНО",IF(AND(OR(F21="",SUMIF($A$11:$A$50,F21,AE$11:AE$50)>=SUMIF($A$11:$A$50,F21,$E$11:$E$50)),OR(G21="",SUMIF($A$11:$A$50,G21,AE$11:AE$50)>=SUMIF($A$11:$A$50,G21,$E$11:$E$50)),OR(H21="",SUMIF($A$11:$A$50,H21,AE$11:AE$50)>=SUMIF($A$11:$A$50,H21,$E$11:$E$50))),"ОТКРЫТО","ЗАКРЫТО")) -> ЗАКРЫТО | AU21: =IF(AF21>=E21,"ИЗУЧЕНО",IF(AND(OR(F21="",SUMIF($A$11:$A$50,F21,AF$11:AF$50)>=SUMIF($A$11:$A$50,F21,$E$11:$E$50)),OR(G21="",SUMIF($A$11:$A$50,G21,AF$11:AF$50)>=SUMIF($A$11:$A$50,G21,$E$11:$E$50)),OR(H21="",SUMIF($A$11:$A$50,H21,AF$11:AF$50)>=SUMIF($A$11:$A$50,H21,$E$11:$E$50))),"ОТКРЫТО","ЗАКРЫТО")) -> ЗАКРЫТО | AV21: =IF(AG21>=E21,"ИЗУЧЕНО",IF(AND(OR(F21="",SUMIF($A$11:$A$50,F21,AG$11:AG$50)>=SUMIF($A$11:$A$50,F21,$E$11:$E$50)),OR(G21="",SUMIF($A$11:$A$50,G21,AG$11:AG$50)>=SUMIF($A$11:$A$50,G21,$E$11:$E$50)),OR(H21="",SUMIF($A$11:$A$50,H21,AG$11:AG$50)>=SUMIF($A$11:$A$50,H21,$E$11:$E$50))),"ОТКРЫТО","ЗАКРЫТО")) -> ЗАКРЫТО | AW21: =IF(AH21>=E21,"ИЗУЧЕНО",IF(AND(OR(F21="",SUMIF($A$11:$A$50,F21,AH$11:AH$50)>=SUMIF($A$11:$A$50,F21,$E$11:$E$50)),OR(G21="",SUMIF($A$11:$A$50,G21,AH$11:AH$50)>=SUMIF($A$11:$A$50,G21,$E$11:$E$50)),OR(H21="",SUMIF($A$11:$A$50,H21,AH$11:AH$50)>=SUMIF($A$11:$A$50,H21,$E$11:$E$50))),"ОТКРЫТО","ЗАКРЫТО")) -> ЗАКРЫТО | AX21: =IF(AI21>=E21,"ИЗУЧЕНО",IF(AND(OR(F21="",SUMIF($A$11:$A$50,F21,AI$11:AI$50)>=SUMIF($A$11:$A$50,F21,$E$11:$E$50)),OR(G21="",SUMIF($A$11:$A$50,G21,AI$11:AI$50)>=SUMIF($A$11:$A$50,G21,$E$11:$E$50)),OR(H21="",SUMIF($A$11:$A$50,H21,AI$11:AI$50)>=SUMIF($A$11:$A$50,H21,$E$11:$E$50))),"ОТКРЫТО","ЗАКРЫТО")) -> ЗАКРЫТО | AY21: =IF(AJ21>=E21,"ИЗУЧЕНО",IF(AND(OR(F21="",SUMIF($A$11:$A$50,F21,AJ$11:AJ$50)>=SUMIF($A$11:$A$50,F21,$E$11:$E$50)),OR(G21="",SUMIF($A$11:$A$50,G21,AJ$11:AJ$50)>=SUMIF($A$11:$A$50,G21,$E$11:$E$50)),OR(H21="",SUMIF($A$11:$A$50,H21,AJ$11:AJ$50)>=SUMIF($A$11:$A$50,H21,$E$11:$E$50))),"ОТКРЫТО","ЗАКРЫТО")) -> ЗАКРЫТО | AZ21: =IF(AK21>=E21,"ИЗУЧЕНО",IF(AND(OR(F21="",SUMIF($A$11:$A$50,F21,AK$11:AK$50)>=SUMIF($A$11:$A$50,F21,$E$11:$E$50)),OR(G21="",SUMIF($A$11:$A$50,G21,AK$11:AK$50)>=SUMIF($A$11:$A$50,G21,$E$11:$E$50)),OR(H21="",SUMIF($A$11:$A$50,H21,AK$11:AK$50)>=SUMIF($A$11:$A$50,H21,$E$11:$E$50))),"ОТКРЫТО","ЗАКРЫТО")) -> ЗАКРЫТО | BA21: =IF(AL21>=E21,"ИЗУЧЕНО",IF(AND(OR(F21="",SUMIF($A$11:$A$50,F21,AL$11:AL$50)>=SUMIF($A$11:$A$50,F21,$E$11:$E$50)),OR(G21="",SUMIF($A$11:$A$50,G21,AL$11:AL$50)>=SUMIF($A$11:$A$50,G21,$E$11:$E$50)),OR(H21="",SUMIF($A$11:$A$50,H21,AL$11:AL$50)>=SUMIF($A$11:$A$50,H21,$E$11:$E$50))),"ОТКРЫТО","ЗАКРЫТО")) -> ЗАКРЫТО | BB21: =IF(AM21>=E21,"ИЗУЧЕНО",IF(AND(OR(F21="",SUMIF($A$11:$A$50,F21,AM$11:AM$50)>=SUMIF($A$11:$A$50,F21,$E$11:$E$50)),OR(G21="",SUMIF($A$11:$A$50,G21,AM$11:AM$50)>=SUMIF($A$11:$A$50,G21,$E$11:$E$50)),OR(H21="",SUMIF($A$11:$A$50,H21,AM$11:AM$50)>=SUMIF($A$11:$A$50,H21,$E$11:$E$50))),"ОТКРЫТО","ЗАКРЫТО")) -> ЗАКРЫТО | BC21: =IF(AN21>=E21,"ИЗУЧЕНО",IF(AND(OR(F21="",SUMIF($A$11:$A$50,F21,AN$11:AN$50)>=SUMIF($A$11:$A$50,F21,$E$11:$E$50)),OR(G21="",SUMIF($A$11:$A$50,G21,AN$11:AN$50)>=SUMIF($A$11:$A$50,G21,$E$11:$E$50)),OR(H21="",SUMIF($A$11:$A$50,H21,AN$11:AN$50)>=SUMIF($A$11:$A$50,H21,$E$11:$E$50))),"ОТКРЫТО","ЗАКРЫТО")) -> ЗАКРЫТО | BD21: =IF(AO21>=E21,"ИЗУЧЕНО",IF(AND(OR(F21="",SUMIF($A$11:$A$50,F21,AO$11:AO$50)>=SUMIF($A$11:$A$50,F21,$E$11:$E$50)),OR(G21="",SUMIF($A$11:$A$50,G21,AO$11:AO$50)>=SUMIF($A$11:$A$50,G21,$E$11:$E$50)),OR(H21="",SUMIF($A$11:$A$50,H21,AO$11:AO$50)>=SUMIF($A$11:$A$50,H21,$E$11:$E$50))),"ОТКРЫТО","ЗАКРЫТО")) -> ЗАКРЫТО | BE21: =IF(AP21>=E21,"ИЗУЧЕНО",IF(AND(OR(F21="",SUMIF($A$11:$A$50,F21,AP$11:AP$50)>=SUMIF($A$11:$A$50,F21,$E$11:$E$50)),OR(G21="",SUMIF($A$11:$A$50,G21,AP$11:AP$50)>=SUMIF($A$11:$A$50,G21,$E$11:$E$50)),OR(H21="",SUMIF($A$11:$A$50,H21,AP$11:AP$50)>=SUMIF($A$11:$A$50,H21,$E$11:$E$50))),"ОТКРЫТО","ЗАКРЫТО")) -> ЗАКРЫТО | BF21: =IF(AQ21>=E21,"ИЗУЧЕНО",IF(AND(OR(F21="",SUMIF($A$11:$A$50,F21,AQ$11:AQ$50)>=SUMIF($A$11:$A$50,F21,$E$11:$E$50)),OR(G21="",SUMIF($A$11:$A$50,G21,AQ$11:AQ$50)>=SUMIF($A$11:$A$50,G21,$E$11:$E$50)),OR(H21="",SUMIF($A$11:$A$50,H21,AQ$11:AQ$50)>=SUMIF($A$11:$A$50,H21,$E$11:$E$50))),"ОТКРЫТО","ЗАКРЫТО")) -> ЗАКРЫТО
A22: M6 | B22: Модели и алгоритмы | C22: V | D22: Самосовершенствующиеся фронтирные модели | E22: 155 | F22: M5 | I22: Системы, автоматизирующие существенную часть собственного улучшения. | J22: Прирост Методов построения моделей +0,15/год; Модельных ресурсов +0,10/год; эффективность науки для M/A/X +15% | K22: =SUMIF('Ход 2026'!$G$29:$G$38,$A22,'Ход 2026'!$I$29:$I$38) -> 0 | L22: =SUMIF('Ход 2027'!$G$29:$G$38,$A22,'Ход 2027'!$I$29:$I$38) -> 0 | M22: =SUMIF('Ход 2028'!$G$29:$G$38,$A22,'Ход 2028'!$I$29:$I$38) -> 0 | N22: =SUMIF('Ход 2029'!$G$29:$G$38,$A22,'Ход 2029'!$I$29:$I$38) -> 0 | O22: =SUMIF('Ход 2030'!$G$29:$G$38,$A22,'Ход 2030'!$I$29:$I$38) -> 0 | P22: =SUMIF('Ход 2031'!$G$29:$G$38,$A22,'Ход 2031'!$I$29:$I$38) -> 0 | Q22: =SUMIF('Ход 2032'!$G$29:$G$38,$A22,'Ход 2032'!$I$29:$I$38) -> 0 | R22: =SUMIF('Ход 2033'!$G$29:$G$38,$A22,'Ход 2033'!$I$29:$I$38) -> 0 | S22: =SUMIF('Ход 2034'!$G$29:$G$38,$A22,'Ход 2034'!$I$29:$I$38) -> 0 | T22: =SUMIF('Ход 2035'!$G$29:$G$38,$A22,'Ход 2035'!$I$29:$I$38) -> 0 | U22: =SUMIF('Ход 2036'!$G$29:$G$38,$A22,'Ход 2036'!$I$29:$I$38) -> 0 | V22: =SUMIF('Ход 2037'!$G$29:$G$38,$A22,'Ход 2037'!$I$29:$I$38) -> 0 | W22: =SUMIF('Ход 2038'!$G$29:$G$38,$A22,'Ход 2038'!$I$29:$I$38) -> 0 | X22: =SUMIF('Ход 2039'!$G$29:$G$38,$A22,'Ход 2039'!$I$29:$I$38) -> 0 | Y22: =SUMIF('Ход 2040'!$G$29:$G$38,$A22,'Ход 2040'!$I$29:$I$38) -> 0 | Z22: =SUM(K22:Y22) -> 0 | AA22: =MAX(0,E22-Z22) -> 155 | AB22: =BF22 -> ЗАКРЫТО | AC22: =SUM($K22:K22) -> 0 | AD22: =SUM($K22:L22) -> 0 | AE22: =SUM($K22:M22) -> 0 | AF22: =SUM($K22:N22) -> 0 | AG22: =SUM($K22:O22) -> 0 | AH22: =SUM($K22:P22) -> 0 | AI22: =SUM($K22:Q22) -> 0 | AJ22: =SUM($K22:R22) -> 0 | ... AQ22: =SUM($K22:Y22) -> 0 | AR22: =IF(AC22>=E22,"ИЗУЧЕНО",IF(AND(OR(F22="",SUMIF($A$11:$A$50,F22,AC$11:AC$50)>=SUMIF($A$11:$A$50,F22,$E$11:$E$50)),OR(G22="",SUMIF($A$11:$A$50,G22,AC$11:AC$50)>=SUMIF($A$11:$A$50,G22,$E$11:$E$50)),OR(H22="",SUMIF($A$11:$A$50,H22,AC$11:AC$50)>=SUMIF($A$11:$A$50,H22,$E$11:$E$50))),"ОТКРЫТО","ЗАКРЫТО")) -> ЗАКРЫТО | AS22: =IF(AD22>=E22,"ИЗУЧЕНО",IF(AND(OR(F22="",SUMIF($A$11:$A$50,F22,AD$11:AD$50)>=SUMIF($A$11:$A$50,F22,$E$11:$E$50)),OR(G22="",SUMIF($A$11:$A$50,G22,AD$11:AD$50)>=SUMIF($A$11:$A$50,G22,$E$11:$E$50)),OR(H22="",SUMIF($A$11:$A$50,H22,AD$11:AD$50)>=SUMIF($A$11:$A$50,H22,$E$11:$E$50))),"ОТКРЫТО","ЗАКРЫТО")) -> ЗАКРЫТО | AT22: =IF(AE22>=E22,"ИЗУЧЕНО",IF(AND(OR(F22="",SUMIF($A$11:$A$50,F22,AE$11:AE$50)>=SUMIF($A$11:$A$50,F22,$E$11:$E$50)),OR(G22="",SUMIF($A$11:$A$50,G22,AE$11:AE$50)>=SUMIF($A$11:$A$50,G22,$E$11:$E$50)),OR(H22="",SUMIF($A$11:$A$50,H22,AE$11:AE$50)>=SUMIF($A$11:$A$50,H22,$E$11:$E$50))),"ОТКРЫТО","ЗАКРЫТО")) -> ЗАКРЫТО | AU22: =IF(AF22>=E22,"ИЗУЧЕНО",IF(AND(OR(F22="",SUMIF($A$11:$A$50,F22,AF$11:AF$50)>=SUMIF($A$11:$A$50,F22,$E$11:$E$50)),OR(G22="",SUMIF($A$11:$A$50,G22,AF$11:AF$50)>=SUMIF($A$11:$A$50,G22,$E$11:$E$50)),OR(H22="",SUMIF($A$11:$A$50,H22,AF$11:AF$50)>=SUMIF($A$11:$A$50,H22,$E$11:$E$50))),"ОТКРЫТО","ЗАКРЫТО")) -> ЗАКРЫТО | AV22: =IF(AG22>=E22,"ИЗУЧЕНО",IF(AND(OR(F22="",SUMIF($A$11:$A$50,F22,AG$11:AG$50)>=SUMIF($A$11:$A$50,F22,$E$11:$E$50)),OR(G22="",SUMIF($A$11:$A$50,G22,AG$11:AG$50)>=SUMIF($A$11:$A$50,G22,$E$11:$E$50)),OR(H22="",SUMIF($A$11:$A$50,H22,AG$11:AG$50)>=SUMIF($A$11:$A$50,H22,$E$11:$E$50))),"ОТКРЫТО","ЗАКРЫТО")) -> ЗАКРЫТО | AW22: =IF(AH22>=E22,"ИЗУЧЕНО",IF(AND(OR(F22="",SUMIF($A$11:$A$50,F22,AH$11:AH$50)>=SUMIF($A$11:$A$50,F22,$E$11:$E$50)),OR(G22="",SUMIF($A$11:$A$50,G22,AH$11:AH$50)>=SUMIF($A$11:$A$50,G22,$E$11:$E$50)),OR(H22="",SUMIF($A$11:$A$50,H22,AH$11:AH$50)>=SUMIF($A$11:$A$50,H22,$E$11:$E$50))),"ОТКРЫТО","ЗАКРЫТО")) -> ЗАКРЫТО | AX22: =IF(AI22>=E22,"ИЗУЧЕНО",IF(AND(OR(F22="",SUMIF($A$11:$A$50,F22,AI$11:AI$50)>=SUMIF($A$11:$A$50,F22,$E$11:$E$50)),OR(G22="",SUMIF($A$11:$A$50,G22,AI$11:AI$50)>=SUMIF($A$11:$A$50,G22,$E$11:$E$50)),OR(H22="",SUMIF($A$11:$A$50,H22,AI$11:AI$50)>=SUMIF($A$11:$A$50,H22,$E$11:$E$50))),"ОТКРЫТО","ЗАКРЫТО")) -> ЗАКРЫТО | AY22: =IF(AJ22>=E22,"ИЗУЧЕНО",IF(AND(OR(F22="",SUMIF($A$11:$A$50,F22,AJ$11:AJ$50)>=SUMIF($A$11:$A$50,F22,$E$11:$E$50)),OR(G22="",SUMIF($A$11:$A$50,G22,AJ$11:AJ$50)>=SUMIF($A$11:$A$50,G22,$E$11:$E$50)),OR(H22="",SUMIF($A$11:$A$50,H22,AJ$11:AJ$50)>=SUMIF($A$11:$A$50,H22,$E$11:$E$50))),"ОТКРЫТО","ЗАКРЫТО")) -> ЗАКРЫТО | AZ22: =IF(AK22>=E22,"ИЗУЧЕНО",IF(AND(OR(F22="",SUMIF($A$11:$A$50,F22,AK$11:AK$50)>=SUMIF($A$11:$A$50,F22,$E$11:$E$50)),OR(G22="",SUMIF($A$11:$A$50,G22,AK$11:AK$50)>=SUMIF($A$11:$A$50,G22,$E$11:$E$50)),OR(H22="",SUMIF($A$11:$A$50,H22,AK$11:AK$50)>=SUMIF($A$11:$A$50,H22,$E$11:$E$50))),"ОТКРЫТО","ЗАКРЫТО")) -> ЗАКРЫТО | BA22: =IF(AL22>=E22,"ИЗУЧЕНО",IF(AND(OR(F22="",SUMIF($A$11:$A$50,F22,AL$11:AL$50)>=SUMIF($A$11:$A$50,F22,$E$11:$E$50)),OR(G22="",SUMIF($A$11:$A$50,G22,AL$11:AL$50)>=SUMIF($A$11:$A$50,G22,$E$11:$E$50)),OR(H22="",SUMIF($A$11:$A$50,H22,AL$11:AL$50)>=SUMIF($A$11:$A$50,H22,$E$11:$E$50))),"ОТКРЫТО","ЗАКРЫТО")) -> ЗАКРЫТО | BB22: =IF(AM22>=E22,"ИЗУЧЕНО",IF(AND(OR(F22="",SUMIF($A$11:$A$50,F22,AM$11:AM$50)>=SUMIF($A$11:$A$50,F22,$E$11:$E$50)),OR(G22="",SUMIF($A$11:$A$50,G22,AM$11:AM$50)>=SUMIF($A$11:$A$50,G22,$E$11:$E$50)),OR(H22="",SUMIF($A$11:$A$50,H22,AM$11:AM$50)>=SUMIF($A$11:$A$50,H22,$E$11:$E$50))),"ОТКРЫТО","ЗАКРЫТО")) -> ЗАКРЫТО | BC22: =IF(AN22>=E22,"ИЗУЧЕНО",IF(AND(OR(F22="",SUMIF($A$11:$A$50,F22,AN$11:AN$50)>=SUMIF($A$11:$A$50,F22,$E$11:$E$50)),OR(G22="",SUMIF($A$11:$A$50,G22,AN$11:AN$50)>=SUMIF($A$11:$A$50,G22,$E$11:$E$50)),OR(H22="",SUMIF($A$11:$A$50,H22,AN$11:AN$50)>=SUMIF($A$11:$A$50,H22,$E$11:$E$50))),"ОТКРЫТО","ЗАКРЫТО")) -> ЗАКРЫТО | BD22: =IF(AO22>=E22,"ИЗУЧЕНО",IF(AND(OR(F22="",SUMIF($A$11:$A$50,F22,AO$11:AO$50)>=SUMIF($A$11:$A$50,F22,$E$11:$E$50)),OR(G22="",SUMIF($A$11:$A$50,G22,AO$11:AO$50)>=SUMIF($A$11:$A$50,G22,$E$11:$E$50)),OR(H22="",SUMIF($A$11:$A$50,H22,AO$11:AO$50)>=SUMIF($A$11:$A$50,H22,$E$11:$E$50))),"ОТКРЫТО","ЗАКРЫТО")) -> ЗАКРЫТО | BE22: =IF(AP22>=E22,"ИЗУЧЕНО",IF(AND(OR(F22="",SUMIF($A$11:$A$50,F22,AP$11:AP$50)>=SUMIF($A$11:$A$50,F22,$E$11:$E$50)),OR(G22="",SUMIF($A$11:$A$50,G22,AP$11:AP$50)>=SUMIF($A$11:$A$50,G22,$E$11:$E$50)),OR(H22="",SUMIF($A$11:$A$50,H22,AP$11:AP$50)>=SUMIF($A$11:$A$50,H22,$E$11:$E$50))),"ОТКРЫТО","ЗАКРЫТО")) -> ЗАКРЫТО | BF22: =IF(AQ22>=E22,"ИЗУЧЕНО",IF(AND(OR(F22="",SUMIF($A$11:$A$50,F22,AQ$11:AQ$50)>=SUMIF($A$11:$A$50,F22,$E$11:$E$50)),OR(G22="",SUMIF($A$11:$A$50,G22,AQ$11:AQ$50)>=SUMIF($A$11:$A$50,G22,$E$11:$E$50)),OR(H22="",SUMIF($A$11:$A$50,H22,AQ$11:AQ$50)>=SUMIF($A$11:$A$50,H22,$E$11:$E$50))),"ОТКРЫТО","ЗАКРЫТО")) -> ЗАКРЫТО
A23: D1 | B23: Данные и знания | C23: I | D23: Интероперабельные пространства данных | E23: 20 | I23: Стандартизованный обмен данными между организациями и системами. | J23: Исходные данные +0,2; Интеграционные ресурсы +0,2; их прирост +0,05/год | K23: =SUMIF('Ход 2026'!$G$29:$G$38,$A23,'Ход 2026'!$I$29:$I$38) -> 0 | L23: =SUMIF('Ход 2027'!$G$29:$G$38,$A23,'Ход 2027'!$I$29:$I$38) -> 0 | M23: =SUMIF('Ход 2028'!$G$29:$G$38,$A23,'Ход 2028'!$I$29:$I$38) -> 0 | N23: =SUMIF('Ход 2029'!$G$29:$G$38,$A23,'Ход 2029'!$I$29:$I$38) -> 0 | O23: =SUMIF('Ход 2030'!$G$29:$G$38,$A23,'Ход 2030'!$I$29:$I$38) -> 0 | P23: =SUMIF('Ход 2031'!$G$29:$G$38,$A23,'Ход 2031'!$I$29:$I$38) -> 0 | Q23: =SUMIF('Ход 2032'!$G$29:$G$38,$A23,'Ход 2032'!$I$29:$I$38) -> 0 | R23: =SUMIF('Ход 2033'!$G$29:$G$38,$A23,'Ход 2033'!$I$29:$I$38) -> 0 | S23: =SUMIF('Ход 2034'!$G$29:$G$38,$A23,'Ход 2034'!$I$29:$I$38) -> 0 | T23: =SUMIF('Ход 2035'!$G$29:$G$38,$A23,'Ход 2035'!$I$29:$I$38) -> 0 | U23: =SUMIF('Ход 2036'!$G$29:$G$38,$A23,'Ход 2036'!$I$29:$I$38) -> 0 | V23: =SUMIF('Ход 2037'!$G$29:$G$38,$A23,'Ход 2037'!$I$29:$I$38) -> 0 | W23: =SUMIF('Ход 2038'!$G$29:$G$38,$A23,'Ход 2038'!$I$29:$I$38) -> 0 | X23: =SUMIF('Ход 2039'!$G$29:$G$38,$A23,'Ход 2039'!$I$29:$I$38) -> 0 | Y23: =SUMIF('Ход 2040'!$G$29:$G$38,$A23,'Ход 2040'!$I$29:$I$38) -> 0 | Z23: =SUM(K23:Y23) -> 0 | AA23: =MAX(0,E23-Z23) -> 20 | AB23: =BF23 -> ОТКРЫТО | AC23: =SUM($K23:K23) -> 0 | AD23: =SUM($K23:L23) -> 0 | AE23: =SUM($K23:M23) -> 0 | AF23: =SUM($K23:N23) -> 0 | AG23: =SUM($K23:O23) -> 0 | AH23: =SUM($K23:P23) -> 0 | AI23: =SUM($K23:Q23) -> 0 | AJ23: =SUM($K23:R23) -> 0 | ... AQ23: =SUM($K23:Y23) -> 0 | AR23: =IF(AC23>=E23,"ИЗУЧЕНО",IF(AND(OR(F23="",SUMIF($A$11:$A$50,F23,AC$11:AC$50)>=SUMIF($A$11:$A$50,F23,$E$11:$E$50)),OR(G23="",SUMIF($A$11:$A$50,G23,AC$11:AC$50)>=SUMIF($A$11:$A$50,G23,$E$11:$E$50)),OR(H23="",SUMIF($A$11:$A$50,H23,AC$11:AC$50)>=SUMIF($A$11:$A$50,H23,$E$11:$E$50))),"ОТКРЫТО","ЗАКРЫТО")) -> ОТКРЫТО | AS23: =IF(AD23>=E23,"ИЗУЧЕНО",IF(AND(OR(F23="",SUMIF($A$11:$A$50,F23,AD$11:AD$50)>=SUMIF($A$11:$A$50,F23,$E$11:$E$50)),OR(G23="",SUMIF($A$11:$A$50,G23,AD$11:AD$50)>=SUMIF($A$11:$A$50,G23,$E$11:$E$50)),OR(H23="",SUMIF($A$11:$A$50,H23,AD$11:AD$50)>=SUMIF($A$11:$A$50,H23,$E$11:$E$50))),"ОТКРЫТО","ЗАКРЫТО")) -> ОТКРЫТО | AT23: =IF(AE23>=E23,"ИЗУЧЕНО",IF(AND(OR(F23="",SUMIF($A$11:$A$50,F23,AE$11:AE$50)>=SUMIF($A$11:$A$50,F23,$E$11:$E$50)),OR(G23="",SUMIF($A$11:$A$50,G23,AE$11:AE$50)>=SUMIF($A$11:$A$50,G23,$E$11:$E$50)),OR(H23="",SUMIF($A$11:$A$50,H23,AE$11:AE$50)>=SUMIF($A$11:$A$50,H23,$E$11:$E$50))),"ОТКРЫТО","ЗАКРЫТО")) -> ОТКРЫТО | AU23: =IF(AF23>=E23,"ИЗУЧЕНО",IF(AND(OR(F23="",SUMIF($A$11:$A$50,F23,AF$11:AF$50)>=SUMIF($A$11:$A$50,F23,$E$11:$E$50)),OR(G23="",SUMIF($A$11:$A$50,G23,AF$11:AF$50)>=SUMIF($A$11:$A$50,G23,$E$11:$E$50)),OR(H23="",SUMIF($A$11:$A$50,H23,AF$11:AF$50)>=SUMIF($A$11:$A$50,H23,$E$11:$E$50))),"ОТКРЫТО","ЗАКРЫТО")) -> ОТКРЫТО | AV23: =IF(AG23>=E23,"ИЗУЧЕНО",IF(AND(OR(F23="",SUMIF($A$11:$A$50,F23,AG$11:AG$50)>=SUMIF($A$11:$A$50,F23,$E$11:$E$50)),OR(G23="",SUMIF($A$11:$A$50,G23,AG$11:AG$50)>=SUMIF($A$11:$A$50,G23,$E$11:$E$50)),OR(H23="",SUMIF($A$11:$A$50,H23,AG$11:AG$50)>=SUMIF($A$11:$A$50,H23,$E$11:$E$50))),"ОТКРЫТО","ЗАКРЫТО")) -> ОТКРЫТО | AW23: =IF(AH23>=E23,"ИЗУЧЕНО",IF(AND(OR(F23="",SUMIF($A$11:$A$50,F23,AH$11:AH$50)>=SUMIF($A$11:$A$50,F23,$E$11:$E$50)),OR(G23="",SUMIF($A$11:$A$50,G23,AH$11:AH$50)>=SUMIF($A$11:$A$50,G23,$E$11:$E$50)),OR(H23="",SUMIF($A$11:$A$50,H23,AH$11:AH$50)>=SUMIF($A$11:$A$50,H23,$E$11:$E$50))),"ОТКРЫТО","ЗАКРЫТО")) -> ОТКРЫТО | AX23: =IF(AI23>=E23,"ИЗУЧЕНО",IF(AND(OR(F23="",SUMIF($A$11:$A$50,F23,AI$11:AI$50)>=SUMIF($A$11:$A$50,F23,$E$11:$E$50)),OR(G23="",SUMIF($A$11:$A$50,G23,AI$11:AI$50)>=SUMIF($A$11:$A$50,G23,$E$11:$E$50)),OR(H23="",SUMIF($A$11:$A$50,H23,AI$11:AI$50)>=SUMIF($A$11:$A$50,H23,$E$11:$E$50))),"ОТКРЫТО","ЗАКРЫТО")) -> ОТКРЫТО | AY23: =IF(AJ23>=E23,"ИЗУЧЕНО",IF(AND(OR(F23="",SUMIF($A$11:$A$50,F23,AJ$11:AJ$50)>=SUMIF($A$11:$A$50,F23,$E$11:$E$50)),OR(G23="",SUMIF($A$11:$A$50,G23,AJ$11:AJ$50)>=SUMIF($A$11:$A$50,G23,$E$11:$E$50)),OR(H23="",SUMIF($A$11:$A$50,H23,AJ$11:AJ$50)>=SUMIF($A$11:$A$50,H23,$E$11:$E$50))),"ОТКРЫТО","ЗАКРЫТО")) -> ОТКРЫТО | AZ23: =IF(AK23>=E23,"ИЗУЧЕНО",IF(AND(OR(F23="",SUMIF($A$11:$A$50,F23,AK$11:AK$50)>=SUMIF($A$11:$A$50,F23,$E$11:$E$50)),OR(G23="",SUMIF($A$11:$A$50,G23,AK$11:AK$50)>=SUMIF($A$11:$A$50,G23,$E$11:$E$50)),OR(H23="",SUMIF($A$11:$A$50,H23,AK$11:AK$50)>=SUMIF($A$11:$A$50,H23,$E$11:$E$50))),"ОТКРЫТО","ЗАКРЫТО")) -> ОТКРЫТО | BA23: =IF(AL23>=E23,"ИЗУЧЕНО",IF(AND(OR(F23="",SUMIF($A$11:$A$50,F23,AL$11:AL$50)>=SUMIF($A$11:$A$50,F23,$E$11:$E$50)),OR(G23="",SUMIF($A$11:$A$50,G23,AL$11:AL$50)>=SUMIF($A$11:$A$50,G23,$E$11:$E$50)),OR(H23="",SUMIF($A$11:$A$50,H23,AL$11:AL$50)>=SUMIF($A$11:$A$50,H23,$E$11:$E$50))),"ОТКРЫТО","ЗАКРЫТО")) -> ОТКРЫТО | BB23: =IF(AM23>=E23,"ИЗУЧЕНО",IF(AND(OR(F23="",SUMIF($A$11:$A$50,F23,AM$11:AM$50)>=SUMIF($A$11:$A$50,F23,$E$11:$E$50)),OR(G23="",SUMIF($A$11:$A$50,G23,AM$11:AM$50)>=SUMIF($A$11:$A$50,G23,$E$11:$E$50)),OR(H23="",SUMIF($A$11:$A$50,H23,AM$11:AM$50)>=SUMIF($A$11:$A$50,H23,$E$11:$E$50))),"ОТКРЫТО","ЗАКРЫТО")) -> ОТКРЫТО | BC23: =IF(AN23>=E23,"ИЗУЧЕНО",IF(AND(OR(F23="",SUMIF($A$11:$A$50,F23,AN$11:AN$50)>=SUMIF($A$11:$A$50,F23,$E$11:$E$50)),OR(G23="",SUMIF($A$11:$A$50,G23,AN$11:AN$50)>=SUMIF($A$11:$A$50,G23,$E$11:$E$50)),OR(H23="",SUMIF($A$11:$A$50,H23,AN$11:AN$50)>=SUMIF($A$11:$A$50,H23,$E$11:$E$50))),"ОТКРЫТО","ЗАКРЫТО")) -> ОТКРЫТО | BD23: =IF(AO23>=E23,"ИЗУЧЕНО",IF(AND(OR(F23="",SUMIF($A$11:$A$50,F23,AO$11:AO$50)>=SUMIF($A$11:$A$50,F23,$E$11:$E$50)),OR(G23="",SUMIF($A$11:$A$50,G23,AO$11:AO$50)>=SUMIF($A$11:$A$50,G23,$E$11:$E$50)),OR(H23="",SUMIF($A$11:$A$50,H23,AO$11:AO$50)>=SUMIF($A$11:$A$50,H23,$E$11:$E$50))),"ОТКРЫТО","ЗАКРЫТО")) -> ОТКРЫТО | BE23: =IF(AP23>=E23,"ИЗУЧЕНО",IF(AND(OR(F23="",SUMIF($A$11:$A$50,F23,AP$11:AP$50)>=SUMIF($A$11:$A$50,F23,$E$11:$E$50)),OR(G23="",SUMIF($A$11:$A$50,G23,AP$11:AP$50)>=SUMIF($A$11:$A$50,G23,$E$11:$E$50)),OR(H23="",SUMIF($A$11:$A$50,H23,AP$11:AP$50)>=SUMIF($A$11:$A$50,H23,$E$11:$E$50))),"ОТКРЫТО","ЗАКРЫТО")) -> ОТКРЫТО | BF23: =IF(AQ23>=E23,"ИЗУЧЕНО",IF(AND(OR(F23="",SUMIF($A$11:$A$50,F23,AQ$11:AQ$50)>=SUMIF($A$11:$A$50,F23,$E$11:$E$50)),OR(G23="",SUMIF($A$11:$A$50,G23,AQ$11:AQ$50)>=SUMIF($A$11:$A$50,G23,$E$11:$E$50)),OR(H23="",SUMIF($A$11:$A$50,H23,AQ$11:AQ$50)>=SUMIF($A$11:$A$50,H23,$E$11:$E$50))),"ОТКРЫТО","ЗАКРЫТО")) -> ОТКРЫТО
A24: D2 | B24: Данные и знания | C24: II | D24: Промышленное производство синтетических данных | E24: 35 | F24: D1 | I24: Генерация обучающих и тестовых данных при дефиците реальных наблюдений. | J24: Производные данные +0,3; их прирост +0,10/год | K24: =SUMIF('Ход 2026'!$G$29:$G$38,$A24,'Ход 2026'!$I$29:$I$38) -> 0 | L24: =SUMIF('Ход 2027'!$G$29:$G$38,$A24,'Ход 2027'!$I$29:$I$38) -> 0 | M24: =SUMIF('Ход 2028'!$G$29:$G$38,$A24,'Ход 2028'!$I$29:$I$38) -> 0 | N24: =SUMIF('Ход 2029'!$G$29:$G$38,$A24,'Ход 2029'!$I$29:$I$38) -> 0 | O24: =SUMIF('Ход 2030'!$G$29:$G$38,$A24,'Ход 2030'!$I$29:$I$38) -> 0 | P24: =SUMIF('Ход 2031'!$G$29:$G$38,$A24,'Ход 2031'!$I$29:$I$38) -> 0 | Q24: =SUMIF('Ход 2032'!$G$29:$G$38,$A24,'Ход 2032'!$I$29:$I$38) -> 0 | R24: =SUMIF('Ход 2033'!$G$29:$G$38,$A24,'Ход 2033'!$I$29:$I$38) -> 0 | S24: =SUMIF('Ход 2034'!$G$29:$G$38,$A24,'Ход 2034'!$I$29:$I$38) -> 0 | T24: =SUMIF('Ход 2035'!$G$29:$G$38,$A24,'Ход 2035'!$I$29:$I$38) -> 0 | U24: =SUMIF('Ход 2036'!$G$29:$G$38,$A24,'Ход 2036'!$I$29:$I$38) -> 0 | V24: =SUMIF('Ход 2037'!$G$29:$G$38,$A24,'Ход 2037'!$I$29:$I$38) -> 0 | W24: =SUMIF('Ход 2038'!$G$29:$G$38,$A24,'Ход 2038'!$I$29:$I$38) -> 0 | X24: =SUMIF('Ход 2039'!$G$29:$G$38,$A24,'Ход 2039'!$I$29:$I$38) -> 0 | Y24: =SUMIF('Ход 2040'!$G$29:$G$38,$A24,'Ход 2040'!$I$29:$I$38) -> 0 | Z24: =SUM(K24:Y24) -> 0 | AA24: =MAX(0,E24-Z24) -> 35 | AB24: =BF24 -> ЗАКРЫТО | AC24: =SUM($K24:K24) -> 0 | AD24: =SUM($K24:L24) -> 0 | AE24: =SUM($K24:M24) -> 0 | AF24: =SUM($K24:N24) -> 0 | AG24: =SUM($K24:O24) -> 0 | AH24: =SUM($K24:P24) -> 0 | AI24: =SUM($K24:Q24) -> 0 | AJ24: =SUM($K24:R24) -> 0 | ... AQ24: =SUM($K24:Y24) -> 0 | AR24: =IF(AC24>=E24,"ИЗУЧЕНО",IF(AND(OR(F24="",SUMIF($A$11:$A$50,F24,AC$11:AC$50)>=SUMIF($A$11:$A$50,F24,$E$11:$E$50)),OR(G24="",SUMIF($A$11:$A$50,G24,AC$11:AC$50)>=SUMIF($A$11:$A$50,G24,$E$11:$E$50)),OR(H24="",SUMIF($A$11:$A$50,H24,AC$11:AC$50)>=SUMIF($A$11:$A$50,H24,$E$11:$E$50))),"ОТКРЫТО","ЗАКРЫТО")) -> ЗАКРЫТО | AS24: =IF(AD24>=E24,"ИЗУЧЕНО",IF(AND(OR(F24="",SUMIF($A$11:$A$50,F24,AD$11:AD$50)>=SUMIF($A$11:$A$50,F24,$E$11:$E$50)),OR(G24="",SUMIF($A$11:$A$50,G24,AD$11:AD$50)>=SUMIF($A$11:$A$50,G24,$E$11:$E$50)),OR(H24="",SUMIF($A$11:$A$50,H24,AD$11:AD$50)>=SUMIF($A$11:$A$50,H24,$E$11:$E$50))),"ОТКРЫТО","ЗАКРЫТО")) -> ЗАКРЫТО | AT24: =IF(AE24>=E24,"ИЗУЧЕНО",IF(AND(OR(F24="",SUMIF($A$11:$A$50,F24,AE$11:AE$50)>=SUMIF($A$11:$A$50,F24,$E$11:$E$50)),OR(G24="",SUMIF($A$11:$A$50,G24,AE$11:AE$50)>=SUMIF($A$11:$A$50,G24,$E$11:$E$50)),OR(H24="",SUMIF($A$11:$A$50,H24,AE$11:AE$50)>=SUMIF($A$11:$A$50,H24,$E$11:$E$50))),"ОТКРЫТО","ЗАКРЫТО")) -> ЗАКРЫТО | AU24: =IF(AF24>=E24,"ИЗУЧЕНО",IF(AND(OR(F24="",SUMIF($A$11:$A$50,F24,AF$11:AF$50)>=SUMIF($A$11:$A$50,F24,$E$11:$E$50)),OR(G24="",SUMIF($A$11:$A$50,G24,AF$11:AF$50)>=SUMIF($A$11:$A$50,G24,$E$11:$E$50)),OR(H24="",SUMIF($A$11:$A$50,H24,AF$11:AF$50)>=SUMIF($A$11:$A$50,H24,$E$11:$E$50))),"ОТКРЫТО","ЗАКРЫТО")) -> ЗАКРЫТО | AV24: =IF(AG24>=E24,"ИЗУЧЕНО",IF(AND(OR(F24="",SUMIF($A$11:$A$50,F24,AG$11:AG$50)>=SUMIF($A$11:$A$50,F24,$E$11:$E$50)),OR(G24="",SUMIF($A$11:$A$50,G24,AG$11:AG$50)>=SUMIF($A$11:$A$50,G24,$E$11:$E$50)),OR(H24="",SUMIF($A$11:$A$50,H24,AG$11:AG$50)>=SUMIF($A$11:$A$50,H24,$E$11:$E$50))),"ОТКРЫТО","ЗАКРЫТО")) -> ЗАКРЫТО | AW24: =IF(AH24>=E24,"ИЗУЧЕНО",IF(AND(OR(F24="",SUMIF($A$11:$A$50,F24,AH$11:AH$50)>=SUMIF($A$11:$A$50,F24,$E$11:$E$50)),OR(G24="",SUMIF($A$11:$A$50,G24,AH$11:AH$50)>=SUMIF($A$11:$A$50,G24,$E$11:$E$50)),OR(H24="",SUMIF($A$11:$A$50,H24,AH$11:AH$50)>=SUMIF($A$11:$A$50,H24,$E$11:$E$50))),"ОТКРЫТО","ЗАКРЫТО")) -> ЗАКРЫТО | AX24: =IF(AI24>=E24,"ИЗУЧЕНО",IF(AND(OR(F24="",SUMIF($A$11:$A$50,F24,AI$11:AI$50)>=SUMIF($A$11:$A$50,F24,$E$11:$E$50)),OR(G24="",SUMIF($A$11:$A$50,G24,AI$11:AI$50)>=SUMIF($A$11:$A$50,G24,$E$11:$E$50)),OR(H24="",SUMIF($A$11:$A$50,H24,AI$11:AI$50)>=SUMIF($A$11:$A$50,H24,$E$11:$E$50))),"ОТКРЫТО","ЗАКРЫТО")) -> ЗАКРЫТО | AY24: =IF(AJ24>=E24,"ИЗУЧЕНО",IF(AND(OR(F24="",SUMIF($A$11:$A$50,F24,AJ$11:AJ$50)>=SUMIF($A$11:$A$50,F24,$E$11:$E$50)),OR(G24="",SUMIF($A$11:$A$50,G24,AJ$11:AJ$50)>=SUMIF($A$11:$A$50,G24,$E$11:$E$50)),OR(H24="",SUMIF($A$11:$A$50,H24,AJ$11:AJ$50)>=SUMIF($A$11:$A$50,H24,$E$11:$E$50))),"ОТКРЫТО","ЗАКРЫТО")) -> ЗАКРЫТО | AZ24: =IF(AK24>=E24,"ИЗУЧЕНО",IF(AND(OR(F24="",SUMIF($A$11:$A$50,F24,AK$11:AK$50)>=SUMIF($A$11:$A$50,F24,$E$11:$E$50)),OR(G24="",SUMIF($A$11:$A$50,G24,AK$11:AK$50)>=SUMIF($A$11:$A$50,G24,$E$11:$E$50)),OR(H24="",SUMIF($A$11:$A$50,H24,AK$11:AK$50)>=SUMIF($A$11:$A$50,H24,$E$11:$E$50))),"ОТКРЫТО","ЗАКРЫТО")) -> ЗАКРЫТО | BA24: =IF(AL24>=E24,"ИЗУЧЕНО",IF(AND(OR(F24="",SUMIF($A$11:$A$50,F24,AL$11:AL$50)>=SUMIF($A$11:$A$50,F24,$E$11:$E$50)),OR(G24="",SUMIF($A$11:$A$50,G24,AL$11:AL$50)>=SUMIF($A$11:$A$50,G24,$E$11:$E$50)),OR(H24="",SUMIF($A$11:$A$50,H24,AL$11:AL$50)>=SUMIF($A$11:$A$50,H24,$E$11:$E$50))),"ОТКРЫТО","ЗАКРЫТО")) -> ЗАКРЫТО | BB24: =IF(AM24>=E24,"ИЗУЧЕНО",IF(AND(OR(F24="",SUMIF($A$11:$A$50,F24,AM$11:AM$50)>=SUMIF($A$11:$A$50,F24,$E$11:$E$50)),OR(G24="",SUMIF($A$11:$A$50,G24,AM$11:AM$50)>=SUMIF($A$11:$A$50,G24,$E$11:$E$50)),OR(H24="",SUMIF($A$11:$A$50,H24,AM$11:AM$50)>=SUMIF($A$11:$A$50,H24,$E$11:$E$50))),"ОТКРЫТО","ЗАКРЫТО")) -> ЗАКРЫТО | BC24: =IF(AN24>=E24,"ИЗУЧЕНО",IF(AND(OR(F24="",SUMIF($A$11:$A$50,F24,AN$11:AN$50)>=SUMIF($A$11:$A$50,F24,$E$11:$E$50)),OR(G24="",SUMIF($A$11:$A$50,G24,AN$11:AN$50)>=SUMIF($A$11:$A$50,G24,$E$11:$E$50)),OR(H24="",SUMIF($A$11:$A$50,H24,AN$11:AN$50)>=SUMIF($A$11:$A$50,H24,$E$11:$E$50))),"ОТКРЫТО","ЗАКРЫТО")) -> ЗАКРЫТО | BD24: =IF(AO24>=E24,"ИЗУЧЕНО",IF(AND(OR(F24="",SUMIF($A$11:$A$50,F24,AO$11:AO$50)>=SUMIF($A$11:$A$50,F24,$E$11:$E$50)),OR(G24="",SUMIF($A$11:$A$50,G24,AO$11:AO$50)>=SUMIF($A$11:$A$50,G24,$E$11:$E$50)),OR(H24="",SUMIF($A$11:$A$50,H24,AO$11:AO$50)>=SUMIF($A$11:$A$50,H24,$E$11:$E$50))),"ОТКРЫТО","ЗАКРЫТО")) -> ЗАКРЫТО | BE24: =IF(AP24>=E24,"ИЗУЧЕНО",IF(AND(OR(F24="",SUMIF($A$11:$A$50,F24,AP$11:AP$50)>=SUMIF($A$11:$A$50,F24,$E$11:$E$50)),OR(G24="",SUMIF($A$11:$A$50,G24,AP$11:AP$50)>=SUMIF($A$11:$A$50,G24,$E$11:$E$50)),OR(H24="",SUMIF($A$11:$A$50,H24,AP$11:AP$50)>=SUMIF($A$11:$A$50,H24,$E$11:$E$50))),"ОТКРЫТО","ЗАКРЫТО")) -> ЗАКРЫТО | BF24: =IF(AQ24>=E24,"ИЗУЧЕНО",IF(AND(OR(F24="",SUMIF($A$11:$A$50,F24,AQ$11:AQ$50)>=SUMIF($A$11:$A$50,F24,$E$11:$E$50)),OR(G24="",SUMIF($A$11:$A$50,G24,AQ$11:AQ$50)>=SUMIF($A$11:$A$50,G24,$E$11:$E$50)),OR(H24="",SUMIF($A$11:$A$50,H24,AQ$11:AQ$50)>=SUMIF($A$11:$A$50,H24,$E$11:$E$50))),"ОТКРЫТО","ЗАКРЫТО")) -> ЗАКРЫТО
A25: D3 | B25: Данные и знания | C25: II | D25: Графы знаний и семантические модели | E25: 40 | F25: D1 | I25: Машиночитаемые связи между объектами, понятиями и фактами. | J25: Контекстные информационные ресурсы +0,3; прирост Познания +0,05/год | K25: =SUMIF('Ход 2026'!$G$29:$G$38,$A25,'Ход 2026'!$I$29:$I$38) -> 0 | L25: =SUMIF('Ход 2027'!$G$29:$G$38,$A25,'Ход 2027'!$I$29:$I$38) -> 0 | M25: =SUMIF('Ход 2028'!$G$29:$G$38,$A25,'Ход 2028'!$I$29:$I$38) -> 0 | N25: =SUMIF('Ход 2029'!$G$29:$G$38,$A25,'Ход 2029'!$I$29:$I$38) -> 0 | O25: =SUMIF('Ход 2030'!$G$29:$G$38,$A25,'Ход 2030'!$I$29:$I$38) -> 0 | P25: =SUMIF('Ход 2031'!$G$29:$G$38,$A25,'Ход 2031'!$I$29:$I$38) -> 0 | Q25: =SUMIF('Ход 2032'!$G$29:$G$38,$A25,'Ход 2032'!$I$29:$I$38) -> 0 | R25: =SUMIF('Ход 2033'!$G$29:$G$38,$A25,'Ход 2033'!$I$29:$I$38) -> 0 | S25: =SUMIF('Ход 2034'!$G$29:$G$38,$A25,'Ход 2034'!$I$29:$I$38) -> 0 | T25: =SUMIF('Ход 2035'!$G$29:$G$38,$A25,'Ход 2035'!$I$29:$I$38) -> 0 | U25: =SUMIF('Ход 2036'!$G$29:$G$38,$A25,'Ход 2036'!$I$29:$I$38) -> 0 | V25: =SUMIF('Ход 2037'!$G$29:$G$38,$A25,'Ход 2037'!$I$29:$I$38) -> 0 | W25: =SUMIF('Ход 2038'!$G$29:$G$38,$A25,'Ход 2038'!$I$29:$I$38) -> 0 | X25: =SUMIF('Ход 2039'!$G$29:$G$38,$A25,'Ход 2039'!$I$29:$I$38) -> 0 | Y25: =SUMIF('Ход 2040'!$G$29:$G$38,$A25,'Ход 2040'!$I$29:$I$38) -> 0 | Z25: =SUM(K25:Y25) -> 0 | AA25: =MAX(0,E25-Z25) -> 40 | AB25: =BF25 -> ЗАКРЫТО | AC25: =SUM($K25:K25) -> 0 | AD25: =SUM($K25:L25) -> 0 | AE25: =SUM($K25:M25) -> 0 | AF25: =SUM($K25:N25) -> 0 | AG25: =SUM($K25:O25) -> 0 | AH25: =SUM($K25:P25) -> 0 | AI25: =SUM($K25:Q25) -> 0 | AJ25: =SUM($K25:R25) -> 0 | ... AQ25: =SUM($K25:Y25) -> 0 | AR25: =IF(AC25>=E25,"ИЗУЧЕНО",IF(AND(OR(F25="",SUMIF($A$11:$A$50,F25,AC$11:AC$50)>=SUMIF($A$11:$A$50,F25,$E$11:$E$50)),OR(G25="",SUMIF($A$11:$A$50,G25,AC$11:AC$50)>=SUMIF($A$11:$A$50,G25,$E$11:$E$50)),OR(H25="",SUMIF($A$11:$A$50,H25,AC$11:AC$50)>=SUMIF($A$11:$A$50,H25,$E$11:$E$50))),"ОТКРЫТО","ЗАКРЫТО")) -> ЗАКРЫТО | AS25: =IF(AD25>=E25,"ИЗУЧЕНО",IF(AND(OR(F25="",SUMIF($A$11:$A$50,F25,AD$11:AD$50)>=SUMIF($A$11:$A$50,F25,$E$11:$E$50)),OR(G25="",SUMIF($A$11:$A$50,G25,AD$11:AD$50)>=SUMIF($A$11:$A$50,G25,$E$11:$E$50)),OR(H25="",SUMIF($A$11:$A$50,H25,AD$11:AD$50)>=SUMIF($A$11:$A$50,H25,$E$11:$E$50))),"ОТКРЫТО","ЗАКРЫТО")) -> ЗАКРЫТО | AT25: =IF(AE25>=E25,"ИЗУЧЕНО",IF(AND(OR(F25="",SUMIF($A$11:$A$50,F25,AE$11:AE$50)>=SUMIF($A$11:$A$50,F25,$E$11:$E$50)),OR(G25="",SUMIF($A$11:$A$50,G25,AE$11:AE$50)>=SUMIF($A$11:$A$50,G25,$E$11:$E$50)),OR(H25="",SUMIF($A$11:$A$50,H25,AE$11:AE$50)>=SUMIF($A$11:$A$50,H25,$E$11:$E$50))),"ОТКРЫТО","ЗАКРЫТО")) -> ЗАКРЫТО | AU25: =IF(AF25>=E25,"ИЗУЧЕНО",IF(AND(OR(F25="",SUMIF($A$11:$A$50,F25,AF$11:AF$50)>=SUMIF($A$11:$A$50,F25,$E$11:$E$50)),OR(G25="",SUMIF($A$11:$A$50,G25,AF$11:AF$50)>=SUMIF($A$11:$A$50,G25,$E$11:$E$50)),OR(H25="",SUMIF($A$11:$A$50,H25,AF$11:AF$50)>=SUMIF($A$11:$A$50,H25,$E$11:$E$50))),"ОТКРЫТО","ЗАКРЫТО")) -> ЗАКРЫТО | AV25: =IF(AG25>=E25,"ИЗУЧЕНО",IF(AND(OR(F25="",SUMIF($A$11:$A$50,F25,AG$11:AG$50)>=SUMIF($A$11:$A$50,F25,$E$11:$E$50)),OR(G25="",SUMIF($A$11:$A$50,G25,AG$11:AG$50)>=SUMIF($A$11:$A$50,G25,$E$11:$E$50)),OR(H25="",SUMIF($A$11:$A$50,H25,AG$11:AG$50)>=SUMIF($A$11:$A$50,H25,$E$11:$E$50))),"ОТКРЫТО","ЗАКРЫТО")) -> ЗАКРЫТО | AW25: =IF(AH25>=E25,"ИЗУЧЕНО",IF(AND(OR(F25="",SUMIF($A$11:$A$50,F25,AH$11:AH$50)>=SUMIF($A$11:$A$50,F25,$E$11:$E$50)),OR(G25="",SUMIF($A$11:$A$50,G25,AH$11:AH$50)>=SUMIF($A$11:$A$50,G25,$E$11:$E$50)),OR(H25="",SUMIF($A$11:$A$50,H25,AH$11:AH$50)>=SUMIF($A$11:$A$50,H25,$E$11:$E$50))),"ОТКРЫТО","ЗАКРЫТО")) -> ЗАКРЫТО | AX25: =IF(AI25>=E25,"ИЗУЧЕНО",IF(AND(OR(F25="",SUMIF($A$11:$A$50,F25,AI$11:AI$50)>=SUMIF($A$11:$A$50,F25,$E$11:$E$50)),OR(G25="",SUMIF($A$11:$A$50,G25,AI$11:AI$50)>=SUMIF($A$11:$A$50,G25,$E$11:$E$50)),OR(H25="",SUMIF($A$11:$A$50,H25,AI$11:AI$50)>=SUMIF($A$11:$A$50,H25,$E$11:$E$50))),"ОТКРЫТО","ЗАКРЫТО")) -> ЗАКРЫТО | AY25: =IF(AJ25>=E25,"ИЗУЧЕНО",IF(AND(OR(F25="",SUMIF($A$11:$A$50,F25,AJ$11:AJ$50)>=SUMIF($A$11:$A$50,F25,$E$11:$E$50)),OR(G25="",SUMIF($A$11:$A$50,G25,AJ$11:AJ$50)>=SUMIF($A$11:$A$50,G25,$E$11:$E$50)),OR(H25="",SUMIF($A$11:$A$50,H25,AJ$11:AJ$50)>=SUMIF($A$11:$A$50,H25,$E$11:$E$50))),"ОТКРЫТО","ЗАКРЫТО")) -> ЗАКРЫТО | AZ25: =IF(AK25>=E25,"ИЗУЧЕНО",IF(AND(OR(F25="",SUMIF($A$11:$A$50,F25,AK$11:AK$50)>=SUMIF($A$11:$A$50,F25,$E$11:$E$50)),OR(G25="",SUMIF($A$11:$A$50,G25,AK$11:AK$50)>=SUMIF($A$11:$A$50,G25,$E$11:$E$50)),OR(H25="",SUMIF($A$11:$A$50,H25,AK$11:AK$50)>=SUMIF($A$11:$A$50,H25,$E$11:$E$50))),"ОТКРЫТО","ЗАКРЫТО")) -> ЗАКРЫТО | BA25: =IF(AL25>=E25,"ИЗУЧЕНО",IF(AND(OR(F25="",SUMIF($A$11:$A$50,F25,AL$11:AL$50)>=SUMIF($A$11:$A$50,F25,$E$11:$E$50)),OR(G25="",SUMIF($A$11:$A$50,G25,AL$11:AL$50)>=SUMIF($A$11:$A$50,G25,$E$11:$E$50)),OR(H25="",SUMIF($A$11:$A$50,H25,AL$11:AL$50)>=SUMIF($A$11:$A$50,H25,$E$11:$E$50))),"ОТКРЫТО","ЗАКРЫТО")) -> ЗАКРЫТО | BB25: =IF(AM25>=E25,"ИЗУЧЕНО",IF(AND(OR(F25="",SUMIF($A$11:$A$50,F25,AM$11:AM$50)>=SUMIF($A$11:$A$50,F25,$E$11:$E$50)),OR(G25="",SUMIF($A$11:$A$50,G25,AM$11:AM$50)>=SUMIF($A$11:$A$50,G25,$E$11:$E$50)),OR(H25="",SUMIF($A$11:$A$50,H25,AM$11:AM$50)>=SUMIF($A$11:$A$50,H25,$E$11:$E$50))),"ОТКРЫТО","ЗАКРЫТО")) -> ЗАКРЫТО | BC25: =IF(AN25>=E25,"ИЗУЧЕНО",IF(AND(OR(F25="",SUMIF($A$11:$A$50,F25,AN$11:AN$50)>=SUMIF($A$11:$A$50,F25,$E$11:$E$50)),OR(G25="",SUMIF($A$11:$A$50,G25,AN$11:AN$50)>=SUMIF($A$11:$A$50,G25,$E$11:$E$50)),OR(H25="",SUMIF($A$11:$A$50,H25,AN$11:AN$50)>=SUMIF($A$11:$A$50,H25,$E$11:$E$50))),"ОТКРЫТО","ЗАКРЫТО")) -> ЗАКРЫТО | BD25: =IF(AO25>=E25,"ИЗУЧЕНО",IF(AND(OR(F25="",SUMIF($A$11:$A$50,F25,AO$11:AO$50)>=SUMIF($A$11:$A$50,F25,$E$11:$E$50)),OR(G25="",SUMIF($A$11:$A$50,G25,AO$11:AO$50)>=SUMIF($A$11:$A$50,G25,$E$11:$E$50)),OR(H25="",SUMIF($A$11:$A$50,H25,AO$11:AO$50)>=SUMIF($A$11:$A$50,H25,$E$11:$E$50))),"ОТКРЫТО","ЗАКРЫТО")) -> ЗАКРЫТО | BE25: =IF(AP25>=E25,"ИЗУЧЕНО",IF(AND(OR(F25="",SUMIF($A$11:$A$50,F25,AP$11:AP$50)>=SUMIF($A$11:$A$50,F25,$E$11:$E$50)),OR(G25="",SUMIF($A$11:$A$50,G25,AP$11:AP$50)>=SUMIF($A$11:$A$50,G25,$E$11:$E$50)),OR(H25="",SUMIF($A$11:$A$50,H25,AP$11:AP$50)>=SUMIF($A$11:$A$50,H25,$E$11:$E$50))),"ОТКРЫТО","ЗАКРЫТО")) -> ЗАКРЫТО | BF25: =IF(AQ25>=E25,"ИЗУЧЕНО",IF(AND(OR(F25="",SUMIF($A$11:$A$50,F25,AQ$11:AQ$50)>=SUMIF($A$11:$A$50,F25,$E$11:$E$50)),OR(G25="",SUMIF($A$11:$A$50,G25,AQ$11:AQ$50)>=SUMIF($A$11:$A$50,G25,$E$11:$E$50)),OR(H25="",SUMIF($A$11:$A$50,H25,AQ$11:AQ$50)>=SUMIF($A$11:$A$50,H25,$E$11:$E$50))),"ОТКРЫТО","ЗАКРЫТО")) -> ЗАКРЫТО
A26: D4 | B26: Данные и знания | C26: III | D26: Проверяемые системы поиска и извлечения знаний | E26: 60 | F26: D2 | G26: D3 | I26: Доступ моделей к документированным и проверяемым источникам. | J26: Документационные ресурсы +0,3; Права доступа +0,2; прирост Госуправления +0,05/год | K26: =SUMIF('Ход 2026'!$G$29:$G$38,$A26,'Ход 2026'!$I$29:$I$38) -> 0 | L26: =SUMIF('Ход 2027'!$G$29:$G$38,$A26,'Ход 2027'!$I$29:$I$38) -> 0 | M26: =SUMIF('Ход 2028'!$G$29:$G$38,$A26,'Ход 2028'!$I$29:$I$38) -> 0 | N26: =SUMIF('Ход 2029'!$G$29:$G$38,$A26,'Ход 2029'!$I$29:$I$38) -> 0 | O26: =SUMIF('Ход 2030'!$G$29:$G$38,$A26,'Ход 2030'!$I$29:$I$38) -> 0 | P26: =SUMIF('Ход 2031'!$G$29:$G$38,$A26,'Ход 2031'!$I$29:$I$38) -> 0 | Q26: =SUMIF('Ход 2032'!$G$29:$G$38,$A26,'Ход 2032'!$I$29:$I$38) -> 0 | R26: =SUMIF('Ход 2033'!$G$29:$G$38,$A26,'Ход 2033'!$I$29:$I$38) -> 0 | S26: =SUMIF('Ход 2034'!$G$29:$G$38,$A26,'Ход 2034'!$I$29:$I$38) -> 0 | T26: =SUMIF('Ход 2035'!$G$29:$G$38,$A26,'Ход 2035'!$I$29:$I$38) -> 0 | U26: =SUMIF('Ход 2036'!$G$29:$G$38,$A26,'Ход 2036'!$I$29:$I$38) -> 0 | V26: =SUMIF('Ход 2037'!$G$29:$G$38,$A26,'Ход 2037'!$I$29:$I$38) -> 0 | W26: =SUMIF('Ход 2038'!$G$29:$G$38,$A26,'Ход 2038'!$I$29:$I$38) -> 0 | X26: =SUMIF('Ход 2039'!$G$29:$G$38,$A26,'Ход 2039'!$I$29:$I$38) -> 0 | Y26: =SUMIF('Ход 2040'!$G$29:$G$38,$A26,'Ход 2040'!$I$29:$I$38) -> 0 | Z26: =SUM(K26:Y26) -> 0 | AA26: =MAX(0,E26-Z26) -> 60 | AB26: =BF26 -> ЗАКРЫТО | AC26: =SUM($K26:K26) -> 0 | AD26: =SUM($K26:L26) -> 0 | AE26: =SUM($K26:M26) -> 0 | AF26: =SUM($K26:N26) -> 0 | AG26: =SUM($K26:O26) -> 0 | AH26: =SUM($K26:P26) -> 0 | AI26: =SUM($K26:Q26) -> 0 | AJ26: =SUM($K26:R26) -> 0 | ... AQ26: =SUM($K26:Y26) -> 0 | AR26: =IF(AC26>=E26,"ИЗУЧЕНО",IF(AND(OR(F26="",SUMIF($A$11:$A$50,F26,AC$11:AC$50)>=SUMIF($A$11:$A$50,F26,$E$11:$E$50)),OR(G26="",SUMIF($A$11:$A$50,G26,AC$11:AC$50)>=SUMIF($A$11:$A$50,G26,$E$11:$E$50)),OR(H26="",SUMIF($A$11:$A$50,H26,AC$11:AC$50)>=SUMIF($A$11:$A$50,H26,$E$11:$E$50))),"ОТКРЫТО","ЗАКРЫТО")) -> ЗАКРЫТО | AS26: =IF(AD26>=E26,"ИЗУЧЕНО",IF(AND(OR(F26="",SUMIF($A$11:$A$50,F26,AD$11:AD$50)>=SUMIF($A$11:$A$50,F26,$E$11:$E$50)),OR(G26="",SUMIF($A$11:$A$50,G26,AD$11:AD$50)>=SUMIF($A$11:$A$50,G26,$E$11:$E$50)),OR(H26="",SUMIF($A$11:$A$50,H26,AD$11:AD$50)>=SUMIF($A$11:$A$50,H26,$E$11:$E$50))),"ОТКРЫТО","ЗАКРЫТО")) -> ЗАКРЫТО | AT26: =IF(AE26>=E26,"ИЗУЧЕНО",IF(AND(OR(F26="",SUMIF($A$11:$A$50,F26,AE$11:AE$50)>=SUMIF($A$11:$A$50,F26,$E$11:$E$50)),OR(G26="",SUMIF($A$11:$A$50,G26,AE$11:AE$50)>=SUMIF($A$11:$A$50,G26,$E$11:$E$50)),OR(H26="",SUMIF($A$11:$A$50,H26,AE$11:AE$50)>=SUMIF($A$11:$A$50,H26,$E$11:$E$50))),"ОТКРЫТО","ЗАКРЫТО")) -> ЗАКРЫТО | AU26: =IF(AF26>=E26,"ИЗУЧЕНО",IF(AND(OR(F26="",SUMIF($A$11:$A$50,F26,AF$11:AF$50)>=SUMIF($A$11:$A$50,F26,$E$11:$E$50)),OR(G26="",SUMIF($A$11:$A$50,G26,AF$11:AF$50)>=SUMIF($A$11:$A$50,G26,$E$11:$E$50)),OR(H26="",SUMIF($A$11:$A$50,H26,AF$11:AF$50)>=SUMIF($A$11:$A$50,H26,$E$11:$E$50))),"ОТКРЫТО","ЗАКРЫТО")) -> ЗАКРЫТО | AV26: =IF(AG26>=E26,"ИЗУЧЕНО",IF(AND(OR(F26="",SUMIF($A$11:$A$50,F26,AG$11:AG$50)>=SUMIF($A$11:$A$50,F26,$E$11:$E$50)),OR(G26="",SUMIF($A$11:$A$50,G26,AG$11:AG$50)>=SUMIF($A$11:$A$50,G26,$E$11:$E$50)),OR(H26="",SUMIF($A$11:$A$50,H26,AG$11:AG$50)>=SUMIF($A$11:$A$50,H26,$E$11:$E$50))),"ОТКРЫТО","ЗАКРЫТО")) -> ЗАКРЫТО | AW26: =IF(AH26>=E26,"ИЗУЧЕНО",IF(AND(OR(F26="",SUMIF($A$11:$A$50,F26,AH$11:AH$50)>=SUMIF($A$11:$A$50,F26,$E$11:$E$50)),OR(G26="",SUMIF($A$11:$A$50,G26,AH$11:AH$50)>=SUMIF($A$11:$A$50,G26,$E$11:$E$50)),OR(H26="",SUMIF($A$11:$A$50,H26,AH$11:AH$50)>=SUMIF($A$11:$A$50,H26,$E$11:$E$50))),"ОТКРЫТО","ЗАКРЫТО")) -> ЗАКРЫТО | AX26: =IF(AI26>=E26,"ИЗУЧЕНО",IF(AND(OR(F26="",SUMIF($A$11:$A$50,F26,AI$11:AI$50)>=SUMIF($A$11:$A$50,F26,$E$11:$E$50)),OR(G26="",SUMIF($A$11:$A$50,G26,AI$11:AI$50)>=SUMIF($A$11:$A$50,G26,$E$11:$E$50)),OR(H26="",SUMIF($A$11:$A$50,H26,AI$11:AI$50)>=SUMIF($A$11:$A$50,H26,$E$11:$E$50))),"ОТКРЫТО","ЗАКРЫТО")) -> ЗАКРЫТО | AY26: =IF(AJ26>=E26,"ИЗУЧЕНО",IF(AND(OR(F26="",SUMIF($A$11:$A$50,F26,AJ$11:AJ$50)>=SUMIF($A$11:$A$50,F26,$E$11:$E$50)),OR(G26="",SUMIF($A$11:$A$50,G26,AJ$11:AJ$50)>=SUMIF($A$11:$A$50,G26,$E$11:$E$50)),OR(H26="",SUMIF($A$11:$A$50,H26,AJ$11:AJ$50)>=SUMIF($A$11:$A$50,H26,$E$11:$E$50))),"ОТКРЫТО","ЗАКРЫТО")) -> ЗАКРЫТО | AZ26: =IF(AK26>=E26,"ИЗУЧЕНО",IF(AND(OR(F26="",SUMIF($A$11:$A$50,F26,AK$11:AK$50)>=SUMIF($A$11:$A$50,F26,$E$11:$E$50)),OR(G26="",SUMIF($A$11:$A$50,G26,AK$11:AK$50)>=SUMIF($A$11:$A$50,G26,$E$11:$E$50)),OR(H26="",SUMIF($A$11:$A$50,H26,AK$11:AK$50)>=SUMIF($A$11:$A$50,H26,$E$11:$E$50))),"ОТКРЫТО","ЗАКРЫТО")) -> ЗАКРЫТО | BA26: =IF(AL26>=E26,"ИЗУЧЕНО",IF(AND(OR(F26="",SUMIF($A$11:$A$50,F26,AL$11:AL$50)>=SUMIF($A$11:$A$50,F26,$E$11:$E$50)),OR(G26="",SUMIF($A$11:$A$50,G26,AL$11:AL$50)>=SUMIF($A$11:$A$50,G26,$E$11:$E$50)),OR(H26="",SUMIF($A$11:$A$50,H26,AL$11:AL$50)>=SUMIF($A$11:$A$50,H26,$E$11:$E$50))),"ОТКРЫТО","ЗАКРЫТО")) -> ЗАКРЫТО | BB26: =IF(AM26>=E26,"ИЗУЧЕНО",IF(AND(OR(F26="",SUMIF($A$11:$A$50,F26,AM$11:AM$50)>=SUMIF($A$11:$A$50,F26,$E$11:$E$50)),OR(G26="",SUMIF($A$11:$A$50,G26,AM$11:AM$50)>=SUMIF($A$11:$A$50,G26,$E$11:$E$50)),OR(H26="",SUMIF($A$11:$A$50,H26,AM$11:AM$50)>=SUMIF($A$11:$A$50,H26,$E$11:$E$50))),"ОТКРЫТО","ЗАКРЫТО")) -> ЗАКРЫТО | BC26: =IF(AN26>=E26,"ИЗУЧЕНО",IF(AND(OR(F26="",SUMIF($A$11:$A$50,F26,AN$11:AN$50)>=SUMIF($A$11:$A$50,F26,$E$11:$E$50)),OR(G26="",SUMIF($A$11:$A$50,G26,AN$11:AN$50)>=SUMIF($A$11:$A$50,G26,$E$11:$E$50)),OR(H26="",SUMIF($A$11:$A$50,H26,AN$11:AN$50)>=SUMIF($A$11:$A$50,H26,$E$11:$E$50))),"ОТКРЫТО","ЗАКРЫТО")) -> ЗАКРЫТО | BD26: =IF(AO26>=E26,"ИЗУЧЕНО",IF(AND(OR(F26="",SUMIF($A$11:$A$50,F26,AO$11:AO$50)>=SUMIF($A$11:$A$50,F26,$E$11:$E$50)),OR(G26="",SUMIF($A$11:$A$50,G26,AO$11:AO$50)>=SUMIF($A$11:$A$50,G26,$E$11:$E$50)),OR(H26="",SUMIF($A$11:$A$50,H26,AO$11:AO$50)>=SUMIF($A$11:$A$50,H26,$E$11:$E$50))),"ОТКРЫТО","ЗАКРЫТО")) -> ЗАКРЫТО | BE26: =IF(AP26>=E26,"ИЗУЧЕНО",IF(AND(OR(F26="",SUMIF($A$11:$A$50,F26,AP$11:AP$50)>=SUMIF($A$11:$A$50,F26,$E$11:$E$50)),OR(G26="",SUMIF($A$11:$A$50,G26,AP$11:AP$50)>=SUMIF($A$11:$A$50,G26,$E$11:$E$50)),OR(H26="",SUMIF($A$11:$A$50,H26,AP$11:AP$50)>=SUMIF($A$11:$A$50,H26,$E$11:$E$50))),"ОТКРЫТО","ЗАКРЫТО")) -> ЗАКРЫТО | BF26: =IF(AQ26>=E26,"ИЗУЧЕНО",IF(AND(OR(F26="",SUMIF($A$11:$A$50,F26,AQ$11:AQ$50)>=SUMIF($A$11:$A$50,F26,$E$11:$E$50)),OR(G26="",SUMIF($A$11:$A$50,G26,AQ$11:AQ$50)>=SUMIF($A$11:$A$50,G26,$E$11:$E$50)),OR(H26="",SUMIF($A$11:$A$50,H26,AQ$11:AQ$50)>=SUMIF($A$11:$A$50,H26,$E$11:$E$50))),"ОТКРЫТО","ЗАКРЫТО")) -> ЗАКРЫТО
A27: D5 | B27: Данные и знания | C27: IV | D27: Национальная машиночитаемая инфраструктура знаний | E27: 95 | F27: D4 | I27: Связанная система государственных, научных и отраслевых знаний. | J27: Контекстные ресурсы +0,5; их прирост +0,10/год; защита Аполлона +15% | K27: =SUMIF('Ход 2026'!$G$29:$G$38,$A27,'Ход 2026'!$I$29:$I$38) -> 0 | L27: =SUMIF('Ход 2027'!$G$29:$G$38,$A27,'Ход 2027'!$I$29:$I$38) -> 0 | M27: =SUMIF('Ход 2028'!$G$29:$G$38,$A27,'Ход 2028'!$I$29:$I$38) -> 0 | N27: =SUMIF('Ход 2029'!$G$29:$G$38,$A27,'Ход 2029'!$I$29:$I$38) -> 0 | O27: =SUMIF('Ход 2030'!$G$29:$G$38,$A27,'Ход 2030'!$I$29:$I$38) -> 0 | P27: =SUMIF('Ход 2031'!$G$29:$G$38,$A27,'Ход 2031'!$I$29:$I$38) -> 0 | Q27: =SUMIF('Ход 2032'!$G$29:$G$38,$A27,'Ход 2032'!$I$29:$I$38) -> 0 | R27: =SUMIF('Ход 2033'!$G$29:$G$38,$A27,'Ход 2033'!$I$29:$I$38) -> 0 | S27: =SUMIF('Ход 2034'!$G$29:$G$38,$A27,'Ход 2034'!$I$29:$I$38) -> 0 | T27: =SUMIF('Ход 2035'!$G$29:$G$38,$A27,'Ход 2035'!$I$29:$I$38) -> 0 | U27: =SUMIF('Ход 2036'!$G$29:$G$38,$A27,'Ход 2036'!$I$29:$I$38) -> 0 | V27: =SUMIF('Ход 2037'!$G$29:$G$38,$A27,'Ход 2037'!$I$29:$I$38) -> 0 | W27: =SUMIF('Ход 2038'!$G$29:$G$38,$A27,'Ход 2038'!$I$29:$I$38) -> 0 | X27: =SUMIF('Ход 2039'!$G$29:$G$38,$A27,'Ход 2039'!$I$29:$I$38) -> 0 | Y27: =SUMIF('Ход 2040'!$G$29:$G$38,$A27,'Ход 2040'!$I$29:$I$38) -> 0 | Z27: =SUM(K27:Y27) -> 0 | AA27: =MAX(0,E27-Z27) -> 95 | AB27: =BF27 -> ЗАКРЫТО | AC27: =SUM($K27:K27) -> 0 | AD27: =SUM($K27:L27) -> 0 | AE27: =SUM($K27:M27) -> 0 | AF27: =SUM($K27:N27) -> 0 | AG27: =SUM($K27:O27) -> 0 | AH27: =SUM($K27:P27) -> 0 | AI27: =SUM($K27:Q27) -> 0 | AJ27: =SUM($K27:R27) -> 0 | ... AQ27: =SUM($K27:Y27) -> 0 | AR27: =IF(AC27>=E27,"ИЗУЧЕНО",IF(AND(OR(F27="",SUMIF($A$11:$A$50,F27,AC$11:AC$50)>=SUMIF($A$11:$A$50,F27,$E$11:$E$50)),OR(G27="",SUMIF($A$11:$A$50,G27,AC$11:AC$50)>=SUMIF($A$11:$A$50,G27,$E$11:$E$50)),OR(H27="",SUMIF($A$11:$A$50,H27,AC$11:AC$50)>=SUMIF($A$11:$A$50,H27,$E$11:$E$50))),"ОТКРЫТО","ЗАКРЫТО")) -> ЗАКРЫТО | AS27: =IF(AD27>=E27,"ИЗУЧЕНО",IF(AND(OR(F27="",SUMIF($A$11:$A$50,F27,AD$11:AD$50)>=SUMIF($A$11:$A$50,F27,$E$11:$E$50)),OR(G27="",SUMIF($A$11:$A$50,G27,AD$11:AD$50)>=SUMIF($A$11:$A$50,G27,$E$11:$E$50)),OR(H27="",SUMIF($A$11:$A$50,H27,AD$11:AD$50)>=SUMIF($A$11:$A$50,H27,$E$11:$E$50))),"ОТКРЫТО","ЗАКРЫТО")) -> ЗАКРЫТО | AT27: =IF(AE27>=E27,"ИЗУЧЕНО",IF(AND(OR(F27="",SUMIF($A$11:$A$50,F27,AE$11:AE$50)>=SUMIF($A$11:$A$50,F27,$E$11:$E$50)),OR(G27="",SUMIF($A$11:$A$50,G27,AE$11:AE$50)>=SUMIF($A$11:$A$50,G27,$E$11:$E$50)),OR(H27="",SUMIF($A$11:$A$50,H27,AE$11:AE$50)>=SUMIF($A$11:$A$50,H27,$E$11:$E$50))),"ОТКРЫТО","ЗАКРЫТО")) -> ЗАКРЫТО | AU27: =IF(AF27>=E27,"ИЗУЧЕНО",IF(AND(OR(F27="",SUMIF($A$11:$A$50,F27,AF$11:AF$50)>=SUMIF($A$11:$A$50,F27,$E$11:$E$50)),OR(G27="",SUMIF($A$11:$A$50,G27,AF$11:AF$50)>=SUMIF($A$11:$A$50,G27,$E$11:$E$50)),OR(H27="",SUMIF($A$11:$A$50,H27,AF$11:AF$50)>=SUMIF($A$11:$A$50,H27,$E$11:$E$50))),"ОТКРЫТО","ЗАКРЫТО")) -> ЗАКРЫТО | AV27: =IF(AG27>=E27,"ИЗУЧЕНО",IF(AND(OR(F27="",SUMIF($A$11:$A$50,F27,AG$11:AG$50)>=SUMIF($A$11:$A$50,F27,$E$11:$E$50)),OR(G27="",SUMIF($A$11:$A$50,G27,AG$11:AG$50)>=SUMIF($A$11:$A$50,G27,$E$11:$E$50)),OR(H27="",SUMIF($A$11:$A$50,H27,AG$11:AG$50)>=SUMIF($A$11:$A$50,H27,$E$11:$E$50))),"ОТКРЫТО","ЗАКРЫТО")) -> ЗАКРЫТО | AW27: =IF(AH27>=E27,"ИЗУЧЕНО",IF(AND(OR(F27="",SUMIF($A$11:$A$50,F27,AH$11:AH$50)>=SUMIF($A$11:$A$50,F27,$E$11:$E$50)),OR(G27="",SUMIF($A$11:$A$50,G27,AH$11:AH$50)>=SUMIF($A$11:$A$50,G27,$E$11:$E$50)),OR(H27="",SUMIF($A$11:$A$50,H27,AH$11:AH$50)>=SUMIF($A$11:$A$50,H27,$E$11:$E$50))),"ОТКРЫТО","ЗАКРЫТО")) -> ЗАКРЫТО | AX27: =IF(AI27>=E27,"ИЗУЧЕНО",IF(AND(OR(F27="",SUMIF($A$11:$A$50,F27,AI$11:AI$50)>=SUMIF($A$11:$A$50,F27,$E$11:$E$50)),OR(G27="",SUMIF($A$11:$A$50,G27,AI$11:AI$50)>=SUMIF($A$11:$A$50,G27,$E$11:$E$50)),OR(H27="",SUMIF($A$11:$A$50,H27,AI$11:AI$50)>=SUMIF($A$11:$A$50,H27,$E$11:$E$50))),"ОТКРЫТО","ЗАКРЫТО")) -> ЗАКРЫТО | AY27: =IF(AJ27>=E27,"ИЗУЧЕНО",IF(AND(OR(F27="",SUMIF($A$11:$A$50,F27,AJ$11:AJ$50)>=SUMIF($A$11:$A$50,F27,$E$11:$E$50)),OR(G27="",SUMIF($A$11:$A$50,G27,AJ$11:AJ$50)>=SUMIF($A$11:$A$50,G27,$E$11:$E$50)),OR(H27="",SUMIF($A$11:$A$50,H27,AJ$11:AJ$50)>=SUMIF($A$11:$A$50,H27,$E$11:$E$50))),"ОТКРЫТО","ЗАКРЫТО")) -> ЗАКРЫТО | AZ27: =IF(AK27>=E27,"ИЗУЧЕНО",IF(AND(OR(F27="",SUMIF($A$11:$A$50,F27,AK$11:AK$50)>=SUMIF($A$11:$A$50,F27,$E$11:$E$50)),OR(G27="",SUMIF($A$11:$A$50,G27,AK$11:AK$50)>=SUMIF($A$11:$A$50,G27,$E$11:$E$50)),OR(H27="",SUMIF($A$11:$A$50,H27,AK$11:AK$50)>=SUMIF($A$11:$A$50,H27,$E$11:$E$50))),"ОТКРЫТО","ЗАКРЫТО")) -> ЗАКРЫТО | BA27: =IF(AL27>=E27,"ИЗУЧЕНО",IF(AND(OR(F27="",SUMIF($A$11:$A$50,F27,AL$11:AL$50)>=SUMIF($A$11:$A$50,F27,$E$11:$E$50)),OR(G27="",SUMIF($A$11:$A$50,G27,AL$11:AL$50)>=SUMIF($A$11:$A$50,G27,$E$11:$E$50)),OR(H27="",SUMIF($A$11:$A$50,H27,AL$11:AL$50)>=SUMIF($A$11:$A$50,H27,$E$11:$E$50))),"ОТКРЫТО","ЗАКРЫТО")) -> ЗАКРЫТО | BB27: =IF(AM27>=E27,"ИЗУЧЕНО",IF(AND(OR(F27="",SUMIF($A$11:$A$50,F27,AM$11:AM$50)>=SUMIF($A$11:$A$50,F27,$E$11:$E$50)),OR(G27="",SUMIF($A$11:$A$50,G27,AM$11:AM$50)>=SUMIF($A$11:$A$50,G27,$E$11:$E$50)),OR(H27="",SUMIF($A$11:$A$50,H27,AM$11:AM$50)>=SUMIF($A$11:$A$50,H27,$E$11:$E$50))),"ОТКРЫТО","ЗАКРЫТО")) -> ЗАКРЫТО | BC27: =IF(AN27>=E27,"ИЗУЧЕНО",IF(AND(OR(F27="",SUMIF($A$11:$A$50,F27,AN$11:AN$50)>=SUMIF($A$11:$A$50,F27,$E$11:$E$50)),OR(G27="",SUMIF($A$11:$A$50,G27,AN$11:AN$50)>=SUMIF($A$11:$A$50,G27,$E$11:$E$50)),OR(H27="",SUMIF($A$11:$A$50,H27,AN$11:AN$50)>=SUMIF($A$11:$A$50,H27,$E$11:$E$50))),"ОТКРЫТО","ЗАКРЫТО")) -> ЗАКРЫТО | BD27: =IF(AO27>=E27,"ИЗУЧЕНО",IF(AND(OR(F27="",SUMIF($A$11:$A$50,F27,AO$11:AO$50)>=SUMIF($A$11:$A$50,F27,$E$11:$E$50)),OR(G27="",SUMIF($A$11:$A$50,G27,AO$11:AO$50)>=SUMIF($A$11:$A$50,G27,$E$11:$E$50)),OR(H27="",SUMIF($A$11:$A$50,H27,AO$11:AO$50)>=SUMIF($A$11:$A$50,H27,$E$11:$E$50))),"ОТКРЫТО","ЗАКРЫТО")) -> ЗАКРЫТО | BE27: =IF(AP27>=E27,"ИЗУЧЕНО",IF(AND(OR(F27="",SUMIF($A$11:$A$50,F27,AP$11:AP$50)>=SUMIF($A$11:$A$50,F27,$E$11:$E$50)),OR(G27="",SUMIF($A$11:$A$50,G27,AP$11:AP$50)>=SUMIF($A$11:$A$50,G27,$E$11:$E$50)),OR(H27="",SUMIF($A$11:$A$50,H27,AP$11:AP$50)>=SUMIF($A$11:$A$50,H27,$E$11:$E$50))),"ОТКРЫТО","ЗАКРЫТО")) -> ЗАКРЫТО | BF27: =IF(AQ27>=E27,"ИЗУЧЕНО",IF(AND(OR(F27="",SUMIF($A$11:$A$50,F27,AQ$11:AQ$50)>=SUMIF($A$11:$A$50,F27,$E$11:$E$50)),OR(G27="",SUMIF($A$11:$A$50,G27,AQ$11:AQ$50)>=SUMIF($A$11:$A$50,G27,$E$11:$E$50)),OR(H27="",SUMIF($A$11:$A$50,H27,AQ$11:AQ$50)>=SUMIF($A$11:$A$50,H27,$E$11:$E$50))),"ОТКРЫТО","ЗАКРЫТО")) -> ЗАКРЫТО
A28: D6 | B28: Данные и знания | C28: V | D28: Автономные экосистемы данных | E28: 140 | F28: D5 | I28: Автоматическое получение, очистка, разметка, проверка и обновление данных. | J28: Прирост Исходных данных +0,10/год; Производных +0,15/год; Ресурсов оценки +0,10/год | K28: =SUMIF('Ход 2026'!$G$29:$G$38,$A28,'Ход 2026'!$I$29:$I$38) -> 0 | L28: =SUMIF('Ход 2027'!$G$29:$G$38,$A28,'Ход 2027'!$I$29:$I$38) -> 0 | M28: =SUMIF('Ход 2028'!$G$29:$G$38,$A28,'Ход 2028'!$I$29:$I$38) -> 0 | N28: =SUMIF('Ход 2029'!$G$29:$G$38,$A28,'Ход 2029'!$I$29:$I$38) -> 0 | O28: =SUMIF('Ход 2030'!$G$29:$G$38,$A28,'Ход 2030'!$I$29:$I$38) -> 0 | P28: =SUMIF('Ход 2031'!$G$29:$G$38,$A28,'Ход 2031'!$I$29:$I$38) -> 0 | Q28: =SUMIF('Ход 2032'!$G$29:$G$38,$A28,'Ход 2032'!$I$29:$I$38) -> 0 | R28: =SUMIF('Ход 2033'!$G$29:$G$38,$A28,'Ход 2033'!$I$29:$I$38) -> 0 | S28: =SUMIF('Ход 2034'!$G$29:$G$38,$A28,'Ход 2034'!$I$29:$I$38) -> 0 | T28: =SUMIF('Ход 2035'!$G$29:$G$38,$A28,'Ход 2035'!$I$29:$I$38) -> 0 | U28: =SUMIF('Ход 2036'!$G$29:$G$38,$A28,'Ход 2036'!$I$29:$I$38) -> 0 | V28: =SUMIF('Ход 2037'!$G$29:$G$38,$A28,'Ход 2037'!$I$29:$I$38) -> 0 | W28: =SUMIF('Ход 2038'!$G$29:$G$38,$A28,'Ход 2038'!$I$29:$I$38) -> 0 | X28: =SUMIF('Ход 2039'!$G$29:$G$38,$A28,'Ход 2039'!$I$29:$I$38) -> 0 | Y28: =SUMIF('Ход 2040'!$G$29:$G$38,$A28,'Ход 2040'!$I$29:$I$38) -> 0 | Z28: =SUM(K28:Y28) -> 0 | AA28: =MAX(0,E28-Z28) -> 140 | AB28: =BF28 -> ЗАКРЫТО | AC28: =SUM($K28:K28) -> 0 | AD28: =SUM($K28:L28) -> 0 | AE28: =SUM($K28:M28) -> 0 | AF28: =SUM($K28:N28) -> 0 | AG28: =SUM($K28:O28) -> 0 | AH28: =SUM($K28:P28) -> 0 | AI28: =SUM($K28:Q28) -> 0 | AJ28: =SUM($K28:R28) -> 0 | ... AQ28: =SUM($K28:Y28) -> 0 | AR28: =IF(AC28>=E28,"ИЗУЧЕНО",IF(AND(OR(F28="",SUMIF($A$11:$A$50,F28,AC$11:AC$50)>=SUMIF($A$11:$A$50,F28,$E$11:$E$50)),OR(G28="",SUMIF($A$11:$A$50,G28,AC$11:AC$50)>=SUMIF($A$11:$A$50,G28,$E$11:$E$50)),OR(H28="",SUMIF($A$11:$A$50,H28,AC$11:AC$50)>=SUMIF($A$11:$A$50,H28,$E$11:$E$50))),"ОТКРЫТО","ЗАКРЫТО")) -> ЗАКРЫТО | AS28: =IF(AD28>=E28,"ИЗУЧЕНО",IF(AND(OR(F28="",SUMIF($A$11:$A$50,F28,AD$11:AD$50)>=SUMIF($A$11:$A$50,F28,$E$11:$E$50)),OR(G28="",SUMIF($A$11:$A$50,G28,AD$11:AD$50)>=SUMIF($A$11:$A$50,G28,$E$11:$E$50)),OR(H28="",SUMIF($A$11:$A$50,H28,AD$11:AD$50)>=SUMIF($A$11:$A$50,H28,$E$11:$E$50))),"ОТКРЫТО","ЗАКРЫТО")) -> ЗАКРЫТО | AT28: =IF(AE28>=E28,"ИЗУЧЕНО",IF(AND(OR(F28="",SUMIF($A$11:$A$50,F28,AE$11:AE$50)>=SUMIF($A$11:$A$50,F28,$E$11:$E$50)),OR(G28="",SUMIF($A$11:$A$50,G28,AE$11:AE$50)>=SUMIF($A$11:$A$50,G28,$E$11:$E$50)),OR(H28="",SUMIF($A$11:$A$50,H28,AE$11:AE$50)>=SUMIF($A$11:$A$50,H28,$E$11:$E$50))),"ОТКРЫТО","ЗАКРЫТО")) -> ЗАКРЫТО | AU28: =IF(AF28>=E28,"ИЗУЧЕНО",IF(AND(OR(F28="",SUMIF($A$11:$A$50,F28,AF$11:AF$50)>=SUMIF($A$11:$A$50,F28,$E$11:$E$50)),OR(G28="",SUMIF($A$11:$A$50,G28,AF$11:AF$50)>=SUMIF($A$11:$A$50,G28,$E$11:$E$50)),OR(H28="",SUMIF($A$11:$A$50,H28,AF$11:AF$50)>=SUMIF($A$11:$A$50,H28,$E$11:$E$50))),"ОТКРЫТО","ЗАКРЫТО")) -> ЗАКРЫТО | AV28: =IF(AG28>=E28,"ИЗУЧЕНО",IF(AND(OR(F28="",SUMIF($A$11:$A$50,F28,AG$11:AG$50)>=SUMIF($A$11:$A$50,F28,$E$11:$E$50)),OR(G28="",SUMIF($A$11:$A$50,G28,AG$11:AG$50)>=SUMIF($A$11:$A$50,G28,$E$11:$E$50)),OR(H28="",SUMIF($A$11:$A$50,H28,AG$11:AG$50)>=SUMIF($A$11:$A$50,H28,$E$11:$E$50))),"ОТКРЫТО","ЗАКРЫТО")) -> ЗАКРЫТО | AW28: =IF(AH28>=E28,"ИЗУЧЕНО",IF(AND(OR(F28="",SUMIF($A$11:$A$50,F28,AH$11:AH$50)>=SUMIF($A$11:$A$50,F28,$E$11:$E$50)),OR(G28="",SUMIF($A$11:$A$50,G28,AH$11:AH$50)>=SUMIF($A$11:$A$50,G28,$E$11:$E$50)),OR(H28="",SUMIF($A$11:$A$50,H28,AH$11:AH$50)>=SUMIF($A$11:$A$50,H28,$E$11:$E$50))),"ОТКРЫТО","ЗАКРЫТО")) -> ЗАКРЫТО | AX28: =IF(AI28>=E28,"ИЗУЧЕНО",IF(AND(OR(F28="",SUMIF($A$11:$A$50,F28,AI$11:AI$50)>=SUMIF($A$11:$A$50,F28,$E$11:$E$50)),OR(G28="",SUMIF($A$11:$A$50,G28,AI$11:AI$50)>=SUMIF($A$11:$A$50,G28,$E$11:$E$50)),OR(H28="",SUMIF($A$11:$A$50,H28,AI$11:AI$50)>=SUMIF($A$11:$A$50,H28,$E$11:$E$50))),"ОТКРЫТО","ЗАКРЫТО")) -> ЗАКРЫТО | AY28: =IF(AJ28>=E28,"ИЗУЧЕНО",IF(AND(OR(F28="",SUMIF($A$11:$A$50,F28,AJ$11:AJ$50)>=SUMIF($A$11:$A$50,F28,$E$11:$E$50)),OR(G28="",SUMIF($A$11:$A$50,G28,AJ$11:AJ$50)>=SUMIF($A$11:$A$50,G28,$E$11:$E$50)),OR(H28="",SUMIF($A$11:$A$50,H28,AJ$11:AJ$50)>=SUMIF($A$11:$A$50,H28,$E$11:$E$50))),"ОТКРЫТО","ЗАКРЫТО")) -> ЗАКРЫТО | AZ28: =IF(AK28>=E28,"ИЗУЧЕНО",IF(AND(OR(F28="",SUMIF($A$11:$A$50,F28,AK$11:AK$50)>=SUMIF($A$11:$A$50,F28,$E$11:$E$50)),OR(G28="",SUMIF($A$11:$A$50,G28,AK$11:AK$50)>=SUMIF($A$11:$A$50,G28,$E$11:$E$50)),OR(H28="",SUMIF($A$11:$A$50,H28,AK$11:AK$50)>=SUMIF($A$11:$A$50,H28,$E$11:$E$50))),"ОТКРЫТО","ЗАКРЫТО")) -> ЗАКРЫТО | BA28: =IF(AL28>=E28,"ИЗУЧЕНО",IF(AND(OR(F28="",SUMIF($A$11:$A$50,F28,AL$11:AL$50)>=SUMIF($A$11:$A$50,F28,$E$11:$E$50)),OR(G28="",SUMIF($A$11:$A$50,G28,AL$11:AL$50)>=SUMIF($A$11:$A$50,G28,$E$11:$E$50)),OR(H28="",SUMIF($A$11:$A$50,H28,AL$11:AL$50)>=SUMIF($A$11:$A$50,H28,$E$11:$E$50))),"ОТКРЫТО","ЗАКРЫТО")) -> ЗАКРЫТО | BB28: =IF(AM28>=E28,"ИЗУЧЕНО",IF(AND(OR(F28="",SUMIF($A$11:$A$50,F28,AM$11:AM$50)>=SUMIF($A$11:$A$50,F28,$E$11:$E$50)),OR(G28="",SUMIF($A$11:$A$50,G28,AM$11:AM$50)>=SUMIF($A$11:$A$50,G28,$E$11:$E$50)),OR(H28="",SUMIF($A$11:$A$50,H28,AM$11:AM$50)>=SUMIF($A$11:$A$50,H28,$E$11:$E$50))),"ОТКРЫТО","ЗАКРЫТО")) -> ЗАКРЫТО | BC28: =IF(AN28>=E28,"ИЗУЧЕНО",IF(AND(OR(F28="",SUMIF($A$11:$A$50,F28,AN$11:AN$50)>=SUMIF($A$11:$A$50,F28,$E$11:$E$50)),OR(G28="",SUMIF($A$11:$A$50,G28,AN$11:AN$50)>=SUMIF($A$11:$A$50,G28,$E$11:$E$50)),OR(H28="",SUMIF($A$11:$A$50,H28,AN$11:AN$50)>=SUMIF($A$11:$A$50,H28,$E$11:$E$50))),"ОТКРЫТО","ЗАКРЫТО")) -> ЗАКРЫТО | BD28: =IF(AO28>=E28,"ИЗУЧЕНО",IF(AND(OR(F28="",SUMIF($A$11:$A$50,F28,AO$11:AO$50)>=SUMIF($A$11:$A$50,F28,$E$11:$E$50)),OR(G28="",SUMIF($A$11:$A$50,G28,AO$11:AO$50)>=SUMIF($A$11:$A$50,G28,$E$11:$E$50)),OR(H28="",SUMIF($A$11:$A$50,H28,AO$11:AO$50)>=SUMIF($A$11:$A$50,H28,$E$11:$E$50))),"ОТКРЫТО","ЗАКРЫТО")) -> ЗАКРЫТО | BE28: =IF(AP28>=E28,"ИЗУЧЕНО",IF(AND(OR(F28="",SUMIF($A$11:$A$50,F28,AP$11:AP$50)>=SUMIF($A$11:$A$50,F28,$E$11:$E$50)),OR(G28="",SUMIF($A$11:$A$50,G28,AP$11:AP$50)>=SUMIF($A$11:$A$50,G28,$E$11:$E$50)),OR(H28="",SUMIF($A$11:$A$50,H28,AP$11:AP$50)>=SUMIF($A$11:$A$50,H28,$E$11:$E$50))),"ОТКРЫТО","ЗАКРЫТО")) -> ЗАКРЫТО | BF28: =IF(AQ28>=E28,"ИЗУЧЕНО",IF(AND(OR(F28="",SUMIF($A$11:$A$50,F28,AQ$11:AQ$50)>=SUMIF($A$11:$A$50,F28,$E$11:$E$50)),OR(G28="",SUMIF($A$11:$A$50,G28,AQ$11:AQ$50)>=SUMIF($A$11:$A$50,G28,$E$11:$E$50)),OR(H28="",SUMIF($A$11:$A$50,H28,AQ$11:AQ$50)>=SUMIF($A$11:$A$50,H28,$E$11:$E$50))),"ОТКРЫТО","ЗАКРЫТО")) -> ЗАКРЫТО
A29: A1 | B29: Агенты и автономные системы | C29: I | D29: ИИ-копилоты с использованием инструментов | E29: 20 | I29: ИИ работает с программами, поиском и информационными системами. | J29: Прирост Управления +0,05/год; прирост Экономики +0,05/год | K29: =SUMIF('Ход 2026'!$G$29:$G$38,$A29,'Ход 2026'!$I$29:$I$38) -> 0 | L29: =SUMIF('Ход 2027'!$G$29:$G$38,$A29,'Ход 2027'!$I$29:$I$38) -> 0 | M29: =SUMIF('Ход 2028'!$G$29:$G$38,$A29,'Ход 2028'!$I$29:$I$38) -> 0 | N29: =SUMIF('Ход 2029'!$G$29:$G$38,$A29,'Ход 2029'!$I$29:$I$38) -> 0 | O29: =SUMIF('Ход 2030'!$G$29:$G$38,$A29,'Ход 2030'!$I$29:$I$38) -> 0 | P29: =SUMIF('Ход 2031'!$G$29:$G$38,$A29,'Ход 2031'!$I$29:$I$38) -> 0 | Q29: =SUMIF('Ход 2032'!$G$29:$G$38,$A29,'Ход 2032'!$I$29:$I$38) -> 0 | R29: =SUMIF('Ход 2033'!$G$29:$G$38,$A29,'Ход 2033'!$I$29:$I$38) -> 0 | S29: =SUMIF('Ход 2034'!$G$29:$G$38,$A29,'Ход 2034'!$I$29:$I$38) -> 0 | T29: =SUMIF('Ход 2035'!$G$29:$G$38,$A29,'Ход 2035'!$I$29:$I$38) -> 0 | U29: =SUMIF('Ход 2036'!$G$29:$G$38,$A29,'Ход 2036'!$I$29:$I$38) -> 0 | V29: =SUMIF('Ход 2037'!$G$29:$G$38,$A29,'Ход 2037'!$I$29:$I$38) -> 0 | W29: =SUMIF('Ход 2038'!$G$29:$G$38,$A29,'Ход 2038'!$I$29:$I$38) -> 0 | X29: =SUMIF('Ход 2039'!$G$29:$G$38,$A29,'Ход 2039'!$I$29:$I$38) -> 0 | Y29: =SUMIF('Ход 2040'!$G$29:$G$38,$A29,'Ход 2040'!$I$29:$I$38) -> 0 | Z29: =SUM(K29:Y29) -> 0 | AA29: =MAX(0,E29-Z29) -> 20 | AB29: =BF29 -> ОТКРЫТО | AC29: =SUM($K29:K29) -> 0 | AD29: =SUM($K29:L29) -> 0 | AE29: =SUM($K29:M29) -> 0 | AF29: =SUM($K29:N29) -> 0 | AG29: =SUM($K29:O29) -> 0 | AH29: =SUM($K29:P29) -> 0 | AI29: =SUM($K29:Q29) -> 0 | AJ29: =SUM($K29:R29) -> 0 | ... AQ29: =SUM($K29:Y29) -> 0 | AR29: =IF(AC29>=E29,"ИЗУЧЕНО",IF(AND(OR(F29="",SUMIF($A$11:$A$50,F29,AC$11:AC$50)>=SUMIF($A$11:$A$50,F29,$E$11:$E$50)),OR(G29="",SUMIF($A$11:$A$50,G29,AC$11:AC$50)>=SUMIF($A$11:$A$50,G29,$E$11:$E$50)),OR(H29="",SUMIF($A$11:$A$50,H29,AC$11:AC$50)>=SUMIF($A$11:$A$50,H29,$E$11:$E$50))),"ОТКРЫТО","ЗАКРЫТО")) -> ОТКРЫТО | AS29: =IF(AD29>=E29,"ИЗУЧЕНО",IF(AND(OR(F29="",SUMIF($A$11:$A$50,F29,AD$11:AD$50)>=SUMIF($A$11:$A$50,F29,$E$11:$E$50)),OR(G29="",SUMIF($A$11:$A$50,G29,AD$11:AD$50)>=SUMIF($A$11:$A$50,G29,$E$11:$E$50)),OR(H29="",SUMIF($A$11:$A$50,H29,AD$11:AD$50)>=SUMIF($A$11:$A$50,H29,$E$11:$E$50))),"ОТКРЫТО","ЗАКРЫТО")) -> ОТКРЫТО | AT29: =IF(AE29>=E29,"ИЗУЧЕНО",IF(AND(OR(F29="",SUMIF($A$11:$A$50,F29,AE$11:AE$50)>=SUMIF($A$11:$A$50,F29,$E$11:$E$50)),OR(G29="",SUMIF($A$11:$A$50,G29,AE$11:AE$50)>=SUMIF($A$11:$A$50,G29,$E$11:$E$50)),OR(H29="",SUMIF($A$11:$A$50,H29,AE$11:AE$50)>=SUMIF($A$11:$A$50,H29,$E$11:$E$50))),"ОТКРЫТО","ЗАКРЫТО")) -> ОТКРЫТО | AU29: =IF(AF29>=E29,"ИЗУЧЕНО",IF(AND(OR(F29="",SUMIF($A$11:$A$50,F29,AF$11:AF$50)>=SUMIF($A$11:$A$50,F29,$E$11:$E$50)),OR(G29="",SUMIF($A$11:$A$50,G29,AF$11:AF$50)>=SUMIF($A$11:$A$50,G29,$E$11:$E$50)),OR(H29="",SUMIF($A$11:$A$50,H29,AF$11:AF$50)>=SUMIF($A$11:$A$50,H29,$E$11:$E$50))),"ОТКРЫТО","ЗАКРЫТО")) -> ОТКРЫТО | AV29: =IF(AG29>=E29,"ИЗУЧЕНО",IF(AND(OR(F29="",SUMIF($A$11:$A$50,F29,AG$11:AG$50)>=SUMIF($A$11:$A$50,F29,$E$11:$E$50)),OR(G29="",SUMIF($A$11:$A$50,G29,AG$11:AG$50)>=SUMIF($A$11:$A$50,G29,$E$11:$E$50)),OR(H29="",SUMIF($A$11:$A$50,H29,AG$11:AG$50)>=SUMIF($A$11:$A$50,H29,$E$11:$E$50))),"ОТКРЫТО","ЗАКРЫТО")) -> ОТКРЫТО | AW29: =IF(AH29>=E29,"ИЗУЧЕНО",IF(AND(OR(F29="",SUMIF($A$11:$A$50,F29,AH$11:AH$50)>=SUMIF($A$11:$A$50,F29,$E$11:$E$50)),OR(G29="",SUMIF($A$11:$A$50,G29,AH$11:AH$50)>=SUMIF($A$11:$A$50,G29,$E$11:$E$50)),OR(H29="",SUMIF($A$11:$A$50,H29,AH$11:AH$50)>=SUMIF($A$11:$A$50,H29,$E$11:$E$50))),"ОТКРЫТО","ЗАКРЫТО")) -> ОТКРЫТО | AX29: =IF(AI29>=E29,"ИЗУЧЕНО",IF(AND(OR(F29="",SUMIF($A$11:$A$50,F29,AI$11:AI$50)>=SUMIF($A$11:$A$50,F29,$E$11:$E$50)),OR(G29="",SUMIF($A$11:$A$50,G29,AI$11:AI$50)>=SUMIF($A$11:$A$50,G29,$E$11:$E$50)),OR(H29="",SUMIF($A$11:$A$50,H29,AI$11:AI$50)>=SUMIF($A$11:$A$50,H29,$E$11:$E$50))),"ОТКРЫТО","ЗАКРЫТО")) -> ОТКРЫТО | AY29: =IF(AJ29>=E29,"ИЗУЧЕНО",IF(AND(OR(F29="",SUMIF($A$11:$A$50,F29,AJ$11:AJ$50)>=SUMIF($A$11:$A$50,F29,$E$11:$E$50)),OR(G29="",SUMIF($A$11:$A$50,G29,AJ$11:AJ$50)>=SUMIF($A$11:$A$50,G29,$E$11:$E$50)),OR(H29="",SUMIF($A$11:$A$50,H29,AJ$11:AJ$50)>=SUMIF($A$11:$A$50,H29,$E$11:$E$50))),"ОТКРЫТО","ЗАКРЫТО")) -> ОТКРЫТО | AZ29: =IF(AK29>=E29,"ИЗУЧЕНО",IF(AND(OR(F29="",SUMIF($A$11:$A$50,F29,AK$11:AK$50)>=SUMIF($A$11:$A$50,F29,$E$11:$E$50)),OR(G29="",SUMIF($A$11:$A$50,G29,AK$11:AK$50)>=SUMIF($A$11:$A$50,G29,$E$11:$E$50)),OR(H29="",SUMIF($A$11:$A$50,H29,AK$11:AK$50)>=SUMIF($A$11:$A$50,H29,$E$11:$E$50))),"ОТКРЫТО","ЗАКРЫТО")) -> ОТКРЫТО | BA29: =IF(AL29>=E29,"ИЗУЧЕНО",IF(AND(OR(F29="",SUMIF($A$11:$A$50,F29,AL$11:AL$50)>=SUMIF($A$11:$A$50,F29,$E$11:$E$50)),OR(G29="",SUMIF($A$11:$A$50,G29,AL$11:AL$50)>=SUMIF($A$11:$A$50,G29,$E$11:$E$50)),OR(H29="",SUMIF($A$11:$A$50,H29,AL$11:AL$50)>=SUMIF($A$11:$A$50,H29,$E$11:$E$50))),"ОТКРЫТО","ЗАКРЫТО")) -> ОТКРЫТО | BB29: =IF(AM29>=E29,"ИЗУЧЕНО",IF(AND(OR(F29="",SUMIF($A$11:$A$50,F29,AM$11:AM$50)>=SUMIF($A$11:$A$50,F29,$E$11:$E$50)),OR(G29="",SUMIF($A$11:$A$50,G29,AM$11:AM$50)>=SUMIF($A$11:$A$50,G29,$E$11:$E$50)),OR(H29="",SUMIF($A$11:$A$50,H29,AM$11:AM$50)>=SUMIF($A$11:$A$50,H29,$E$11:$E$50))),"ОТКРЫТО","ЗАКРЫТО")) -> ОТКРЫТО | BC29: =IF(AN29>=E29,"ИЗУЧЕНО",IF(AND(OR(F29="",SUMIF($A$11:$A$50,F29,AN$11:AN$50)>=SUMIF($A$11:$A$50,F29,$E$11:$E$50)),OR(G29="",SUMIF($A$11:$A$50,G29,AN$11:AN$50)>=SUMIF($A$11:$A$50,G29,$E$11:$E$50)),OR(H29="",SUMIF($A$11:$A$50,H29,AN$11:AN$50)>=SUMIF($A$11:$A$50,H29,$E$11:$E$50))),"ОТКРЫТО","ЗАКРЫТО")) -> ОТКРЫТО | BD29: =IF(AO29>=E29,"ИЗУЧЕНО",IF(AND(OR(F29="",SUMIF($A$11:$A$50,F29,AO$11:AO$50)>=SUMIF($A$11:$A$50,F29,$E$11:$E$50)),OR(G29="",SUMIF($A$11:$A$50,G29,AO$11:AO$50)>=SUMIF($A$11:$A$50,G29,$E$11:$E$50)),OR(H29="",SUMIF($A$11:$A$50,H29,AO$11:AO$50)>=SUMIF($A$11:$A$50,H29,$E$11:$E$50))),"ОТКРЫТО","ЗАКРЫТО")) -> ОТКРЫТО | BE29: =IF(AP29>=E29,"ИЗУЧЕНО",IF(AND(OR(F29="",SUMIF($A$11:$A$50,F29,AP$11:AP$50)>=SUMIF($A$11:$A$50,F29,$E$11:$E$50)),OR(G29="",SUMIF($A$11:$A$50,G29,AP$11:AP$50)>=SUMIF($A$11:$A$50,G29,$E$11:$E$50)),OR(H29="",SUMIF($A$11:$A$50,H29,AP$11:AP$50)>=SUMIF($A$11:$A$50,H29,$E$11:$E$50))),"ОТКРЫТО","ЗАКРЫТО")) -> ОТКРЫТО | BF29: =IF(AQ29>=E29,"ИЗУЧЕНО",IF(AND(OR(F29="",SUMIF($A$11:$A$50,F29,AQ$11:AQ$50)>=SUMIF($A$11:$A$50,F29,$E$11:$E$50)),OR(G29="",SUMIF($A$11:$A$50,G29,AQ$11:AQ$50)>=SUMIF($A$11:$A$50,G29,$E$11:$E$50)),OR(H29="",SUMIF($A$11:$A$50,H29,AQ$11:AQ$50)>=SUMIF($A$11:$A$50,H29,$E$11:$E$50))),"ОТКРЫТО","ЗАКРЫТО")) -> ОТКРЫТО
A30: A2 | B30: Агенты и автономные системы | C30: II | D30: Агенты рабочих процессов | E30: 35 | F30: A1 | I30: Выполнение многошаговых процессов внутри организаций. | J30: Организационная архитектура внедрения +0,3; её прирост +0,08/год | K30: =SUMIF('Ход 2026'!$G$29:$G$38,$A30,'Ход 2026'!$I$29:$I$38) -> 0 | L30: =SUMIF('Ход 2027'!$G$29:$G$38,$A30,'Ход 2027'!$I$29:$I$38) -> 0 | M30: =SUMIF('Ход 2028'!$G$29:$G$38,$A30,'Ход 2028'!$I$29:$I$38) -> 0 | N30: =SUMIF('Ход 2029'!$G$29:$G$38,$A30,'Ход 2029'!$I$29:$I$38) -> 0 | O30: =SUMIF('Ход 2030'!$G$29:$G$38,$A30,'Ход 2030'!$I$29:$I$38) -> 0 | P30: =SUMIF('Ход 2031'!$G$29:$G$38,$A30,'Ход 2031'!$I$29:$I$38) -> 0 | Q30: =SUMIF('Ход 2032'!$G$29:$G$38,$A30,'Ход 2032'!$I$29:$I$38) -> 0 | R30: =SUMIF('Ход 2033'!$G$29:$G$38,$A30,'Ход 2033'!$I$29:$I$38) -> 0 | S30: =SUMIF('Ход 2034'!$G$29:$G$38,$A30,'Ход 2034'!$I$29:$I$38) -> 0 | T30: =SUMIF('Ход 2035'!$G$29:$G$38,$A30,'Ход 2035'!$I$29:$I$38) -> 0 | U30: =SUMIF('Ход 2036'!$G$29:$G$38,$A30,'Ход 2036'!$I$29:$I$38) -> 0 | V30: =SUMIF('Ход 2037'!$G$29:$G$38,$A30,'Ход 2037'!$I$29:$I$38) -> 0 | W30: =SUMIF('Ход 2038'!$G$29:$G$38,$A30,'Ход 2038'!$I$29:$I$38) -> 0 | X30: =SUMIF('Ход 2039'!$G$29:$G$38,$A30,'Ход 2039'!$I$29:$I$38) -> 0 | Y30: =SUMIF('Ход 2040'!$G$29:$G$38,$A30,'Ход 2040'!$I$29:$I$38) -> 0 | Z30: =SUM(K30:Y30) -> 0 | AA30: =MAX(0,E30-Z30) -> 35 | AB30: =BF30 -> ЗАКРЫТО | AC30: =SUM($K30:K30) -> 0 | AD30: =SUM($K30:L30) -> 0 | AE30: =SUM($K30:M30) -> 0 | AF30: =SUM($K30:N30) -> 0 | AG30: =SUM($K30:O30) -> 0 | AH30: =SUM($K30:P30) -> 0 | AI30: =SUM($K30:Q30) -> 0 | AJ30: =SUM($K30:R30) -> 0 | ... AQ30: =SUM($K30:Y30) -> 0 | AR30: =IF(AC30>=E30,"ИЗУЧЕНО",IF(AND(OR(F30="",SUMIF($A$11:$A$50,F30,AC$11:AC$50)>=SUMIF($A$11:$A$50,F30,$E$11:$E$50)),OR(G30="",SUMIF($A$11:$A$50,G30,AC$11:AC$50)>=SUMIF($A$11:$A$50,G30,$E$11:$E$50)),OR(H30="",SUMIF($A$11:$A$50,H30,AC$11:AC$50)>=SUMIF($A$11:$A$50,H30,$E$11:$E$50))),"ОТКРЫТО","ЗАКРЫТО")) -> ЗАКРЫТО | AS30: =IF(AD30>=E30,"ИЗУЧЕНО",IF(AND(OR(F30="",SUMIF($A$11:$A$50,F30,AD$11:AD$50)>=SUMIF($A$11:$A$50,F30,$E$11:$E$50)),OR(G30="",SUMIF($A$11:$A$50,G30,AD$11:AD$50)>=SUMIF($A$11:$A$50,G30,$E$11:$E$50)),OR(H30="",SUMIF($A$11:$A$50,H30,AD$11:AD$50)>=SUMIF($A$11:$A$50,H30,$E$11:$E$50))),"ОТКРЫТО","ЗАКРЫТО")) -> ЗАКРЫТО | AT30: =IF(AE30>=E30,"ИЗУЧЕНО",IF(AND(OR(F30="",SUMIF($A$11:$A$50,F30,AE$11:AE$50)>=SUMIF($A$11:$A$50,F30,$E$11:$E$50)),OR(G30="",SUMIF($A$11:$A$50,G30,AE$11:AE$50)>=SUMIF($A$11:$A$50,G30,$E$11:$E$50)),OR(H30="",SUMIF($A$11:$A$50,H30,AE$11:AE$50)>=SUMIF($A$11:$A$50,H30,$E$11:$E$50))),"ОТКРЫТО","ЗАКРЫТО")) -> ЗАКРЫТО | AU30: =IF(AF30>=E30,"ИЗУЧЕНО",IF(AND(OR(F30="",SUMIF($A$11:$A$50,F30,AF$11:AF$50)>=SUMIF($A$11:$A$50,F30,$E$11:$E$50)),OR(G30="",SUMIF($A$11:$A$50,G30,AF$11:AF$50)>=SUMIF($A$11:$A$50,G30,$E$11:$E$50)),OR(H30="",SUMIF($A$11:$A$50,H30,AF$11:AF$50)>=SUMIF($A$11:$A$50,H30,$E$11:$E$50))),"ОТКРЫТО","ЗАКРЫТО")) -> ЗАКРЫТО | AV30: =IF(AG30>=E30,"ИЗУЧЕНО",IF(AND(OR(F30="",SUMIF($A$11:$A$50,F30,AG$11:AG$50)>=SUMIF($A$11:$A$50,F30,$E$11:$E$50)),OR(G30="",SUMIF($A$11:$A$50,G30,AG$11:AG$50)>=SUMIF($A$11:$A$50,G30,$E$11:$E$50)),OR(H30="",SUMIF($A$11:$A$50,H30,AG$11:AG$50)>=SUMIF($A$11:$A$50,H30,$E$11:$E$50))),"ОТКРЫТО","ЗАКРЫТО")) -> ЗАКРЫТО | AW30: =IF(AH30>=E30,"ИЗУЧЕНО",IF(AND(OR(F30="",SUMIF($A$11:$A$50,F30,AH$11:AH$50)>=SUMIF($A$11:$A$50,F30,$E$11:$E$50)),OR(G30="",SUMIF($A$11:$A$50,G30,AH$11:AH$50)>=SUMIF($A$11:$A$50,G30,$E$11:$E$50)),OR(H30="",SUMIF($A$11:$A$50,H30,AH$11:AH$50)>=SUMIF($A$11:$A$50,H30,$E$11:$E$50))),"ОТКРЫТО","ЗАКРЫТО")) -> ЗАКРЫТО | AX30: =IF(AI30>=E30,"ИЗУЧЕНО",IF(AND(OR(F30="",SUMIF($A$11:$A$50,F30,AI$11:AI$50)>=SUMIF($A$11:$A$50,F30,$E$11:$E$50)),OR(G30="",SUMIF($A$11:$A$50,G30,AI$11:AI$50)>=SUMIF($A$11:$A$50,G30,$E$11:$E$50)),OR(H30="",SUMIF($A$11:$A$50,H30,AI$11:AI$50)>=SUMIF($A$11:$A$50,H30,$E$11:$E$50))),"ОТКРЫТО","ЗАКРЫТО")) -> ЗАКРЫТО | AY30: =IF(AJ30>=E30,"ИЗУЧЕНО",IF(AND(OR(F30="",SUMIF($A$11:$A$50,F30,AJ$11:AJ$50)>=SUMIF($A$11:$A$50,F30,$E$11:$E$50)),OR(G30="",SUMIF($A$11:$A$50,G30,AJ$11:AJ$50)>=SUMIF($A$11:$A$50,G30,$E$11:$E$50)),OR(H30="",SUMIF($A$11:$A$50,H30,AJ$11:AJ$50)>=SUMIF($A$11:$A$50,H30,$E$11:$E$50))),"ОТКРЫТО","ЗАКРЫТО")) -> ЗАКРЫТО | AZ30: =IF(AK30>=E30,"ИЗУЧЕНО",IF(AND(OR(F30="",SUMIF($A$11:$A$50,F30,AK$11:AK$50)>=SUMIF($A$11:$A$50,F30,$E$11:$E$50)),OR(G30="",SUMIF($A$11:$A$50,G30,AK$11:AK$50)>=SUMIF($A$11:$A$50,G30,$E$11:$E$50)),OR(H30="",SUMIF($A$11:$A$50,H30,AK$11:AK$50)>=SUMIF($A$11:$A$50,H30,$E$11:$E$50))),"ОТКРЫТО","ЗАКРЫТО")) -> ЗАКРЫТО | BA30: =IF(AL30>=E30,"ИЗУЧЕНО",IF(AND(OR(F30="",SUMIF($A$11:$A$50,F30,AL$11:AL$50)>=SUMIF($A$11:$A$50,F30,$E$11:$E$50)),OR(G30="",SUMIF($A$11:$A$50,G30,AL$11:AL$50)>=SUMIF($A$11:$A$50,G30,$E$11:$E$50)),OR(H30="",SUMIF($A$11:$A$50,H30,AL$11:AL$50)>=SUMIF($A$11:$A$50,H30,$E$11:$E$50))),"ОТКРЫТО","ЗАКРЫТО")) -> ЗАКРЫТО | BB30: =IF(AM30>=E30,"ИЗУЧЕНО",IF(AND(OR(F30="",SUMIF($A$11:$A$50,F30,AM$11:AM$50)>=SUMIF($A$11:$A$50,F30,$E$11:$E$50)),OR(G30="",SUMIF($A$11:$A$50,G30,AM$11:AM$50)>=SUMIF($A$11:$A$50,G30,$E$11:$E$50)),OR(H30="",SUMIF($A$11:$A$50,H30,AM$11:AM$50)>=SUMIF($A$11:$A$50,H30,$E$11:$E$50))),"ОТКРЫТО","ЗАКРЫТО")) -> ЗАКРЫТО | BC30: =IF(AN30>=E30,"ИЗУЧЕНО",IF(AND(OR(F30="",SUMIF($A$11:$A$50,F30,AN$11:AN$50)>=SUMIF($A$11:$A$50,F30,$E$11:$E$50)),OR(G30="",SUMIF($A$11:$A$50,G30,AN$11:AN$50)>=SUMIF($A$11:$A$50,G30,$E$11:$E$50)),OR(H30="",SUMIF($A$11:$A$50,H30,AN$11:AN$50)>=SUMIF($A$11:$A$50,H30,$E$11:$E$50))),"ОТКРЫТО","ЗАКРЫТО")) -> ЗАКРЫТО | BD30: =IF(AO30>=E30,"ИЗУЧЕНО",IF(AND(OR(F30="",SUMIF($A$11:$A$50,F30,AO$11:AO$50)>=SUMIF($A$11:$A$50,F30,$E$11:$E$50)),OR(G30="",SUMIF($A$11:$A$50,G30,AO$11:AO$50)>=SUMIF($A$11:$A$50,G30,$E$11:$E$50)),OR(H30="",SUMIF($A$11:$A$50,H30,AO$11:AO$50)>=SUMIF($A$11:$A$50,H30,$E$11:$E$50))),"ОТКРЫТО","ЗАКРЫТО")) -> ЗАКРЫТО | BE30: =IF(AP30>=E30,"ИЗУЧЕНО",IF(AND(OR(F30="",SUMIF($A$11:$A$50,F30,AP$11:AP$50)>=SUMIF($A$11:$A$50,F30,$E$11:$E$50)),OR(G30="",SUMIF($A$11:$A$50,G30,AP$11:AP$50)>=SUMIF($A$11:$A$50,G30,$E$11:$E$50)),OR(H30="",SUMIF($A$11:$A$50,H30,AP$11:AP$50)>=SUMIF($A$11:$A$50,H30,$E$11:$E$50))),"ОТКРЫТО","ЗАКРЫТО")) -> ЗАКРЫТО | BF30: =IF(AQ30>=E30,"ИЗУЧЕНО",IF(AND(OR(F30="",SUMIF($A$11:$A$50,F30,AQ$11:AQ$50)>=SUMIF($A$11:$A$50,F30,$E$11:$E$50)),OR(G30="",SUMIF($A$11:$A$50,G30,AQ$11:AQ$50)>=SUMIF($A$11:$A$50,G30,$E$11:$E$50)),OR(H30="",SUMIF($A$11:$A$50,H30,AQ$11:AQ$50)>=SUMIF($A$11:$A$50,H30,$E$11:$E$50))),"ОТКРЫТО","ЗАКРЫТО")) -> ЗАКРЫТО
A31: A3 | B31: Агенты и автономные системы | C31: III | D31: Многоагентная оркестрация | E31: 55 | F31: A2 | I31: Координация множества специализированных агентов. | J31: Прирост Управления +0,08/год; атака Афины +10% | K31: =SUMIF('Ход 2026'!$G$29:$G$38,$A31,'Ход 2026'!$I$29:$I$38) -> 0 | L31: =SUMIF('Ход 2027'!$G$29:$G$38,$A31,'Ход 2027'!$I$29:$I$38) -> 0 | M31: =SUMIF('Ход 2028'!$G$29:$G$38,$A31,'Ход 2028'!$I$29:$I$38) -> 0 | N31: =SUMIF('Ход 2029'!$G$29:$G$38,$A31,'Ход 2029'!$I$29:$I$38) -> 0 | O31: =SUMIF('Ход 2030'!$G$29:$G$38,$A31,'Ход 2030'!$I$29:$I$38) -> 0 | P31: =SUMIF('Ход 2031'!$G$29:$G$38,$A31,'Ход 2031'!$I$29:$I$38) -> 0 | Q31: =SUMIF('Ход 2032'!$G$29:$G$38,$A31,'Ход 2032'!$I$29:$I$38) -> 0 | R31: =SUMIF('Ход 2033'!$G$29:$G$38,$A31,'Ход 2033'!$I$29:$I$38) -> 0 | S31: =SUMIF('Ход 2034'!$G$29:$G$38,$A31,'Ход 2034'!$I$29:$I$38) -> 0 | T31: =SUMIF('Ход 2035'!$G$29:$G$38,$A31,'Ход 2035'!$I$29:$I$38) -> 0 | U31: =SUMIF('Ход 2036'!$G$29:$G$38,$A31,'Ход 2036'!$I$29:$I$38) -> 0 | V31: =SUMIF('Ход 2037'!$G$29:$G$38,$A31,'Ход 2037'!$I$29:$I$38) -> 0 | W31: =SUMIF('Ход 2038'!$G$29:$G$38,$A31,'Ход 2038'!$I$29:$I$38) -> 0 | X31: =SUMIF('Ход 2039'!$G$29:$G$38,$A31,'Ход 2039'!$I$29:$I$38) -> 0 | Y31: =SUMIF('Ход 2040'!$G$29:$G$38,$A31,'Ход 2040'!$I$29:$I$38) -> 0 | Z31: =SUM(K31:Y31) -> 0 | AA31: =MAX(0,E31-Z31) -> 55 | AB31: =BF31 -> ЗАКРЫТО | AC31: =SUM($K31:K31) -> 0 | AD31: =SUM($K31:L31) -> 0 | AE31: =SUM($K31:M31) -> 0 | AF31: =SUM($K31:N31) -> 0 | AG31: =SUM($K31:O31) -> 0 | AH31: =SUM($K31:P31) -> 0 | AI31: =SUM($K31:Q31) -> 0 | AJ31: =SUM($K31:R31) -> 0 | ... AQ31: =SUM($K31:Y31) -> 0 | AR31: =IF(AC31>=E31,"ИЗУЧЕНО",IF(AND(OR(F31="",SUMIF($A$11:$A$50,F31,AC$11:AC$50)>=SUMIF($A$11:$A$50,F31,$E$11:$E$50)),OR(G31="",SUMIF($A$11:$A$50,G31,AC$11:AC$50)>=SUMIF($A$11:$A$50,G31,$E$11:$E$50)),OR(H31="",SUMIF($A$11:$A$50,H31,AC$11:AC$50)>=SUMIF($A$11:$A$50,H31,$E$11:$E$50))),"ОТКРЫТО","ЗАКРЫТО")) -> ЗАКРЫТО | AS31: =IF(AD31>=E31,"ИЗУЧЕНО",IF(AND(OR(F31="",SUMIF($A$11:$A$50,F31,AD$11:AD$50)>=SUMIF($A$11:$A$50,F31,$E$11:$E$50)),OR(G31="",SUMIF($A$11:$A$50,G31,AD$11:AD$50)>=SUMIF($A$11:$A$50,G31,$E$11:$E$50)),OR(H31="",SUMIF($A$11:$A$50,H31,AD$11:AD$50)>=SUMIF($A$11:$A$50,H31,$E$11:$E$50))),"ОТКРЫТО","ЗАКРЫТО")) -> ЗАКРЫТО | AT31: =IF(AE31>=E31,"ИЗУЧЕНО",IF(AND(OR(F31="",SUMIF($A$11:$A$50,F31,AE$11:AE$50)>=SUMIF($A$11:$A$50,F31,$E$11:$E$50)),OR(G31="",SUMIF($A$11:$A$50,G31,AE$11:AE$50)>=SUMIF($A$11:$A$50,G31,$E$11:$E$50)),OR(H31="",SUMIF($A$11:$A$50,H31,AE$11:AE$50)>=SUMIF($A$11:$A$50,H31,$E$11:$E$50))),"ОТКРЫТО","ЗАКРЫТО")) -> ЗАКРЫТО | AU31: =IF(AF31>=E31,"ИЗУЧЕНО",IF(AND(OR(F31="",SUMIF($A$11:$A$50,F31,AF$11:AF$50)>=SUMIF($A$11:$A$50,F31,$E$11:$E$50)),OR(G31="",SUMIF($A$11:$A$50,G31,AF$11:AF$50)>=SUMIF($A$11:$A$50,G31,$E$11:$E$50)),OR(H31="",SUMIF($A$11:$A$50,H31,AF$11:AF$50)>=SUMIF($A$11:$A$50,H31,$E$11:$E$50))),"ОТКРЫТО","ЗАКРЫТО")) -> ЗАКРЫТО | AV31: =IF(AG31>=E31,"ИЗУЧЕНО",IF(AND(OR(F31="",SUMIF($A$11:$A$50,F31,AG$11:AG$50)>=SUMIF($A$11:$A$50,F31,$E$11:$E$50)),OR(G31="",SUMIF($A$11:$A$50,G31,AG$11:AG$50)>=SUMIF($A$11:$A$50,G31,$E$11:$E$50)),OR(H31="",SUMIF($A$11:$A$50,H31,AG$11:AG$50)>=SUMIF($A$11:$A$50,H31,$E$11:$E$50))),"ОТКРЫТО","ЗАКРЫТО")) -> ЗАКРЫТО | AW31: =IF(AH31>=E31,"ИЗУЧЕНО",IF(AND(OR(F31="",SUMIF($A$11:$A$50,F31,AH$11:AH$50)>=SUMIF($A$11:$A$50,F31,$E$11:$E$50)),OR(G31="",SUMIF($A$11:$A$50,G31,AH$11:AH$50)>=SUMIF($A$11:$A$50,G31,$E$11:$E$50)),OR(H31="",SUMIF($A$11:$A$50,H31,AH$11:AH$50)>=SUMIF($A$11:$A$50,H31,$E$11:$E$50))),"ОТКРЫТО","ЗАКРЫТО")) -> ЗАКРЫТО | AX31: =IF(AI31>=E31,"ИЗУЧЕНО",IF(AND(OR(F31="",SUMIF($A$11:$A$50,F31,AI$11:AI$50)>=SUMIF($A$11:$A$50,F31,$E$11:$E$50)),OR(G31="",SUMIF($A$11:$A$50,G31,AI$11:AI$50)>=SUMIF($A$11:$A$50,G31,$E$11:$E$50)),OR(H31="",SUMIF($A$11:$A$50,H31,AI$11:AI$50)>=SUMIF($A$11:$A$50,H31,$E$11:$E$50))),"ОТКРЫТО","ЗАКРЫТО")) -> ЗАКРЫТО | AY31: =IF(AJ31>=E31,"ИЗУЧЕНО",IF(AND(OR(F31="",SUMIF($A$11:$A$50,F31,AJ$11:AJ$50)>=SUMIF($A$11:$A$50,F31,$E$11:$E$50)),OR(G31="",SUMIF($A$11:$A$50,G31,AJ$11:AJ$50)>=SUMIF($A$11:$A$50,G31,$E$11:$E$50)),OR(H31="",SUMIF($A$11:$A$50,H31,AJ$11:AJ$50)>=SUMIF($A$11:$A$50,H31,$E$11:$E$50))),"ОТКРЫТО","ЗАКРЫТО")) -> ЗАКРЫТО | AZ31: =IF(AK31>=E31,"ИЗУЧЕНО",IF(AND(OR(F31="",SUMIF($A$11:$A$50,F31,AK$11:AK$50)>=SUMIF($A$11:$A$50,F31,$E$11:$E$50)),OR(G31="",SUMIF($A$11:$A$50,G31,AK$11:AK$50)>=SUMIF($A$11:$A$50,G31,$E$11:$E$50)),OR(H31="",SUMIF($A$11:$A$50,H31,AK$11:AK$50)>=SUMIF($A$11:$A$50,H31,$E$11:$E$50))),"ОТКРЫТО","ЗАКРЫТО")) -> ЗАКРЫТО | BA31: =IF(AL31>=E31,"ИЗУЧЕНО",IF(AND(OR(F31="",SUMIF($A$11:$A$50,F31,AL$11:AL$50)>=SUMIF($A$11:$A$50,F31,$E$11:$E$50)),OR(G31="",SUMIF($A$11:$A$50,G31,AL$11:AL$50)>=SUMIF($A$11:$A$50,G31,$E$11:$E$50)),OR(H31="",SUMIF($A$11:$A$50,H31,AL$11:AL$50)>=SUMIF($A$11:$A$50,H31,$E$11:$E$50))),"ОТКРЫТО","ЗАКРЫТО")) -> ЗАКРЫТО | BB31: =IF(AM31>=E31,"ИЗУЧЕНО",IF(AND(OR(F31="",SUMIF($A$11:$A$50,F31,AM$11:AM$50)>=SUMIF($A$11:$A$50,F31,$E$11:$E$50)),OR(G31="",SUMIF($A$11:$A$50,G31,AM$11:AM$50)>=SUMIF($A$11:$A$50,G31,$E$11:$E$50)),OR(H31="",SUMIF($A$11:$A$50,H31,AM$11:AM$50)>=SUMIF($A$11:$A$50,H31,$E$11:$E$50))),"ОТКРЫТО","ЗАКРЫТО")) -> ЗАКРЫТО | BC31: =IF(AN31>=E31,"ИЗУЧЕНО",IF(AND(OR(F31="",SUMIF($A$11:$A$50,F31,AN$11:AN$50)>=SUMIF($A$11:$A$50,F31,$E$11:$E$50)),OR(G31="",SUMIF($A$11:$A$50,G31,AN$11:AN$50)>=SUMIF($A$11:$A$50,G31,$E$11:$E$50)),OR(H31="",SUMIF($A$11:$A$50,H31,AN$11:AN$50)>=SUMIF($A$11:$A$50,H31,$E$11:$E$50))),"ОТКРЫТО","ЗАКРЫТО")) -> ЗАКРЫТО | BD31: =IF(AO31>=E31,"ИЗУЧЕНО",IF(AND(OR(F31="",SUMIF($A$11:$A$50,F31,AO$11:AO$50)>=SUMIF($A$11:$A$50,F31,$E$11:$E$50)),OR(G31="",SUMIF($A$11:$A$50,G31,AO$11:AO$50)>=SUMIF($A$11:$A$50,G31,$E$11:$E$50)),OR(H31="",SUMIF($A$11:$A$50,H31,AO$11:AO$50)>=SUMIF($A$11:$A$50,H31,$E$11:$E$50))),"ОТКРЫТО","ЗАКРЫТО")) -> ЗАКРЫТО | BE31: =IF(AP31>=E31,"ИЗУЧЕНО",IF(AND(OR(F31="",SUMIF($A$11:$A$50,F31,AP$11:AP$50)>=SUMIF($A$11:$A$50,F31,$E$11:$E$50)),OR(G31="",SUMIF($A$11:$A$50,G31,AP$11:AP$50)>=SUMIF($A$11:$A$50,G31,$E$11:$E$50)),OR(H31="",SUMIF($A$11:$A$50,H31,AP$11:AP$50)>=SUMIF($A$11:$A$50,H31,$E$11:$E$50))),"ОТКРЫТО","ЗАКРЫТО")) -> ЗАКРЫТО | BF31: =IF(AQ31>=E31,"ИЗУЧЕНО",IF(AND(OR(F31="",SUMIF($A$11:$A$50,F31,AQ$11:AQ$50)>=SUMIF($A$11:$A$50,F31,$E$11:$E$50)),OR(G31="",SUMIF($A$11:$A$50,G31,AQ$11:AQ$50)>=SUMIF($A$11:$A$50,G31,$E$11:$E$50)),OR(H31="",SUMIF($A$11:$A$50,H31,AQ$11:AQ$50)>=SUMIF($A$11:$A$50,H31,$E$11:$E$50))),"ОТКРЫТО","ЗАКРЫТО")) -> ЗАКРЫТО
A32: A4 | B32: Агенты и автономные системы | C32: III | D32: Автономные организационные процессы | E32: 70 | F32: A3 | I32: Автоматическое ведение существенной части типовых процессов организаций. | J32: Организационная способность к изменению +0,4; прирост Экономики +0,08/год | K32: =SUMIF('Ход 2026'!$G$29:$G$38,$A32,'Ход 2026'!$I$29:$I$38) -> 0 | L32: =SUMIF('Ход 2027'!$G$29:$G$38,$A32,'Ход 2027'!$I$29:$I$38) -> 0 | M32: =SUMIF('Ход 2028'!$G$29:$G$38,$A32,'Ход 2028'!$I$29:$I$38) -> 0 | N32: =SUMIF('Ход 2029'!$G$29:$G$38,$A32,'Ход 2029'!$I$29:$I$38) -> 0 | O32: =SUMIF('Ход 2030'!$G$29:$G$38,$A32,'Ход 2030'!$I$29:$I$38) -> 0 | P32: =SUMIF('Ход 2031'!$G$29:$G$38,$A32,'Ход 2031'!$I$29:$I$38) -> 0 | Q32: =SUMIF('Ход 2032'!$G$29:$G$38,$A32,'Ход 2032'!$I$29:$I$38) -> 0 | R32: =SUMIF('Ход 2033'!$G$29:$G$38,$A32,'Ход 2033'!$I$29:$I$38) -> 0 | S32: =SUMIF('Ход 2034'!$G$29:$G$38,$A32,'Ход 2034'!$I$29:$I$38) -> 0 | T32: =SUMIF('Ход 2035'!$G$29:$G$38,$A32,'Ход 2035'!$I$29:$I$38) -> 0 | U32: =SUMIF('Ход 2036'!$G$29:$G$38,$A32,'Ход 2036'!$I$29:$I$38) -> 0 | V32: =SUMIF('Ход 2037'!$G$29:$G$38,$A32,'Ход 2037'!$I$29:$I$38) -> 0 | W32: =SUMIF('Ход 2038'!$G$29:$G$38,$A32,'Ход 2038'!$I$29:$I$38) -> 0 | X32: =SUMIF('Ход 2039'!$G$29:$G$38,$A32,'Ход 2039'!$I$29:$I$38) -> 0 | Y32: =SUMIF('Ход 2040'!$G$29:$G$38,$A32,'Ход 2040'!$I$29:$I$38) -> 0 | Z32: =SUM(K32:Y32) -> 0 | AA32: =MAX(0,E32-Z32) -> 70 | AB32: =BF32 -> ЗАКРЫТО | AC32: =SUM($K32:K32) -> 0 | AD32: =SUM($K32:L32) -> 0 | AE32: =SUM($K32:M32) -> 0 | AF32: =SUM($K32:N32) -> 0 | AG32: =SUM($K32:O32) -> 0 | AH32: =SUM($K32:P32) -> 0 | AI32: =SUM($K32:Q32) -> 0 | AJ32: =SUM($K32:R32) -> 0 | ... AQ32: =SUM($K32:Y32) -> 0 | AR32: =IF(AC32>=E32,"ИЗУЧЕНО",IF(AND(OR(F32="",SUMIF($A$11:$A$50,F32,AC$11:AC$50)>=SUMIF($A$11:$A$50,F32,$E$11:$E$50)),OR(G32="",SUMIF($A$11:$A$50,G32,AC$11:AC$50)>=SUMIF($A$11:$A$50,G32,$E$11:$E$50)),OR(H32="",SUMIF($A$11:$A$50,H32,AC$11:AC$50)>=SUMIF($A$11:$A$50,H32,$E$11:$E$50))),"ОТКРЫТО","ЗАКРЫТО")) -> ЗАКРЫТО | AS32: =IF(AD32>=E32,"ИЗУЧЕНО",IF(AND(OR(F32="",SUMIF($A$11:$A$50,F32,AD$11:AD$50)>=SUMIF($A$11:$A$50,F32,$E$11:$E$50)),OR(G32="",SUMIF($A$11:$A$50,G32,AD$11:AD$50)>=SUMIF($A$11:$A$50,G32,$E$11:$E$50)),OR(H32="",SUMIF($A$11:$A$50,H32,AD$11:AD$50)>=SUMIF($A$11:$A$50,H32,$E$11:$E$50))),"ОТКРЫТО","ЗАКРЫТО")) -> ЗАКРЫТО | AT32: =IF(AE32>=E32,"ИЗУЧЕНО",IF(AND(OR(F32="",SUMIF($A$11:$A$50,F32,AE$11:AE$50)>=SUMIF($A$11:$A$50,F32,$E$11:$E$50)),OR(G32="",SUMIF($A$11:$A$50,G32,AE$11:AE$50)>=SUMIF($A$11:$A$50,G32,$E$11:$E$50)),OR(H32="",SUMIF($A$11:$A$50,H32,AE$11:AE$50)>=SUMIF($A$11:$A$50,H32,$E$11:$E$50))),"ОТКРЫТО","ЗАКРЫТО")) -> ЗАКРЫТО | AU32: =IF(AF32>=E32,"ИЗУЧЕНО",IF(AND(OR(F32="",SUMIF($A$11:$A$50,F32,AF$11:AF$50)>=SUMIF($A$11:$A$50,F32,$E$11:$E$50)),OR(G32="",SUMIF($A$11:$A$50,G32,AF$11:AF$50)>=SUMIF($A$11:$A$50,G32,$E$11:$E$50)),OR(H32="",SUMIF($A$11:$A$50,H32,AF$11:AF$50)>=SUMIF($A$11:$A$50,H32,$E$11:$E$50))),"ОТКРЫТО","ЗАКРЫТО")) -> ЗАКРЫТО | AV32: =IF(AG32>=E32,"ИЗУЧЕНО",IF(AND(OR(F32="",SUMIF($A$11:$A$50,F32,AG$11:AG$50)>=SUMIF($A$11:$A$50,F32,$E$11:$E$50)),OR(G32="",SUMIF($A$11:$A$50,G32,AG$11:AG$50)>=SUMIF($A$11:$A$50,G32,$E$11:$E$50)),OR(H32="",SUMIF($A$11:$A$50,H32,AG$11:AG$50)>=SUMIF($A$11:$A$50,H32,$E$11:$E$50))),"ОТКРЫТО","ЗАКРЫТО")) -> ЗАКРЫТО | AW32: =IF(AH32>=E32,"ИЗУЧЕНО",IF(AND(OR(F32="",SUMIF($A$11:$A$50,F32,AH$11:AH$50)>=SUMIF($A$11:$A$50,F32,$E$11:$E$50)),OR(G32="",SUMIF($A$11:$A$50,G32,AH$11:AH$50)>=SUMIF($A$11:$A$50,G32,$E$11:$E$50)),OR(H32="",SUMIF($A$11:$A$50,H32,AH$11:AH$50)>=SUMIF($A$11:$A$50,H32,$E$11:$E$50))),"ОТКРЫТО","ЗАКРЫТО")) -> ЗАКРЫТО | AX32: =IF(AI32>=E32,"ИЗУЧЕНО",IF(AND(OR(F32="",SUMIF($A$11:$A$50,F32,AI$11:AI$50)>=SUMIF($A$11:$A$50,F32,$E$11:$E$50)),OR(G32="",SUMIF($A$11:$A$50,G32,AI$11:AI$50)>=SUMIF($A$11:$A$50,G32,$E$11:$E$50)),OR(H32="",SUMIF($A$11:$A$50,H32,AI$11:AI$50)>=SUMIF($A$11:$A$50,H32,$E$11:$E$50))),"ОТКРЫТО","ЗАКРЫТО")) -> ЗАКРЫТО | AY32: =IF(AJ32>=E32,"ИЗУЧЕНО",IF(AND(OR(F32="",SUMIF($A$11:$A$50,F32,AJ$11:AJ$50)>=SUMIF($A$11:$A$50,F32,$E$11:$E$50)),OR(G32="",SUMIF($A$11:$A$50,G32,AJ$11:AJ$50)>=SUMIF($A$11:$A$50,G32,$E$11:$E$50)),OR(H32="",SUMIF($A$11:$A$50,H32,AJ$11:AJ$50)>=SUMIF($A$11:$A$50,H32,$E$11:$E$50))),"ОТКРЫТО","ЗАКРЫТО")) -> ЗАКРЫТО | AZ32: =IF(AK32>=E32,"ИЗУЧЕНО",IF(AND(OR(F32="",SUMIF($A$11:$A$50,F32,AK$11:AK$50)>=SUMIF($A$11:$A$50,F32,$E$11:$E$50)),OR(G32="",SUMIF($A$11:$A$50,G32,AK$11:AK$50)>=SUMIF($A$11:$A$50,G32,$E$11:$E$50)),OR(H32="",SUMIF($A$11:$A$50,H32,AK$11:AK$50)>=SUMIF($A$11:$A$50,H32,$E$11:$E$50))),"ОТКРЫТО","ЗАКРЫТО")) -> ЗАКРЫТО | BA32: =IF(AL32>=E32,"ИЗУЧЕНО",IF(AND(OR(F32="",SUMIF($A$11:$A$50,F32,AL$11:AL$50)>=SUMIF($A$11:$A$50,F32,$E$11:$E$50)),OR(G32="",SUMIF($A$11:$A$50,G32,AL$11:AL$50)>=SUMIF($A$11:$A$50,G32,$E$11:$E$50)),OR(H32="",SUMIF($A$11:$A$50,H32,AL$11:AL$50)>=SUMIF($A$11:$A$50,H32,$E$11:$E$50))),"ОТКРЫТО","ЗАКРЫТО")) -> ЗАКРЫТО | BB32: =IF(AM32>=E32,"ИЗУЧЕНО",IF(AND(OR(F32="",SUMIF($A$11:$A$50,F32,AM$11:AM$50)>=SUMIF($A$11:$A$50,F32,$E$11:$E$50)),OR(G32="",SUMIF($A$11:$A$50,G32,AM$11:AM$50)>=SUMIF($A$11:$A$50,G32,$E$11:$E$50)),OR(H32="",SUMIF($A$11:$A$50,H32,AM$11:AM$50)>=SUMIF($A$11:$A$50,H32,$E$11:$E$50))),"ОТКРЫТО","ЗАКРЫТО")) -> ЗАКРЫТО | BC32: =IF(AN32>=E32,"ИЗУЧЕНО",IF(AND(OR(F32="",SUMIF($A$11:$A$50,F32,AN$11:AN$50)>=SUMIF($A$11:$A$50,F32,$E$11:$E$50)),OR(G32="",SUMIF($A$11:$A$50,G32,AN$11:AN$50)>=SUMIF($A$11:$A$50,G32,$E$11:$E$50)),OR(H32="",SUMIF($A$11:$A$50,H32,AN$11:AN$50)>=SUMIF($A$11:$A$50,H32,$E$11:$E$50))),"ОТКРЫТО","ЗАКРЫТО")) -> ЗАКРЫТО | BD32: =IF(AO32>=E32,"ИЗУЧЕНО",IF(AND(OR(F32="",SUMIF($A$11:$A$50,F32,AO$11:AO$50)>=SUMIF($A$11:$A$50,F32,$E$11:$E$50)),OR(G32="",SUMIF($A$11:$A$50,G32,AO$11:AO$50)>=SUMIF($A$11:$A$50,G32,$E$11:$E$50)),OR(H32="",SUMIF($A$11:$A$50,H32,AO$11:AO$50)>=SUMIF($A$11:$A$50,H32,$E$11:$E$50))),"ОТКРЫТО","ЗАКРЫТО")) -> ЗАКРЫТО | BE32: =IF(AP32>=E32,"ИЗУЧЕНО",IF(AND(OR(F32="",SUMIF($A$11:$A$50,F32,AP$11:AP$50)>=SUMIF($A$11:$A$50,F32,$E$11:$E$50)),OR(G32="",SUMIF($A$11:$A$50,G32,AP$11:AP$50)>=SUMIF($A$11:$A$50,G32,$E$11:$E$50)),OR(H32="",SUMIF($A$11:$A$50,H32,AP$11:AP$50)>=SUMIF($A$11:$A$50,H32,$E$11:$E$50))),"ОТКРЫТО","ЗАКРЫТО")) -> ЗАКРЫТО | BF32: =IF(AQ32>=E32,"ИЗУЧЕНО",IF(AND(OR(F32="",SUMIF($A$11:$A$50,F32,AQ$11:AQ$50)>=SUMIF($A$11:$A$50,F32,$E$11:$E$50)),OR(G32="",SUMIF($A$11:$A$50,G32,AQ$11:AQ$50)>=SUMIF($A$11:$A$50,G32,$E$11:$E$50)),OR(H32="",SUMIF($A$11:$A$50,H32,AQ$11:AQ$50)>=SUMIF($A$11:$A$50,H32,$E$11:$E$50))),"ОТКРЫТО","ЗАКРЫТО")) -> ЗАКРЫТО
A33: A5 | B33: Агенты и автономные системы | C33: IV | D33: Государственные ИИ-агенты | E33: 105 | F33: A4 | I33: Агентные системы в масштабах государственного управления. | J33: Прирост Госуправления +0,12/год; Управления +0,08/год; улучшение отношений +10% | K33: =SUMIF('Ход 2026'!$G$29:$G$38,$A33,'Ход 2026'!$I$29:$I$38) -> 0 | L33: =SUMIF('Ход 2027'!$G$29:$G$38,$A33,'Ход 2027'!$I$29:$I$38) -> 0 | M33: =SUMIF('Ход 2028'!$G$29:$G$38,$A33,'Ход 2028'!$I$29:$I$38) -> 0 | N33: =SUMIF('Ход 2029'!$G$29:$G$38,$A33,'Ход 2029'!$I$29:$I$38) -> 0 | O33: =SUMIF('Ход 2030'!$G$29:$G$38,$A33,'Ход 2030'!$I$29:$I$38) -> 0 | P33: =SUMIF('Ход 2031'!$G$29:$G$38,$A33,'Ход 2031'!$I$29:$I$38) -> 0 | Q33: =SUMIF('Ход 2032'!$G$29:$G$38,$A33,'Ход 2032'!$I$29:$I$38) -> 0 | R33: =SUMIF('Ход 2033'!$G$29:$G$38,$A33,'Ход 2033'!$I$29:$I$38) -> 0 | S33: =SUMIF('Ход 2034'!$G$29:$G$38,$A33,'Ход 2034'!$I$29:$I$38) -> 0 | T33: =SUMIF('Ход 2035'!$G$29:$G$38,$A33,'Ход 2035'!$I$29:$I$38) -> 0 | U33: =SUMIF('Ход 2036'!$G$29:$G$38,$A33,'Ход 2036'!$I$29:$I$38) -> 0 | V33: =SUMIF('Ход 2037'!$G$29:$G$38,$A33,'Ход 2037'!$I$29:$I$38) -> 0 | W33: =SUMIF('Ход 2038'!$G$29:$G$38,$A33,'Ход 2038'!$I$29:$I$38) -> 0 | X33: =SUMIF('Ход 2039'!$G$29:$G$38,$A33,'Ход 2039'!$I$29:$I$38) -> 0 | Y33: =SUMIF('Ход 2040'!$G$29:$G$38,$A33,'Ход 2040'!$I$29:$I$38) -> 0 | Z33: =SUM(K33:Y33) -> 0 | AA33: =MAX(0,E33-Z33) -> 105 | AB33: =BF33 -> ЗАКРЫТО | AC33: =SUM($K33:K33) -> 0 | AD33: =SUM($K33:L33) -> 0 | AE33: =SUM($K33:M33) -> 0 | AF33: =SUM($K33:N33) -> 0 | AG33: =SUM($K33:O33) -> 0 | AH33: =SUM($K33:P33) -> 0 | AI33: =SUM($K33:Q33) -> 0 | AJ33: =SUM($K33:R33) -> 0 | ... AQ33: =SUM($K33:Y33) -> 0 | AR33: =IF(AC33>=E33,"ИЗУЧЕНО",IF(AND(OR(F33="",SUMIF($A$11:$A$50,F33,AC$11:AC$50)>=SUMIF($A$11:$A$50,F33,$E$11:$E$50)),OR(G33="",SUMIF($A$11:$A$50,G33,AC$11:AC$50)>=SUMIF($A$11:$A$50,G33,$E$11:$E$50)),OR(H33="",SUMIF($A$11:$A$50,H33,AC$11:AC$50)>=SUMIF($A$11:$A$50,H33,$E$11:$E$50))),"ОТКРЫТО","ЗАКРЫТО")) -> ЗАКРЫТО | AS33: =IF(AD33>=E33,"ИЗУЧЕНО",IF(AND(OR(F33="",SUMIF($A$11:$A$50,F33,AD$11:AD$50)>=SUMIF($A$11:$A$50,F33,$E$11:$E$50)),OR(G33="",SUMIF($A$11:$A$50,G33,AD$11:AD$50)>=SUMIF($A$11:$A$50,G33,$E$11:$E$50)),OR(H33="",SUMIF($A$11:$A$50,H33,AD$11:AD$50)>=SUMIF($A$11:$A$50,H33,$E$11:$E$50))),"ОТКРЫТО","ЗАКРЫТО")) -> ЗАКРЫТО | AT33: =IF(AE33>=E33,"ИЗУЧЕНО",IF(AND(OR(F33="",SUMIF($A$11:$A$50,F33,AE$11:AE$50)>=SUMIF($A$11:$A$50,F33,$E$11:$E$50)),OR(G33="",SUMIF($A$11:$A$50,G33,AE$11:AE$50)>=SUMIF($A$11:$A$50,G33,$E$11:$E$50)),OR(H33="",SUMIF($A$11:$A$50,H33,AE$11:AE$50)>=SUMIF($A$11:$A$50,H33,$E$11:$E$50))),"ОТКРЫТО","ЗАКРЫТО")) -> ЗАКРЫТО | AU33: =IF(AF33>=E33,"ИЗУЧЕНО",IF(AND(OR(F33="",SUMIF($A$11:$A$50,F33,AF$11:AF$50)>=SUMIF($A$11:$A$50,F33,$E$11:$E$50)),OR(G33="",SUMIF($A$11:$A$50,G33,AF$11:AF$50)>=SUMIF($A$11:$A$50,G33,$E$11:$E$50)),OR(H33="",SUMIF($A$11:$A$50,H33,AF$11:AF$50)>=SUMIF($A$11:$A$50,H33,$E$11:$E$50))),"ОТКРЫТО","ЗАКРЫТО")) -> ЗАКРЫТО | AV33: =IF(AG33>=E33,"ИЗУЧЕНО",IF(AND(OR(F33="",SUMIF($A$11:$A$50,F33,AG$11:AG$50)>=SUMIF($A$11:$A$50,F33,$E$11:$E$50)),OR(G33="",SUMIF($A$11:$A$50,G33,AG$11:AG$50)>=SUMIF($A$11:$A$50,G33,$E$11:$E$50)),OR(H33="",SUMIF($A$11:$A$50,H33,AG$11:AG$50)>=SUMIF($A$11:$A$50,H33,$E$11:$E$50))),"ОТКРЫТО","ЗАКРЫТО")) -> ЗАКРЫТО | AW33: =IF(AH33>=E33,"ИЗУЧЕНО",IF(AND(OR(F33="",SUMIF($A$11:$A$50,F33,AH$11:AH$50)>=SUMIF($A$11:$A$50,F33,$E$11:$E$50)),OR(G33="",SUMIF($A$11:$A$50,G33,AH$11:AH$50)>=SUMIF($A$11:$A$50,G33,$E$11:$E$50)),OR(H33="",SUMIF($A$11:$A$50,H33,AH$11:AH$50)>=SUMIF($A$11:$A$50,H33,$E$11:$E$50))),"ОТКРЫТО","ЗАКРЫТО")) -> ЗАКРЫТО | AX33: =IF(AI33>=E33,"ИЗУЧЕНО",IF(AND(OR(F33="",SUMIF($A$11:$A$50,F33,AI$11:AI$50)>=SUMIF($A$11:$A$50,F33,$E$11:$E$50)),OR(G33="",SUMIF($A$11:$A$50,G33,AI$11:AI$50)>=SUMIF($A$11:$A$50,G33,$E$11:$E$50)),OR(H33="",SUMIF($A$11:$A$50,H33,AI$11:AI$50)>=SUMIF($A$11:$A$50,H33,$E$11:$E$50))),"ОТКРЫТО","ЗАКРЫТО")) -> ЗАКРЫТО | AY33: =IF(AJ33>=E33,"ИЗУЧЕНО",IF(AND(OR(F33="",SUMIF($A$11:$A$50,F33,AJ$11:AJ$50)>=SUMIF($A$11:$A$50,F33,$E$11:$E$50)),OR(G33="",SUMIF($A$11:$A$50,G33,AJ$11:AJ$50)>=SUMIF($A$11:$A$50,G33,$E$11:$E$50)),OR(H33="",SUMIF($A$11:$A$50,H33,AJ$11:AJ$50)>=SUMIF($A$11:$A$50,H33,$E$11:$E$50))),"ОТКРЫТО","ЗАКРЫТО")) -> ЗАКРЫТО | AZ33: =IF(AK33>=E33,"ИЗУЧЕНО",IF(AND(OR(F33="",SUMIF($A$11:$A$50,F33,AK$11:AK$50)>=SUMIF($A$11:$A$50,F33,$E$11:$E$50)),OR(G33="",SUMIF($A$11:$A$50,G33,AK$11:AK$50)>=SUMIF($A$11:$A$50,G33,$E$11:$E$50)),OR(H33="",SUMIF($A$11:$A$50,H33,AK$11:AK$50)>=SUMIF($A$11:$A$50,H33,$E$11:$E$50))),"ОТКРЫТО","ЗАКРЫТО")) -> ЗАКРЫТО | BA33: =IF(AL33>=E33,"ИЗУЧЕНО",IF(AND(OR(F33="",SUMIF($A$11:$A$50,F33,AL$11:AL$50)>=SUMIF($A$11:$A$50,F33,$E$11:$E$50)),OR(G33="",SUMIF($A$11:$A$50,G33,AL$11:AL$50)>=SUMIF($A$11:$A$50,G33,$E$11:$E$50)),OR(H33="",SUMIF($A$11:$A$50,H33,AL$11:AL$50)>=SUMIF($A$11:$A$50,H33,$E$11:$E$50))),"ОТКРЫТО","ЗАКРЫТО")) -> ЗАКРЫТО | BB33: =IF(AM33>=E33,"ИЗУЧЕНО",IF(AND(OR(F33="",SUMIF($A$11:$A$50,F33,AM$11:AM$50)>=SUMIF($A$11:$A$50,F33,$E$11:$E$50)),OR(G33="",SUMIF($A$11:$A$50,G33,AM$11:AM$50)>=SUMIF($A$11:$A$50,G33,$E$11:$E$50)),OR(H33="",SUMIF($A$11:$A$50,H33,AM$11:AM$50)>=SUMIF($A$11:$A$50,H33,$E$11:$E$50))),"ОТКРЫТО","ЗАКРЫТО")) -> ЗАКРЫТО | BC33: =IF(AN33>=E33,"ИЗУЧЕНО",IF(AND(OR(F33="",SUMIF($A$11:$A$50,F33,AN$11:AN$50)>=SUMIF($A$11:$A$50,F33,$E$11:$E$50)),OR(G33="",SUMIF($A$11:$A$50,G33,AN$11:AN$50)>=SUMIF($A$11:$A$50,G33,$E$11:$E$50)),OR(H33="",SUMIF($A$11:$A$50,H33,AN$11:AN$50)>=SUMIF($A$11:$A$50,H33,$E$11:$E$50))),"ОТКРЫТО","ЗАКРЫТО")) -> ЗАКРЫТО | BD33: =IF(AO33>=E33,"ИЗУЧЕНО",IF(AND(OR(F33="",SUMIF($A$11:$A$50,F33,AO$11:AO$50)>=SUMIF($A$11:$A$50,F33,$E$11:$E$50)),OR(G33="",SUMIF($A$11:$A$50,G33,AO$11:AO$50)>=SUMIF($A$11:$A$50,G33,$E$11:$E$50)),OR(H33="",SUMIF($A$11:$A$50,H33,AO$11:AO$50)>=SUMIF($A$11:$A$50,H33,$E$11:$E$50))),"ОТКРЫТО","ЗАКРЫТО")) -> ЗАКРЫТО | BE33: =IF(AP33>=E33,"ИЗУЧЕНО",IF(AND(OR(F33="",SUMIF($A$11:$A$50,F33,AP$11:AP$50)>=SUMIF($A$11:$A$50,F33,$E$11:$E$50)),OR(G33="",SUMIF($A$11:$A$50,G33,AP$11:AP$50)>=SUMIF($A$11:$A$50,G33,$E$11:$E$50)),OR(H33="",SUMIF($A$11:$A$50,H33,AP$11:AP$50)>=SUMIF($A$11:$A$50,H33,$E$11:$E$50))),"ОТКРЫТО","ЗАКРЫТО")) -> ЗАКРЫТО | BF33: =IF(AQ33>=E33,"ИЗУЧЕНО",IF(AND(OR(F33="",SUMIF($A$11:$A$50,F33,AQ$11:AQ$50)>=SUMIF($A$11:$A$50,F33,$E$11:$E$50)),OR(G33="",SUMIF($A$11:$A$50,G33,AQ$11:AQ$50)>=SUMIF($A$11:$A$50,G33,$E$11:$E$50)),OR(H33="",SUMIF($A$11:$A$50,H33,AQ$11:AQ$50)>=SUMIF($A$11:$A$50,H33,$E$11:$E$50))),"ОТКРЫТО","ЗАКРЫТО")) -> ЗАКРЫТО
A34: A6 | B34: Агенты и автономные системы | C34: V | D34: Стратегические автономные агентные системы | E34: 155 | F34: A5 | I34: Агентные контуры, самостоятельно планирующие длинные цепочки действий. | J34: Управление +0,4; атака Афины +15%; атака Аполлона +15% | K34: =SUMIF('Ход 2026'!$G$29:$G$38,$A34,'Ход 2026'!$I$29:$I$38) -> 0 | L34: =SUMIF('Ход 2027'!$G$29:$G$38,$A34,'Ход 2027'!$I$29:$I$38) -> 0 | M34: =SUMIF('Ход 2028'!$G$29:$G$38,$A34,'Ход 2028'!$I$29:$I$38) -> 0 | N34: =SUMIF('Ход 2029'!$G$29:$G$38,$A34,'Ход 2029'!$I$29:$I$38) -> 0 | O34: =SUMIF('Ход 2030'!$G$29:$G$38,$A34,'Ход 2030'!$I$29:$I$38) -> 0 | P34: =SUMIF('Ход 2031'!$G$29:$G$38,$A34,'Ход 2031'!$I$29:$I$38) -> 0 | Q34: =SUMIF('Ход 2032'!$G$29:$G$38,$A34,'Ход 2032'!$I$29:$I$38) -> 0 | R34: =SUMIF('Ход 2033'!$G$29:$G$38,$A34,'Ход 2033'!$I$29:$I$38) -> 0 | S34: =SUMIF('Ход 2034'!$G$29:$G$38,$A34,'Ход 2034'!$I$29:$I$38) -> 0 | T34: =SUMIF('Ход 2035'!$G$29:$G$38,$A34,'Ход 2035'!$I$29:$I$38) -> 0 | U34: =SUMIF('Ход 2036'!$G$29:$G$38,$A34,'Ход 2036'!$I$29:$I$38) -> 0 | V34: =SUMIF('Ход 2037'!$G$29:$G$38,$A34,'Ход 2037'!$I$29:$I$38) -> 0 | W34: =SUMIF('Ход 2038'!$G$29:$G$38,$A34,'Ход 2038'!$I$29:$I$38) -> 0 | X34: =SUMIF('Ход 2039'!$G$29:$G$38,$A34,'Ход 2039'!$I$29:$I$38) -> 0 | Y34: =SUMIF('Ход 2040'!$G$29:$G$38,$A34,'Ход 2040'!$I$29:$I$38) -> 0 | Z34: =SUM(K34:Y34) -> 0 | AA34: =MAX(0,E34-Z34) -> 155 | AB34: =BF34 -> ЗАКРЫТО | AC34: =SUM($K34:K34) -> 0 | AD34: =SUM($K34:L34) -> 0 | AE34: =SUM($K34:M34) -> 0 | AF34: =SUM($K34:N34) -> 0 | AG34: =SUM($K34:O34) -> 0 | AH34: =SUM($K34:P34) -> 0 | AI34: =SUM($K34:Q34) -> 0 | AJ34: =SUM($K34:R34) -> 0 | ... AQ34: =SUM($K34:Y34) -> 0 | AR34: =IF(AC34>=E34,"ИЗУЧЕНО",IF(AND(OR(F34="",SUMIF($A$11:$A$50,F34,AC$11:AC$50)>=SUMIF($A$11:$A$50,F34,$E$11:$E$50)),OR(G34="",SUMIF($A$11:$A$50,G34,AC$11:AC$50)>=SUMIF($A$11:$A$50,G34,$E$11:$E$50)),OR(H34="",SUMIF($A$11:$A$50,H34,AC$11:AC$50)>=SUMIF($A$11:$A$50,H34,$E$11:$E$50))),"ОТКРЫТО","ЗАКРЫТО")) -> ЗАКРЫТО | AS34: =IF(AD34>=E34,"ИЗУЧЕНО",IF(AND(OR(F34="",SUMIF($A$11:$A$50,F34,AD$11:AD$50)>=SUMIF($A$11:$A$50,F34,$E$11:$E$50)),OR(G34="",SUMIF($A$11:$A$50,G34,AD$11:AD$50)>=SUMIF($A$11:$A$50,G34,$E$11:$E$50)),OR(H34="",SUMIF($A$11:$A$50,H34,AD$11:AD$50)>=SUMIF($A$11:$A$50,H34,$E$11:$E$50))),"ОТКРЫТО","ЗАКРЫТО")) -> ЗАКРЫТО | AT34: =IF(AE34>=E34,"ИЗУЧЕНО",IF(AND(OR(F34="",SUMIF($A$11:$A$50,F34,AE$11:AE$50)>=SUMIF($A$11:$A$50,F34,$E$11:$E$50)),OR(G34="",SUMIF($A$11:$A$50,G34,AE$11:AE$50)>=SUMIF($A$11:$A$50,G34,$E$11:$E$50)),OR(H34="",SUMIF($A$11:$A$50,H34,AE$11:AE$50)>=SUMIF($A$11:$A$50,H34,$E$11:$E$50))),"ОТКРЫТО","ЗАКРЫТО")) -> ЗАКРЫТО | AU34: =IF(AF34>=E34,"ИЗУЧЕНО",IF(AND(OR(F34="",SUMIF($A$11:$A$50,F34,AF$11:AF$50)>=SUMIF($A$11:$A$50,F34,$E$11:$E$50)),OR(G34="",SUMIF($A$11:$A$50,G34,AF$11:AF$50)>=SUMIF($A$11:$A$50,G34,$E$11:$E$50)),OR(H34="",SUMIF($A$11:$A$50,H34,AF$11:AF$50)>=SUMIF($A$11:$A$50,H34,$E$11:$E$50))),"ОТКРЫТО","ЗАКРЫТО")) -> ЗАКРЫТО | AV34: =IF(AG34>=E34,"ИЗУЧЕНО",IF(AND(OR(F34="",SUMIF($A$11:$A$50,F34,AG$11:AG$50)>=SUMIF($A$11:$A$50,F34,$E$11:$E$50)),OR(G34="",SUMIF($A$11:$A$50,G34,AG$11:AG$50)>=SUMIF($A$11:$A$50,G34,$E$11:$E$50)),OR(H34="",SUMIF($A$11:$A$50,H34,AG$11:AG$50)>=SUMIF($A$11:$A$50,H34,$E$11:$E$50))),"ОТКРЫТО","ЗАКРЫТО")) -> ЗАКРЫТО | AW34: =IF(AH34>=E34,"ИЗУЧЕНО",IF(AND(OR(F34="",SUMIF($A$11:$A$50,F34,AH$11:AH$50)>=SUMIF($A$11:$A$50,F34,$E$11:$E$50)),OR(G34="",SUMIF($A$11:$A$50,G34,AH$11:AH$50)>=SUMIF($A$11:$A$50,G34,$E$11:$E$50)),OR(H34="",SUMIF($A$11:$A$50,H34,AH$11:AH$50)>=SUMIF($A$11:$A$50,H34,$E$11:$E$50))),"ОТКРЫТО","ЗАКРЫТО")) -> ЗАКРЫТО | AX34: =IF(AI34>=E34,"ИЗУЧЕНО",IF(AND(OR(F34="",SUMIF($A$11:$A$50,F34,AI$11:AI$50)>=SUMIF($A$11:$A$50,F34,$E$11:$E$50)),OR(G34="",SUMIF($A$11:$A$50,G34,AI$11:AI$50)>=SUMIF($A$11:$A$50,G34,$E$11:$E$50)),OR(H34="",SUMIF($A$11:$A$50,H34,AI$11:AI$50)>=SUMIF($A$11:$A$50,H34,$E$11:$E$50))),"ОТКРЫТО","ЗАКРЫТО")) -> ЗАКРЫТО | AY34: =IF(AJ34>=E34,"ИЗУЧЕНО",IF(AND(OR(F34="",SUMIF($A$11:$A$50,F34,AJ$11:AJ$50)>=SUMIF($A$11:$A$50,F34,$E$11:$E$50)),OR(G34="",SUMIF($A$11:$A$50,G34,AJ$11:AJ$50)>=SUMIF($A$11:$A$50,G34,$E$11:$E$50)),OR(H34="",SUMIF($A$11:$A$50,H34,AJ$11:AJ$50)>=SUMIF($A$11:$A$50,H34,$E$11:$E$50))),"ОТКРЫТО","ЗАКРЫТО")) -> ЗАКРЫТО | AZ34: =IF(AK34>=E34,"ИЗУЧЕНО",IF(AND(OR(F34="",SUMIF($A$11:$A$50,F34,AK$11:AK$50)>=SUMIF($A$11:$A$50,F34,$E$11:$E$50)),OR(G34="",SUMIF($A$11:$A$50,G34,AK$11:AK$50)>=SUMIF($A$11:$A$50,G34,$E$11:$E$50)),OR(H34="",SUMIF($A$11:$A$50,H34,AK$11:AK$50)>=SUMIF($A$11:$A$50,H34,$E$11:$E$50))),"ОТКРЫТО","ЗАКРЫТО")) -> ЗАКРЫТО | BA34: =IF(AL34>=E34,"ИЗУЧЕНО",IF(AND(OR(F34="",SUMIF($A$11:$A$50,F34,AL$11:AL$50)>=SUMIF($A$11:$A$50,F34,$E$11:$E$50)),OR(G34="",SUMIF($A$11:$A$50,G34,AL$11:AL$50)>=SUMIF($A$11:$A$50,G34,$E$11:$E$50)),OR(H34="",SUMIF($A$11:$A$50,H34,AL$11:AL$50)>=SUMIF($A$11:$A$50,H34,$E$11:$E$50))),"ОТКРЫТО","ЗАКРЫТО")) -> ЗАКРЫТО | BB34: =IF(AM34>=E34,"ИЗУЧЕНО",IF(AND(OR(F34="",SUMIF($A$11:$A$50,F34,AM$11:AM$50)>=SUMIF($A$11:$A$50,F34,$E$11:$E$50)),OR(G34="",SUMIF($A$11:$A$50,G34,AM$11:AM$50)>=SUMIF($A$11:$A$50,G34,$E$11:$E$50)),OR(H34="",SUMIF($A$11:$A$50,H34,AM$11:AM$50)>=SUMIF($A$11:$A$50,H34,$E$11:$E$50))),"ОТКРЫТО","ЗАКРЫТО")) -> ЗАКРЫТО | BC34: =IF(AN34>=E34,"ИЗУЧЕНО",IF(AND(OR(F34="",SUMIF($A$11:$A$50,F34,AN$11:AN$50)>=SUMIF($A$11:$A$50,F34,$E$11:$E$50)),OR(G34="",SUMIF($A$11:$A$50,G34,AN$11:AN$50)>=SUMIF($A$11:$A$50,G34,$E$11:$E$50)),OR(H34="",SUMIF($A$11:$A$50,H34,AN$11:AN$50)>=SUMIF($A$11:$A$50,H34,$E$11:$E$50))),"ОТКРЫТО","ЗАКРЫТО")) -> ЗАКРЫТО | BD34: =IF(AO34>=E34,"ИЗУЧЕНО",IF(AND(OR(F34="",SUMIF($A$11:$A$50,F34,AO$11:AO$50)>=SUMIF($A$11:$A$50,F34,$E$11:$E$50)),OR(G34="",SUMIF($A$11:$A$50,G34,AO$11:AO$50)>=SUMIF($A$11:$A$50,G34,$E$11:$E$50)),OR(H34="",SUMIF($A$11:$A$50,H34,AO$11:AO$50)>=SUMIF($A$11:$A$50,H34,$E$11:$E$50))),"ОТКРЫТО","ЗАКРЫТО")) -> ЗАКРЫТО | BE34: =IF(AP34>=E34,"ИЗУЧЕНО",IF(AND(OR(F34="",SUMIF($A$11:$A$50,F34,AP$11:AP$50)>=SUMIF($A$11:$A$50,F34,$E$11:$E$50)),OR(G34="",SUMIF($A$11:$A$50,G34,AP$11:AP$50)>=SUMIF($A$11:$A$50,G34,$E$11:$E$50)),OR(H34="",SUMIF($A$11:$A$50,H34,AP$11:AP$50)>=SUMIF($A$11:$A$50,H34,$E$11:$E$50))),"ОТКРЫТО","ЗАКРЫТО")) -> ЗАКРЫТО | BF34: =IF(AQ34>=E34,"ИЗУЧЕНО",IF(AND(OR(F34="",SUMIF($A$11:$A$50,F34,AQ$11:AQ$50)>=SUMIF($A$11:$A$50,F34,$E$11:$E$50)),OR(G34="",SUMIF($A$11:$A$50,G34,AQ$11:AQ$50)>=SUMIF($A$11:$A$50,G34,$E$11:$E$50)),OR(H34="",SUMIF($A$11:$A$50,H34,AQ$11:AQ$50)>=SUMIF($A$11:$A$50,H34,$E$11:$E$50))),"ОТКРЫТО","ЗАКРЫТО")) -> ЗАКРЫТО
A35: R1 | B35: Физический ИИ и робототехника | C35: I | D35: Машинное зрение и интеллектуальное управление | E35: 20 | I35: Распознавание физической среды и управление оборудованием. | J35: Оцифрованность деятельности +0,2; прирост Производства +0,05/год | K35: =SUMIF('Ход 2026'!$G$29:$G$38,$A35,'Ход 2026'!$I$29:$I$38) -> 0 | L35: =SUMIF('Ход 2027'!$G$29:$G$38,$A35,'Ход 2027'!$I$29:$I$38) -> 0 | M35: =SUMIF('Ход 2028'!$G$29:$G$38,$A35,'Ход 2028'!$I$29:$I$38) -> 0 | N35: =SUMIF('Ход 2029'!$G$29:$G$38,$A35,'Ход 2029'!$I$29:$I$38) -> 0 | O35: =SUMIF('Ход 2030'!$G$29:$G$38,$A35,'Ход 2030'!$I$29:$I$38) -> 0 | P35: =SUMIF('Ход 2031'!$G$29:$G$38,$A35,'Ход 2031'!$I$29:$I$38) -> 0 | Q35: =SUMIF('Ход 2032'!$G$29:$G$38,$A35,'Ход 2032'!$I$29:$I$38) -> 0 | R35: =SUMIF('Ход 2033'!$G$29:$G$38,$A35,'Ход 2033'!$I$29:$I$38) -> 0 | S35: =SUMIF('Ход 2034'!$G$29:$G$38,$A35,'Ход 2034'!$I$29:$I$38) -> 0 | T35: =SUMIF('Ход 2035'!$G$29:$G$38,$A35,'Ход 2035'!$I$29:$I$38) -> 0 | U35: =SUMIF('Ход 2036'!$G$29:$G$38,$A35,'Ход 2036'!$I$29:$I$38) -> 0 | V35: =SUMIF('Ход 2037'!$G$29:$G$38,$A35,'Ход 2037'!$I$29:$I$38) -> 0 | W35: =SUMIF('Ход 2038'!$G$29:$G$38,$A35,'Ход 2038'!$I$29:$I$38) -> 0 | X35: =SUMIF('Ход 2039'!$G$29:$G$38,$A35,'Ход 2039'!$I$29:$I$38) -> 0 | Y35: =SUMIF('Ход 2040'!$G$29:$G$38,$A35,'Ход 2040'!$I$29:$I$38) -> 0 | Z35: =SUM(K35:Y35) -> 0 | AA35: =MAX(0,E35-Z35) -> 20 | AB35: =BF35 -> ОТКРЫТО | AC35: =SUM($K35:K35) -> 0 | AD35: =SUM($K35:L35) -> 0 | AE35: =SUM($K35:M35) -> 0 | AF35: =SUM($K35:N35) -> 0 | AG35: =SUM($K35:O35) -> 0 | AH35: =SUM($K35:P35) -> 0 | AI35: =SUM($K35:Q35) -> 0 | AJ35: =SUM($K35:R35) -> 0 | ... AQ35: =SUM($K35:Y35) -> 0 | AR35: =IF(AC35>=E35,"ИЗУЧЕНО",IF(AND(OR(F35="",SUMIF($A$11:$A$50,F35,AC$11:AC$50)>=SUMIF($A$11:$A$50,F35,$E$11:$E$50)),OR(G35="",SUMIF($A$11:$A$50,G35,AC$11:AC$50)>=SUMIF($A$11:$A$50,G35,$E$11:$E$50)),OR(H35="",SUMIF($A$11:$A$50,H35,AC$11:AC$50)>=SUMIF($A$11:$A$50,H35,$E$11:$E$50))),"ОТКРЫТО","ЗАКРЫТО")) -> ОТКРЫТО | AS35: =IF(AD35>=E35,"ИЗУЧЕНО",IF(AND(OR(F35="",SUMIF($A$11:$A$50,F35,AD$11:AD$50)>=SUMIF($A$11:$A$50,F35,$E$11:$E$50)),OR(G35="",SUMIF($A$11:$A$50,G35,AD$11:AD$50)>=SUMIF($A$11:$A$50,G35,$E$11:$E$50)),OR(H35="",SUMIF($A$11:$A$50,H35,AD$11:AD$50)>=SUMIF($A$11:$A$50,H35,$E$11:$E$50))),"ОТКРЫТО","ЗАКРЫТО")) -> ОТКРЫТО | AT35: =IF(AE35>=E35,"ИЗУЧЕНО",IF(AND(OR(F35="",SUMIF($A$11:$A$50,F35,AE$11:AE$50)>=SUMIF($A$11:$A$50,F35,$E$11:$E$50)),OR(G35="",SUMIF($A$11:$A$50,G35,AE$11:AE$50)>=SUMIF($A$11:$A$50,G35,$E$11:$E$50)),OR(H35="",SUMIF($A$11:$A$50,H35,AE$11:AE$50)>=SUMIF($A$11:$A$50,H35,$E$11:$E$50))),"ОТКРЫТО","ЗАКРЫТО")) -> ОТКРЫТО | AU35: =IF(AF35>=E35,"ИЗУЧЕНО",IF(AND(OR(F35="",SUMIF($A$11:$A$50,F35,AF$11:AF$50)>=SUMIF($A$11:$A$50,F35,$E$11:$E$50)),OR(G35="",SUMIF($A$11:$A$50,G35,AF$11:AF$50)>=SUMIF($A$11:$A$50,G35,$E$11:$E$50)),OR(H35="",SUMIF($A$11:$A$50,H35,AF$11:AF$50)>=SUMIF($A$11:$A$50,H35,$E$11:$E$50))),"ОТКРЫТО","ЗАКРЫТО")) -> ОТКРЫТО | AV35: =IF(AG35>=E35,"ИЗУЧЕНО",IF(AND(OR(F35="",SUMIF($A$11:$A$50,F35,AG$11:AG$50)>=SUMIF($A$11:$A$50,F35,$E$11:$E$50)),OR(G35="",SUMIF($A$11:$A$50,G35,AG$11:AG$50)>=SUMIF($A$11:$A$50,G35,$E$11:$E$50)),OR(H35="",SUMIF($A$11:$A$50,H35,AG$11:AG$50)>=SUMIF($A$11:$A$50,H35,$E$11:$E$50))),"ОТКРЫТО","ЗАКРЫТО")) -> ОТКРЫТО | AW35: =IF(AH35>=E35,"ИЗУЧЕНО",IF(AND(OR(F35="",SUMIF($A$11:$A$50,F35,AH$11:AH$50)>=SUMIF($A$11:$A$50,F35,$E$11:$E$50)),OR(G35="",SUMIF($A$11:$A$50,G35,AH$11:AH$50)>=SUMIF($A$11:$A$50,G35,$E$11:$E$50)),OR(H35="",SUMIF($A$11:$A$50,H35,AH$11:AH$50)>=SUMIF($A$11:$A$50,H35,$E$11:$E$50))),"ОТКРЫТО","ЗАКРЫТО")) -> ОТКРЫТО | AX35: =IF(AI35>=E35,"ИЗУЧЕНО",IF(AND(OR(F35="",SUMIF($A$11:$A$50,F35,AI$11:AI$50)>=SUMIF($A$11:$A$50,F35,$E$11:$E$50)),OR(G35="",SUMIF($A$11:$A$50,G35,AI$11:AI$50)>=SUMIF($A$11:$A$50,G35,$E$11:$E$50)),OR(H35="",SUMIF($A$11:$A$50,H35,AI$11:AI$50)>=SUMIF($A$11:$A$50,H35,$E$11:$E$50))),"ОТКРЫТО","ЗАКРЫТО")) -> ОТКРЫТО | AY35: =IF(AJ35>=E35,"ИЗУЧЕНО",IF(AND(OR(F35="",SUMIF($A$11:$A$50,F35,AJ$11:AJ$50)>=SUMIF($A$11:$A$50,F35,$E$11:$E$50)),OR(G35="",SUMIF($A$11:$A$50,G35,AJ$11:AJ$50)>=SUMIF($A$11:$A$50,G35,$E$11:$E$50)),OR(H35="",SUMIF($A$11:$A$50,H35,AJ$11:AJ$50)>=SUMIF($A$11:$A$50,H35,$E$11:$E$50))),"ОТКРЫТО","ЗАКРЫТО")) -> ОТКРЫТО | AZ35: =IF(AK35>=E35,"ИЗУЧЕНО",IF(AND(OR(F35="",SUMIF($A$11:$A$50,F35,AK$11:AK$50)>=SUMIF($A$11:$A$50,F35,$E$11:$E$50)),OR(G35="",SUMIF($A$11:$A$50,G35,AK$11:AK$50)>=SUMIF($A$11:$A$50,G35,$E$11:$E$50)),OR(H35="",SUMIF($A$11:$A$50,H35,AK$11:AK$50)>=SUMIF($A$11:$A$50,H35,$E$11:$E$50))),"ОТКРЫТО","ЗАКРЫТО")) -> ОТКРЫТО | BA35: =IF(AL35>=E35,"ИЗУЧЕНО",IF(AND(OR(F35="",SUMIF($A$11:$A$50,F35,AL$11:AL$50)>=SUMIF($A$11:$A$50,F35,$E$11:$E$50)),OR(G35="",SUMIF($A$11:$A$50,G35,AL$11:AL$50)>=SUMIF($A$11:$A$50,G35,$E$11:$E$50)),OR(H35="",SUMIF($A$11:$A$50,H35,AL$11:AL$50)>=SUMIF($A$11:$A$50,H35,$E$11:$E$50))),"ОТКРЫТО","ЗАКРЫТО")) -> ОТКРЫТО | BB35: =IF(AM35>=E35,"ИЗУЧЕНО",IF(AND(OR(F35="",SUMIF($A$11:$A$50,F35,AM$11:AM$50)>=SUMIF($A$11:$A$50,F35,$E$11:$E$50)),OR(G35="",SUMIF($A$11:$A$50,G35,AM$11:AM$50)>=SUMIF($A$11:$A$50,G35,$E$11:$E$50)),OR(H35="",SUMIF($A$11:$A$50,H35,AM$11:AM$50)>=SUMIF($A$11:$A$50,H35,$E$11:$E$50))),"ОТКРЫТО","ЗАКРЫТО")) -> ОТКРЫТО | BC35: =IF(AN35>=E35,"ИЗУЧЕНО",IF(AND(OR(F35="",SUMIF($A$11:$A$50,F35,AN$11:AN$50)>=SUMIF($A$11:$A$50,F35,$E$11:$E$50)),OR(G35="",SUMIF($A$11:$A$50,G35,AN$11:AN$50)>=SUMIF($A$11:$A$50,G35,$E$11:$E$50)),OR(H35="",SUMIF($A$11:$A$50,H35,AN$11:AN$50)>=SUMIF($A$11:$A$50,H35,$E$11:$E$50))),"ОТКРЫТО","ЗАКРЫТО")) -> ОТКРЫТО | BD35: =IF(AO35>=E35,"ИЗУЧЕНО",IF(AND(OR(F35="",SUMIF($A$11:$A$50,F35,AO$11:AO$50)>=SUMIF($A$11:$A$50,F35,$E$11:$E$50)),OR(G35="",SUMIF($A$11:$A$50,G35,AO$11:AO$50)>=SUMIF($A$11:$A$50,G35,$E$11:$E$50)),OR(H35="",SUMIF($A$11:$A$50,H35,AO$11:AO$50)>=SUMIF($A$11:$A$50,H35,$E$11:$E$50))),"ОТКРЫТО","ЗАКРЫТО")) -> ОТКРЫТО | BE35: =IF(AP35>=E35,"ИЗУЧЕНО",IF(AND(OR(F35="",SUMIF($A$11:$A$50,F35,AP$11:AP$50)>=SUMIF($A$11:$A$50,F35,$E$11:$E$50)),OR(G35="",SUMIF($A$11:$A$50,G35,AP$11:AP$50)>=SUMIF($A$11:$A$50,G35,$E$11:$E$50)),OR(H35="",SUMIF($A$11:$A$50,H35,AP$11:AP$50)>=SUMIF($A$11:$A$50,H35,$E$11:$E$50))),"ОТКРЫТО","ЗАКРЫТО")) -> ОТКРЫТО | BF35: =IF(AQ35>=E35,"ИЗУЧЕНО",IF(AND(OR(F35="",SUMIF($A$11:$A$50,F35,AQ$11:AQ$50)>=SUMIF($A$11:$A$50,F35,$E$11:$E$50)),OR(G35="",SUMIF($A$11:$A$50,G35,AQ$11:AQ$50)>=SUMIF($A$11:$A$50,G35,$E$11:$E$50)),OR(H35="",SUMIF($A$11:$A$50,H35,AQ$11:AQ$50)>=SUMIF($A$11:$A$50,H35,$E$11:$E$50))),"ОТКРЫТО","ЗАКРЫТО")) -> ОТКРЫТО
A36: R2 | B36: Физический ИИ и робототехника | C36: II | D36: Интеллектуальная промышленная робототехника | E36: 40 | F36: R1 | I36: Роботы, способные адаптироваться к производственным операциям. | J36: Производство +0,3; его прирост +0,08/год | K36: =SUMIF('Ход 2026'!$G$29:$G$38,$A36,'Ход 2026'!$I$29:$I$38) -> 0 | L36: =SUMIF('Ход 2027'!$G$29:$G$38,$A36,'Ход 2027'!$I$29:$I$38) -> 0 | M36: =SUMIF('Ход 2028'!$G$29:$G$38,$A36,'Ход 2028'!$I$29:$I$38) -> 0 | N36: =SUMIF('Ход 2029'!$G$29:$G$38,$A36,'Ход 2029'!$I$29:$I$38) -> 0 | O36: =SUMIF('Ход 2030'!$G$29:$G$38,$A36,'Ход 2030'!$I$29:$I$38) -> 0 | P36: =SUMIF('Ход 2031'!$G$29:$G$38,$A36,'Ход 2031'!$I$29:$I$38) -> 0 | Q36: =SUMIF('Ход 2032'!$G$29:$G$38,$A36,'Ход 2032'!$I$29:$I$38) -> 0 | R36: =SUMIF('Ход 2033'!$G$29:$G$38,$A36,'Ход 2033'!$I$29:$I$38) -> 0 | S36: =SUMIF('Ход 2034'!$G$29:$G$38,$A36,'Ход 2034'!$I$29:$I$38) -> 0 | T36: =SUMIF('Ход 2035'!$G$29:$G$38,$A36,'Ход 2035'!$I$29:$I$38) -> 0 | U36: =SUMIF('Ход 2036'!$G$29:$G$38,$A36,'Ход 2036'!$I$29:$I$38) -> 0 | V36: =SUMIF('Ход 2037'!$G$29:$G$38,$A36,'Ход 2037'!$I$29:$I$38) -> 0 | W36: =SUMIF('Ход 2038'!$G$29:$G$38,$A36,'Ход 2038'!$I$29:$I$38) -> 0 | X36: =SUMIF('Ход 2039'!$G$29:$G$38,$A36,'Ход 2039'!$I$29:$I$38) -> 0 | Y36: =SUMIF('Ход 2040'!$G$29:$G$38,$A36,'Ход 2040'!$I$29:$I$38) -> 0 | Z36: =SUM(K36:Y36) -> 0 | AA36: =MAX(0,E36-Z36) -> 40 | AB36: =BF36 -> ЗАКРЫТО | AC36: =SUM($K36:K36) -> 0 | AD36: =SUM($K36:L36) -> 0 | AE36: =SUM($K36:M36) -> 0 | AF36: =SUM($K36:N36) -> 0 | AG36: =SUM($K36:O36) -> 0 | AH36: =SUM($K36:P36) -> 0 | AI36: =SUM($K36:Q36) -> 0 | AJ36: =SUM($K36:R36) -> 0 | ... AQ36: =SUM($K36:Y36) -> 0 | AR36: =IF(AC36>=E36,"ИЗУЧЕНО",IF(AND(OR(F36="",SUMIF($A$11:$A$50,F36,AC$11:AC$50)>=SUMIF($A$11:$A$50,F36,$E$11:$E$50)),OR(G36="",SUMIF($A$11:$A$50,G36,AC$11:AC$50)>=SUMIF($A$11:$A$50,G36,$E$11:$E$50)),OR(H36="",SUMIF($A$11:$A$50,H36,AC$11:AC$50)>=SUMIF($A$11:$A$50,H36,$E$11:$E$50))),"ОТКРЫТО","ЗАКРЫТО")) -> ЗАКРЫТО | AS36: =IF(AD36>=E36,"ИЗУЧЕНО",IF(AND(OR(F36="",SUMIF($A$11:$A$50,F36,AD$11:AD$50)>=SUMIF($A$11:$A$50,F36,$E$11:$E$50)),OR(G36="",SUMIF($A$11:$A$50,G36,AD$11:AD$50)>=SUMIF($A$11:$A$50,G36,$E$11:$E$50)),OR(H36="",SUMIF($A$11:$A$50,H36,AD$11:AD$50)>=SUMIF($A$11:$A$50,H36,$E$11:$E$50))),"ОТКРЫТО","ЗАКРЫТО")) -> ЗАКРЫТО | AT36: =IF(AE36>=E36,"ИЗУЧЕНО",IF(AND(OR(F36="",SUMIF($A$11:$A$50,F36,AE$11:AE$50)>=SUMIF($A$11:$A$50,F36,$E$11:$E$50)),OR(G36="",SUMIF($A$11:$A$50,G36,AE$11:AE$50)>=SUMIF($A$11:$A$50,G36,$E$11:$E$50)),OR(H36="",SUMIF($A$11:$A$50,H36,AE$11:AE$50)>=SUMIF($A$11:$A$50,H36,$E$11:$E$50))),"ОТКРЫТО","ЗАКРЫТО")) -> ЗАКРЫТО | AU36: =IF(AF36>=E36,"ИЗУЧЕНО",IF(AND(OR(F36="",SUMIF($A$11:$A$50,F36,AF$11:AF$50)>=SUMIF($A$11:$A$50,F36,$E$11:$E$50)),OR(G36="",SUMIF($A$11:$A$50,G36,AF$11:AF$50)>=SUMIF($A$11:$A$50,G36,$E$11:$E$50)),OR(H36="",SUMIF($A$11:$A$50,H36,AF$11:AF$50)>=SUMIF($A$11:$A$50,H36,$E$11:$E$50))),"ОТКРЫТО","ЗАКРЫТО")) -> ЗАКРЫТО | AV36: =IF(AG36>=E36,"ИЗУЧЕНО",IF(AND(OR(F36="",SUMIF($A$11:$A$50,F36,AG$11:AG$50)>=SUMIF($A$11:$A$50,F36,$E$11:$E$50)),OR(G36="",SUMIF($A$11:$A$50,G36,AG$11:AG$50)>=SUMIF($A$11:$A$50,G36,$E$11:$E$50)),OR(H36="",SUMIF($A$11:$A$50,H36,AG$11:AG$50)>=SUMIF($A$11:$A$50,H36,$E$11:$E$50))),"ОТКРЫТО","ЗАКРЫТО")) -> ЗАКРЫТО | AW36: =IF(AH36>=E36,"ИЗУЧЕНО",IF(AND(OR(F36="",SUMIF($A$11:$A$50,F36,AH$11:AH$50)>=SUMIF($A$11:$A$50,F36,$E$11:$E$50)),OR(G36="",SUMIF($A$11:$A$50,G36,AH$11:AH$50)>=SUMIF($A$11:$A$50,G36,$E$11:$E$50)),OR(H36="",SUMIF($A$11:$A$50,H36,AH$11:AH$50)>=SUMIF($A$11:$A$50,H36,$E$11:$E$50))),"ОТКРЫТО","ЗАКРЫТО")) -> ЗАКРЫТО | AX36: =IF(AI36>=E36,"ИЗУЧЕНО",IF(AND(OR(F36="",SUMIF($A$11:$A$50,F36,AI$11:AI$50)>=SUMIF($A$11:$A$50,F36,$E$11:$E$50)),OR(G36="",SUMIF($A$11:$A$50,G36,AI$11:AI$50)>=SUMIF($A$11:$A$50,G36,$E$11:$E$50)),OR(H36="",SUMIF($A$11:$A$50,H36,AI$11:AI$50)>=SUMIF($A$11:$A$50,H36,$E$11:$E$50))),"ОТКРЫТО","ЗАКРЫТО")) -> ЗАКРЫТО | AY36: =IF(AJ36>=E36,"ИЗУЧЕНО",IF(AND(OR(F36="",SUMIF($A$11:$A$50,F36,AJ$11:AJ$50)>=SUMIF($A$11:$A$50,F36,$E$11:$E$50)),OR(G36="",SUMIF($A$11:$A$50,G36,AJ$11:AJ$50)>=SUMIF($A$11:$A$50,G36,$E$11:$E$50)),OR(H36="",SUMIF($A$11:$A$50,H36,AJ$11:AJ$50)>=SUMIF($A$11:$A$50,H36,$E$11:$E$50))),"ОТКРЫТО","ЗАКРЫТО")) -> ЗАКРЫТО | AZ36: =IF(AK36>=E36,"ИЗУЧЕНО",IF(AND(OR(F36="",SUMIF($A$11:$A$50,F36,AK$11:AK$50)>=SUMIF($A$11:$A$50,F36,$E$11:$E$50)),OR(G36="",SUMIF($A$11:$A$50,G36,AK$11:AK$50)>=SUMIF($A$11:$A$50,G36,$E$11:$E$50)),OR(H36="",SUMIF($A$11:$A$50,H36,AK$11:AK$50)>=SUMIF($A$11:$A$50,H36,$E$11:$E$50))),"ОТКРЫТО","ЗАКРЫТО")) -> ЗАКРЫТО | BA36: =IF(AL36>=E36,"ИЗУЧЕНО",IF(AND(OR(F36="",SUMIF($A$11:$A$50,F36,AL$11:AL$50)>=SUMIF($A$11:$A$50,F36,$E$11:$E$50)),OR(G36="",SUMIF($A$11:$A$50,G36,AL$11:AL$50)>=SUMIF($A$11:$A$50,G36,$E$11:$E$50)),OR(H36="",SUMIF($A$11:$A$50,H36,AL$11:AL$50)>=SUMIF($A$11:$A$50,H36,$E$11:$E$50))),"ОТКРЫТО","ЗАКРЫТО")) -> ЗАКРЫТО | BB36: =IF(AM36>=E36,"ИЗУЧЕНО",IF(AND(OR(F36="",SUMIF($A$11:$A$50,F36,AM$11:AM$50)>=SUMIF($A$11:$A$50,F36,$E$11:$E$50)),OR(G36="",SUMIF($A$11:$A$50,G36,AM$11:AM$50)>=SUMIF($A$11:$A$50,G36,$E$11:$E$50)),OR(H36="",SUMIF($A$11:$A$50,H36,AM$11:AM$50)>=SUMIF($A$11:$A$50,H36,$E$11:$E$50))),"ОТКРЫТО","ЗАКРЫТО")) -> ЗАКРЫТО | BC36: =IF(AN36>=E36,"ИЗУЧЕНО",IF(AND(OR(F36="",SUMIF($A$11:$A$50,F36,AN$11:AN$50)>=SUMIF($A$11:$A$50,F36,$E$11:$E$50)),OR(G36="",SUMIF($A$11:$A$50,G36,AN$11:AN$50)>=SUMIF($A$11:$A$50,G36,$E$11:$E$50)),OR(H36="",SUMIF($A$11:$A$50,H36,AN$11:AN$50)>=SUMIF($A$11:$A$50,H36,$E$11:$E$50))),"ОТКРЫТО","ЗАКРЫТО")) -> ЗАКРЫТО | BD36: =IF(AO36>=E36,"ИЗУЧЕНО",IF(AND(OR(F36="",SUMIF($A$11:$A$50,F36,AO$11:AO$50)>=SUMIF($A$11:$A$50,F36,$E$11:$E$50)),OR(G36="",SUMIF($A$11:$A$50,G36,AO$11:AO$50)>=SUMIF($A$11:$A$50,G36,$E$11:$E$50)),OR(H36="",SUMIF($A$11:$A$50,H36,AO$11:AO$50)>=SUMIF($A$11:$A$50,H36,$E$11:$E$50))),"ОТКРЫТО","ЗАКРЫТО")) -> ЗАКРЫТО | BE36: =IF(AP36>=E36,"ИЗУЧЕНО",IF(AND(OR(F36="",SUMIF($A$11:$A$50,F36,AP$11:AP$50)>=SUMIF($A$11:$A$50,F36,$E$11:$E$50)),OR(G36="",SUMIF($A$11:$A$50,G36,AP$11:AP$50)>=SUMIF($A$11:$A$50,G36,$E$11:$E$50)),OR(H36="",SUMIF($A$11:$A$50,H36,AP$11:AP$50)>=SUMIF($A$11:$A$50,H36,$E$11:$E$50))),"ОТКРЫТО","ЗАКРЫТО")) -> ЗАКРЫТО | BF36: =IF(AQ36>=E36,"ИЗУЧЕНО",IF(AND(OR(F36="",SUMIF($A$11:$A$50,F36,AQ$11:AQ$50)>=SUMIF($A$11:$A$50,F36,$E$11:$E$50)),OR(G36="",SUMIF($A$11:$A$50,G36,AQ$11:AQ$50)>=SUMIF($A$11:$A$50,G36,$E$11:$E$50)),OR(H36="",SUMIF($A$11:$A$50,H36,AQ$11:AQ$50)>=SUMIF($A$11:$A$50,H36,$E$11:$E$50))),"ОТКРЫТО","ЗАКРЫТО")) -> ЗАКРЫТО
A37: R3 | B37: Физический ИИ и робототехника | C37: II | D37: Автономная логистика | E37: 45 | F37: R1 | I37: Автоматизированные транспортные, складские и распределительные системы. | J37: Прирост Экономики +0,08/год; защита Афины +10% | K37: =SUMIF('Ход 2026'!$G$29:$G$38,$A37,'Ход 2026'!$I$29:$I$38) -> 0 | L37: =SUMIF('Ход 2027'!$G$29:$G$38,$A37,'Ход 2027'!$I$29:$I$38) -> 0 | M37: =SUMIF('Ход 2028'!$G$29:$G$38,$A37,'Ход 2028'!$I$29:$I$38) -> 0 | N37: =SUMIF('Ход 2029'!$G$29:$G$38,$A37,'Ход 2029'!$I$29:$I$38) -> 0 | O37: =SUMIF('Ход 2030'!$G$29:$G$38,$A37,'Ход 2030'!$I$29:$I$38) -> 0 | P37: =SUMIF('Ход 2031'!$G$29:$G$38,$A37,'Ход 2031'!$I$29:$I$38) -> 0 | Q37: =SUMIF('Ход 2032'!$G$29:$G$38,$A37,'Ход 2032'!$I$29:$I$38) -> 0 | R37: =SUMIF('Ход 2033'!$G$29:$G$38,$A37,'Ход 2033'!$I$29:$I$38) -> 0 | S37: =SUMIF('Ход 2034'!$G$29:$G$38,$A37,'Ход 2034'!$I$29:$I$38) -> 0 | T37: =SUMIF('Ход 2035'!$G$29:$G$38,$A37,'Ход 2035'!$I$29:$I$38) -> 0 | U37: =SUMIF('Ход 2036'!$G$29:$G$38,$A37,'Ход 2036'!$I$29:$I$38) -> 0 | V37: =SUMIF('Ход 2037'!$G$29:$G$38,$A37,'Ход 2037'!$I$29:$I$38) -> 0 | W37: =SUMIF('Ход 2038'!$G$29:$G$38,$A37,'Ход 2038'!$I$29:$I$38) -> 0 | X37: =SUMIF('Ход 2039'!$G$29:$G$38,$A37,'Ход 2039'!$I$29:$I$38) -> 0 | Y37: =SUMIF('Ход 2040'!$G$29:$G$38,$A37,'Ход 2040'!$I$29:$I$38) -> 0 | Z37: =SUM(K37:Y37) -> 0 | AA37: =MAX(0,E37-Z37) -> 45 | AB37: =BF37 -> ЗАКРЫТО | AC37: =SUM($K37:K37) -> 0 | AD37: =SUM($K37:L37) -> 0 | AE37: =SUM($K37:M37) -> 0 | AF37: =SUM($K37:N37) -> 0 | AG37: =SUM($K37:O37) -> 0 | AH37: =SUM($K37:P37) -> 0 | AI37: =SUM($K37:Q37) -> 0 | AJ37: =SUM($K37:R37) -> 0 | ... AQ37: =SUM($K37:Y37) -> 0 | AR37: =IF(AC37>=E37,"ИЗУЧЕНО",IF(AND(OR(F37="",SUMIF($A$11:$A$50,F37,AC$11:AC$50)>=SUMIF($A$11:$A$50,F37,$E$11:$E$50)),OR(G37="",SUMIF($A$11:$A$50,G37,AC$11:AC$50)>=SUMIF($A$11:$A$50,G37,$E$11:$E$50)),OR(H37="",SUMIF($A$11:$A$50,H37,AC$11:AC$50)>=SUMIF($A$11:$A$50,H37,$E$11:$E$50))),"ОТКРЫТО","ЗАКРЫТО")) -> ЗАКРЫТО | AS37: =IF(AD37>=E37,"ИЗУЧЕНО",IF(AND(OR(F37="",SUMIF($A$11:$A$50,F37,AD$11:AD$50)>=SUMIF($A$11:$A$50,F37,$E$11:$E$50)),OR(G37="",SUMIF($A$11:$A$50,G37,AD$11:AD$50)>=SUMIF($A$11:$A$50,G37,$E$11:$E$50)),OR(H37="",SUMIF($A$11:$A$50,H37,AD$11:AD$50)>=SUMIF($A$11:$A$50,H37,$E$11:$E$50))),"ОТКРЫТО","ЗАКРЫТО")) -> ЗАКРЫТО | AT37: =IF(AE37>=E37,"ИЗУЧЕНО",IF(AND(OR(F37="",SUMIF($A$11:$A$50,F37,AE$11:AE$50)>=SUMIF($A$11:$A$50,F37,$E$11:$E$50)),OR(G37="",SUMIF($A$11:$A$50,G37,AE$11:AE$50)>=SUMIF($A$11:$A$50,G37,$E$11:$E$50)),OR(H37="",SUMIF($A$11:$A$50,H37,AE$11:AE$50)>=SUMIF($A$11:$A$50,H37,$E$11:$E$50))),"ОТКРЫТО","ЗАКРЫТО")) -> ЗАКРЫТО | AU37: =IF(AF37>=E37,"ИЗУЧЕНО",IF(AND(OR(F37="",SUMIF($A$11:$A$50,F37,AF$11:AF$50)>=SUMIF($A$11:$A$50,F37,$E$11:$E$50)),OR(G37="",SUMIF($A$11:$A$50,G37,AF$11:AF$50)>=SUMIF($A$11:$A$50,G37,$E$11:$E$50)),OR(H37="",SUMIF($A$11:$A$50,H37,AF$11:AF$50)>=SUMIF($A$11:$A$50,H37,$E$11:$E$50))),"ОТКРЫТО","ЗАКРЫТО")) -> ЗАКРЫТО | AV37: =IF(AG37>=E37,"ИЗУЧЕНО",IF(AND(OR(F37="",SUMIF($A$11:$A$50,F37,AG$11:AG$50)>=SUMIF($A$11:$A$50,F37,$E$11:$E$50)),OR(G37="",SUMIF($A$11:$A$50,G37,AG$11:AG$50)>=SUMIF($A$11:$A$50,G37,$E$11:$E$50)),OR(H37="",SUMIF($A$11:$A$50,H37,AG$11:AG$50)>=SUMIF($A$11:$A$50,H37,$E$11:$E$50))),"ОТКРЫТО","ЗАКРЫТО")) -> ЗАКРЫТО | AW37: =IF(AH37>=E37,"ИЗУЧЕНО",IF(AND(OR(F37="",SUMIF($A$11:$A$50,F37,AH$11:AH$50)>=SUMIF($A$11:$A$50,F37,$E$11:$E$50)),OR(G37="",SUMIF($A$11:$A$50,G37,AH$11:AH$50)>=SUMIF($A$11:$A$50,G37,$E$11:$E$50)),OR(H37="",SUMIF($A$11:$A$50,H37,AH$11:AH$50)>=SUMIF($A$11:$A$50,H37,$E$11:$E$50))),"ОТКРЫТО","ЗАКРЫТО")) -> ЗАКРЫТО | AX37: =IF(AI37>=E37,"ИЗУЧЕНО",IF(AND(OR(F37="",SUMIF($A$11:$A$50,F37,AI$11:AI$50)>=SUMIF($A$11:$A$50,F37,$E$11:$E$50)),OR(G37="",SUMIF($A$11:$A$50,G37,AI$11:AI$50)>=SUMIF($A$11:$A$50,G37,$E$11:$E$50)),OR(H37="",SUMIF($A$11:$A$50,H37,AI$11:AI$50)>=SUMIF($A$11:$A$50,H37,$E$11:$E$50))),"ОТКРЫТО","ЗАКРЫТО")) -> ЗАКРЫТО | AY37: =IF(AJ37>=E37,"ИЗУЧЕНО",IF(AND(OR(F37="",SUMIF($A$11:$A$50,F37,AJ$11:AJ$50)>=SUMIF($A$11:$A$50,F37,$E$11:$E$50)),OR(G37="",SUMIF($A$11:$A$50,G37,AJ$11:AJ$50)>=SUMIF($A$11:$A$50,G37,$E$11:$E$50)),OR(H37="",SUMIF($A$11:$A$50,H37,AJ$11:AJ$50)>=SUMIF($A$11:$A$50,H37,$E$11:$E$50))),"ОТКРЫТО","ЗАКРЫТО")) -> ЗАКРЫТО | AZ37: =IF(AK37>=E37,"ИЗУЧЕНО",IF(AND(OR(F37="",SUMIF($A$11:$A$50,F37,AK$11:AK$50)>=SUMIF($A$11:$A$50,F37,$E$11:$E$50)),OR(G37="",SUMIF($A$11:$A$50,G37,AK$11:AK$50)>=SUMIF($A$11:$A$50,G37,$E$11:$E$50)),OR(H37="",SUMIF($A$11:$A$50,H37,AK$11:AK$50)>=SUMIF($A$11:$A$50,H37,$E$11:$E$50))),"ОТКРЫТО","ЗАКРЫТО")) -> ЗАКРЫТО | BA37: =IF(AL37>=E37,"ИЗУЧЕНО",IF(AND(OR(F37="",SUMIF($A$11:$A$50,F37,AL$11:AL$50)>=SUMIF($A$11:$A$50,F37,$E$11:$E$50)),OR(G37="",SUMIF($A$11:$A$50,G37,AL$11:AL$50)>=SUMIF($A$11:$A$50,G37,$E$11:$E$50)),OR(H37="",SUMIF($A$11:$A$50,H37,AL$11:AL$50)>=SUMIF($A$11:$A$50,H37,$E$11:$E$50))),"ОТКРЫТО","ЗАКРЫТО")) -> ЗАКРЫТО | BB37: =IF(AM37>=E37,"ИЗУЧЕНО",IF(AND(OR(F37="",SUMIF($A$11:$A$50,F37,AM$11:AM$50)>=SUMIF($A$11:$A$50,F37,$E$11:$E$50)),OR(G37="",SUMIF($A$11:$A$50,G37,AM$11:AM$50)>=SUMIF($A$11:$A$50,G37,$E$11:$E$50)),OR(H37="",SUMIF($A$11:$A$50,H37,AM$11:AM$50)>=SUMIF($A$11:$A$50,H37,$E$11:$E$50))),"ОТКРЫТО","ЗАКРЫТО")) -> ЗАКРЫТО | BC37: =IF(AN37>=E37,"ИЗУЧЕНО",IF(AND(OR(F37="",SUMIF($A$11:$A$50,F37,AN$11:AN$50)>=SUMIF($A$11:$A$50,F37,$E$11:$E$50)),OR(G37="",SUMIF($A$11:$A$50,G37,AN$11:AN$50)>=SUMIF($A$11:$A$50,G37,$E$11:$E$50)),OR(H37="",SUMIF($A$11:$A$50,H37,AN$11:AN$50)>=SUMIF($A$11:$A$50,H37,$E$11:$E$50))),"ОТКРЫТО","ЗАКРЫТО")) -> ЗАКРЫТО | BD37: =IF(AO37>=E37,"ИЗУЧЕНО",IF(AND(OR(F37="",SUMIF($A$11:$A$50,F37,AO$11:AO$50)>=SUMIF($A$11:$A$50,F37,$E$11:$E$50)),OR(G37="",SUMIF($A$11:$A$50,G37,AO$11:AO$50)>=SUMIF($A$11:$A$50,G37,$E$11:$E$50)),OR(H37="",SUMIF($A$11:$A$50,H37,AO$11:AO$50)>=SUMIF($A$11:$A$50,H37,$E$11:$E$50))),"ОТКРЫТО","ЗАКРЫТО")) -> ЗАКРЫТО | BE37: =IF(AP37>=E37,"ИЗУЧЕНО",IF(AND(OR(F37="",SUMIF($A$11:$A$50,F37,AP$11:AP$50)>=SUMIF($A$11:$A$50,F37,$E$11:$E$50)),OR(G37="",SUMIF($A$11:$A$50,G37,AP$11:AP$50)>=SUMIF($A$11:$A$50,G37,$E$11:$E$50)),OR(H37="",SUMIF($A$11:$A$50,H37,AP$11:AP$50)>=SUMIF($A$11:$A$50,H37,$E$11:$E$50))),"ОТКРЫТО","ЗАКРЫТО")) -> ЗАКРЫТО | BF37: =IF(AQ37>=E37,"ИЗУЧЕНО",IF(AND(OR(F37="",SUMIF($A$11:$A$50,F37,AQ$11:AQ$50)>=SUMIF($A$11:$A$50,F37,$E$11:$E$50)),OR(G37="",SUMIF($A$11:$A$50,G37,AQ$11:AQ$50)>=SUMIF($A$11:$A$50,G37,$E$11:$E$50)),OR(H37="",SUMIF($A$11:$A$50,H37,AQ$11:AQ$50)>=SUMIF($A$11:$A$50,H37,$E$11:$E$50))),"ОТКРЫТО","ЗАКРЫТО")) -> ЗАКРЫТО
A38: R4 | B38: Физический ИИ и робототехника | C38: III | D38: Автономные мобильные системы | E38: 70 | F38: R2 | G38: R3 | I38: Воздушные, наземные и морские автономные платформы. | J38: Прирост Войны +0,08/год; атака Ареса +15% | K38: =SUMIF('Ход 2026'!$G$29:$G$38,$A38,'Ход 2026'!$I$29:$I$38) -> 0 | L38: =SUMIF('Ход 2027'!$G$29:$G$38,$A38,'Ход 2027'!$I$29:$I$38) -> 0 | M38: =SUMIF('Ход 2028'!$G$29:$G$38,$A38,'Ход 2028'!$I$29:$I$38) -> 0 | N38: =SUMIF('Ход 2029'!$G$29:$G$38,$A38,'Ход 2029'!$I$29:$I$38) -> 0 | O38: =SUMIF('Ход 2030'!$G$29:$G$38,$A38,'Ход 2030'!$I$29:$I$38) -> 0 | P38: =SUMIF('Ход 2031'!$G$29:$G$38,$A38,'Ход 2031'!$I$29:$I$38) -> 0 | Q38: =SUMIF('Ход 2032'!$G$29:$G$38,$A38,'Ход 2032'!$I$29:$I$38) -> 0 | R38: =SUMIF('Ход 2033'!$G$29:$G$38,$A38,'Ход 2033'!$I$29:$I$38) -> 0 | S38: =SUMIF('Ход 2034'!$G$29:$G$38,$A38,'Ход 2034'!$I$29:$I$38) -> 0 | T38: =SUMIF('Ход 2035'!$G$29:$G$38,$A38,'Ход 2035'!$I$29:$I$38) -> 0 | U38: =SUMIF('Ход 2036'!$G$29:$G$38,$A38,'Ход 2036'!$I$29:$I$38) -> 0 | V38: =SUMIF('Ход 2037'!$G$29:$G$38,$A38,'Ход 2037'!$I$29:$I$38) -> 0 | W38: =SUMIF('Ход 2038'!$G$29:$G$38,$A38,'Ход 2038'!$I$29:$I$38) -> 0 | X38: =SUMIF('Ход 2039'!$G$29:$G$38,$A38,'Ход 2039'!$I$29:$I$38) -> 0 | Y38: =SUMIF('Ход 2040'!$G$29:$G$38,$A38,'Ход 2040'!$I$29:$I$38) -> 0 | Z38: =SUM(K38:Y38) -> 0 | AA38: =MAX(0,E38-Z38) -> 70 | AB38: =BF38 -> ЗАКРЫТО | AC38: =SUM($K38:K38) -> 0 | AD38: =SUM($K38:L38) -> 0 | AE38: =SUM($K38:M38) -> 0 | AF38: =SUM($K38:N38) -> 0 | AG38: =SUM($K38:O38) -> 0 | AH38: =SUM($K38:P38) -> 0 | AI38: =SUM($K38:Q38) -> 0 | AJ38: =SUM($K38:R38) -> 0 | ... AQ38: =SUM($K38:Y38) -> 0 | AR38: =IF(AC38>=E38,"ИЗУЧЕНО",IF(AND(OR(F38="",SUMIF($A$11:$A$50,F38,AC$11:AC$50)>=SUMIF($A$11:$A$50,F38,$E$11:$E$50)),OR(G38="",SUMIF($A$11:$A$50,G38,AC$11:AC$50)>=SUMIF($A$11:$A$50,G38,$E$11:$E$50)),OR(H38="",SUMIF($A$11:$A$50,H38,AC$11:AC$50)>=SUMIF($A$11:$A$50,H38,$E$11:$E$50))),"ОТКРЫТО","ЗАКРЫТО")) -> ЗАКРЫТО | AS38: =IF(AD38>=E38,"ИЗУЧЕНО",IF(AND(OR(F38="",SUMIF($A$11:$A$50,F38,AD$11:AD$50)>=SUMIF($A$11:$A$50,F38,$E$11:$E$50)),OR(G38="",SUMIF($A$11:$A$50,G38,AD$11:AD$50)>=SUMIF($A$11:$A$50,G38,$E$11:$E$50)),OR(H38="",SUMIF($A$11:$A$50,H38,AD$11:AD$50)>=SUMIF($A$11:$A$50,H38,$E$11:$E$50))),"ОТКРЫТО","ЗАКРЫТО")) -> ЗАКРЫТО | AT38: =IF(AE38>=E38,"ИЗУЧЕНО",IF(AND(OR(F38="",SUMIF($A$11:$A$50,F38,AE$11:AE$50)>=SUMIF($A$11:$A$50,F38,$E$11:$E$50)),OR(G38="",SUMIF($A$11:$A$50,G38,AE$11:AE$50)>=SUMIF($A$11:$A$50,G38,$E$11:$E$50)),OR(H38="",SUMIF($A$11:$A$50,H38,AE$11:AE$50)>=SUMIF($A$11:$A$50,H38,$E$11:$E$50))),"ОТКРЫТО","ЗАКРЫТО")) -> ЗАКРЫТО | AU38: =IF(AF38>=E38,"ИЗУЧЕНО",IF(AND(OR(F38="",SUMIF($A$11:$A$50,F38,AF$11:AF$50)>=SUMIF($A$11:$A$50,F38,$E$11:$E$50)),OR(G38="",SUMIF($A$11:$A$50,G38,AF$11:AF$50)>=SUMIF($A$11:$A$50,G38,$E$11:$E$50)),OR(H38="",SUMIF($A$11:$A$50,H38,AF$11:AF$50)>=SUMIF($A$11:$A$50,H38,$E$11:$E$50))),"ОТКРЫТО","ЗАКРЫТО")) -> ЗАКРЫТО | AV38: =IF(AG38>=E38,"ИЗУЧЕНО",IF(AND(OR(F38="",SUMIF($A$11:$A$50,F38,AG$11:AG$50)>=SUMIF($A$11:$A$50,F38,$E$11:$E$50)),OR(G38="",SUMIF($A$11:$A$50,G38,AG$11:AG$50)>=SUMIF($A$11:$A$50,G38,$E$11:$E$50)),OR(H38="",SUMIF($A$11:$A$50,H38,AG$11:AG$50)>=SUMIF($A$11:$A$50,H38,$E$11:$E$50))),"ОТКРЫТО","ЗАКРЫТО")) -> ЗАКРЫТО | AW38: =IF(AH38>=E38,"ИЗУЧЕНО",IF(AND(OR(F38="",SUMIF($A$11:$A$50,F38,AH$11:AH$50)>=SUMIF($A$11:$A$50,F38,$E$11:$E$50)),OR(G38="",SUMIF($A$11:$A$50,G38,AH$11:AH$50)>=SUMIF($A$11:$A$50,G38,$E$11:$E$50)),OR(H38="",SUMIF($A$11:$A$50,H38,AH$11:AH$50)>=SUMIF($A$11:$A$50,H38,$E$11:$E$50))),"ОТКРЫТО","ЗАКРЫТО")) -> ЗАКРЫТО | AX38: =IF(AI38>=E38,"ИЗУЧЕНО",IF(AND(OR(F38="",SUMIF($A$11:$A$50,F38,AI$11:AI$50)>=SUMIF($A$11:$A$50,F38,$E$11:$E$50)),OR(G38="",SUMIF($A$11:$A$50,G38,AI$11:AI$50)>=SUMIF($A$11:$A$50,G38,$E$11:$E$50)),OR(H38="",SUMIF($A$11:$A$50,H38,AI$11:AI$50)>=SUMIF($A$11:$A$50,H38,$E$11:$E$50))),"ОТКРЫТО","ЗАКРЫТО")) -> ЗАКРЫТО | AY38: =IF(AJ38>=E38,"ИЗУЧЕНО",IF(AND(OR(F38="",SUMIF($A$11:$A$50,F38,AJ$11:AJ$50)>=SUMIF($A$11:$A$50,F38,$E$11:$E$50)),OR(G38="",SUMIF($A$11:$A$50,G38,AJ$11:AJ$50)>=SUMIF($A$11:$A$50,G38,$E$11:$E$50)),OR(H38="",SUMIF($A$11:$A$50,H38,AJ$11:AJ$50)>=SUMIF($A$11:$A$50,H38,$E$11:$E$50))),"ОТКРЫТО","ЗАКРЫТО")) -> ЗАКРЫТО | AZ38: =IF(AK38>=E38,"ИЗУЧЕНО",IF(AND(OR(F38="",SUMIF($A$11:$A$50,F38,AK$11:AK$50)>=SUMIF($A$11:$A$50,F38,$E$11:$E$50)),OR(G38="",SUMIF($A$11:$A$50,G38,AK$11:AK$50)>=SUMIF($A$11:$A$50,G38,$E$11:$E$50)),OR(H38="",SUMIF($A$11:$A$50,H38,AK$11:AK$50)>=SUMIF($A$11:$A$50,H38,$E$11:$E$50))),"ОТКРЫТО","ЗАКРЫТО")) -> ЗАКРЫТО | BA38: =IF(AL38>=E38,"ИЗУЧЕНО",IF(AND(OR(F38="",SUMIF($A$11:$A$50,F38,AL$11:AL$50)>=SUMIF($A$11:$A$50,F38,$E$11:$E$50)),OR(G38="",SUMIF($A$11:$A$50,G38,AL$11:AL$50)>=SUMIF($A$11:$A$50,G38,$E$11:$E$50)),OR(H38="",SUMIF($A$11:$A$50,H38,AL$11:AL$50)>=SUMIF($A$11:$A$50,H38,$E$11:$E$50))),"ОТКРЫТО","ЗАКРЫТО")) -> ЗАКРЫТО | BB38: =IF(AM38>=E38,"ИЗУЧЕНО",IF(AND(OR(F38="",SUMIF($A$11:$A$50,F38,AM$11:AM$50)>=SUMIF($A$11:$A$50,F38,$E$11:$E$50)),OR(G38="",SUMIF($A$11:$A$50,G38,AM$11:AM$50)>=SUMIF($A$11:$A$50,G38,$E$11:$E$50)),OR(H38="",SUMIF($A$11:$A$50,H38,AM$11:AM$50)>=SUMIF($A$11:$A$50,H38,$E$11:$E$50))),"ОТКРЫТО","ЗАКРЫТО")) -> ЗАКРЫТО | BC38: =IF(AN38>=E38,"ИЗУЧЕНО",IF(AND(OR(F38="",SUMIF($A$11:$A$50,F38,AN$11:AN$50)>=SUMIF($A$11:$A$50,F38,$E$11:$E$50)),OR(G38="",SUMIF($A$11:$A$50,G38,AN$11:AN$50)>=SUMIF($A$11:$A$50,G38,$E$11:$E$50)),OR(H38="",SUMIF($A$11:$A$50,H38,AN$11:AN$50)>=SUMIF($A$11:$A$50,H38,$E$11:$E$50))),"ОТКРЫТО","ЗАКРЫТО")) -> ЗАКРЫТО | BD38: =IF(AO38>=E38,"ИЗУЧЕНО",IF(AND(OR(F38="",SUMIF($A$11:$A$50,F38,AO$11:AO$50)>=SUMIF($A$11:$A$50,F38,$E$11:$E$50)),OR(G38="",SUMIF($A$11:$A$50,G38,AO$11:AO$50)>=SUMIF($A$11:$A$50,G38,$E$11:$E$50)),OR(H38="",SUMIF($A$11:$A$50,H38,AO$11:AO$50)>=SUMIF($A$11:$A$50,H38,$E$11:$E$50))),"ОТКРЫТО","ЗАКРЫТО")) -> ЗАКРЫТО | BE38: =IF(AP38>=E38,"ИЗУЧЕНО",IF(AND(OR(F38="",SUMIF($A$11:$A$50,F38,AP$11:AP$50)>=SUMIF($A$11:$A$50,F38,$E$11:$E$50)),OR(G38="",SUMIF($A$11:$A$50,G38,AP$11:AP$50)>=SUMIF($A$11:$A$50,G38,$E$11:$E$50)),OR(H38="",SUMIF($A$11:$A$50,H38,AP$11:AP$50)>=SUMIF($A$11:$A$50,H38,$E$11:$E$50))),"ОТКРЫТО","ЗАКРЫТО")) -> ЗАКРЫТО | BF38: =IF(AQ38>=E38,"ИЗУЧЕНО",IF(AND(OR(F38="",SUMIF($A$11:$A$50,F38,AQ$11:AQ$50)>=SUMIF($A$11:$A$50,F38,$E$11:$E$50)),OR(G38="",SUMIF($A$11:$A$50,G38,AQ$11:AQ$50)>=SUMIF($A$11:$A$50,G38,$E$11:$E$50)),OR(H38="",SUMIF($A$11:$A$50,H38,AQ$11:AQ$50)>=SUMIF($A$11:$A$50,H38,$E$11:$E$50))),"ОТКРЫТО","ЗАКРЫТО")) -> ЗАКРЫТО
A39: R5 | B39: Физический ИИ и робототехника | C39: IV | D39: Универсальный воплощённый ИИ | E39: 105 | F39: R4 | I39: Роботизированные системы, способные осваивать новые физические задачи. | J39: Прирост Производства +0,12/год; Готовность работников +0,2; прирост Принятия ИИ +0,05/год | K39: =SUMIF('Ход 2026'!$G$29:$G$38,$A39,'Ход 2026'!$I$29:$I$38) -> 0 | L39: =SUMIF('Ход 2027'!$G$29:$G$38,$A39,'Ход 2027'!$I$29:$I$38) -> 0 | M39: =SUMIF('Ход 2028'!$G$29:$G$38,$A39,'Ход 2028'!$I$29:$I$38) -> 0 | N39: =SUMIF('Ход 2029'!$G$29:$G$38,$A39,'Ход 2029'!$I$29:$I$38) -> 0 | O39: =SUMIF('Ход 2030'!$G$29:$G$38,$A39,'Ход 2030'!$I$29:$I$38) -> 0 | P39: =SUMIF('Ход 2031'!$G$29:$G$38,$A39,'Ход 2031'!$I$29:$I$38) -> 0 | Q39: =SUMIF('Ход 2032'!$G$29:$G$38,$A39,'Ход 2032'!$I$29:$I$38) -> 0 | R39: =SUMIF('Ход 2033'!$G$29:$G$38,$A39,'Ход 2033'!$I$29:$I$38) -> 0 | S39: =SUMIF('Ход 2034'!$G$29:$G$38,$A39,'Ход 2034'!$I$29:$I$38) -> 0 | T39: =SUMIF('Ход 2035'!$G$29:$G$38,$A39,'Ход 2035'!$I$29:$I$38) -> 0 | U39: =SUMIF('Ход 2036'!$G$29:$G$38,$A39,'Ход 2036'!$I$29:$I$38) -> 0 | V39: =SUMIF('Ход 2037'!$G$29:$G$38,$A39,'Ход 2037'!$I$29:$I$38) -> 0 | W39: =SUMIF('Ход 2038'!$G$29:$G$38,$A39,'Ход 2038'!$I$29:$I$38) -> 0 | X39: =SUMIF('Ход 2039'!$G$29:$G$38,$A39,'Ход 2039'!$I$29:$I$38) -> 0 | Y39: =SUMIF('Ход 2040'!$G$29:$G$38,$A39,'Ход 2040'!$I$29:$I$38) -> 0 | Z39: =SUM(K39:Y39) -> 0 | AA39: =MAX(0,E39-Z39) -> 105 | AB39: =BF39 -> ЗАКРЫТО | AC39: =SUM($K39:K39) -> 0 | AD39: =SUM($K39:L39) -> 0 | AE39: =SUM($K39:M39) -> 0 | AF39: =SUM($K39:N39) -> 0 | AG39: =SUM($K39:O39) -> 0 | AH39: =SUM($K39:P39) -> 0 | AI39: =SUM($K39:Q39) -> 0 | AJ39: =SUM($K39:R39) -> 0 | ... AQ39: =SUM($K39:Y39) -> 0 | AR39: =IF(AC39>=E39,"ИЗУЧЕНО",IF(AND(OR(F39="",SUMIF($A$11:$A$50,F39,AC$11:AC$50)>=SUMIF($A$11:$A$50,F39,$E$11:$E$50)),OR(G39="",SUMIF($A$11:$A$50,G39,AC$11:AC$50)>=SUMIF($A$11:$A$50,G39,$E$11:$E$50)),OR(H39="",SUMIF($A$11:$A$50,H39,AC$11:AC$50)>=SUMIF($A$11:$A$50,H39,$E$11:$E$50))),"ОТКРЫТО","ЗАКРЫТО")) -> ЗАКРЫТО | AS39: =IF(AD39>=E39,"ИЗУЧЕНО",IF(AND(OR(F39="",SUMIF($A$11:$A$50,F39,AD$11:AD$50)>=SUMIF($A$11:$A$50,F39,$E$11:$E$50)),OR(G39="",SUMIF($A$11:$A$50,G39,AD$11:AD$50)>=SUMIF($A$11:$A$50,G39,$E$11:$E$50)),OR(H39="",SUMIF($A$11:$A$50,H39,AD$11:AD$50)>=SUMIF($A$11:$A$50,H39,$E$11:$E$50))),"ОТКРЫТО","ЗАКРЫТО")) -> ЗАКРЫТО | AT39: =IF(AE39>=E39,"ИЗУЧЕНО",IF(AND(OR(F39="",SUMIF($A$11:$A$50,F39,AE$11:AE$50)>=SUMIF($A$11:$A$50,F39,$E$11:$E$50)),OR(G39="",SUMIF($A$11:$A$50,G39,AE$11:AE$50)>=SUMIF($A$11:$A$50,G39,$E$11:$E$50)),OR(H39="",SUMIF($A$11:$A$50,H39,AE$11:AE$50)>=SUMIF($A$11:$A$50,H39,$E$11:$E$50))),"ОТКРЫТО","ЗАКРЫТО")) -> ЗАКРЫТО | AU39: =IF(AF39>=E39,"ИЗУЧЕНО",IF(AND(OR(F39="",SUMIF($A$11:$A$50,F39,AF$11:AF$50)>=SUMIF($A$11:$A$50,F39,$E$11:$E$50)),OR(G39="",SUMIF($A$11:$A$50,G39,AF$11:AF$50)>=SUMIF($A$11:$A$50,G39,$E$11:$E$50)),OR(H39="",SUMIF($A$11:$A$50,H39,AF$11:AF$50)>=SUMIF($A$11:$A$50,H39,$E$11:$E$50))),"ОТКРЫТО","ЗАКРЫТО")) -> ЗАКРЫТО | AV39: =IF(AG39>=E39,"ИЗУЧЕНО",IF(AND(OR(F39="",SUMIF($A$11:$A$50,F39,AG$11:AG$50)>=SUMIF($A$11:$A$50,F39,$E$11:$E$50)),OR(G39="",SUMIF($A$11:$A$50,G39,AG$11:AG$50)>=SUMIF($A$11:$A$50,G39,$E$11:$E$50)),OR(H39="",SUMIF($A$11:$A$50,H39,AG$11:AG$50)>=SUMIF($A$11:$A$50,H39,$E$11:$E$50))),"ОТКРЫТО","ЗАКРЫТО")) -> ЗАКРЫТО | AW39: =IF(AH39>=E39,"ИЗУЧЕНО",IF(AND(OR(F39="",SUMIF($A$11:$A$50,F39,AH$11:AH$50)>=SUMIF($A$11:$A$50,F39,$E$11:$E$50)),OR(G39="",SUMIF($A$11:$A$50,G39,AH$11:AH$50)>=SUMIF($A$11:$A$50,G39,$E$11:$E$50)),OR(H39="",SUMIF($A$11:$A$50,H39,AH$11:AH$50)>=SUMIF($A$11:$A$50,H39,$E$11:$E$50))),"ОТКРЫТО","ЗАКРЫТО")) -> ЗАКРЫТО | AX39: =IF(AI39>=E39,"ИЗУЧЕНО",IF(AND(OR(F39="",SUMIF($A$11:$A$50,F39,AI$11:AI$50)>=SUMIF($A$11:$A$50,F39,$E$11:$E$50)),OR(G39="",SUMIF($A$11:$A$50,G39,AI$11:AI$50)>=SUMIF($A$11:$A$50,G39,$E$11:$E$50)),OR(H39="",SUMIF($A$11:$A$50,H39,AI$11:AI$50)>=SUMIF($A$11:$A$50,H39,$E$11:$E$50))),"ОТКРЫТО","ЗАКРЫТО")) -> ЗАКРЫТО | AY39: =IF(AJ39>=E39,"ИЗУЧЕНО",IF(AND(OR(F39="",SUMIF($A$11:$A$50,F39,AJ$11:AJ$50)>=SUMIF($A$11:$A$50,F39,$E$11:$E$50)),OR(G39="",SUMIF($A$11:$A$50,G39,AJ$11:AJ$50)>=SUMIF($A$11:$A$50,G39,$E$11:$E$50)),OR(H39="",SUMIF($A$11:$A$50,H39,AJ$11:AJ$50)>=SUMIF($A$11:$A$50,H39,$E$11:$E$50))),"ОТКРЫТО","ЗАКРЫТО")) -> ЗАКРЫТО | AZ39: =IF(AK39>=E39,"ИЗУЧЕНО",IF(AND(OR(F39="",SUMIF($A$11:$A$50,F39,AK$11:AK$50)>=SUMIF($A$11:$A$50,F39,$E$11:$E$50)),OR(G39="",SUMIF($A$11:$A$50,G39,AK$11:AK$50)>=SUMIF($A$11:$A$50,G39,$E$11:$E$50)),OR(H39="",SUMIF($A$11:$A$50,H39,AK$11:AK$50)>=SUMIF($A$11:$A$50,H39,$E$11:$E$50))),"ОТКРЫТО","ЗАКРЫТО")) -> ЗАКРЫТО | BA39: =IF(AL39>=E39,"ИЗУЧЕНО",IF(AND(OR(F39="",SUMIF($A$11:$A$50,F39,AL$11:AL$50)>=SUMIF($A$11:$A$50,F39,$E$11:$E$50)),OR(G39="",SUMIF($A$11:$A$50,G39,AL$11:AL$50)>=SUMIF($A$11:$A$50,G39,$E$11:$E$50)),OR(H39="",SUMIF($A$11:$A$50,H39,AL$11:AL$50)>=SUMIF($A$11:$A$50,H39,$E$11:$E$50))),"ОТКРЫТО","ЗАКРЫТО")) -> ЗАКРЫТО | BB39: =IF(AM39>=E39,"ИЗУЧЕНО",IF(AND(OR(F39="",SUMIF($A$11:$A$50,F39,AM$11:AM$50)>=SUMIF($A$11:$A$50,F39,$E$11:$E$50)),OR(G39="",SUMIF($A$11:$A$50,G39,AM$11:AM$50)>=SUMIF($A$11:$A$50,G39,$E$11:$E$50)),OR(H39="",SUMIF($A$11:$A$50,H39,AM$11:AM$50)>=SUMIF($A$11:$A$50,H39,$E$11:$E$50))),"ОТКРЫТО","ЗАКРЫТО")) -> ЗАКРЫТО | BC39: =IF(AN39>=E39,"ИЗУЧЕНО",IF(AND(OR(F39="",SUMIF($A$11:$A$50,F39,AN$11:AN$50)>=SUMIF($A$11:$A$50,F39,$E$11:$E$50)),OR(G39="",SUMIF($A$11:$A$50,G39,AN$11:AN$50)>=SUMIF($A$11:$A$50,G39,$E$11:$E$50)),OR(H39="",SUMIF($A$11:$A$50,H39,AN$11:AN$50)>=SUMIF($A$11:$A$50,H39,$E$11:$E$50))),"ОТКРЫТО","ЗАКРЫТО")) -> ЗАКРЫТО | BD39: =IF(AO39>=E39,"ИЗУЧЕНО",IF(AND(OR(F39="",SUMIF($A$11:$A$50,F39,AO$11:AO$50)>=SUMIF($A$11:$A$50,F39,$E$11:$E$50)),OR(G39="",SUMIF($A$11:$A$50,G39,AO$11:AO$50)>=SUMIF($A$11:$A$50,G39,$E$11:$E$50)),OR(H39="",SUMIF($A$11:$A$50,H39,AO$11:AO$50)>=SUMIF($A$11:$A$50,H39,$E$11:$E$50))),"ОТКРЫТО","ЗАКРЫТО")) -> ЗАКРЫТО | BE39: =IF(AP39>=E39,"ИЗУЧЕНО",IF(AND(OR(F39="",SUMIF($A$11:$A$50,F39,AP$11:AP$50)>=SUMIF($A$11:$A$50,F39,$E$11:$E$50)),OR(G39="",SUMIF($A$11:$A$50,G39,AP$11:AP$50)>=SUMIF($A$11:$A$50,G39,$E$11:$E$50)),OR(H39="",SUMIF($A$11:$A$50,H39,AP$11:AP$50)>=SUMIF($A$11:$A$50,H39,$E$11:$E$50))),"ОТКРЫТО","ЗАКРЫТО")) -> ЗАКРЫТО | BF39: =IF(AQ39>=E39,"ИЗУЧЕНО",IF(AND(OR(F39="",SUMIF($A$11:$A$50,F39,AQ$11:AQ$50)>=SUMIF($A$11:$A$50,F39,$E$11:$E$50)),OR(G39="",SUMIF($A$11:$A$50,G39,AQ$11:AQ$50)>=SUMIF($A$11:$A$50,G39,$E$11:$E$50)),OR(H39="",SUMIF($A$11:$A$50,H39,AQ$11:AQ$50)>=SUMIF($A$11:$A$50,H39,$E$11:$E$50))),"ОТКРЫТО","ЗАКРЫТО")) -> ЗАКРЫТО
A40: R6 | B40: Физический ИИ и робототехника | C40: V | D40: Автономные производственные комплексы | E40: 150 | F40: R5 | I40: Производство с минимальным постоянным человеческим оперативным управлением. | J40: Производство +0,5; его прирост +0,15/год; очки трансформации в ресурсы группы I эффективнее на 15% | K40: =SUMIF('Ход 2026'!$G$29:$G$38,$A40,'Ход 2026'!$I$29:$I$38) -> 0 | L40: =SUMIF('Ход 2027'!$G$29:$G$38,$A40,'Ход 2027'!$I$29:$I$38) -> 0 | M40: =SUMIF('Ход 2028'!$G$29:$G$38,$A40,'Ход 2028'!$I$29:$I$38) -> 0 | N40: =SUMIF('Ход 2029'!$G$29:$G$38,$A40,'Ход 2029'!$I$29:$I$38) -> 0 | O40: =SUMIF('Ход 2030'!$G$29:$G$38,$A40,'Ход 2030'!$I$29:$I$38) -> 0 | P40: =SUMIF('Ход 2031'!$G$29:$G$38,$A40,'Ход 2031'!$I$29:$I$38) -> 0 | Q40: =SUMIF('Ход 2032'!$G$29:$G$38,$A40,'Ход 2032'!$I$29:$I$38) -> 0 | R40: =SUMIF('Ход 2033'!$G$29:$G$38,$A40,'Ход 2033'!$I$29:$I$38) -> 0 | S40: =SUMIF('Ход 2034'!$G$29:$G$38,$A40,'Ход 2034'!$I$29:$I$38) -> 0 | T40: =SUMIF('Ход 2035'!$G$29:$G$38,$A40,'Ход 2035'!$I$29:$I$38) -> 0 | U40: =SUMIF('Ход 2036'!$G$29:$G$38,$A40,'Ход 2036'!$I$29:$I$38) -> 0 | V40: =SUMIF('Ход 2037'!$G$29:$G$38,$A40,'Ход 2037'!$I$29:$I$38) -> 0 | W40: =SUMIF('Ход 2038'!$G$29:$G$38,$A40,'Ход 2038'!$I$29:$I$38) -> 0 | X40: =SUMIF('Ход 2039'!$G$29:$G$38,$A40,'Ход 2039'!$I$29:$I$38) -> 0 | Y40: =SUMIF('Ход 2040'!$G$29:$G$38,$A40,'Ход 2040'!$I$29:$I$38) -> 0 | Z40: =SUM(K40:Y40) -> 0 | AA40: =MAX(0,E40-Z40) -> 150 | AB40: =BF40 -> ЗАКРЫТО | AC40: =SUM($K40:K40) -> 0 | AD40: =SUM($K40:L40) -> 0 | AE40: =SUM($K40:M40) -> 0 | AF40: =SUM($K40:N40) -> 0 | AG40: =SUM($K40:O40) -> 0 | AH40: =SUM($K40:P40) -> 0 | AI40: =SUM($K40:Q40) -> 0 | AJ40: =SUM($K40:R40) -> 0 | ... AQ40: =SUM($K40:Y40) -> 0 | AR40: =IF(AC40>=E40,"ИЗУЧЕНО",IF(AND(OR(F40="",SUMIF($A$11:$A$50,F40,AC$11:AC$50)>=SUMIF($A$11:$A$50,F40,$E$11:$E$50)),OR(G40="",SUMIF($A$11:$A$50,G40,AC$11:AC$50)>=SUMIF($A$11:$A$50,G40,$E$11:$E$50)),OR(H40="",SUMIF($A$11:$A$50,H40,AC$11:AC$50)>=SUMIF($A$11:$A$50,H40,$E$11:$E$50))),"ОТКРЫТО","ЗАКРЫТО")) -> ЗАКРЫТО | AS40: =IF(AD40>=E40,"ИЗУЧЕНО",IF(AND(OR(F40="",SUMIF($A$11:$A$50,F40,AD$11:AD$50)>=SUMIF($A$11:$A$50,F40,$E$11:$E$50)),OR(G40="",SUMIF($A$11:$A$50,G40,AD$11:AD$50)>=SUMIF($A$11:$A$50,G40,$E$11:$E$50)),OR(H40="",SUMIF($A$11:$A$50,H40,AD$11:AD$50)>=SUMIF($A$11:$A$50,H40,$E$11:$E$50))),"ОТКРЫТО","ЗАКРЫТО")) -> ЗАКРЫТО | AT40: =IF(AE40>=E40,"ИЗУЧЕНО",IF(AND(OR(F40="",SUMIF($A$11:$A$50,F40,AE$11:AE$50)>=SUMIF($A$11:$A$50,F40,$E$11:$E$50)),OR(G40="",SUMIF($A$11:$A$50,G40,AE$11:AE$50)>=SUMIF($A$11:$A$50,G40,$E$11:$E$50)),OR(H40="",SUMIF($A$11:$A$50,H40,AE$11:AE$50)>=SUMIF($A$11:$A$50,H40,$E$11:$E$50))),"ОТКРЫТО","ЗАКРЫТО")) -> ЗАКРЫТО | AU40: =IF(AF40>=E40,"ИЗУЧЕНО",IF(AND(OR(F40="",SUMIF($A$11:$A$50,F40,AF$11:AF$50)>=SUMIF($A$11:$A$50,F40,$E$11:$E$50)),OR(G40="",SUMIF($A$11:$A$50,G40,AF$11:AF$50)>=SUMIF($A$11:$A$50,G40,$E$11:$E$50)),OR(H40="",SUMIF($A$11:$A$50,H40,AF$11:AF$50)>=SUMIF($A$11:$A$50,H40,$E$11:$E$50))),"ОТКРЫТО","ЗАКРЫТО")) -> ЗАКРЫТО | AV40: =IF(AG40>=E40,"ИЗУЧЕНО",IF(AND(OR(F40="",SUMIF($A$11:$A$50,F40,AG$11:AG$50)>=SUMIF($A$11:$A$50,F40,$E$11:$E$50)),OR(G40="",SUMIF($A$11:$A$50,G40,AG$11:AG$50)>=SUMIF($A$11:$A$50,G40,$E$11:$E$50)),OR(H40="",SUMIF($A$11:$A$50,H40,AG$11:AG$50)>=SUMIF($A$11:$A$50,H40,$E$11:$E$50))),"ОТКРЫТО","ЗАКРЫТО")) -> ЗАКРЫТО | AW40: =IF(AH40>=E40,"ИЗУЧЕНО",IF(AND(OR(F40="",SUMIF($A$11:$A$50,F40,AH$11:AH$50)>=SUMIF($A$11:$A$50,F40,$E$11:$E$50)),OR(G40="",SUMIF($A$11:$A$50,G40,AH$11:AH$50)>=SUMIF($A$11:$A$50,G40,$E$11:$E$50)),OR(H40="",SUMIF($A$11:$A$50,H40,AH$11:AH$50)>=SUMIF($A$11:$A$50,H40,$E$11:$E$50))),"ОТКРЫТО","ЗАКРЫТО")) -> ЗАКРЫТО | AX40: =IF(AI40>=E40,"ИЗУЧЕНО",IF(AND(OR(F40="",SUMIF($A$11:$A$50,F40,AI$11:AI$50)>=SUMIF($A$11:$A$50,F40,$E$11:$E$50)),OR(G40="",SUMIF($A$11:$A$50,G40,AI$11:AI$50)>=SUMIF($A$11:$A$50,G40,$E$11:$E$50)),OR(H40="",SUMIF($A$11:$A$50,H40,AI$11:AI$50)>=SUMIF($A$11:$A$50,H40,$E$11:$E$50))),"ОТКРЫТО","ЗАКРЫТО")) -> ЗАКРЫТО | AY40: =IF(AJ40>=E40,"ИЗУЧЕНО",IF(AND(OR(F40="",SUMIF($A$11:$A$50,F40,AJ$11:AJ$50)>=SUMIF($A$11:$A$50,F40,$E$11:$E$50)),OR(G40="",SUMIF($A$11:$A$50,G40,AJ$11:AJ$50)>=SUMIF($A$11:$A$50,G40,$E$11:$E$50)),OR(H40="",SUMIF($A$11:$A$50,H40,AJ$11:AJ$50)>=SUMIF($A$11:$A$50,H40,$E$11:$E$50))),"ОТКРЫТО","ЗАКРЫТО")) -> ЗАКРЫТО | AZ40: =IF(AK40>=E40,"ИЗУЧЕНО",IF(AND(OR(F40="",SUMIF($A$11:$A$50,F40,AK$11:AK$50)>=SUMIF($A$11:$A$50,F40,$E$11:$E$50)),OR(G40="",SUMIF($A$11:$A$50,G40,AK$11:AK$50)>=SUMIF($A$11:$A$50,G40,$E$11:$E$50)),OR(H40="",SUMIF($A$11:$A$50,H40,AK$11:AK$50)>=SUMIF($A$11:$A$50,H40,$E$11:$E$50))),"ОТКРЫТО","ЗАКРЫТО")) -> ЗАКРЫТО | BA40: =IF(AL40>=E40,"ИЗУЧЕНО",IF(AND(OR(F40="",SUMIF($A$11:$A$50,F40,AL$11:AL$50)>=SUMIF($A$11:$A$50,F40,$E$11:$E$50)),OR(G40="",SUMIF($A$11:$A$50,G40,AL$11:AL$50)>=SUMIF($A$11:$A$50,G40,$E$11:$E$50)),OR(H40="",SUMIF($A$11:$A$50,H40,AL$11:AL$50)>=SUMIF($A$11:$A$50,H40,$E$11:$E$50))),"ОТКРЫТО","ЗАКРЫТО")) -> ЗАКРЫТО | BB40: =IF(AM40>=E40,"ИЗУЧЕНО",IF(AND(OR(F40="",SUMIF($A$11:$A$50,F40,AM$11:AM$50)>=SUMIF($A$11:$A$50,F40,$E$11:$E$50)),OR(G40="",SUMIF($A$11:$A$50,G40,AM$11:AM$50)>=SUMIF($A$11:$A$50,G40,$E$11:$E$50)),OR(H40="",SUMIF($A$11:$A$50,H40,AM$11:AM$50)>=SUMIF($A$11:$A$50,H40,$E$11:$E$50))),"ОТКРЫТО","ЗАКРЫТО")) -> ЗАКРЫТО | BC40: =IF(AN40>=E40,"ИЗУЧЕНО",IF(AND(OR(F40="",SUMIF($A$11:$A$50,F40,AN$11:AN$50)>=SUMIF($A$11:$A$50,F40,$E$11:$E$50)),OR(G40="",SUMIF($A$11:$A$50,G40,AN$11:AN$50)>=SUMIF($A$11:$A$50,G40,$E$11:$E$50)),OR(H40="",SUMIF($A$11:$A$50,H40,AN$11:AN$50)>=SUMIF($A$11:$A$50,H40,$E$11:$E$50))),"ОТКРЫТО","ЗАКРЫТО")) -> ЗАКРЫТО | BD40: =IF(AO40>=E40,"ИЗУЧЕНО",IF(AND(OR(F40="",SUMIF($A$11:$A$50,F40,AO$11:AO$50)>=SUMIF($A$11:$A$50,F40,$E$11:$E$50)),OR(G40="",SUMIF($A$11:$A$50,G40,AO$11:AO$50)>=SUMIF($A$11:$A$50,G40,$E$11:$E$50)),OR(H40="",SUMIF($A$11:$A$50,H40,AO$11:AO$50)>=SUMIF($A$11:$A$50,H40,$E$11:$E$50))),"ОТКРЫТО","ЗАКРЫТО")) -> ЗАКРЫТО | BE40: =IF(AP40>=E40,"ИЗУЧЕНО",IF(AND(OR(F40="",SUMIF($A$11:$A$50,F40,AP$11:AP$50)>=SUMIF($A$11:$A$50,F40,$E$11:$E$50)),OR(G40="",SUMIF($A$11:$A$50,G40,AP$11:AP$50)>=SUMIF($A$11:$A$50,G40,$E$11:$E$50)),OR(H40="",SUMIF($A$11:$A$50,H40,AP$11:AP$50)>=SUMIF($A$11:$A$50,H40,$E$11:$E$50))),"ОТКРЫТО","ЗАКРЫТО")) -> ЗАКРЫТО | BF40: =IF(AQ40>=E40,"ИЗУЧЕНО",IF(AND(OR(F40="",SUMIF($A$11:$A$50,F40,AQ$11:AQ$50)>=SUMIF($A$11:$A$50,F40,$E$11:$E$50)),OR(G40="",SUMIF($A$11:$A$50,G40,AQ$11:AQ$50)>=SUMIF($A$11:$A$50,G40,$E$11:$E$50)),OR(H40="",SUMIF($A$11:$A$50,H40,AQ$11:AQ$50)>=SUMIF($A$11:$A$50,H40,$E$11:$E$50))),"ОТКРЫТО","ЗАКРЫТО")) -> ЗАКРЫТО
